Workbook

Sheet Nombre Equipo
C3: Integrantes del equipo
C4: 1 | D4: Alondra Abril Alarcón Alvarez
C5: =+C4+1 -> 2 | D5: Angelica Guadalupe Cravioto Perez
C6: =+C5+1 -> 3 | D6: Arturo Cortés Islas
C7: =+C6+1 -> 4 | D7: Dereck Favila Limón
C8: =+C7+1 -> 5 | D8: Ismael Ruiz Carbajal
C9: =+C8+1 -> 6 | D9: José Julián Alcalá Alcántara
C10: =+C9+1 -> 7 | D10: Melissa González Cortés

Sheet Triangulo1
C2: Calcula el IBNR del siguiente triangulo usando Chain Ladder, BF y Cape Cod
D3: 1. el loss ratio a priori es 55%
D4: 2. tasa de interes | E4: 0.06
C7: Contesta las sig preguntas:
D8: 1. Qué metodología escogerías para cada trimestre y por qué? | G8: Chain Ladder para períodos antiguos debido a que ya se cuenta con la suficiente experiencia observada y BF/CC para los periodos recientes, ya que, utilizamos una estimación del loss ratio basada en la experiencia agregada de la cartera, esto reduce el sesgo por tener poca experiencia observada.
D9: 2. Excluiste algun periodo para el calculo de lo factores? Di que periodo y en que desarrollo y por qué | G9: Sí, se utilizaron los últimos 8peridos, ya que presentan mayor estabilidad y son los más representativos respecto a la experiencia reciente.
D10: 3. Cómo sale el bakctesting para tu selección de ultimate para los trimestres del 1Q19 al 4Q20? | G10: El backtesting resulta satisfactorio para el triángulo en los primeros trimestres (1Q19–4Q20). Las estimaciones obtenidas mediante Chain Ladder para los periodos maduros se mantienen prácticamente sin variaciones al incorporar información adicional. Asimismo, la estimación del loss ratio calculada con CC presenta cambios mínimos, lo que refuerza la elección de esta metodología para los trimestres comprendidos entre 1Q19 y 4Q20.
D11: 4. Qué duración tiene está cartera? | G11: Para el Triángulo 1, utilizando el patrón de pagos y la tasa de descuento considerada en el archivo, se obtiene una duración de Macaulay de aproximadamente 0.984 años, equivalente a alrededor de 11.8 meses. La duración modificada es aproximadamente 0.928 años
C13: TRIÁNGULO-PAGADO
D15: 1 | E15: =+D15+1 -> 2 | F15: =+E15+1 -> 3 | G15: =+F15+1 -> 4 | H15: =+G15+1 -> 5 | I15: =+H15+1 -> 6 | J15: =+I15+1 -> 7 | K15: =+J15+1 -> 8 | L15: =+K15+1 -> 9 | ... AA15: =+Z15+1 -> 24
C16: 1Q19 | D16: 6418198 | E16: 8351947 | F16: 9393090 | G16: 11183194 | H16: 12100800 | I16: 12721118 | J16: 13073728 | K16: 13548698 | L16: 13729852 | M16: 14178002 | N16: 14403018 | O16: 14589694 | P16: 14666170 | Q16: 14699145 | R16: 14709918 | S16: 14721902 | T16: 14723975 | U16: 14724778 | V16: 14725216 | W16: 14725343 | X16: 14725356 | Y16: 14725361 | Z16: 14725369 | AA16: 14725385
C17: 2Q19 | D17: 7475822 | E17: 10450029 | F17: 12515657 | G17: 13149304 | H17: 14417681 | I17: 15145227 | J17: 15971980 | K17: 16442175 | L17: 16761977 | M17: 17230340 | N17: 17479823 | O17: 17658472 | P17: 17691106 | Q17: 17707511 | R17: 17727251 | S17: 17731572 | T17: 17733454 | U17: 17734435 | V17: 17734974 | W17: 17735197 | X17: 17735258 | Y17: 17735268 | Z17: 17735279
C18: 3Q19 | D18: 4944676 | E18: 5651989 | F18: 6603749 | G18: 7627857 | H18: 8503366 | I18: 9687265 | J18: 10329156 | K18: 10705380 | L18: 11007279 | M18: 11432174 | N18: 11644639 | O18: 11802250 | P18: 11840837 | Q18: 11864201 | R18: 11873586 | S18: 11878223 | T18: 11880065 | U18: 11880905 | V18: 11881492 | W18: 11881607 | X18: 11881725 | Y18: 11881761
C19: 4Q19 | D19: 5990844 | E19: 12990844 | F19: 14795084 | G19: 15558421 | H19: 16698078 | I19: 17591115 | J19: 17858613 | K19: 18161498 | L19: 18751439 | M19: 18855100 | N19: 19152179 | O19: 19349458 | P19: 19426010 | Q19: 19444545 | R19: 19453256 | S19: 19457999 | T19: 19459976 | U19: 19461146 | V19: 19461559 | W19: 19461649 | X19: 19461650
C20: 1Q20 | D20: 6106533 | E20: 7227067 | F20: 8316481 | G20: 8778769 | H20: 9616196 | I20: 9944940 | J20: 10596973 | K20: 10938865 | L20: 11091033 | M20: 11574757 | N20: 11660948 | O20: 11754449 | P20: 11785976 | Q20: 11801623 | R20: 11808422 | S20: 11812430 | T20: 11814677 | U20: 11815553 | V20: 11815994 | W20: 11816173
C21: 2Q20 | D21: 3511339 | E21: 5097855 | F21: 6037374 | G21: 6436248 | H21: 7366573 | I21: 8575992 | J21: 9082448 | K21: 12082448 | L21: 12687409 | M21: 12838372 | N21: 12930641 | O21: 12990612 | P21: 13017211 | Q21: 13032985 | R21: 13041104 | S21: 13045224 | T21: 13046906 | U21: 13047997 | V21: 13048471
C22: 3Q20 | D22: 4141271 | E22: 5675304 | F22: 6514051 | G22: 7799341 | H22: 8118940 | I22: 8328067 | J22: 9073367 | K22: 9580777 | L22: 10084545 | M22: 10574369 | N22: 10704764 | O22: 10779530 | P22: 10810916 | Q22: 10825407 | R22: 10831969 | S22: 10836654 | T22: 10839043 | U22: 10840140
C23: 4Q20 | D23: 6591656 | E23: 9149839 | F23: 9876574 | G23: 11324778 | H23: 11791969 | I23: 12446387 | J23: 12820241 | K23: 13419392 | L23: 13586619 | M23: 13861205 | N23: 13987078 | O23: 14043493 | P23: 14079323 | Q23: 14095393 | R23: 14104571 | S23: 14109322 | T23: 14111136
C24: 1Q21 | D24: 6289704 | E24: 9074583 | F24: 11031640 | G24: 12328713 | H24: 12743016 | I24: 13716063 | J24: 13936735 | K24: 14684360 | L24: 15224487 | M24: 15505624 | N24: 15616491 | O24: 15669883 | P24: 15701026 | Q24: 15717007 | R24: 15725357 | S24: 15729334
C25: 2Q21 | D25: 4959185 | E25: 7332815 | F25: 8942057 | G25: 10413724 | H25: 11109326 | I25: 11743877 | J25: 12264947 | K25: 13331758 | L25: 13881470 | M25: 14105853 | N25: 14231236 | O25: 14285043 | P25: 14317196 | Q25: 14335249 | R25: 14343596
C26: 3Q21 | D26: 6194048 | E26: 7741218 | F26: 9386858 | G26: 9734366 | H26: 10964336 | I26: 11346897 | J26: 13064544 | K26: 14121948 | L26: 14605429 | M26: 14862271 | N26: 15012968 | O26: 15074585 | P26: 15104696 | Q26: 15119935
C27: 4Q21 | D27: 6500694 | E27: 9436157 | F27: 11552953 | G27: 12130358 | H27: 13369514 | I27: 15030308 | J27: 16697100 | K27: 17828453 | L27: 18294564 | M27: 18522862 | N27: 18641988 | O27: 18693587 | P27: 18730024
C28: 1Q22 | D28: 5205434 | E28: 7752400 | F28: 9411446 | G28: 10805763 | H28: 13284336 | I28: 15384835 | J28: 17438864 | K28: 18514044 | L28: 19125680 | M28: 19431036 | N28: 19572822 | O28: 19627354
C29: 2Q22 | D29: 5184519 | E29: 7275135 | F29: 7974797 | G29: 11597296 | H29: 14585912 | I29: 16285147 | J29: 18338971 | K29: 19214501 | L29: 19700684 | M29: 19926910 | N29: 20049671
C30: 3Q22 | D30: 3419011 | E30: 4773306 | F30: 8697825 | G30: 12220494 | H30: 14462971 | I30: 16656668 | J30: 19017438 | K30: 19939378 | L30: 20384099 | M30: 20688336
C31: 4Q22 | D31: 5498188 | E31: 10669557 | F31: 14420577 | G31: 17838126 | H31: 20243242 | I31: 22179116 | J31: 24155749 | K31: 25145296 | L31: 25647723
C32: 1Q23 | D32: 6382667 | E32: 10460689 | F32: 15242265 | G32: 19075882 | H32: 21908553 | I32: 23938666 | J32: 25653115 | K32: 26811464
C33: 2Q23 | D33: 3022770 | E33: 7899209 | F33: 11259161 | G33: 14497513 | H33: 17221120 | I33: 19234288 | J33: 21399003
C34: 3Q23 | D34: 6936281 | E34: 21936281 | F34: 25150070 | G34: 28898330 | H34: 31903741 | I34: 33589263
C35: 4Q23 | D35: 6691248 | E35: 11756013 | F35: 15391294 | G35: 18736499 | H35: 21705785
C36: 1Q24 | D36: 4191817 | E36: 9775450 | F36: 14374440 | G36: 17306094
C37: 2Q24 | D37: 5916671 | E37: 11716355 | F37: 15374462
C38: 3Q24 | D38: 4926500 | E38: 9321834
C39: 4Q24 | D39: 5149958
C41: FACTORES
D43: 1 | E43: =+D43+1 -> 2 | F43: =+E43+1 -> 3 | G43: =+F43+1 -> 4 | H43: =+G43+1 -> 5 | I43: =+H43+1 -> 6 | J43: =+I43+1 -> 7 | K43: =+J43+1 -> 8 | L43: =+K43+1 -> 9 | ... AA43: =+Z43+1 -> 24
C44: 1Q19 | D44: =E16/D16 -> 1.3012916 | E44: =F16/E16 -> 1.1246587 | F44: =G16/F16 -> 1.1905767 | G44: =H16/G16 -> 1.0820522 | H44: =I16/H16 -> 1.0512626 | I44: =J16/I16 -> 1.0277185 | J44: =K16/J16 -> 1.0363301 | K44: =L16/K16 -> 1.0133706 | ... Z44: =AA16/Z16 -> 1.0000011
C45: 2Q19 | D45: =E17/D17 -> 1.3978435 | E45: =F17/E17 -> 1.1976672 | F45: =G17/F17 -> 1.0506283 | G45: =H17/G17 -> 1.0964596 | H45: =I17/H17 -> 1.0504621 | I45: =J17/I17 -> 1.0545884 | J45: =K17/J17 -> 1.0294387 | K45: =L17/K17 -> 1.0194501 | ... Y45: =Z17/Y17 -> 1.0000006
C46: 3Q19 | D46: =E18/D18 -> 1.1430454 | E46: =F18/E18 -> 1.1683938 | F46: =G18/F18 -> 1.1550798 | G46: =H18/G18 -> 1.1147778 | H46: =I18/H18 -> 1.1392271 | I46: =J18/I18 -> 1.0662613 | J46: =K18/J18 -> 1.0364235 | K46: =L18/K18 -> 1.0282007 | ... X46: =Y18/X18 -> 1.000003
C47: 4Q19 | D47: =E19/D19 -> 2.1684497 | E47: =F19/E19 -> 1.1388855 | F47: =G19/F19 -> 1.051594 | G47: =H19/G19 -> 1.0732502 | H47: =I19/H19 -> 1.0534814 | I47: =J19/I19 -> 1.0152064 | J47: =K19/J19 -> 1.0169602 | K47: =L19/K19 -> 1.0324831 | ... W47: =X19/W19 -> 1.0000001
C48: 1Q20 | D48: =E20/D20 -> 1.1834976 | E48: =F20/E20 -> 1.1507408 | F48: =G20/F20 -> 1.055587 | G48: =H20/G20 -> 1.0953923 | H48: =I20/H20 -> 1.0341865 | I48: =J20/I20 -> 1.0655643 | J48: =K20/J20 -> 1.0322632 | K48: =L20/K20 -> 1.0139108 | ... V48: =W20/V20 -> 1.0000151
C49: 2Q20 | D49: =E21/D21 -> 1.4518265 | E49: =F21/E21 -> 1.1842969 | F49: =G21/F21 -> 1.0660675 | G49: =H21/G21 -> 1.1445446 | H49: =I21/H21 -> 1.1641766 | I49: =J21/I21 -> 1.0590551 | J49: =K21/J21 -> 1.3303074 | K49: =L21/K21 -> 1.0500694 | ... U49: =V21/U21 -> 1.0000363
C50: 3Q20 | D50: =E22/D22 -> 1.3704256 | E50: =F22/E22 -> 1.1477889 | F50: =G22/F22 -> 1.1973104 | G50: =H22/G22 -> 1.0409777 | H50: =I22/H22 -> 1.0257579 | I50: =J22/I22 -> 1.0894926 | J50: =K22/J22 -> 1.055923 | K50: =L22/K22 -> 1.0525811 | ... T50: =U22/T22 -> 1.0001012
C51: 4Q20 | D51: =E23/D23 -> 1.3880941 | E51: =F23/E23 -> 1.079426 | F51: =G23/F23 -> 1.1466302 | G51: =H23/G23 -> 1.0412539 | H51: =I23/H23 -> 1.0554969 | I51: =J23/I23 -> 1.0300372 | J51: =K23/J23 -> 1.0467348 | K51: =L23/K23 -> 1.0124616 | ... S51: =T23/S23 -> 1.0001286
C52: 1Q21 | D52: =E24/D24 -> 1.4427679 | E52: =F24/E24 -> 1.2156636 | F52: =G24/F24 -> 1.1175775 | G52: =H24/G24 -> 1.0336047 | H52: =I24/H24 -> 1.0763592 | I52: =J24/I24 -> 1.0160886 | J52: =K24/J24 -> 1.0536442 | K52: =L24/K24 -> 1.0367825 | ... R52: =S24/R24 -> 1.0002529
C53: 2Q21 | D53: =E25/D25 -> 1.4786331 | E53: =F25/E25 -> 1.2194576 | F53: =G25/F25 -> 1.1645781 | G53: =H25/G25 -> 1.0667967 | H53: =I25/H25 -> 1.0571188 | I53: =J25/I25 -> 1.0443695 | J53: =K25/J25 -> 1.0869805 | K53: =L25/K25 -> 1.0412333 | ... Q53: =R25/Q25 -> 1.0005823
C54: 3Q21 | D54: =E26/D26 -> 1.2497833 | E54: =F26/E26 -> 1.2125815 | F54: =G26/F26 -> 1.0370207 | G54: =H26/G26 -> 1.1263534 | H54: =I26/H26 -> 1.0348914 | I54: =J26/I26 -> 1.1513759 | J54: =K26/J26 -> 1.0809369 | K54: =L26/K26 -> 1.0342361 | ... P54: =Q26/P26 -> 1.0010089
C55: 4Q21 | D55: =E27/D27 -> 1.4515615 | E55: =F27/E27 -> 1.2243282 | F55: =G27/F27 -> 1.049979 | G55: =H27/G27 -> 1.1021533 | H55: =I27/H27 -> 1.1242225 | I55: =J27/I27 -> 1.1108954 | J55: =K27/J27 -> 1.0677575 | K55: =L27/K27 -> 1.0261442 | ... O55: =P27/O27 -> 1.0019492
C56: 1Q22 | D56: =E28/D28 -> 1.4892898 | E56: =F28/E28 -> 1.2140042 | F56: =G28/F28 -> 1.1481512 | G56: =H28/G28 -> 1.2293751 | H56: =I28/H28 -> 1.1581185 | I56: =J28/I28 -> 1.13351 | J56: =K28/J28 -> 1.0616542 | K56: =L28/K28 -> 1.0330363 | ... N56: =O28/N28 -> 1.0027861
C57: 2Q22 | D57: =E29/D29 -> 1.403242 | E57: =F29/E29 -> 1.0961717 | F57: =G29/F29 -> 1.4542434 | G57: =H29/G29 -> 1.2576994 | H57: =I29/H29 -> 1.1164984 | I57: =J29/I29 -> 1.1261164 | J57: =K29/J29 -> 1.0477415 | K57: =L29/K29 -> 1.0253029 | ... M57: =N29/M29 -> 1.0061606
C58: 3Q22 | D58: =E30/D30 -> 1.3961072 | E58: =F30/E30 -> 1.8221805 | F58: =G30/F30 -> 1.4050057 | G58: =H30/G30 -> 1.1835013 | H58: =I30/H30 -> 1.1516768 | I58: =J30/I30 -> 1.1417312 | J58: =K30/J30 -> 1.0484787 | K58: =L30/K30 -> 1.0223037 | L58: =M30/L30 -> 1.0149252
C59: 4Q22 | D59: =E31/D31 -> 1.9405588 | E59: =F31/E31 -> 1.3515629 | F59: =G31/F31 -> 1.2369911 | G59: =H31/G31 -> 1.1348301 | H59: =I31/H31 -> 1.0956306 | I59: =J31/I31 -> 1.0891214 | J59: =K31/J31 -> 1.0409653 | K59: =L31/K31 -> 1.019981
C60: 1Q23 | D60: =E32/D32 -> 1.6389213 | E60: =F32/E32 -> 1.4570995 | F60: =G32/F32 -> 1.2515123 | G60: =H32/G32 -> 1.1484949 | H60: =I32/H32 -> 1.092663 | I60: =J32/I32 -> 1.0716184 | J60: =K32/J32 -> 1.0451543
C61: 2Q23 | D61: =E33/D33 -> 2.6132352 | E61: =F33/E33 -> 1.425353 | F61: =G33/F33 -> 1.2876193 | G61: =H33/G33 -> 1.1878672 | H61: =I33/H33 -> 1.1169011 | I61: =J33/I33 -> 1.1125446
C62: 3Q23 | D62: =E34/D34 -> 3.1625421 | E62: =F34/E34 -> 1.1465056 | F62: =G34/F34 -> 1.1490358 | G62: =H34/G34 -> 1.1039995 | H62: =I34/H34 -> 1.0528315
C63: 4Q23 | D63: =E35/D35 -> 1.7569238 | E63: =F35/E35 -> 1.3092274 | F63: =G35/F35 -> 1.217344 | G63: =H35/G35 -> 1.158476
C64: 1Q24 | D64: =E36/D36 -> 2.3320317 | E64: =F36/E36 -> 1.4704633 | F64: =G36/F36 -> 1.2039491
C65: 2Q24 | D65: =E37/D37 -> 1.9802276 | E65: =F37/E37 -> 1.3122223
C66: 3Q24 | D66: =E38/D38 -> 1.8921819
C67: 4Q24
C68: Mediana | D68: =MEDIAN(D44:D66) -> 1.4518265 | E68: =MEDIAN(E44:E66) -> 1.2132929 | F68: =MEDIAN(F44:F66) -> 1.1550798 | G68: =MEDIAN(G44:G66) -> 1.1093887 | H68: =MEDIAN(H44:H66) -> 1.0763592 | I68: =MEDIAN(I44:I66) -> 1.0689399 | J68: =MEDIAN(J44:J66) -> 1.0477415 | K68: =MEDIAN(K44:K66) -> 1.0271725 | ... Z68: =MEDIAN(Z44:Z66) -> 1.0000011
C69: Promedio_2024 | D69: =AVERAGE(D44:D66) -> 1.6796731 | E69: =AVERAGE(E44:E66) -> 1.2576672 | F69: =AVERAGE(F44:F66) -> 1.1731658 | G69: =AVERAGE(G44:G66) -> 1.121093 | H69: =AVERAGE(H44:H66) -> 1.0868928 | I69: =AVERAGE(I44:I66) -> 1.0780719 | J69: =AVERAGE(J44:J66) -> 1.0657467 | K69: =AVERAGE(K44:K66) -> 1.0288467 | ... Z69: =AVERAGE(Z44:Z66) -> 1.0000011 | AA69: 1
C70: Promedio_2023 | D70: =AVERAGE(D44:D63) -> 1.621402 | E70: =AVERAGE(E44:E63) -> 1.2442997 | F70: =AVERAGE(F44:F63) -> 1.1716266 | G70: =AVERAGE(G44:G63) -> 1.121093 | H70: =AVERAGE(H44:H63) -> 1.0868928 | I70: =AVERAGE(I44:I63) -> 1.0780719 | J70: =AVERAGE(J44:J63) -> 1.0657467 | K70: =AVERAGE(K44:K63) -> 1.0288467 | ... V70: =AVERAGE(V44:V63) -> 1.0000101 | W70: 1
D73: FACTORES Y ULTIMATES CORTE 2024 | M73: FACTORES Y ULTIMATES CORTE 2023 | V73: FACTORES Y ULTIMATES CORTE 2022
D74: FACTORES | G74: Ultimates | J74: IBNR | M74: FACTORES | P74: Ultimates | S74: IBNR | V74: FACTORES | Y74: Ultimates | AB74: IBNR
D75: Ultimos8 | E75: todo | F75: promedio_simple | G75: Ultimos8 | H75: todo | I75: promedio_simple | J75: Ultimos8 | K75: todo | L75: promedio_simple | M75: Ultimos8 | N75: todo | O75: promedio_simple | P75: Ultimos8 | Q75: todo | R75: promedio_simple | S75: Ultimos8 | T75: todo | U75: promedio_simple | V75: Ultimos8 | W75: todo | X75: promedio_simple | Y75: Ultimos8 | Z75: todo | AA75: promedio_simple | AB75: Ultimos8 | AC75: todo | AD75: promedio_simple
C76: 1Q19 | D76: {=TRANSPOSE(ultimos8_corte2024_promedio_pro!C30:Z30)} -> 2.1469743 | E76: {=TRANSPOSE(todo_corte2024_promedo_prom!C30:Z30)} -> 1.6720745 | F76: {=TRANSPOSE(todo_corte2024_promedio_simple!C30:Z30)} -> 1.6796731 | G76: =ultimos8_corte2024_promedio_pro!AA4 -> 14725385 | H76: =todo_corte2024_promedo_prom!AA4 -> 14725385 | I76: =todo_corte2024_promedio_simple!AA4 -> 14725385 | J76: =ultimos8_corte2024_promedio_pro!AC4 -> 0 | K76: =todo_corte2024_promedo_prom!AC4 -> 0 | L76: =todo_corte2024_promedio_simple!AC4 -> 0 | M76: {=TRANSPOSE(ultimos8_corte2023_promedio!C26:V26)} -> 1.9028129 | N76: {=TRANSPOSE(todo_corte2023_promedo_prom!C26:V26)} -> 1.6125002 | O76: {=TRANSPOSE(todo_corte2023_promedo_simple!C26:V26)} -> 1.621402 | P76: =ultimos8_corte2023_promedio!W4 -> 14725343 | Q76: =todo_corte2023_promedo_prom!W4 -> 14725343 | R76: =todo_corte2023_promedo_simple!W4 -> 14725343 | S76: =ultimos8_corte2023_promedio!Y4 -> 0 | T76: =todo_corte2023_promedo_prom!Y4 -> 0 | U76: =todo_corte2023_promedo_simple!Y4 -> 0
C77: 2Q19 | D77: 1.3475034 | E77: 1.2476228 | F77: 1.2576672 | G77: =ultimos8_corte2024_promedio_pro!AA5 -> 17735298 | H77: =todo_corte2024_promedo_prom!AA5 -> 17735298 | I77: =todo_corte2024_promedio_simple!AA5 -> 17735298 | J77: =ultimos8_corte2024_promedio_pro!AC5 -> 19.270448 | K77: =todo_corte2024_promedo_prom!AC5 -> 19.270448 | L77: =todo_corte2024_promedio_simple!AC5 -> 19.270448 | M77: 1.3323585 | N77: 1.2378186 | O77: 1.2442997 | P77: =ultimos8_corte2023_promedio!W5 -> 17735127 | Q77: =todo_corte2023_promedo_prom!W5 -> 17735127 | R77: =todo_corte2023_promedo_simple!W5 -> 17735154 | S77: =ultimos8_corte2023_promedio!Y5 -> 152.95814 | T77: =todo_corte2023_promedo_prom!Y5 -> 152.95814 | U77: =todo_corte2023_promedo_simple!Y5 -> 179.65906
C78: 3Q19 | D78: 1.2458421 | E78: 1.1711937 | F78: 1.1731658 | G78: =ultimos8_corte2024_promedio_pro!AA6 -> 11881781 | H78: =todo_corte2024_promedo_prom!AA6 -> 11881781 | I78: =todo_corte2024_promedio_simple!AA6 -> 11881781 | J78: =ultimos8_corte2024_promedio_pro!AC6 -> 19.864942 | K78: =todo_corte2024_promedo_prom!AC6 -> 19.864942 | L78: =todo_corte2024_promedio_simple!AC6 -> 19.822551 | M78: 1.2123962 | N78: 1.1598603 | O78: 1.1716266 | P78: =ultimos8_corte2023_promedio!W6 -> 11881365 | Q78: =todo_corte2023_promedo_prom!W6 -> 11881365 | R78: =todo_corte2023_promedo_simple!W6 -> 11881430 | S78: =ultimos8_corte2023_promedio!Y6 -> 460.07894 | T78: =todo_corte2023_promedo_prom!Y6 -> 460.07894 | U78: =todo_corte2023_promedo_simple!Y6 -> 525.13968
C79: 4Q19 | D79: 1.1619344 | E79: 1.122938 | F79: 1.121093 | G79: =ultimos8_corte2024_promedio_pro!AA7 -> 19461705 | H79: =todo_corte2024_promedo_prom!AA7 -> 19461705 | I79: =todo_corte2024_promedio_simple!AA7 -> 19461708 | J79: =ultimos8_corte2024_promedio_pro!AC7 -> 54.921351 | K79: =todo_corte2024_promedo_prom!AC7 -> 54.921351 | L79: =todo_corte2024_promedio_simple!AC7 -> 57.984178 | M79: 1.1410732 | N79: 1.1142898 | O79: 1.121093 | P79: =ultimos8_corte2023_promedio!W7 -> 19461881 | Q79: =todo_corte2023_promedo_prom!W7 -> 19461881 | R79: =todo_corte2023_promedo_simple!W7 -> 19462225 | S79: =ultimos8_corte2023_promedio!Y7 -> 1905.3056 | T79: =todo_corte2023_promedo_prom!Y7 -> 1905.3056 | U79: =todo_corte2023_promedo_simple!Y7 -> 2249.2536
C80: 1Q20 | D80: 1.1042248 | E80: 1.0855575 | F80: 1.0868928 | G80: =ultimos8_corte2024_promedio_pro!AA8 -> 11816242 | H80: =todo_corte2024_promedo_prom!AA8 -> 11816242 | I80: =todo_corte2024_promedio_simple!AA8 -> 11816250 | J80: =ultimos8_corte2024_promedio_pro!AC8 -> 69.088413 | K80: =todo_corte2024_promedo_prom!AC8 -> 69.088413 | L80: =todo_corte2024_promedio_simple!AC8 -> 77.462962 | M80: 1.1006614 | N80: 1.0863654 | O80: 1.0868928 | P80: =ultimos8_corte2023_promedio!W8 -> 11815026 | Q80: =todo_corte2023_promedo_prom!W8 -> 11815026 | R80: =todo_corte2023_promedo_simple!W8 -> 11815526 | S80: =ultimos8_corte2023_promedio!Y8 -> 2596.255 | T80: =todo_corte2023_promedo_prom!Y8 -> 2596.255 | U80: =todo_corte2023_promedo_simple!Y8 -> 3095.7612
C81: 2Q20 | D81: 1.1121613 | E81: 1.0800789 | F81: 1.0780719 | G81: =ultimos8_corte2024_promedio_pro!AA9 -> 13048674 | H81: =todo_corte2024_promedo_prom!AA9 -> 13048674 | I81: =todo_corte2024_promedio_simple!AA9 -> 13048689 | J81: =ultimos8_corte2024_promedio_pro!AC9 -> 202.94963 | K81: =todo_corte2024_promedo_prom!AC9 -> 202.94963 | L81: =todo_corte2024_promedio_simple!AC9 -> 217.72616 | M81: 1.0896917 | N81: 1.0708099 | O81: 1.0780719 | P81: =ultimos8_corte2023_promedio!W9 -> 13049095 | Q81: =todo_corte2023_promedo_prom!W9 -> 13049095 | R81: =todo_corte2023_promedo_simple!W9 -> 13049407 | S81: =ultimos8_corte2023_promedio!Y9 -> 7991.3833 | T81: =todo_corte2023_promedo_prom!Y9 -> 7991.3833 | U81: =todo_corte2023_promedo_simple!Y9 -> 8302.7777
C82: 3Q20 | D82: 1.0564419 | E82: 1.0582035 | F82: 1.0657467 | G82: =ultimos8_corte2024_promedio_pro!AA10 -> 10840662 | H82: =todo_corte2024_promedo_prom!AA10 -> 10840662 | I82: =todo_corte2024_promedio_simple!AA10 -> 10840690 | J82: =ultimos8_corte2024_promedio_pro!AC10 -> 522.18308 | K82: =todo_corte2024_promedo_prom!AC10 -> 522.18308 | L82: =todo_corte2024_promedio_simple!AC10 -> 550.2051 | M82: 1.0879966 | N82: 1.0647534 | O82: 1.0657467 | P82: =ultimos8_corte2023_promedio!W10 -> 10839812 | Q82: =todo_corte2023_promedo_prom!W10 -> 10839812 | R82: =todo_corte2023_promedo_simple!W10 -> 10839510 | S82: =ultimos8_corte2023_promedio!Y10 -> 14404.695 | T82: =todo_corte2023_promedo_prom!Y10 -> 14404.695 | U82: =todo_corte2023_promedo_simple!Y10 -> 14102.774
C83: 4Q20 | D83: 1.0286063 | E83: 1.0278824 | F83: 1.0288467 | G83: =ultimos8_corte2024_promedio_pro!AA11 -> 14112788 | H83: =todo_corte2024_promedo_prom!AA11 -> 14112788 | I83: =todo_corte2024_promedio_simple!AA11 -> 14112860 | J83: =ultimos8_corte2024_promedio_pro!AC11 -> 1652.4212 | K83: =todo_corte2024_promedo_prom!AC11 -> 1652.4212 | L83: =todo_corte2024_promedio_simple!AC11 -> 1723.5343 | M83: 1.0327165 | N83: 1.0294842 | O83: 1.0288467 | P83: =ultimos8_corte2023_promedio!W11 -> 14117547 | Q83: =todo_corte2023_promedo_prom!W11 -> 14117547 | R83: =todo_corte2023_promedo_simple!W11 -> 14116135 | S83: =ultimos8_corte2023_promedio!Y11 -> 38224.212 | T83: =todo_corte2023_promedo_prom!Y11 -> 38224.212 | U83: =todo_corte2023_promedo_simple!Y11 -> 36812.056
C84: 1Q21 | D84: 1.0155862 | E84: 1.0204033 | F84: 1.022405 | G84: =ultimos8_corte2024_promedio_pro!AA12 -> 15733379 | H84: =todo_corte2024_promedo_prom!AA12 -> 15733379 | I84: =todo_corte2024_promedio_simple!AA12 -> 15733559 | J84: =ultimos8_corte2024_promedio_pro!AC12 -> 4044.684 | K84: =todo_corte2024_promedo_prom!AC12 -> 4044.684 | L84: =todo_corte2024_promedio_simple!AC12 -> 4225.4334 | M84: 1.0206084 | N84: 1.0238194 | O84: 1.022405 | P84: =ultimos8_corte2023_promedio!W12 -> 15761049 | Q84: =todo_corte2023_promedo_prom!W12 -> 15761049 | R84: =todo_corte2023_promedo_simple!W12 -> 15753657 | S84: =ultimos8_corte2023_promedio!Y12 -> 91166.174 | T84: =todo_corte2023_promedo_prom!Y12 -> 91166.174 | U84: =todo_corte2023_promedo_simple!Y12 -> 83773.899
C85: 2Q21 | D85: 1.0080991 | E85: 1.0102837 | F85: 1.010486 | G85: =ultimos8_corte2024_promedio_pro!AA13 -> 14351698 | H85: =todo_corte2024_promedo_prom!AA13 -> 14352526 | I85: =todo_corte2024_promedio_simple!AA13 -> 14352822 | J85: =ultimos8_corte2024_promedio_pro!AC13 -> 8101.7825 | K85: =todo_corte2024_promedo_prom!AC13 -> 8929.6014 | L85: =todo_corte2024_promedio_simple!AC13 -> 9226.1169 | M85: 1.0108556 | N85: 1.0118084 | O85: 1.010486 | P85: =ultimos8_corte2023_promedio!W13 -> 14424266 | Q85: =todo_corte2023_promedo_prom!W13 -> 14432766 | R85: =todo_corte2023_promedo_simple!W13 -> 14403672 | S85: =ultimos8_corte2023_promedio!Y13 -> 193030.03 | T85: =todo_corte2023_promedo_prom!Y13 -> 201529.72 | U85: =todo_corte2023_promedo_simple!Y13 -> 172435.73
C86: 3Q21 | D86: 1.0038617 | E86: 1.0065619 | F86: 1.0067345 | G86: =ultimos8_corte2024_promedio_pro!AA14 -> 15137386 | H86: =todo_corte2024_promedo_prom!AA14 -> 15139464 | I86: =todo_corte2024_promedio_simple!AA14 -> 15139732 | J86: =ultimos8_corte2024_promedio_pro!AC14 -> 17451.426 | K86: =todo_corte2024_promedo_prom!AC14 -> 19528.865 | L86: =todo_corte2024_promedio_simple!AC14 -> 19796.711 | M86: 1.0077011 | N86: 1.0082949 | O86: 1.0067345 | P86: =ultimos8_corte2023_promedio!W14 -> 15227388 | Q86: =todo_corte2023_promedo_prom!W14 -> 15250722 | R86: =todo_corte2023_promedo_simple!W14 -> 15200086 | S86: =ultimos8_corte2023_promedio!Y14 -> 365116.95 | T86: =todo_corte2023_promedo_prom!Y14 -> 388451.33 | U86: =todo_corte2023_promedo_simple!Y14 -> 337815.44
C87: 4Q21 | D87: 1.0022525 | E87: 1.0027134 | F87: 1.0027244 | G87: =ultimos8_corte2024_promedio_pro!AA15 -> 18772946 | H87: =todo_corte2024_promedo_prom!AA15 -> 18778189 | I87: =todo_corte2024_promedio_simple!AA15 -> 18779119 | J87: =ultimos8_corte2024_promedio_pro!AC15 -> 42921.81 | K87: =todo_corte2024_promedo_prom!AC15 -> 48165.107 | L87: =todo_corte2024_promedio_simple!AC15 -> 49094.973 | M87: 1.0030946 | N87: 1.0030946 | O87: 1.0027244 | P87: =ultimos8_corte2023_promedio!W15 -> 19130285 | Q87: =todo_corte2023_promedo_prom!W15 -> 19219879 | R87: =todo_corte2023_promedo_simple!W15 -> 19129601 | S87: =ultimos8_corte2023_promedio!Y15 -> 835721.05 | T87: =todo_corte2023_promedo_prom!Y15 -> 925314.82 | U87: =todo_corte2023_promedo_simple!Y15 -> 835037.19
C88: 1Q22 | D88: 1.0011361 | E88: 1.0012783 | F88: 1.0013102 | G88: =ultimos8_corte2024_promedio_pro!AA16 -> 19716644 | H88: =todo_corte2024_promedo_prom!AA16 -> 19731221 | I88: =todo_corte2024_promedio_simple!AA16 -> 19732415 | J88: =ultimos8_corte2024_promedio_pro!AC16 -> 89289.649 | K88: =todo_corte2024_promedo_prom!AC16 -> 103866.61 | L88: =todo_corte2024_promedio_simple!AC16 -> 105060.58 | M88: 1.0013824 | N88: 1.0013824 | O88: 1.0013102 | P88: =ultimos8_corte2023_promedio!W16 -> 19993176 | Q88: =todo_corte2023_promedo_prom!W16 -> 20023942 | R88: =todo_corte2023_promedo_simple!W16 -> 19917545 | S88: =ultimos8_corte2023_promedio!Y16 -> 1479131.5 | T88: =todo_corte2023_promedo_prom!Y16 -> 1509897.8 | U88: =todo_corte2023_promedo_simple!Y16 -> 1403501.4
... C95: 4Q23 | D95: 1.000003 | E95: 1.000003 | F95: 1.0000036 | G95: =ultimos8_corte2024_promedio_pro!AA23 -> 29906164 | H95: =todo_corte2024_promedo_prom!AA23 -> 28876481 | I95: =todo_corte2024_promedio_simple!AA23 -> 29160926 | J95: =ultimos8_corte2024_promedio_pro!AC23 -> 8200379.3 | K95: =todo_corte2024_promedo_prom!AC23 -> 7170696 | L95: =todo_corte2024_promedio_simple!AC23 -> 7455141.3 | M95: 1 | N95: 1 | O95: 1 | P95: =ultimos8_corte2023_promedio!W23 -> 33071035 | Q95: =todo_corte2023_promedo_prom!W23 -> 23123490 | R95: =todo_corte2023_promedo_simple!W23 -> 23821914 | S95: =ultimos8_corte2023_promedio!Y23 -> 26379787 | T95: =todo_corte2023_promedo_prom!Y23 -> 16432242 | U95: =todo_corte2023_promedo_simple!Y23 -> 17130666
C96: 1Q24 | D96: 1.0000012 | E96: 1.0000012 | F96: 1.0000013 | G96: =ultimos8_corte2024_promedio_pro!AA24 -> 27705493 | H96: =todo_corte2024_promedo_prom!AA24 -> 25853754 | I96: =todo_corte2024_promedio_simple!AA24 -> 26065527 | J96: =ultimos8_corte2024_promedio_pro!AC24 -> 10399399 | K96: =todo_corte2024_promedo_prom!AC24 -> 8547660.2 | L96: =todo_corte2024_promedio_simple!AC24 -> 8759433.3
C97: 2Q24 | D97: 1.0000006 | E97: 1.0000006 | F97: 1.0000006 | G97: =ultimos8_corte2024_promedio_pro!AA25 -> 30664068 | H97: =todo_corte2024_promedo_prom!AA25 -> 26900057 | I97: =todo_corte2024_promedio_simple!AA25 -> 27166067 | J97: =ultimos8_corte2024_promedio_pro!AC25 -> 15289606 | K97: =todo_corte2024_promedo_prom!AC25 -> 11525595 | L97: =todo_corte2024_promedio_simple!AC25 -> 11791605
C98: 3Q24 | D98: 1.0000011 | E98: 1.0000011 | F98: 1.0000011 | G98: =ultimos8_corte2024_promedio_pro!AA26 -> 25053077 | H98: =todo_corte2024_promedo_prom!AA26 -> 20348760 | I98: =todo_corte2024_promedio_simple!AA26 -> 20715430 | J98: =ultimos8_corte2024_promedio_pro!AC26 -> 15731243 | K98: =todo_corte2024_promedo_prom!AC26 -> 11026926 | L98: =todo_corte2024_promedio_simple!AC26 -> 11393596
C99: 4Q24 | D99: 1 | E99: 1 | F99: 1 | G99: =ultimos8_corte2024_promedio_pro!AA27 -> 29715993 | H99: =todo_corte2024_promedo_prom!AA27 -> 18797318 | I99: =todo_corte2024_promedio_simple!AA27 -> 19222994 | J99: =ultimos8_corte2024_promedio_pro!AC27 -> 24566035 | K99: =todo_corte2024_promedo_prom!AC27 -> 13647360 | L99: =todo_corte2024_promedio_simple!AC27 -> 14073036

Sheet ultimos8_corte2024_promedio_pro
A1: CHAIN-LADDER — Triángulo Proyectado e IBNR | Vinculado a hojas 1_Triangulo y 2_Factores
A2: AZUL=observado (hoja 1) · AMARILLO=proyección CL = C_{i,j-1} × f̂_{j-1} (hoja 2) · VERDE=IBNR
A3: AO | B3: Trim. | C3: T01 | D3: T02 | E3: T03 | F3: T04 | G3: T05 | H3: T06 | I3: T07 | J3: T08 | K3: T09 | L3: T10 | M3: T11 | N3: T12 | O3: T13 | P3: T14 | Q3: T15 | R3: T16 | S3: T17 | T3: T18 | U3: T19 | V3: T20 | W3: T21 | X3: T22 | Y3: T23 | Z3: T24 | AA3: Último Proy. | AB3: Pagado Actual | AC3: IBNR CL
A4: AO01 | B4: 1Q19 | R4: =IF(Triangulo1!S16=0,"-",Triangulo1!S16) -> 14721902 | S4: =IF(Triangulo1!T16=0,"-",Triangulo1!T16) -> 14723975 | T4: =IF(Triangulo1!U16=0,"-",Triangulo1!U16) -> 14724778 | U4: =IF(Triangulo1!V16=0,"-",Triangulo1!V16) -> 14725216 | V4: =IF(Triangulo1!W16=0,"-",Triangulo1!W16) -> 14725343 | W4: =IF(Triangulo1!X16=0,"-",Triangulo1!X16) -> 14725356 | X4: =IF(Triangulo1!Y16=0,"-",Triangulo1!Y16) -> 14725361 | Y4: =IF(Triangulo1!Z16=0,"-",Triangulo1!Z16) -> 14725369 | Z4: =IF(Triangulo1!AA16=0,"-",Triangulo1!AA16) -> 14725385 | AA4: =+Z4 -> 14725385 | AB4: =+Z4 -> 14725385 | AC4: =AA4-AB4 -> 0
A5: AO02 | B5: 2Q19 | Q5: =IF(Triangulo1!R17=0,"-",Triangulo1!R17) -> 17727251 | R5: =IF(Triangulo1!S17=0,"-",Triangulo1!S17) -> 17731572 | S5: =IF(Triangulo1!T17=0,"-",Triangulo1!T17) -> 17733454 | T5: =IF(Triangulo1!U17=0,"-",Triangulo1!U17) -> 17734435 | U5: =IF(Triangulo1!V17=0,"-",Triangulo1!V17) -> 17734974 | V5: =IF(Triangulo1!W17=0,"-",Triangulo1!W17) -> 17735197 | W5: =IF(Triangulo1!X17=0,"-",Triangulo1!X17) -> 17735258 | X5: =IF(Triangulo1!Y17=0,"-",Triangulo1!Y17) -> 17735268 | Y5: =IF(Triangulo1!Z17=0,"-",Triangulo1!Z17) -> 17735279 | Z5: =+Y5*Y$30 -> 17735298 | AA5: =+Z5 -> 17735298 | AB5: =+Y5 -> 17735279 | AC5: =AA5-AB5 -> 19.270448
A6: AO03 | B6: 3Q19 | P6: =IF(Triangulo1!Q18=0,"-",Triangulo1!Q18) -> 11864201 | Q6: =IF(Triangulo1!R18=0,"-",Triangulo1!R18) -> 11873586 | R6: =IF(Triangulo1!S18=0,"-",Triangulo1!S18) -> 11878223 | S6: =IF(Triangulo1!T18=0,"-",Triangulo1!T18) -> 11880065 | T6: =IF(Triangulo1!U18=0,"-",Triangulo1!U18) -> 11880905 | U6: =IF(Triangulo1!V18=0,"-",Triangulo1!V18) -> 11881492 | V6: =IF(Triangulo1!W18=0,"-",Triangulo1!W18) -> 11881607 | W6: =IF(Triangulo1!X18=0,"-",Triangulo1!X18) -> 11881725 | X6: =IF(Triangulo1!Y18=0,"-",Triangulo1!Y18) -> 11881761 | Y6: =+X6*X$30 -> 11881768 | Z6: =+Y6*Y$30 -> 11881781 | AA6: =+Z6 -> 11881781 | AB6: =+X6 -> 11881761 | AC6: =AA6-AB6 -> 19.864942
A7: AO04 | B7: 4Q19 | O7: =IF(Triangulo1!P19=0,"-",Triangulo1!P19) -> 19426010 | P7: =IF(Triangulo1!Q19=0,"-",Triangulo1!Q19) -> 19444545 | Q7: =IF(Triangulo1!R19=0,"-",Triangulo1!R19) -> 19453256 | R7: =IF(Triangulo1!S19=0,"-",Triangulo1!S19) -> 19457999 | S7: =IF(Triangulo1!T19=0,"-",Triangulo1!T19) -> 19459976 | T7: =IF(Triangulo1!U19=0,"-",Triangulo1!U19) -> 19461146 | U7: =IF(Triangulo1!V19=0,"-",Triangulo1!V19) -> 19461559 | V7: =IF(Triangulo1!W19=0,"-",Triangulo1!W19) -> 19461649 | W7: =IF(Triangulo1!X19=0,"-",Triangulo1!X19) -> 19461650 | X7: =+W7*W$30 -> 19461672 | Y7: =+X7*X$30 -> 19461684 | Z7: =+Y7*Y$30 -> 19461705 | AA7: =+Z7 -> 19461705 | AB7: =+W7 -> 19461650 | AC7: =AA7-AB7 -> 54.921351
A8: AO05 | B8: 1Q20 | N8: =IF(Triangulo1!O20=0,"-",Triangulo1!O20) -> 11754449 | O8: =IF(Triangulo1!P20=0,"-",Triangulo1!P20) -> 11785976 | P8: =IF(Triangulo1!Q20=0,"-",Triangulo1!Q20) -> 11801623 | Q8: =IF(Triangulo1!R20=0,"-",Triangulo1!R20) -> 11808422 | R8: =IF(Triangulo1!S20=0,"-",Triangulo1!S20) -> 11812430 | S8: =IF(Triangulo1!T20=0,"-",Triangulo1!T20) -> 11814677 | T8: =IF(Triangulo1!U20=0,"-",Triangulo1!U20) -> 11815553 | U8: =IF(Triangulo1!V20=0,"-",Triangulo1!V20) -> 11815994 | V8: =IF(Triangulo1!W20=0,"-",Triangulo1!W20) -> 11816173 | W8: =+V8*V$30 -> 11816209 | X8: =+W8*W$30 -> 11816222 | Y8: =+X8*X$30 -> 11816229 | Z8: =+Y8*Y$30 -> 11816242 | AA8: =+Z8 -> 11816242 | AB8: =+V8 -> 11816173 | AC8: =AA8-AB8 -> 69.088413
A9: AO06 | B9: 2Q20 | M9: =IF(Triangulo1!N21=0,"-",Triangulo1!N21) -> 12930641 | N9: =IF(Triangulo1!O21=0,"-",Triangulo1!O21) -> 12990612 | O9: =IF(Triangulo1!P21=0,"-",Triangulo1!P21) -> 13017211 | P9: =IF(Triangulo1!Q21=0,"-",Triangulo1!Q21) -> 13032985 | Q9: =IF(Triangulo1!R21=0,"-",Triangulo1!R21) -> 13041104 | R9: =IF(Triangulo1!S21=0,"-",Triangulo1!S21) -> 13045224 | S9: =IF(Triangulo1!T21=0,"-",Triangulo1!T21) -> 13046906 | T9: =IF(Triangulo1!U21=0,"-",Triangulo1!U21) -> 13047997 | U9: =IF(Triangulo1!V21=0,"-",Triangulo1!V21) -> 13048471 | V9: =+U9*U$30 -> 13048598 | W9: =+V9*V$30 -> 13048637 | X9: =+W9*W$30 -> 13048652 | Y9: =+X9*X$30 -> 13048660 | Z9: =+Y9*Y$30 -> 13048674 | AA9: =+Z9 -> 13048674 | AB9: =+U9 -> 13048471 | AC9: =AA9-AB9 -> 202.94963
A10: AO07 | B10: 3Q20 | L10: =IF(Triangulo1!M22=0,"-",Triangulo1!M22) -> 10574369 | M10: =IF(Triangulo1!N22=0,"-",Triangulo1!N22) -> 10704764 | N10: =IF(Triangulo1!O22=0,"-",Triangulo1!O22) -> 10779530 | O10: =IF(Triangulo1!P22=0,"-",Triangulo1!P22) -> 10810916 | P10: =IF(Triangulo1!Q22=0,"-",Triangulo1!Q22) -> 10825407 | Q10: =IF(Triangulo1!R22=0,"-",Triangulo1!R22) -> 10831969 | R10: =IF(Triangulo1!S22=0,"-",Triangulo1!S22) -> 10836654 | S10: =IF(Triangulo1!T22=0,"-",Triangulo1!T22) -> 10839043 | T10: =IF(Triangulo1!U22=0,"-",Triangulo1!U22) -> 10840140 | U10: =+T10*T$30 -> 10840494 | V10: =+U10*U$30 -> 10840599 | W10: =+V10*V$30 -> 10840632 | X10: =+W10*W$30 -> 10840644 | Y10: =+X10*X$30 -> 10840650 | Z10: =+Y10*Y$30 -> 10840662 | AA10: =+Z10 -> 10840662 | AB10: =+T10 -> 10840140 | AC10: =AA10-AB10 -> 522.18308
A11: AO08 | B11: 4Q20 | K11: =IF(Triangulo1!L23=0,"-",Triangulo1!L23) -> 13586619 | L11: =IF(Triangulo1!M23=0,"-",Triangulo1!M23) -> 13861205 | M11: =IF(Triangulo1!N23=0,"-",Triangulo1!N23) -> 13987078 | N11: =IF(Triangulo1!O23=0,"-",Triangulo1!O23) -> 14043493 | O11: =IF(Triangulo1!P23=0,"-",Triangulo1!P23) -> 14079323 | P11: =IF(Triangulo1!Q23=0,"-",Triangulo1!Q23) -> 14095393 | Q11: =IF(Triangulo1!R23=0,"-",Triangulo1!R23) -> 14104571 | R11: =IF(Triangulo1!S23=0,"-",Triangulo1!S23) -> 14109322 | S11: =IF(Triangulo1!T23=0,"-",Triangulo1!T23) -> 14111136 | T11: =+S11*S$30 -> 14112109 | U11: =+T11*T$30 -> 14112569 | V11: =+U11*U$30 -> 14112706 | W11: =+V11*V$30 -> 14112749 | X11: =+W11*W$30 -> 14112765 | Y11: =+X11*X$30 -> 14112773 | Z11: =+Y11*Y$30 -> 14112788 | AA11: =+Z11 -> 14112788 | AB11: =+S11 -> 14111136 | AC11: =AA11-AB11 -> 1652.4212
A12: AO09 | B12: 1Q21 | J12: =IF(Triangulo1!K24=0,"-",Triangulo1!K24) -> 14684360 | K12: =IF(Triangulo1!L24=0,"-",Triangulo1!L24) -> 15224487 | L12: =IF(Triangulo1!M24=0,"-",Triangulo1!M24) -> 15505624 | M12: =IF(Triangulo1!N24=0,"-",Triangulo1!N24) -> 15616491 | N12: =IF(Triangulo1!O24=0,"-",Triangulo1!O24) -> 15669883 | O12: =IF(Triangulo1!P24=0,"-",Triangulo1!P24) -> 15701026 | P12: =IF(Triangulo1!Q24=0,"-",Triangulo1!Q24) -> 15717007 | Q12: =IF(Triangulo1!R24=0,"-",Triangulo1!R24) -> 15725357 | R12: =IF(Triangulo1!S24=0,"-",Triangulo1!S24) -> 15729334 | S12: =+R12*R30 -> 15731537 | T12: =+S12*S30 -> 15732621 | U12: =+T12*T30 -> 15733134 | V12: =+U12*U30 -> 15733287 | W12: =+V12*V30 -> 15733334 | X12: =+W12*W30 -> 15733352 | Y12: =+X12*X30 -> 15733362 | Z12: =+Y12*Y30 -> 15733379 | AA12: =+Z12 -> 15733379 | AB12: =+R12 -> 15729334 | AC12: =AA12-AB12 -> 4044.684
A13: AO10 | B13: 2Q21 | I13: =IF(Triangulo1!J25=0,"-",Triangulo1!J25) -> 12264947 | J13: =IF(Triangulo1!K25=0,"-",Triangulo1!K25) -> 13331758 | K13: =IF(Triangulo1!L25=0,"-",Triangulo1!L25) -> 13881470 | L13: =IF(Triangulo1!M25=0,"-",Triangulo1!M25) -> 14105853 | M13: =IF(Triangulo1!N25=0,"-",Triangulo1!N25) -> 14231236 | N13: =IF(Triangulo1!O25=0,"-",Triangulo1!O25) -> 14285043 | O13: =IF(Triangulo1!P25=0,"-",Triangulo1!P25) -> 14317196 | P13: =IF(Triangulo1!Q25=0,"-",Triangulo1!Q25) -> 14335249 | Q13: =IF(Triangulo1!R25=0,"-",Triangulo1!R25) -> 14343596 | R13: =+Q13*Q30 -> 14348008 | S13: =+R13*R30 -> 14350017 | T13: =+S13*S30 -> 14351006 | U13: =+T13*T30 -> 14351475 | V13: =+U13*U30 -> 14351614 | W13: =+V13*V30 -> 14351657 | X13: =+W13*W30 -> 14351674 | Y13: =+X13*X30 -> 14351682 | Z13: =+Y13*Y30 -> 14351698 | AA13: =+Z13 -> 14351698 | AB13: =+Q13 -> 14343596 | AC13: =AA13-AB13 -> 8101.7825
A14: AO11 | B14: 3Q21 | H14: =IF(Triangulo1!I26=0,"-",Triangulo1!I26) -> 11346897 | I14: =IF(Triangulo1!J26=0,"-",Triangulo1!J26) -> 13064544 | J14: =IF(Triangulo1!K26=0,"-",Triangulo1!K26) -> 14121948 | K14: =IF(Triangulo1!L26=0,"-",Triangulo1!L26) -> 14605429 | L14: =IF(Triangulo1!M26=0,"-",Triangulo1!M26) -> 14862271 | M14: =IF(Triangulo1!N26=0,"-",Triangulo1!N26) -> 15012968 | N14: =IF(Triangulo1!O26=0,"-",Triangulo1!O26) -> 15074585 | O14: =IF(Triangulo1!P26=0,"-",Triangulo1!P26) -> 15104696 | P14: =IF(Triangulo1!Q26=0,"-",Triangulo1!Q26) -> 15119935 | Q14: =+P14*P30 -> 15128841 | R14: =+Q14*Q30 -> 15133495 | S14: =+R14*R30 -> 15135614 | T14: =+S14*S30 -> 15136657 | U14: =+T14*T30 -> 15137151 | V14: =+U14*U30 -> 15137298 | W14: =+V14*V30 -> 15137344 | X14: =+W14*W30 -> 15137361 | ... Z14: =+Y14*Y30 -> 15137386 | AA14: =+Z14 -> 15137386 | AB14: =+P14 -> 15119935 | AC14: =AA14-AB14 -> 17451.426
A15: AO12 | B15: 4Q21 | G15: =IF(Triangulo1!H27=0,"-",Triangulo1!H27) -> 13369514 | H15: =IF(Triangulo1!I27=0,"-",Triangulo1!I27) -> 15030308 | I15: =IF(Triangulo1!J27=0,"-",Triangulo1!J27) -> 16697100 | J15: =IF(Triangulo1!K27=0,"-",Triangulo1!K27) -> 17828453 | K15: =IF(Triangulo1!L27=0,"-",Triangulo1!L27) -> 18294564 | L15: =IF(Triangulo1!M27=0,"-",Triangulo1!M27) -> 18522862 | M15: =IF(Triangulo1!N27=0,"-",Triangulo1!N27) -> 18641988 | N15: =IF(Triangulo1!O27=0,"-",Triangulo1!O27) -> 18693587 | O15: =IF(Triangulo1!P27=0,"-",Triangulo1!P27) -> 18730024 | P15: =+O15*O30 -> 18751303 | Q15: =+P15*P30 -> 18762348 | R15: =+Q15*Q30 -> 18768120 | S15: =+R15*R30 -> 18770748 | T15: =+S15*S30 -> 18772042 | U15: =+T15*T30 -> 18772654 | V15: =+U15*U30 -> 18772836 | W15: =+V15*V30 -> 18772893 | ... Z15: =+Y15*Y30 -> 18772946 | AA15: =+Z15 -> 18772946 | AB15: =+O15 -> 18730024 | AC15: =AA15-AB15 -> 42921.81
A16: AO13 | B16: 1Q22 | F16: =IF(Triangulo1!G28=0,"-",Triangulo1!G28) -> 10805763 | G16: =IF(Triangulo1!H28=0,"-",Triangulo1!H28) -> 13284336 | H16: =IF(Triangulo1!I28=0,"-",Triangulo1!I28) -> 15384835 | I16: =IF(Triangulo1!J28=0,"-",Triangulo1!J28) -> 17438864 | J16: =IF(Triangulo1!K28=0,"-",Triangulo1!K28) -> 18514044 | K16: =IF(Triangulo1!L28=0,"-",Triangulo1!L28) -> 19125680 | L16: =IF(Triangulo1!M28=0,"-",Triangulo1!M28) -> 19431036 | M16: =IF(Triangulo1!N28=0,"-",Triangulo1!N28) -> 19572822 | N16: =IF(Triangulo1!O28=0,"-",Triangulo1!O28) -> 19627354 | O16: =+N16*N30 -> 19671564 | P16: =+O16*O30 -> 19693913 | Q16: =+P16*P30 -> 19705513 | R16: =+Q16*Q30 -> 19711575 | S16: =+R16*R30 -> 19714335 | T16: =+S16*S30 -> 19715694 | U16: =+T16*T30 -> 19716337 | V16: =+U16*U30 -> 19716528 | ... Z16: =+Y16*Y30 -> 19716644 | AA16: =+Z16 -> 19716644 | AB16: =+N16 -> 19627354 | AC16: =AA16-AB16 -> 89289.649
A17: AO14 | B17: 2Q22 | E17: =IF(Triangulo1!F29=0,"-",Triangulo1!F29) -> 7974797 | F17: =IF(Triangulo1!G29=0,"-",Triangulo1!G29) -> 11597296 | G17: =IF(Triangulo1!H29=0,"-",Triangulo1!H29) -> 14585912 | H17: =IF(Triangulo1!I29=0,"-",Triangulo1!I29) -> 16285147 | I17: =IF(Triangulo1!J29=0,"-",Triangulo1!J29) -> 18338971 | J17: =IF(Triangulo1!K29=0,"-",Triangulo1!K29) -> 19214501 | K17: =IF(Triangulo1!L29=0,"-",Triangulo1!L29) -> 19700684 | L17: =IF(Triangulo1!M29=0,"-",Triangulo1!M29) -> 19926910 | M17: =IF(Triangulo1!N29=0,"-",Triangulo1!N29) -> 20049671 | N17: =+M17*M30 -> 20127097 | O17: =+N17*N30 -> 20172433 | P17: =+O17*O30 -> 20195350 | Q17: =+P17*P30 -> 20207246 | R17: =+Q17*Q30 -> 20213462 | S17: =+R17*R30 -> 20216293 | T17: =+S17*S30 -> 20217686 | U17: =+T17*T30 -> 20218345 | ... Z17: =+Y17*Y30 -> 20218660 | AA17: =+Z17 -> 20218660 | AB17: =+M17 -> 20049671 | AC17: =AA17-AB17 -> 168988.85
A18: AO15 | B18: 3Q22 | D18: =IF(Triangulo1!E30=0,"-",Triangulo1!E30) -> 4773306 | E18: =IF(Triangulo1!F30=0,"-",Triangulo1!F30) -> 8697825 | F18: =IF(Triangulo1!G30=0,"-",Triangulo1!G30) -> 12220494 | G18: =IF(Triangulo1!H30=0,"-",Triangulo1!H30) -> 14462971 | H18: =IF(Triangulo1!I30=0,"-",Triangulo1!I30) -> 16656668 | I18: =IF(Triangulo1!J30=0,"-",Triangulo1!J30) -> 19017438 | J18: =IF(Triangulo1!K30=0,"-",Triangulo1!K30) -> 19939378 | K18: =IF(Triangulo1!L30=0,"-",Triangulo1!L30) -> 20384099 | L18: =IF(Triangulo1!M30=0,"-",Triangulo1!M30) -> 20688336 | M18: =+L18*L30 -> 20855893 | N18: =+M18*M30 -> 20936432 | O18: =+N18*N30 -> 20983591 | P18: =+O18*O30 -> 21007431 | Q18: =+P18*P30 -> 21019805 | R18: =+Q18*Q30 -> 21026271 | S18: =+R18*R30 -> 21029215 | T18: =+S18*S30 -> 21030664 | ... Z18: =+Y18*Y30 -> 21031677 | AA18: =+Z18 -> 21031677 | AB18: =+L18 -> 20688336 | AC18: =AA18-AB18 -> 343341.34
A19: AO16 | B19: 4Q22 | C19: =IF(Triangulo1!D31=0,"-",Triangulo1!D31) -> 5498188 | D19: =IF(Triangulo1!E31=0,"-",Triangulo1!E31) -> 10669557 | E19: =IF(Triangulo1!F31=0,"-",Triangulo1!F31) -> 14420577 | F19: =IF(Triangulo1!G31=0,"-",Triangulo1!G31) -> 17838126 | G19: =IF(Triangulo1!H31=0,"-",Triangulo1!H31) -> 20243242 | H19: =IF(Triangulo1!I31=0,"-",Triangulo1!I31) -> 22179116 | I19: =IF(Triangulo1!J31=0,"-",Triangulo1!J31) -> 24155749 | J19: =IF(Triangulo1!K31=0,"-",Triangulo1!K31) -> 25145296 | K19: =IF(Triangulo1!L31=0,"-",Triangulo1!L31) -> 25647723 | L19: =+K19*K30 -> 26047473 | M19: =+L19*L30 -> 26258435 | N19: =+M19*M30 -> 26359837 | O19: =+N19*N30 -> 26419212 | P19: =+O19*O30 -> 26449226 | Q19: =+P19*P30 -> 26464806 | R19: =+Q19*Q30 -> 26472947 | S19: =+R19*R30 -> 26476654 | ... Z19: =+Y19*Y30 -> 26479754 | AA19: =+Z19 -> 26479754 | AB19: =+K19 -> 25647723 | AC19: =AA19-AB19 -> 832031.14
A20: AO17 | B20: 1Q23 | C20: =IF(Triangulo1!D32=0,"-",Triangulo1!D32) -> 6382667 | D20: =IF(Triangulo1!E32=0,"-",Triangulo1!E32) -> 10460689 | E20: =IF(Triangulo1!F32=0,"-",Triangulo1!F32) -> 15242265 | F20: =IF(Triangulo1!G32=0,"-",Triangulo1!G32) -> 19075882 | G20: =IF(Triangulo1!H32=0,"-",Triangulo1!H32) -> 21908553 | H20: =IF(Triangulo1!I32=0,"-",Triangulo1!I32) -> 23938666 | I20: =IF(Triangulo1!J32=0,"-",Triangulo1!J32) -> 25653115 | J20: =IF(Triangulo1!K32=0,"-",Triangulo1!K32) -> 26811464 | K20: =+J20*J30 -> 27578440 | L20: =+K20*K30 -> 28008283 | M20: =+L20*L30 -> 28235125 | N20: =+M20*M30 -> 28344161 | O20: =+N20*N30 -> 28408006 | P20: =+O20*O30 -> 28440280 | Q20: =+P20*P30 -> 28457032 | R20: =+Q20*Q30 -> 28465786 | ... Z20: =+Y20*Y30 -> 28473105 | AA20: =+Z20 -> 28473105 | AB20: =+J20 -> 26811464 | AC20: =AA20-AB20 -> 1661641.4
A21: AO18 | B21: 2Q23 | C21: =IF(Triangulo1!D33=0,"-",Triangulo1!D33) -> 3022770 | D21: =IF(Triangulo1!E33=0,"-",Triangulo1!E33) -> 7899209 | E21: =IF(Triangulo1!F33=0,"-",Triangulo1!F33) -> 11259161 | F21: =IF(Triangulo1!G33=0,"-",Triangulo1!G33) -> 14497513 | G21: =IF(Triangulo1!H33=0,"-",Triangulo1!H33) -> 17221120 | H21: =IF(Triangulo1!I33=0,"-",Triangulo1!I33) -> 19234288 | I21: =IF(Triangulo1!J33=0,"-",Triangulo1!J33) -> 21399003 | J21: =+I21*I30 -> 22606803 | K21: =+J21*J30 -> 23253500 | L21: =+K21*K30 -> 23615933 | M21: =+L21*L30 -> 23807201 | N21: =+M21*M30 -> 23899137 | O21: =+N21*N30 -> 23952970 | P21: =+O21*O30 -> 23980182 | Q21: =+P21*P30 -> 23994308 | ... Z21: =+Y21*Y30 -> 24007860 | AA21: =+Z21 -> 24007860 | AB21: =+I21 -> 21399003 | AC21: =AA21-AB21 -> 2608857.4
A22: AO19 | B22: 3Q23 | C22: =IF(Triangulo1!D34=0,"-",Triangulo1!D34) -> 6936281 | D22: =IF(Triangulo1!E34=0,"-",Triangulo1!E34) -> 21936281 | E22: =IF(Triangulo1!F34=0,"-",Triangulo1!F34) -> 25150070 | F22: =IF(Triangulo1!G34=0,"-",Triangulo1!G34) -> 28898330 | G22: =IF(Triangulo1!H34=0,"-",Triangulo1!H34) -> 31903741 | H22: =IF(Triangulo1!I34=0,"-",Triangulo1!I34) -> 33589263 | I22: =H30*H22 -> 37356679 | J22: =I30*I22 -> 39465161 | K22: =J30*J22 -> 40594112 | L22: =K30*K22 -> 41226820 | M22: =L30*L22 -> 41560721 | N22: =M30*M22 -> 41721215 | O22: =N30*N22 -> 41815192 | P22: =O30*O22 -> 41862698 | ... Z22: =Y30*Y22 -> 41911015 | AA22: =+Z22 -> 41911015 | AB22: =+H22 -> 33589263 | AC22: =AA22-AB22 -> 8321752.4
A23: AO20 | B23: 4Q23 | C23: =IF(Triangulo1!D35=0,"-",Triangulo1!D35) -> 6691248 | D23: =IF(Triangulo1!E35=0,"-",Triangulo1!E35) -> 11756013 | E23: =IF(Triangulo1!F35=0,"-",Triangulo1!F35) -> 15391294 | F23: =IF(Triangulo1!G35=0,"-",Triangulo1!G35) -> 18736499 | G23: =IF(Triangulo1!H35=0,"-",Triangulo1!H35) -> 21705785 | H23: =G30*G23 -> 23968067 | I23: =H30*H23 -> 26656357 | J23: =I30*I23 -> 28160892 | K23: =J30*J23 -> 28966470 | L23: =K30*K23 -> 29417947 | M23: =L30*L23 -> 29656207 | N23: =M30*M23 -> 29770730 | O23: =N30*N23 -> 29837788 | ... Z23: =Y30*Y23 -> 29906164 | AA23: =+Z23 -> 29906164 | AB23: =+G23 -> 21705785 | AC23: =AA23-AB23 -> 8200379.3
A24: AO21 | B24: 1Q24 | C24: =IF(Triangulo1!D36=0,"-",Triangulo1!D36) -> 4191817 | D24: =IF(Triangulo1!E36=0,"-",Triangulo1!E36) -> 9775450 | E24: =IF(Triangulo1!F36=0,"-",Triangulo1!F36) -> 14374440 | F24: =IF(Triangulo1!G36=0,"-",Triangulo1!G36) -> 17306094 | G24: =F30*F24 -> 20108546 | H24: =G30*G24 -> 22204356 | I24: =H30*H24 -> 24694826 | J24: =I30*I24 -> 26088649 | K24: =J30*J24 -> 26834948 | L24: =K30*K24 -> 27253202 | M24: =L30*L24 -> 27473929 | N24: =M30*M24 -> 27580025 | ... Z24: =Y30*Y24 -> 27705493 | AA24: =+Z24 -> 27705493 | AB24: =+F24 -> 17306094 | AC24: =AA24-AB24 -> 10399399
A25: AO22 | B25: 2Q24 | C25: =IF(Triangulo1!D37=0,"-",Triangulo1!D37) -> 5916671 | D25: =IF(Triangulo1!E37=0,"-",Triangulo1!E37) -> 11716355 | E25: =IF(Triangulo1!F37=0,"-",Triangulo1!F37) -> 15374462 | F25: =E25*E30 -> 19154153 | G25: =F25*F30 -> 22255869 | H25: =G25*G30 -> 24575483 | I25: =H25*H30 -> 27331902 | J25: =I25*I30 -> 28874566 | K25: =J25*J30 -> 29700560 | L25: =K25*K30 -> 30163479 | M25: =L25*L30 -> 30407776 | ... Z25: =Y25*Y30 -> 30664068 | AA25: =+Z25 -> 30664068 | AB25: =+E25 -> 15374462 | AC25: =AA25-AB25 -> 15289606
A26: AO23 | B26: 3Q24 | C26: =IF(Triangulo1!D38=0,"-",Triangulo1!D38) -> 4926500 | D26: =IF(Triangulo1!E38=0,"-",Triangulo1!E38) -> 9321834 | E26: =D26*D30 -> 12561203 | F26: =E26*E30 -> 15649276 | G26: =F26*F30 -> 18183432 | H26: =G26*G30 -> 20078597 | I26: =H26*H30 -> 22330639 | J26: =I26*I30 -> 23591023 | K26: =J26*J30 -> 24265874 | L26: =K26*K30 -> 24644087 | ... Z26: =Y26*Y30 -> 25053077 | AA26: =+Z26 -> 25053077 | AB26: =+D26 -> 9321834 | AC26: =AA26-AB26 -> 15731243
A27: AO24 | B27: 4Q24 | C27: =IF(Triangulo1!D39=0,"-",Triangulo1!D39) -> 5149958 | D27: =C27*C30 -> 11056828 | E27: =D27*D30 -> 14899112 | F27: =E27*E30 -> 18561942 | G27: =F27*F30 -> 21567759 | H27: =G27*G30 -> 23815655 | I27: =H27*H30 -> 26486851 | J27: =I27*I30 -> 27981819 | K27: =J27*J30 -> 28782275 | ... Z27: =Y27*Y30 -> 29715993 | AA27: =+Z27 -> 29715993 | AB27: =+C27 -> 5149958 | AC27: =AA27-AB27 -> 24566035
A28: Numerado | C28: =SUM(D19:D26) -> 93535388 | D28: =SUM(E18:E25) -> 119910094 | E28: =SUM(F17:F24) -> 140170234 | F28: =SUM(G16:G23) -> 155315660 | G28: =SUM(H15:H22) -> 162298291 | H28: =SUM(I14:I21) -> 155764784 | I28: =SUM(J13:J20) -> 154906842 | J28: =SUM(K12:K19) -> 146864136 | K28: =SUM(L11:L18) -> 136904097 | L28: =SUM(M10:M17) -> 127817018 | M28: =SUM(N9:N16) -> 121164087 | N28: =SUM(O8:O15) -> 113546368 | O28: =SUM(P7:P14) -> 114372144 | P28: =SUM(Q6:Q13) -> 111181861 | Q28: =SUM(R5:R12) -> 114600758 | R28: =SUM(S4:S11) -> 113609232 | S28: =SUM(T4:T10) -> 99504954 | T28: =SUM(U4:U9) -> 88667706 | U28: =SUM(V4:V8) -> 75619969 | V28: =SUM(W4:W7) -> 63803989 | W28: =SUM(X4:X6) -> 44342390 | X28: =SUM(Y4:Y5) -> 32460648 | Y28: =SUM(Z4) -> 14725385
A29: Denominador | C29: =SUM(C19:C26) -> 43566142 | D29: =SUM(D18:D25) -> 88986860 | E29: =SUM(E17:E24) -> 112510429 | F29: =SUM(F16:F23) -> 133669903 | G29: =SUM(G15:G22) -> 146979389 | H29: =SUM(H14:H21) -> 140055925 | I29: =SUM(I13:I20) -> 146630728 | J29: =SUM(J12:J19) -> 142779738 | K29: =SUM(K11:K18) -> 134803032 | L29: =SUM(L10:L17) -> 126790130 | M29: =SUM(M9:M16) -> 120697988 | N29: =SUM(N8:N15) -> 113291182 | O29: =SUM(O7:O14) -> 114242354 | P29: =SUM(P6:P13) -> 111116410 | Q29: =SUM(Q5:Q12) -> 114565516 | R29: =SUM(R4:R11) -> 113593326 | S29: =SUM(S4:S10) -> 99498096 | T29: =SUM(T4:T9) -> 88664814 | U29: =SUM(U4:U8) -> 75619235 | V29: =SUM(V4:V7) -> 63803796 | W29: =SUM(W4:W6) -> 44342339 | X29: =SUM(X4:X5) -> 32460629 | Y29: =SUM(Y4) -> 14725369
A30: Factores | C30: =C28/C29 -> 2.1469743 | D30: =D28/D29 -> 1.3475034 | E30: =E28/E29 -> 1.2458421 | F30: =F28/F29 -> 1.1619344 | G30: =G28/G29 -> 1.1042248 | H30: =H28/H29 -> 1.1121613 | I30: =I28/I29 -> 1.0564419 | J30: =J28/J29 -> 1.0286063 | ... Y30: =Y28/Y29 -> 1.0000011 | Z30: 1
A31: Factor acum. F_j^{→25} | C31: =+C30*D31 -> 5.7701428 | D31: =+D30*E31 -> 2.6875695 | E31: =+E30*F31 -> 1.9944807 | F31: =+F30*G31 -> 1.6009097 | G31: =+G30*H31 -> 1.3777969 | H31: =+H30*I31 -> 1.2477504 | I31: =+I30*J31 -> 1.1219149 | J31: =+J30*K31 -> 1.061975 | ... Y31: =+Y30*Z31 -> 1.0000011 | Z31: 1
A32: % Desarrollado = 1/F_j | C32: =1/C31 -> 0.17330594 | D32: =1/D31 -> 0.3720834 | E32: =1/E31 -> 0.50138363 | F32: =1/F31 -> 0.62464486 | G32: =1/G31 -> 0.72579635 | H32: =1/H31 -> 0.80144236 | I32: =1/I31 -> 0.8913332 | J32: =1/J31 -> 0.94164172 | ... Y32: =1/Y31 -> 0.99999891 | Z32: 1
A33: Total | AA33: =+SUM(AA4:AA27) -> 5.0250146e+08 | AB33: =+SUM(AB4:AB27) -> 414213831 | AC33: =SUM(AC4:AC28) -> 88287626

Sheet ultimos8_corte2023_promedio
A1: CHAIN-LADDER — Triángulo Proyectado e IBNR | Vinculado a hojas 1_Triangulo y 2_Factores
A2: AZUL=observado (hoja 1) · AMARILLO=proyección CL = C_{i,j-1} × f̂_{j-1} (hoja 2) · VERDE=IBNR
A3: AO | B3: Trim. | C3: T01 | D3: T02 | E3: T03 | F3: T04 | G3: T05 | H3: T06 | I3: T07 | J3: T08 | K3: T09 | L3: T10 | M3: T11 | N3: T12 | O3: T13 | P3: T14 | Q3: T15 | R3: T16 | S3: T17 | T3: T18 | U3: T19 | V3: T20 | W3: Último Proy. | X3: Pagado Actual | Y3: IBNR CL
A4: AO01 | B4: 1Q19 | N4: =IF(Triangulo1!O16=0,"-",Triangulo1!O16) -> 14589694 | O4: =IF(Triangulo1!P16=0,"-",Triangulo1!P16) -> 14666170 | P4: =IF(Triangulo1!Q16=0,"-",Triangulo1!Q16) -> 14699145 | Q4: =IF(Triangulo1!R16=0,"-",Triangulo1!R16) -> 14709918 | R4: =IF(Triangulo1!S16=0,"-",Triangulo1!S16) -> 14721902 | S4: =IF(Triangulo1!T16=0,"-",Triangulo1!T16) -> 14723975 | T4: =IF(Triangulo1!U16=0,"-",Triangulo1!U16) -> 14724778 | U4: =IF(Triangulo1!V16=0,"-",Triangulo1!V16) -> 14725216 | V4: =IF(Triangulo1!W16=0,"-",Triangulo1!W16) -> 14725343 | W4: =V4 -> 14725343 | X4: =V4 -> 14725343 | Y4: =W4-X4 -> 0
A5: AO02 | B5: 2Q19 | M5: =IF(Triangulo1!N17=0,"-",Triangulo1!N17) -> 17479823 | N5: =IF(Triangulo1!O17=0,"-",Triangulo1!O17) -> 17658472 | O5: =IF(Triangulo1!P17=0,"-",Triangulo1!P17) -> 17691106 | P5: =IF(Triangulo1!Q17=0,"-",Triangulo1!Q17) -> 17707511 | Q5: =IF(Triangulo1!R17=0,"-",Triangulo1!R17) -> 17727251 | R5: =IF(Triangulo1!S17=0,"-",Triangulo1!S17) -> 17731572 | S5: =IF(Triangulo1!T17=0,"-",Triangulo1!T17) -> 17733454 | T5: =IF(Triangulo1!U17=0,"-",Triangulo1!U17) -> 17734435 | U5: =IF(Triangulo1!V17=0,"-",Triangulo1!V17) -> 17734974 | V5: =U5*U$26 -> 17735127 | W5: =V5 -> 17735127 | X5: =U5 -> 17734974 | Y5: =W5-X5 -> 152.95814
A6: AO03 | B6: 3Q19 | L6: =IF(Triangulo1!M18=0,"-",Triangulo1!M18) -> 11432174 | M6: =IF(Triangulo1!N18=0,"-",Triangulo1!N18) -> 11644639 | N6: =IF(Triangulo1!O18=0,"-",Triangulo1!O18) -> 11802250 | O6: =IF(Triangulo1!P18=0,"-",Triangulo1!P18) -> 11840837 | P6: =IF(Triangulo1!Q18=0,"-",Triangulo1!Q18) -> 11864201 | Q6: =IF(Triangulo1!R18=0,"-",Triangulo1!R18) -> 11873586 | R6: =IF(Triangulo1!S18=0,"-",Triangulo1!S18) -> 11878223 | S6: =IF(Triangulo1!T18=0,"-",Triangulo1!T18) -> 11880065 | T6: =IF(Triangulo1!U18=0,"-",Triangulo1!U18) -> 11880905 | U6: =T6*T$26 -> 11881263 | V6: =U6*U$26 -> 11881365 | W6: =V6 -> 11881365 | X6: =T6 -> 11880905 | Y6: =W6-X6 -> 460.07894
A7: AO04 | B7: 4Q19 | K7: =IF(Triangulo1!L19=0,"-",Triangulo1!L19) -> 18751439 | L7: =IF(Triangulo1!M19=0,"-",Triangulo1!M19) -> 18855100 | M7: =IF(Triangulo1!N19=0,"-",Triangulo1!N19) -> 19152179 | N7: =IF(Triangulo1!O19=0,"-",Triangulo1!O19) -> 19349458 | O7: =IF(Triangulo1!P19=0,"-",Triangulo1!P19) -> 19426010 | P7: =IF(Triangulo1!Q19=0,"-",Triangulo1!Q19) -> 19444545 | Q7: =IF(Triangulo1!R19=0,"-",Triangulo1!R19) -> 19453256 | R7: =IF(Triangulo1!S19=0,"-",Triangulo1!S19) -> 19457999 | S7: =IF(Triangulo1!T19=0,"-",Triangulo1!T19) -> 19459976 | T7: =S7*S$26 -> 19461128 | U7: =T7*T$26 -> 19461713 | V7: =U7*U$26 -> 19461881 | W7: =V7 -> 19461881 | X7: =S7 -> 19459976 | Y7: =W7-X7 -> 1905.3056
A8: AO05 | B8: 1Q20 | J8: =IF(Triangulo1!K20=0,"-",Triangulo1!K20) -> 10938865 | K8: =IF(Triangulo1!L20=0,"-",Triangulo1!L20) -> 11091033 | L8: =IF(Triangulo1!M20=0,"-",Triangulo1!M20) -> 11574757 | M8: =IF(Triangulo1!N20=0,"-",Triangulo1!N20) -> 11660948 | N8: =IF(Triangulo1!O20=0,"-",Triangulo1!O20) -> 11754449 | O8: =IF(Triangulo1!P20=0,"-",Triangulo1!P20) -> 11785976 | P8: =IF(Triangulo1!Q20=0,"-",Triangulo1!Q20) -> 11801623 | Q8: =IF(Triangulo1!R20=0,"-",Triangulo1!R20) -> 11808422 | R8: =IF(Triangulo1!S20=0,"-",Triangulo1!S20) -> 11812430 | S8: =R8*R$26 -> 11813870 | T8: =S8*S$26 -> 11814569 | U8: =T8*T$26 -> 11814924 | V8: =U8*U$26 -> 11815026 | W8: =V8 -> 11815026 | X8: =R8 -> 11812430 | Y8: =W8-X8 -> 2596.255
A9: AO06 | B9: 2Q20 | I9: =IF(Triangulo1!J21=0,"-",Triangulo1!J21) -> 9082448 | J9: =IF(Triangulo1!K21=0,"-",Triangulo1!K21) -> 12082448 | K9: =IF(Triangulo1!L21=0,"-",Triangulo1!L21) -> 12687409 | L9: =IF(Triangulo1!M21=0,"-",Triangulo1!M21) -> 12838372 | M9: =IF(Triangulo1!N21=0,"-",Triangulo1!N21) -> 12930641 | N9: =IF(Triangulo1!O21=0,"-",Triangulo1!O21) -> 12990612 | O9: =IF(Triangulo1!P21=0,"-",Triangulo1!P21) -> 13017211 | P9: =IF(Triangulo1!Q21=0,"-",Triangulo1!Q21) -> 13032985 | Q9: =IF(Triangulo1!R21=0,"-",Triangulo1!R21) -> 13041104 | R9: =Q9*Q$26 -> 13046228 | S9: =R9*R$26 -> 13047818 | T9: =S9*S$26 -> 13048590 | U9: =T9*T$26 -> 13048983 | V9: =U9*U$26 -> 13049095 | W9: =V9 -> 13049095 | X9: =Q9 -> 13041104 | Y9: =W9-X9 -> 7991.3833
A10: AO07 | B10: 3Q20 | H10: =IF(Triangulo1!I22=0,"-",Triangulo1!I22) -> 8328067 | I10: =IF(Triangulo1!J22=0,"-",Triangulo1!J22) -> 9073367 | J10: =IF(Triangulo1!K22=0,"-",Triangulo1!K22) -> 9580777 | K10: =IF(Triangulo1!L22=0,"-",Triangulo1!L22) -> 10084545 | L10: =IF(Triangulo1!M22=0,"-",Triangulo1!M22) -> 10574369 | M10: =IF(Triangulo1!N22=0,"-",Triangulo1!N22) -> 10704764 | N10: =IF(Triangulo1!O22=0,"-",Triangulo1!O22) -> 10779530 | O10: =IF(Triangulo1!P22=0,"-",Triangulo1!P22) -> 10810916 | P10: =IF(Triangulo1!Q22=0,"-",Triangulo1!Q22) -> 10825407 | Q10: =P10*P$26 -> 10833173 | R10: =Q10*Q$26 -> 10837430 | S10: =R10*R$26 -> 10838750 | T10: =S10*S$26 -> 10839392 | U10: =T10*T$26 -> 10839718 | V10: =U10*U$26 -> 10839812 | W10: =V10 -> 10839812 | X10: =P10 -> 10825407 | Y10: =W10-X10 -> 14404.695
A11: AO08 | B11: 4Q20 | G11: =IF(Triangulo1!H23=0,"-",Triangulo1!H23) -> 11791969 | H11: =IF(Triangulo1!I23=0,"-",Triangulo1!I23) -> 12446387 | I11: =IF(Triangulo1!J23=0,"-",Triangulo1!J23) -> 12820241 | J11: =IF(Triangulo1!K23=0,"-",Triangulo1!K23) -> 13419392 | K11: =IF(Triangulo1!L23=0,"-",Triangulo1!L23) -> 13586619 | L11: =IF(Triangulo1!M23=0,"-",Triangulo1!M23) -> 13861205 | M11: =IF(Triangulo1!N23=0,"-",Triangulo1!N23) -> 13987078 | N11: =IF(Triangulo1!O23=0,"-",Triangulo1!O23) -> 14043493 | O11: =IF(Triangulo1!P23=0,"-",Triangulo1!P23) -> 14079323 | P11: =O11*O$26 -> 14098787 | Q11: =P11*P$26 -> 14108901 | R11: =Q11*Q$26 -> 14114445 | S11: =R11*R$26 -> 14116165 | T11: =S11*S$26 -> 14117001 | U11: =T11*T$26 -> 14117425 | V11: =U11*U$26 -> 14117547 | W11: =V11 -> 14117547 | X11: =O11 -> 14079323 | Y11: =W11-X11 -> 38224.212
A12: AO09 | B12: 1Q21 | F12: =IF(Triangulo1!G24=0,"-",Triangulo1!G24) -> 12328713 | G12: =IF(Triangulo1!H24=0,"-",Triangulo1!H24) -> 12743016 | H12: =IF(Triangulo1!I24=0,"-",Triangulo1!I24) -> 13716063 | I12: =IF(Triangulo1!J24=0,"-",Triangulo1!J24) -> 13936735 | J12: =IF(Triangulo1!K24=0,"-",Triangulo1!K24) -> 14684360 | K12: =IF(Triangulo1!L24=0,"-",Triangulo1!L24) -> 15224487 | L12: =IF(Triangulo1!M24=0,"-",Triangulo1!M24) -> 15505624 | M12: =IF(Triangulo1!N24=0,"-",Triangulo1!N24) -> 15616491 | N12: =IF(Triangulo1!O24=0,"-",Triangulo1!O24) -> 15669883 | O12: =N12*N$26 -> 15718375 | P12: =O12*O$26 -> 15740105 | Q12: =P12*P$26 -> 15751397 | R12: =Q12*Q$26 -> 15757586 | S12: =R12*R$26 -> 15759506 | T12: =S12*S$26 -> 15760439 | U12: =T12*T$26 -> 15760913 | V12: =U12*U$26 -> 15761049 | W12: =V12 -> 15761049 | X12: =N12 -> 15669883 | Y12: =W12-X12 -> 91166.174
A13: AO10 | B13: 2Q21 | E13: =IF(Triangulo1!F25=0,"-",Triangulo1!F25) -> 8942057 | F13: =IF(Triangulo1!G25=0,"-",Triangulo1!G25) -> 10413724 | G13: =IF(Triangulo1!H25=0,"-",Triangulo1!H25) -> 11109326 | H13: =IF(Triangulo1!I25=0,"-",Triangulo1!I25) -> 11743877 | I13: =IF(Triangulo1!J25=0,"-",Triangulo1!J25) -> 12264947 | J13: =IF(Triangulo1!K25=0,"-",Triangulo1!K25) -> 13331758 | K13: =IF(Triangulo1!L25=0,"-",Triangulo1!L25) -> 13881470 | L13: =IF(Triangulo1!M25=0,"-",Triangulo1!M25) -> 14105853 | M13: =IF(Triangulo1!N25=0,"-",Triangulo1!N25) -> 14231236 | N13: =M13*M$26 -> 14340832 | O13: =N13*N$26 -> 14385211 | P13: =O13*O$26 -> 14405098 | Q13: =P13*P$26 -> 14415432 | R13: =Q13*Q$26 -> 14421096 | S13: =R13*R$26 -> 14422854 | T13: =S13*S$26 -> 14423707 | U13: =T13*T$26 -> 14424142 | V13: =U13*U$26 -> 14424266 | W13: =V13 -> 14424266 | X13: =M13 -> 14231236 | Y13: =W13-X13 -> 193030.03
A14: AO11 | B14: 3Q21 | D14: =IF(Triangulo1!E26=0,"-",Triangulo1!E26) -> 7741218 | E14: =IF(Triangulo1!F26=0,"-",Triangulo1!F26) -> 9386858 | F14: =IF(Triangulo1!G26=0,"-",Triangulo1!G26) -> 9734366 | G14: =IF(Triangulo1!H26=0,"-",Triangulo1!H26) -> 10964336 | H14: =IF(Triangulo1!I26=0,"-",Triangulo1!I26) -> 11346897 | I14: =IF(Triangulo1!J26=0,"-",Triangulo1!J26) -> 13064544 | J14: =IF(Triangulo1!K26=0,"-",Triangulo1!K26) -> 14121948 | K14: =IF(Triangulo1!L26=0,"-",Triangulo1!L26) -> 14605429 | L14: =IF(Triangulo1!M26=0,"-",Triangulo1!M26) -> 14862271 | M14: =L14*L$26 -> 15023610 | N14: =M14*M$26 -> 15139309 | O14: =N14*N$26 -> 15186159 | P14: =O14*O$26 -> 15207153 | Q14: =P14*P$26 -> 15218063 | R14: =Q14*Q$26 -> 15224042 | S14: =R14*R$26 -> 15225897 | T14: =S14*S$26 -> 15226798 | ... V14: =U14*U$26 -> 15227388 | W14: =V14 -> 15227388 | X14: =L14 -> 14862271 | Y14: =W14-X14 -> 365116.95
A15: AO12 | B15: 4Q21 | C15: =IF(Triangulo1!D27=0,"-",Triangulo1!D27) -> 6500694 | D15: =IF(Triangulo1!E27=0,"-",Triangulo1!E27) -> 9436157 | E15: =IF(Triangulo1!F27=0,"-",Triangulo1!F27) -> 11552953 | F15: =IF(Triangulo1!G27=0,"-",Triangulo1!G27) -> 12130358 | G15: =IF(Triangulo1!H27=0,"-",Triangulo1!H27) -> 13369514 | H15: =IF(Triangulo1!I27=0,"-",Triangulo1!I27) -> 15030308 | I15: =IF(Triangulo1!J27=0,"-",Triangulo1!J27) -> 16697100 | J15: =IF(Triangulo1!K27=0,"-",Triangulo1!K27) -> 17828453 | K15: =IF(Triangulo1!L27=0,"-",Triangulo1!L27) -> 18294564 | L15: =K15*K$26 -> 18671586 | M15: =L15*L$26 -> 18874278 | N15: =M15*M$26 -> 19019630 | O15: =N15*N$26 -> 19078489 | P15: =O15*O$26 -> 19104863 | Q15: =P15*P$26 -> 19118569 | R15: =Q15*Q$26 -> 19126081 | S15: =R15*R$26 -> 19128412 | ... V15: =U15*U$26 -> 19130285 | W15: =V15 -> 19130285 | X15: =K15 -> 18294564 | Y15: =W15-X15 -> 835721.05
A16: AO13 | B16: 1Q22 | C16: =IF(Triangulo1!D28=0,"-",Triangulo1!D28) -> 5205434 | D16: =IF(Triangulo1!E28=0,"-",Triangulo1!E28) -> 7752400 | E16: =IF(Triangulo1!F28=0,"-",Triangulo1!F28) -> 9411446 | F16: =IF(Triangulo1!G28=0,"-",Triangulo1!G28) -> 10805763 | G16: =IF(Triangulo1!H28=0,"-",Triangulo1!H28) -> 13284336 | H16: =IF(Triangulo1!I28=0,"-",Triangulo1!I28) -> 15384835 | I16: =IF(Triangulo1!J28=0,"-",Triangulo1!J28) -> 17438864 | J16: =IF(Triangulo1!K28=0,"-",Triangulo1!K28) -> 18514044 | K16: =J16*J$26 -> 19119758 | L16: =K16*K$26 -> 19513786 | M16: =L16*L$26 -> 19725621 | N16: =M16*M$26 -> 19877530 | O16: =N16*N$26 -> 19939043 | P16: =O16*O$26 -> 19966607 | Q16: =P16*P$26 -> 19980932 | R16: =Q16*Q$26 -> 19988782 | ... V16: =U16*U$26 -> 19993176 | W16: =V16 -> 19993176 | X16: =J16 -> 18514044 | Y16: =W16-X16 -> 1479131.5
A17: AO14 | B17: 2Q22 | C17: =IF(Triangulo1!D29=0,"-",Triangulo1!D29) -> 5184519 | D17: =IF(Triangulo1!E29=0,"-",Triangulo1!E29) -> 7275135 | E17: =IF(Triangulo1!F29=0,"-",Triangulo1!F29) -> 7974797 | F17: =IF(Triangulo1!G29=0,"-",Triangulo1!G29) -> 11597296 | G17: =IF(Triangulo1!H29=0,"-",Triangulo1!H29) -> 14585912 | H17: =IF(Triangulo1!I29=0,"-",Triangulo1!I29) -> 16285147 | I17: =IF(Triangulo1!J29=0,"-",Triangulo1!J29) -> 18338971 | J17: =I17*I$26 -> 19952739 | K17: =J17*J$26 -> 20605522 | L17: =K17*K$26 -> 21030169 | M17: =L17*L$26 -> 21258465 | N17: =M17*M$26 -> 21422178 | O17: =N17*N$26 -> 21488472 | P17: =O17*O$26 -> 21518178 | Q17: =P17*P$26 -> 21533616 | ... V17: =U17*U$26 -> 21546811 | W17: =V17 -> 21546811 | X17: =I17 -> 18338971 | Y17: =W17-X17 -> 3207840
A18: AO15 | B18: 3Q22 | C18: =IF(Triangulo1!D30=0,"-",Triangulo1!D30) -> 3419011 | D18: =IF(Triangulo1!E30=0,"-",Triangulo1!E30) -> 4773306 | E18: =IF(Triangulo1!F30=0,"-",Triangulo1!F30) -> 8697825 | F18: =IF(Triangulo1!G30=0,"-",Triangulo1!G30) -> 12220494 | G18: =IF(Triangulo1!H30=0,"-",Triangulo1!H30) -> 14462971 | H18: =IF(Triangulo1!I30=0,"-",Triangulo1!I30) -> 16656668 | I18: =H18*H$26 -> 18150632 | J18: =I18*I$26 -> 19747827 | K18: =J18*J$26 -> 20393906 | L18: =K18*K$26 -> 20814192 | M18: =L18*L$26 -> 21040143 | N18: =M18*M$26 -> 21202175 | O18: =N18*N$26 -> 21267788 | P18: =O18*O$26 -> 21297189 | ... V18: =U18*U$26 -> 21325528 | W18: =V18 -> 21325528 | X18: =H18 -> 16656668 | Y18: =W18-X18 -> 4668860.1
A19: AO16 | B19: 4Q22 | C19: =IF(Triangulo1!D31=0,"-",Triangulo1!D31) -> 5498188 | D19: =IF(Triangulo1!E31=0,"-",Triangulo1!E31) -> 10669557 | E19: =IF(Triangulo1!F31=0,"-",Triangulo1!F31) -> 14420577 | F19: =IF(Triangulo1!G31=0,"-",Triangulo1!G31) -> 17838126 | G19: =IF(Triangulo1!H31=0,"-",Triangulo1!H31) -> 20243242 | H19: =G19*G$26 -> 22280954 | I19: =H19*H$26 -> 24279370 | J19: =I19*I$26 -> 26415873 | K19: =J19*J$26 -> 27280107 | L19: =K19*K$26 -> 27842307 | M19: =L19*L$26 -> 28144552 | N19: =M19*M$26 -> 28361296 | O19: =N19*N$26 -> 28449063 | ... V19: =U19*U$26 -> 28526300 | W19: =V19 -> 28526300 | X19: =G19 -> 20243242 | Y19: =W19-X19 -> 8283058.3
A20: AO17 | B20: 1Q23 | C20: =IF(Triangulo1!D32=0,"-",Triangulo1!D32) -> 6382667 | D20: =IF(Triangulo1!E32=0,"-",Triangulo1!E32) -> 10460689 | E20: =IF(Triangulo1!F32=0,"-",Triangulo1!F32) -> 15242265 | F20: =IF(Triangulo1!G32=0,"-",Triangulo1!G32) -> 19075882 | G20: =F20*F$26 -> 21766978 | H20: =G20*G$26 -> 23958071 | I20: =H20*H$26 -> 26106911 | J20: =I20*I$26 -> 28404231 | K20: =J20*J$26 -> 29333517 | L20: =K20*K$26 -> 29938034 | M20: =L20*L$26 -> 30263031 | N20: =M20*M$26 -> 30496089 | ... V20: =U20*U$26 -> 30673513 | W20: =V20 -> 30673513 | X20: =F20 -> 19075882 | Y20: =W20-X20 -> 11597631
A21: AO18 | B21: 2Q23 | C21: =IF(Triangulo1!D33=0,"-",Triangulo1!D33) -> 3022770 | D21: =IF(Triangulo1!E33=0,"-",Triangulo1!E33) -> 7899209 | E21: =IF(Triangulo1!F33=0,"-",Triangulo1!F33) -> 11259161 | F21: =E21*E$26 -> 13650565 | G21: =F21*F$26 -> 15576294 | H21: =G21*G$26 -> 17144224 | I21: =H21*H$26 -> 18681918 | J21: =I21*I$26 -> 20325864 | K21: =J21*J$26 -> 20990855 | L21: =K21*K$26 -> 21423443 | M21: =L21*L$26 -> 21656008 | ... V21: =U21*U$26 -> 21949746 | W21: =V21 -> 21949746 | X21: =E21 -> 11259161 | Y21: =W21-X21 -> 10690585
A22: AO19 | B22: 3Q23 | C22: =IF(Triangulo1!D34=0,"-",Triangulo1!D34) -> 6936281 | D22: =IF(Triangulo1!E34=0,"-",Triangulo1!E34) -> 21936281 | E22: =D22*D$26 -> 29226991 | F22: =E22*E$26 -> 35434694 | G22: =F22*F$26 -> 40433580 | H22: =G22*G$26 -> 44503679 | I22: =H22*H$26 -> 48495287 | J22: =I22*I$26 -> 52762709 | K22: =J22*J$26 -> 54488920 | L22: =K22*K$26 -> 55611850 | ... V22: =U22*U$26 -> 56978049 | W22: =V22 -> 56978049 | X22: =D22 -> 21936281 | Y22: =W22-X22 -> 35041768
A23: AO20 | B23: 4Q23 | C23: =IF(Triangulo1!D35=0,"-",Triangulo1!D35) -> 6691248 | D23: =C23*C$26 -> 12732193 | E23: =D23*D$26 -> 16963846 | F23: =E23*E$26 -> 20566903 | G23: =F23*F$26 -> 23468342 | H23: =G23*G$26 -> 25830697 | I23: =H23*H$26 -> 28147495 | J23: =I23*I$26 -> 30624380 | K23: =J23*J$26 -> 31626302 | ... V23: =U23*U$26 -> 33071035 | W23: =V23 -> 33071035 | X23: =C23 -> 6691248 | Y23: =W23-X23 -> 26379787
A24: Numerado | C24: =SUM(D15:D22) -> 80202734 | D24: =SUM(E14:E21) -> 87945882 | E24: =SUM(F13:F20) -> 103816009 | F24: =SUM(G12:G19) -> 110762653 | G24: =SUM(H11:H18) -> 112610182 | H24: =SUM(I10:I17) -> 113634769 | I24: =SUM(J9:J16) -> 113563180 | J24: =SUM(K8:K15) -> 109455556 | K24: =SUM(L7:L14) -> 112177551 | L24: =SUM(M6:M13) -> 109927976 | M24: =SUM(N5:N12) -> 114048147 | N24: =SUM(O4:O11) -> 113317549 | O24: =SUM(P4:P10) -> 99375417 | P24: =SUM(Q4:Q9) -> 88613537 | Q24: =SUM(R4:R8) -> 75602126 | R24: =SUM(S4:S7) -> 63797470 | S24: =SUM(T4:T6) -> 44340118 | T24: =SUM(U4:U5) -> 32460190 | U24: =SUM(V4) -> 14725343 | V24: =V4 -> 14725343
A25: Denominador | C25: =SUM(C15:C22) -> 42149564 | D25: =SUM(D14:D21) -> 66007671 | E25: =SUM(E13:E20) -> 85628778 | F25: =SUM(F12:F19) -> 97068840 | G25: =SUM(G11:G18) -> 102311380 | H25: =SUM(H10:H17) -> 104281581 | I25: =SUM(I9:I16) -> 104378246 | J25: =SUM(J8:J15) -> 105988001 | K25: =SUM(K7:K14) -> 109912431 | L25: =SUM(L6:L13) -> 108747454 | M25: =SUM(M5:M12) -> 113176563 | N25: =SUM(N4:N11) -> 112967958 | O25: =SUM(O4:O10) -> 99238226 | P25: =SUM(P4:P9) -> 88550010 | Q25: =SUM(Q4:Q8) -> 75572433 | R25: =SUM(R4:R7) -> 63789696 | S25: =SUM(S4:S6) -> 44337494 | T25: =SUM(T4:T5) -> 32459213 | U25: =SUM(U4) -> 14725216 | V25: =SUM(V4) -> 14725343
A26: Factores | C26: =C24/C25 -> 1.9028129 | D26: =D24/D25 -> 1.3323585 | E26: =E24/E25 -> 1.2123962 | F26: =F24/F25 -> 1.1410732 | G26: =G24/G25 -> 1.1006614 | H26: =H24/H25 -> 1.0896917 | I26: =I24/I25 -> 1.0879966 | J26: =J24/J25 -> 1.0327165 | ... V26: =V24/V25 -> 1
A27: Total | W27: =+SUM(W4:W23) -> 4.1223234e+08 | X27: =+SUM(X4:X23) -> 309332913 | Y27: =SUM(Y4:Y24) -> 1.0289943e+08

Sheet todo_corte2024_promedo_prom
A1: CHAIN-LADDER — Triángulo Proyectado e IBNR | Vinculado a hojas 1_Triangulo y 2_Factores
A2: AZUL=observado (hoja 1) · AMARILLO=proyección CL = C_{i,j-1} × f̂_{j-1} (hoja 2) · VERDE=IBNR
A3: AO | B3: Trim. | C3: T01 | D3: T02 | E3: T03 | F3: T04 | G3: T05 | H3: T06 | I3: T07 | J3: T08 | K3: T09 | L3: T10 | M3: T11 | N3: T12 | O3: T13 | P3: T14 | Q3: T15 | R3: T16 | S3: T17 | T3: T18 | U3: T19 | V3: T20 | W3: T21 | X3: T22 | Y3: T23 | Z3: T24 | AA3: Último Proy. | AB3: Pagado Actual | AC3: IBNR CL
A4: AO01 | B4: 1Q19 | C4: =IF(Triangulo1!D16=0,"-",Triangulo1!D16) -> 6418198 | D4: =IF(Triangulo1!E16=0,"-",Triangulo1!E16) -> 8351947 | E4: =IF(Triangulo1!F16=0,"-",Triangulo1!F16) -> 9393090 | F4: =IF(Triangulo1!G16=0,"-",Triangulo1!G16) -> 11183194 | G4: =IF(Triangulo1!H16=0,"-",Triangulo1!H16) -> 12100800 | H4: =IF(Triangulo1!I16=0,"-",Triangulo1!I16) -> 12721118 | I4: =IF(Triangulo1!J16=0,"-",Triangulo1!J16) -> 13073728 | J4: =IF(Triangulo1!K16=0,"-",Triangulo1!K16) -> 13548698 | ... Z4: =IF(Triangulo1!AA16=0,"-",Triangulo1!AA16) -> 14725385 | AA4: =+Z4 -> 14725385 | AB4: =+Z4 -> 14725385 | AC4: =AA4-AB4 -> 0
A5: AO02 | B5: 2Q19 | C5: =IF(Triangulo1!D17=0,"-",Triangulo1!D17) -> 7475822 | D5: =IF(Triangulo1!E17=0,"-",Triangulo1!E17) -> 10450029 | E5: =IF(Triangulo1!F17=0,"-",Triangulo1!F17) -> 12515657 | F5: =IF(Triangulo1!G17=0,"-",Triangulo1!G17) -> 13149304 | G5: =IF(Triangulo1!H17=0,"-",Triangulo1!H17) -> 14417681 | H5: =IF(Triangulo1!I17=0,"-",Triangulo1!I17) -> 15145227 | I5: =IF(Triangulo1!J17=0,"-",Triangulo1!J17) -> 15971980 | J5: =IF(Triangulo1!K17=0,"-",Triangulo1!K17) -> 16442175 | ... Y5: =IF(Triangulo1!Z17=0,"-",Triangulo1!Z17) -> 17735279 | Z5: =+Y5*Y$30 -> 17735298 | AA5: =+Z5 -> 17735298 | AB5: =+Y5 -> 17735279 | AC5: =AA5-AB5 -> 19.270448
A6: AO03 | B6: 3Q19 | C6: =IF(Triangulo1!D18=0,"-",Triangulo1!D18) -> 4944676 | D6: =IF(Triangulo1!E18=0,"-",Triangulo1!E18) -> 5651989 | E6: =IF(Triangulo1!F18=0,"-",Triangulo1!F18) -> 6603749 | F6: =IF(Triangulo1!G18=0,"-",Triangulo1!G18) -> 7627857 | G6: =IF(Triangulo1!H18=0,"-",Triangulo1!H18) -> 8503366 | H6: =IF(Triangulo1!I18=0,"-",Triangulo1!I18) -> 9687265 | I6: =IF(Triangulo1!J18=0,"-",Triangulo1!J18) -> 10329156 | J6: =IF(Triangulo1!K18=0,"-",Triangulo1!K18) -> 10705380 | ... X6: =IF(Triangulo1!Y18=0,"-",Triangulo1!Y18) -> 11881761 | Y6: =+X6*X$30 -> 11881768 | Z6: =+Y6*Y$30 -> 11881781 | AA6: =+Z6 -> 11881781 | AB6: =+X6 -> 11881761 | AC6: =AA6-AB6 -> 19.864942
A7: AO04 | B7: 4Q19 | C7: =IF(Triangulo1!D19=0,"-",Triangulo1!D19) -> 5990844 | D7: =IF(Triangulo1!E19=0,"-",Triangulo1!E19) -> 12990844 | E7: =IF(Triangulo1!F19=0,"-",Triangulo1!F19) -> 14795084 | F7: =IF(Triangulo1!G19=0,"-",Triangulo1!G19) -> 15558421 | G7: =IF(Triangulo1!H19=0,"-",Triangulo1!H19) -> 16698078 | H7: =IF(Triangulo1!I19=0,"-",Triangulo1!I19) -> 17591115 | I7: =IF(Triangulo1!J19=0,"-",Triangulo1!J19) -> 17858613 | J7: =IF(Triangulo1!K19=0,"-",Triangulo1!K19) -> 18161498 | ... W7: =IF(Triangulo1!X19=0,"-",Triangulo1!X19) -> 19461650 | X7: =+W7*W$30 -> 19461672 | Y7: =+X7*X$30 -> 19461684 | Z7: =+Y7*Y$30 -> 19461705 | AA7: =+Z7 -> 19461705 | AB7: =+W7 -> 19461650 | AC7: =AA7-AB7 -> 54.921351
A8: AO05 | B8: 1Q20 | C8: =IF(Triangulo1!D20=0,"-",Triangulo1!D20) -> 6106533 | D8: =IF(Triangulo1!E20=0,"-",Triangulo1!E20) -> 7227067 | E8: =IF(Triangulo1!F20=0,"-",Triangulo1!F20) -> 8316481 | F8: =IF(Triangulo1!G20=0,"-",Triangulo1!G20) -> 8778769 | G8: =IF(Triangulo1!H20=0,"-",Triangulo1!H20) -> 9616196 | H8: =IF(Triangulo1!I20=0,"-",Triangulo1!I20) -> 9944940 | I8: =IF(Triangulo1!J20=0,"-",Triangulo1!J20) -> 10596973 | J8: =IF(Triangulo1!K20=0,"-",Triangulo1!K20) -> 10938865 | ... V8: =IF(Triangulo1!W20=0,"-",Triangulo1!W20) -> 11816173 | W8: =+V8*V$30 -> 11816209 | X8: =+W8*W$30 -> 11816222 | Y8: =+X8*X$30 -> 11816229 | Z8: =+Y8*Y$30 -> 11816242 | AA8: =+Z8 -> 11816242 | AB8: =+V8 -> 11816173 | AC8: =AA8-AB8 -> 69.088413
A9: AO06 | B9: 2Q20 | C9: =IF(Triangulo1!D21=0,"-",Triangulo1!D21) -> 3511339 | D9: =IF(Triangulo1!E21=0,"-",Triangulo1!E21) -> 5097855 | E9: =IF(Triangulo1!F21=0,"-",Triangulo1!F21) -> 6037374 | F9: =IF(Triangulo1!G21=0,"-",Triangulo1!G21) -> 6436248 | G9: =IF(Triangulo1!H21=0,"-",Triangulo1!H21) -> 7366573 | H9: =IF(Triangulo1!I21=0,"-",Triangulo1!I21) -> 8575992 | I9: =IF(Triangulo1!J21=0,"-",Triangulo1!J21) -> 9082448 | J9: =IF(Triangulo1!K21=0,"-",Triangulo1!K21) -> 12082448 | ... U9: =IF(Triangulo1!V21=0,"-",Triangulo1!V21) -> 13048471 | V9: =+U9*U$30 -> 13048598 | W9: =+V9*V$30 -> 13048637 | X9: =+W9*W$30 -> 13048652 | Y9: =+X9*X$30 -> 13048660 | Z9: =+Y9*Y$30 -> 13048674 | AA9: =+Z9 -> 13048674 | AB9: =+U9 -> 13048471 | AC9: =AA9-AB9 -> 202.94963
A10: AO07 | B10: 3Q20 | C10: =IF(Triangulo1!D22=0,"-",Triangulo1!D22) -> 4141271 | D10: =IF(Triangulo1!E22=0,"-",Triangulo1!E22) -> 5675304 | E10: =IF(Triangulo1!F22=0,"-",Triangulo1!F22) -> 6514051 | F10: =IF(Triangulo1!G22=0,"-",Triangulo1!G22) -> 7799341 | G10: =IF(Triangulo1!H22=0,"-",Triangulo1!H22) -> 8118940 | H10: =IF(Triangulo1!I22=0,"-",Triangulo1!I22) -> 8328067 | I10: =IF(Triangulo1!J22=0,"-",Triangulo1!J22) -> 9073367 | J10: =IF(Triangulo1!K22=0,"-",Triangulo1!K22) -> 9580777 | ... T10: =IF(Triangulo1!U22=0,"-",Triangulo1!U22) -> 10840140 | U10: =+T10*T$30 -> 10840494 | V10: =+U10*U$30 -> 10840599 | W10: =+V10*V$30 -> 10840632 | X10: =+W10*W$30 -> 10840644 | Y10: =+X10*X$30 -> 10840650 | Z10: =+Y10*Y$30 -> 10840662 | AA10: =+Z10 -> 10840662 | AB10: =+T10 -> 10840140 | AC10: =AA10-AB10 -> 522.18308
A11: AO08 | B11: 4Q20 | C11: =IF(Triangulo1!D23=0,"-",Triangulo1!D23) -> 6591656 | D11: =IF(Triangulo1!E23=0,"-",Triangulo1!E23) -> 9149839 | E11: =IF(Triangulo1!F23=0,"-",Triangulo1!F23) -> 9876574 | F11: =IF(Triangulo1!G23=0,"-",Triangulo1!G23) -> 11324778 | G11: =IF(Triangulo1!H23=0,"-",Triangulo1!H23) -> 11791969 | H11: =IF(Triangulo1!I23=0,"-",Triangulo1!I23) -> 12446387 | I11: =IF(Triangulo1!J23=0,"-",Triangulo1!J23) -> 12820241 | J11: =IF(Triangulo1!K23=0,"-",Triangulo1!K23) -> 13419392 | ... S11: =IF(Triangulo1!T23=0,"-",Triangulo1!T23) -> 14111136 | T11: =+S11*S$30 -> 14112109 | U11: =+T11*T$30 -> 14112569 | V11: =+U11*U$30 -> 14112706 | W11: =+V11*V$30 -> 14112749 | X11: =+W11*W$30 -> 14112765 | Y11: =+X11*X$30 -> 14112773 | Z11: =+Y11*Y$30 -> 14112788 | AA11: =+Z11 -> 14112788 | AB11: =+S11 -> 14111136 | AC11: =AA11-AB11 -> 1652.4212
A12: AO09 | B12: 1Q21 | C12: =IF(Triangulo1!D24=0,"-",Triangulo1!D24) -> 6289704 | D12: =IF(Triangulo1!E24=0,"-",Triangulo1!E24) -> 9074583 | E12: =IF(Triangulo1!F24=0,"-",Triangulo1!F24) -> 11031640 | F12: =IF(Triangulo1!G24=0,"-",Triangulo1!G24) -> 12328713 | G12: =IF(Triangulo1!H24=0,"-",Triangulo1!H24) -> 12743016 | H12: =IF(Triangulo1!I24=0,"-",Triangulo1!I24) -> 13716063 | I12: =IF(Triangulo1!J24=0,"-",Triangulo1!J24) -> 13936735 | J12: =IF(Triangulo1!K24=0,"-",Triangulo1!K24) -> 14684360 | ... R12: =IF(Triangulo1!S24=0,"-",Triangulo1!S24) -> 15729334 | S12: =+R12*R30 -> 15731537 | T12: =+S12*S30 -> 15732621 | U12: =+T12*T30 -> 15733134 | V12: =+U12*U30 -> 15733287 | W12: =+V12*V30 -> 15733334 | X12: =+W12*W30 -> 15733352 | Y12: =+X12*X30 -> 15733362 | Z12: =+Y12*Y30 -> 15733379 | AA12: =+Z12 -> 15733379 | AB12: =+R12 -> 15729334 | AC12: =AA12-AB12 -> 4044.684
A13: AO10 | B13: 2Q21 | C13: =IF(Triangulo1!D25=0,"-",Triangulo1!D25) -> 4959185 | D13: =IF(Triangulo1!E25=0,"-",Triangulo1!E25) -> 7332815 | E13: =IF(Triangulo1!F25=0,"-",Triangulo1!F25) -> 8942057 | F13: =IF(Triangulo1!G25=0,"-",Triangulo1!G25) -> 10413724 | G13: =IF(Triangulo1!H25=0,"-",Triangulo1!H25) -> 11109326 | H13: =IF(Triangulo1!I25=0,"-",Triangulo1!I25) -> 11743877 | I13: =IF(Triangulo1!J25=0,"-",Triangulo1!J25) -> 12264947 | J13: =IF(Triangulo1!K25=0,"-",Triangulo1!K25) -> 13331758 | ... Q13: =IF(Triangulo1!R25=0,"-",Triangulo1!R25) -> 14343596 | R13: =+Q13*Q30 -> 14348836 | S13: =+R13*R30 -> 14350845 | T13: =+S13*S30 -> 14351834 | U13: =+T13*T30 -> 14352302 | V13: =+U13*U30 -> 14352442 | W13: =+V13*V30 -> 14352485 | X13: =+W13*W30 -> 14352502 | Y13: =+X13*X30 -> 14352510 | Z13: =+Y13*Y30 -> 14352526 | AA13: =+Z13 -> 14352526 | AB13: =+Q13 -> 14343596 | AC13: =AA13-AB13 -> 8929.6014
A14: AO11 | B14: 3Q21 | C14: =IF(Triangulo1!D26=0,"-",Triangulo1!D26) -> 6194048 | D14: =IF(Triangulo1!E26=0,"-",Triangulo1!E26) -> 7741218 | E14: =IF(Triangulo1!F26=0,"-",Triangulo1!F26) -> 9386858 | F14: =IF(Triangulo1!G26=0,"-",Triangulo1!G26) -> 9734366 | G14: =IF(Triangulo1!H26=0,"-",Triangulo1!H26) -> 10964336 | H14: =IF(Triangulo1!I26=0,"-",Triangulo1!I26) -> 11346897 | I14: =IF(Triangulo1!J26=0,"-",Triangulo1!J26) -> 13064544 | J14: =IF(Triangulo1!K26=0,"-",Triangulo1!K26) -> 14121948 | ... P14: =IF(Triangulo1!Q26=0,"-",Triangulo1!Q26) -> 15119935 | Q14: =+P14*P30 -> 15130045 | R14: =+Q14*Q30 -> 15135572 | S14: =+R14*R30 -> 15137691 | T14: =+S14*S30 -> 15138735 | U14: =+T14*T30 -> 15139228 | V14: =+U14*U30 -> 15139375 | W14: =+V14*V30 -> 15139421 | X14: =+W14*W30 -> 15139439 | ... Z14: =+Y14*Y30 -> 15139464 | AA14: =+Z14 -> 15139464 | AB14: =+P14 -> 15119935 | AC14: =AA14-AB14 -> 19528.865
A15: AO12 | B15: 4Q21 | C15: =IF(Triangulo1!D27=0,"-",Triangulo1!D27) -> 6500694 | D15: =IF(Triangulo1!E27=0,"-",Triangulo1!E27) -> 9436157 | E15: =IF(Triangulo1!F27=0,"-",Triangulo1!F27) -> 11552953 | F15: =IF(Triangulo1!G27=0,"-",Triangulo1!G27) -> 12130358 | G15: =IF(Triangulo1!H27=0,"-",Triangulo1!H27) -> 13369514 | H15: =IF(Triangulo1!I27=0,"-",Triangulo1!I27) -> 15030308 | I15: =IF(Triangulo1!J27=0,"-",Triangulo1!J27) -> 16697100 | J15: =IF(Triangulo1!K27=0,"-",Triangulo1!K27) -> 17828453 | ... O15: =IF(Triangulo1!P27=0,"-",Triangulo1!P27) -> 18730024 | P15: =+O15*O30 -> 18753967 | Q15: =+P15*P30 -> 18766506 | R15: =+Q15*Q30 -> 18773362 | S15: =+R15*R30 -> 18775990 | T15: =+S15*S30 -> 18777285 | U15: =+T15*T30 -> 18777897 | V15: =+U15*U30 -> 18778079 | W15: =+V15*V30 -> 18778136 | ... Z15: =+Y15*Y30 -> 18778189 | AA15: =+Z15 -> 18778189 | AB15: =+O15 -> 18730024 | AC15: =AA15-AB15 -> 48165.107
A16: AO13 | B16: 1Q22 | C16: =IF(Triangulo1!D28=0,"-",Triangulo1!D28) -> 5205434 | D16: =IF(Triangulo1!E28=0,"-",Triangulo1!E28) -> 7752400 | E16: =IF(Triangulo1!F28=0,"-",Triangulo1!F28) -> 9411446 | F16: =IF(Triangulo1!G28=0,"-",Triangulo1!G28) -> 10805763 | G16: =IF(Triangulo1!H28=0,"-",Triangulo1!H28) -> 13284336 | H16: =IF(Triangulo1!I28=0,"-",Triangulo1!I28) -> 15384835 | I16: =IF(Triangulo1!J28=0,"-",Triangulo1!J28) -> 17438864 | J16: =IF(Triangulo1!K28=0,"-",Triangulo1!K28) -> 18514044 | ... N16: =IF(Triangulo1!O28=0,"-",Triangulo1!O28) -> 19627354 | O16: =+N16*N30 -> 19680611 | P16: =+O16*O30 -> 19705769 | Q16: =+P16*P30 -> 19718945 | R16: =+Q16*Q30 -> 19726148 | S16: =+R16*R30 -> 19728910 | T16: =+S16*S30 -> 19730270 | U16: =+T16*T30 -> 19730914 | V16: =+U16*U30 -> 19731105 | ... Z16: =+Y16*Y30 -> 19731221 | AA16: =+Z16 -> 19731221 | AB16: =+N16 -> 19627354 | AC16: =AA16-AB16 -> 103866.61
A17: AO14 | B17: 2Q22 | C17: =IF(Triangulo1!D29=0,"-",Triangulo1!D29) -> 5184519 | D17: =IF(Triangulo1!E29=0,"-",Triangulo1!E29) -> 7275135 | E17: =IF(Triangulo1!F29=0,"-",Triangulo1!F29) -> 7974797 | F17: =IF(Triangulo1!G29=0,"-",Triangulo1!G29) -> 11597296 | G17: =IF(Triangulo1!H29=0,"-",Triangulo1!H29) -> 14585912 | H17: =IF(Triangulo1!I29=0,"-",Triangulo1!I29) -> 16285147 | I17: =IF(Triangulo1!J29=0,"-",Triangulo1!J29) -> 18338971 | J17: =IF(Triangulo1!K29=0,"-",Triangulo1!K29) -> 19214501 | ... M17: =IF(Triangulo1!N29=0,"-",Triangulo1!N29) -> 20049671 | N17: =+M17*M30 -> 20181234 | O17: =+N17*N30 -> 20235994 | P17: =+O17*O30 -> 20261862 | Q17: =+P17*P30 -> 20275409 | R17: =+Q17*Q30 -> 20282816 | S17: =+R17*R30 -> 20285656 | T17: =+S17*S30 -> 20287054 | U17: =+T17*T30 -> 20287716 | ... Z17: =+Y17*Y30 -> 20288032 | AA17: =+Z17 -> 20288032 | AB17: =+M17 -> 20049671 | AC17: =AA17-AB17 -> 238360.74
A18: AO15 | B18: 3Q22 | C18: =IF(Triangulo1!D30=0,"-",Triangulo1!D30) -> 3419011 | D18: =IF(Triangulo1!E30=0,"-",Triangulo1!E30) -> 4773306 | E18: =IF(Triangulo1!F30=0,"-",Triangulo1!F30) -> 8697825 | F18: =IF(Triangulo1!G30=0,"-",Triangulo1!G30) -> 12220494 | G18: =IF(Triangulo1!H30=0,"-",Triangulo1!H30) -> 14462971 | H18: =IF(Triangulo1!I30=0,"-",Triangulo1!I30) -> 16656668 | I18: =IF(Triangulo1!J30=0,"-",Triangulo1!J30) -> 19017438 | J18: =IF(Triangulo1!K30=0,"-",Triangulo1!K30) -> 19939378 | ... L18: =IF(Triangulo1!M30=0,"-",Triangulo1!M30) -> 20688336 | M18: =+L18*L30 -> 20901089 | N18: =+M18*M30 -> 21038239 | O18: =+N18*N30 -> 21095324 | P18: =+O18*O30 -> 21122290 | Q18: =+P18*P30 -> 21136413 | R18: =+Q18*Q30 -> 21144135 | S18: =+R18*R30 -> 21147095 | T18: =+S18*S30 -> 21148553 | ... Z18: =+Y18*Y30 -> 21149572 | AA18: =+Z18 -> 21149572 | AB18: =+L18 -> 20688336 | AC18: =AA18-AB18 -> 461235.75
A19: AO16 | B19: 4Q22 | C19: =IF(Triangulo1!D31=0,"-",Triangulo1!D31) -> 5498188 | D19: =IF(Triangulo1!E31=0,"-",Triangulo1!E31) -> 10669557 | E19: =IF(Triangulo1!F31=0,"-",Triangulo1!F31) -> 14420577 | F19: =IF(Triangulo1!G31=0,"-",Triangulo1!G31) -> 17838126 | G19: =IF(Triangulo1!H31=0,"-",Triangulo1!H31) -> 20243242 | H19: =IF(Triangulo1!I31=0,"-",Triangulo1!I31) -> 22179116 | I19: =IF(Triangulo1!J31=0,"-",Triangulo1!J31) -> 24155749 | J19: =IF(Triangulo1!K31=0,"-",Triangulo1!K31) -> 25145296 | K19: =IF(Triangulo1!L31=0,"-",Triangulo1!L31) -> 25647723 | L19: =+K19*K30 -> 26171020 | M19: =+L19*L30 -> 26440156 | N19: =+M19*M30 -> 26613652 | O19: =+N19*N30 -> 26685866 | P19: =+O19*O30 -> 26719978 | Q19: =+P19*P30 -> 26737844 | R19: =+Q19*Q30 -> 26747612 | S19: =+R19*R30 -> 26751357 | ... Z19: =+Y19*Y30 -> 26754490 | AA19: =+Z19 -> 26754490 | AB19: =+K19 -> 25647723 | AC19: =AA19-AB19 -> 1106766.6
A20: AO17 | B20: 1Q23 | C20: =IF(Triangulo1!D32=0,"-",Triangulo1!D32) -> 6382667 | D20: =IF(Triangulo1!E32=0,"-",Triangulo1!E32) -> 10460689 | E20: =IF(Triangulo1!F32=0,"-",Triangulo1!F32) -> 15242265 | F20: =IF(Triangulo1!G32=0,"-",Triangulo1!G32) -> 19075882 | G20: =IF(Triangulo1!H32=0,"-",Triangulo1!H32) -> 21908553 | H20: =IF(Triangulo1!I32=0,"-",Triangulo1!I32) -> 23938666 | I20: =IF(Triangulo1!J32=0,"-",Triangulo1!J32) -> 25653115 | J20: =IF(Triangulo1!K32=0,"-",Triangulo1!K32) -> 26811464 | K20: =+J20*J30 -> 27559031 | L20: =+K20*K30 -> 28121325 | M20: =+L20*L30 -> 28410517 | N20: =+M20*M30 -> 28596943 | O20: =+N20*N30 -> 28674538 | P20: =+O20*O30 -> 28711192 | Q20: =+P20*P30 -> 28730390 | R20: =+Q20*Q30 -> 28740885 | ... Z20: =+Y20*Y30 -> 28748276 | AA20: =+Z20 -> 28748276 | AB20: =+J20 -> 26811464 | AC20: =AA20-AB20 -> 1936811.6
A21: AO18 | B21: 2Q23 | C21: =IF(Triangulo1!D33=0,"-",Triangulo1!D33) -> 3022770 | D21: =IF(Triangulo1!E33=0,"-",Triangulo1!E33) -> 7899209 | E21: =IF(Triangulo1!F33=0,"-",Triangulo1!F33) -> 11259161 | F21: =IF(Triangulo1!G33=0,"-",Triangulo1!G33) -> 14497513 | G21: =IF(Triangulo1!H33=0,"-",Triangulo1!H33) -> 17221120 | H21: =IF(Triangulo1!I33=0,"-",Triangulo1!I33) -> 19234288 | I21: =IF(Triangulo1!J33=0,"-",Triangulo1!J33) -> 21399003 | J21: =+I21*I30 -> 22644499 | K21: =+J21*J30 -> 23275882 | L21: =+K21*K30 -> 23750785 | M21: =+L21*L30 -> 23995032 | N21: =+M21*M30 -> 24152484 | O21: =+N21*N30 -> 24218019 | P21: =+O21*O30 -> 24248977 | Q21: =+P21*P30 -> 24265191 | ... Z21: =+Y21*Y30 -> 24280297 | AA21: =+Z21 -> 24280297 | AB21: =+I21 -> 21399003 | AC21: =AA21-AB21 -> 2881293.9
A22: AO19 | B22: 3Q23 | C22: =IF(Triangulo1!D34=0,"-",Triangulo1!D34) -> 6936281 | D22: =IF(Triangulo1!E34=0,"-",Triangulo1!E34) -> 21936281 | E22: =IF(Triangulo1!F34=0,"-",Triangulo1!F34) -> 25150070 | F22: =IF(Triangulo1!G34=0,"-",Triangulo1!G34) -> 28898330 | G22: =IF(Triangulo1!H34=0,"-",Triangulo1!H34) -> 31903741 | H22: =IF(Triangulo1!I34=0,"-",Triangulo1!I34) -> 33589263 | I22: =H30*H22 -> 36279055 | J22: =I30*I22 -> 38390622 | K22: =J30*J22 -> 39461044 | L22: =K30*K22 -> 40266178 | M22: =L30*L22 -> 40680263 | N22: =M30*M22 -> 40947201 | O22: =N30*N22 -> 41058308 | P22: =O30*O22 -> 41110793 | ... Z22: =Y30*Y22 -> 41163891 | AA22: =+Z22 -> 41163891 | AB22: =+H22 -> 33589263 | AC22: =AA22-AB22 -> 7574628.3
A23: AO20 | B23: 4Q23 | C23: =IF(Triangulo1!D35=0,"-",Triangulo1!D35) -> 6691248 | D23: =IF(Triangulo1!E35=0,"-",Triangulo1!E35) -> 11756013 | E23: =IF(Triangulo1!F35=0,"-",Triangulo1!F35) -> 15391294 | F23: =IF(Triangulo1!G35=0,"-",Triangulo1!G35) -> 18736499 | G23: =IF(Triangulo1!H35=0,"-",Triangulo1!H35) -> 21705785 | H23: =G30*G23 -> 23562877 | I23: =H30*H23 -> 25449767 | J23: =I30*I23 -> 26931032 | K23: =J30*J23 -> 27681933 | L23: =K30*K23 -> 28246735 | M23: =L30*L23 -> 28537216 | N23: =M30*M23 -> 28724473 | O23: =N30*N23 -> 28802414 | ... Z23: =Y30*Y23 -> 28876481 | AA23: =+Z23 -> 28876481 | AB23: =+G23 -> 21705785 | AC23: =AA23-AB23 -> 7170696
A24: AO21 | B24: 1Q24 | C24: =IF(Triangulo1!D36=0,"-",Triangulo1!D36) -> 4191817 | D24: =IF(Triangulo1!E36=0,"-",Triangulo1!E36) -> 9775450 | E24: =IF(Triangulo1!F36=0,"-",Triangulo1!F36) -> 14374440 | F24: =IF(Triangulo1!G36=0,"-",Triangulo1!G36) -> 17306094 | G24: =F30*F24 -> 19433671 | H24: =G30*G24 -> 21096367 | I24: =H30*H24 -> 22785741 | J24: =I30*I24 -> 24111951 | K24: =J30*J24 -> 24784249 | L24: =K30*K24 -> 25289928 | M24: =L30*L24 -> 25550003 | N24: =M30*M24 -> 25717658 | ... Z24: =Y30*Y24 -> 25853754 | AA24: =+Z24 -> 25853754 | AB24: =+F24 -> 17306094 | AC24: =AA24-AB24 -> 8547660.2
A25: AO22 | B25: 2Q24 | C25: =IF(Triangulo1!D37=0,"-",Triangulo1!D37) -> 5916671 | D25: =IF(Triangulo1!E37=0,"-",Triangulo1!E37) -> 11716355 | E25: =IF(Triangulo1!F37=0,"-",Triangulo1!F37) -> 15374462 | F25: =E25*E30 -> 18006472 | G25: =F25*F30 -> 20220152 | H25: =G25*G30 -> 21950138 | I25: =H25*H30 -> 23707881 | J25: =I25*I30 -> 25087762 | K25: =J25*J30 -> 25787268 | L25: =K25*K30 -> 26313413 | M25: =L25*L30 -> 26584012 | ... Z25: =Y25*Y30 -> 26900057 | AA25: =+Z25 -> 26900057 | AB25: =+E25 -> 15374462 | AC25: =AA25-AB25 -> 11525595
A26: AO23 | B26: 3Q24 | C26: =IF(Triangulo1!D38=0,"-",Triangulo1!D38) -> 4926500 | D26: =IF(Triangulo1!E38=0,"-",Triangulo1!E38) -> 9321834 | E26: =D26*D30 -> 11630133 | F26: =E26*E30 -> 13621138 | G26: =F26*F30 -> 15295694 | H26: =G26*G30 -> 16604355 | I26: =H26*H30 -> 17934014 | J26: =I26*I30 -> 18977836 | K26: =J26*J30 -> 19506982 | L26: =K26*K30 -> 19904989 | ... Z26: =Y26*Y30 -> 20348760 | AA26: =+Z26 -> 20348760 | AB26: =+D26 -> 9321834 | AC26: =AA26-AB26 -> 11026926
A27: AO24 | B27: 4Q24 | C27: =IF(Triangulo1!D39=0,"-",Triangulo1!D39) -> 5149958 | D27: =C27*C30 -> 8611113.3 | E27: =D27*D30 -> 10743422 | F27: =E27*E30 -> 12582627 | G27: =F27*F30 -> 14129511 | H27: =G27*G30 -> 15338396 | I27: =H27*H30 -> 16566678 | J27: =I27*I30 -> 17530916 | K27: =J27*J30 -> 18019720 | ... Z27: =Y27*Y30 -> 18797318 | AA27: =+Z27 -> 18797318 | AB27: =+C27 -> 5149958 | AC27: =AA27-AB27 -> 13647360
A28: Numerado | C28: =SUM(D4:D26) -> 211515876 | D28: =SUM(E4:E25) -> 252261905 | E28: =SUM(F4:F24) -> 277441070 | F28: =SUM(G4:G23) -> 292115455 | G28: =SUM(H4:H22) -> 293545239 | H28: =SUM(I4:I21) -> 280772972 | I28: =SUM(J4:J20) -> 274470435 | J28: =SUM(K4:K19) -> 254564289 | K28: =SUM(L4:L18) -> 233587211 | L28: =SUM(M4:M17) -> 215088266 | M28: =SUM(N4:N16) -> 196318410 | N28: =SUM(O4:O15) -> 177170491 | O28: =SUM(P4:P14) -> 158643001 | P28: =SUM(Q4:Q13) -> 143619030 | Q28: =SUM(R4:R12) -> 129322660 | R28: =SUM(S4:S11) -> 113609232 | S28: =SUM(T4:T10) -> 99504954 | T28: =SUM(U4:U9) -> 88667706 | U28: =SUM(V4:V8) -> 75619969 | V28: =SUM(W4:W7) -> 63803989 | W28: =SUM(X4:X6) -> 44342390 | X28: =SUM(Y4:Y5) -> 32460648 | Y28: =SUM(Z4) -> 14725385
A29: Denominador | C29: =SUM(C4:C26) -> 126499076 | D29: =SUM(D4:D25) -> 202194042 | E29: =SUM(E4:E24) -> 236887443 | F29: =SUM(F4:F23) -> 260134976 | G29: =SUM(G4:G22) -> 270409670 | H29: =SUM(H4:H21) -> 259955976 | I29: =SUM(I4:I20) -> 259373969 | J29: =SUM(J4:J19) -> 247658971 | K29: =SUM(K4:K18) -> 228916566 | L29: =SUM(L4:L17) -> 212898875 | M29: =SUM(M4:M16) -> 195038595 | N29: =SUM(N4:N15) -> 176691056 | O29: =SUM(O4:O14) -> 158440467 | P29: =SUM(P4:P13) -> 143523066 | Q29: =SUM(Q4:Q12) -> 129275434 | R29: =SUM(R4:R11) -> 113593326 | S29: =SUM(S4:S10) -> 99498096 | T29: =SUM(T4:T9) -> 88664814 | U29: =SUM(U4:U8) -> 75619235 | V29: =SUM(V4:V7) -> 63803796 | W29: =SUM(W4:W6) -> 44342339 | X29: =SUM(X4:X5) -> 32460629 | Y29: =SUM(Y4) -> 14725369
A30: Factores | C30: =C28/C29 -> 1.6720745 | D30: =D28/D29 -> 1.2476228 | E30: =E28/E29 -> 1.1711937 | F30: =F28/F29 -> 1.122938 | G30: =G28/G29 -> 1.0855575 | H30: =H28/H29 -> 1.0800789 | I30: =I28/I29 -> 1.0582035 | J30: =J28/J29 -> 1.0278824 | ... Y30: =Y28/Y29 -> 1.0000011 | Z30: 1
A31: Factor acum. F_j^{→25} | C31: =+C30*D31 -> 3.6499944 | D31: =+D30*E31 -> 2.1829138 | E31: =+E30*F31 -> 1.7496584 | F31: =+F30*G31 -> 1.4939104 | G31: =+G30*H31 -> 1.3303587 | H31: =+H30*I31 -> 1.2255074 | I31: =+I30*J31 -> 1.1346462 | J31: =+J30*K31 -> 1.0722382 | ... Y31: =+Y30*Z31 -> 1.0000011 | Z31: 1
A32: % Desarrollado = 1/F_j | C32: =1/C31 -> 0.27397302 | D32: =1/D31 -> 0.4581033 | E32: =1/E31 -> 0.57154013 | F32: =1/F31 -> 0.66938418 | G32: =1/G31 -> 0.75167694 | H32: =1/H31 -> 0.81598853 | I32: =1/I31 -> 0.88133201 | J32: =1/J31 -> 0.9326286 | ... Y32: =1/Y31 -> 0.99999891 | Z32: 1
A33: Total | AA33: =+SUM(AA4:AA27) -> 4.8051824e+08 | AB33: =+SUM(AB4:AB27) -> 414213831 | AC33: =SUM(AC4:AC28) -> 66304409

Sheet todo_corte2023_promedo_prom
A1: CHAIN-LADDER — Triángulo Proyectado e IBNR | Vinculado a hojas 1_Triangulo y 2_Factores
A2: AZUL=observado (hoja 1) · AMARILLO=proyección CL = C_{i,j-1} × f̂_{j-1} (hoja 2) · VERDE=IBNR
A3: AO | B3: Trim. | C3: T01 | D3: T02 | E3: T03 | F3: T04 | G3: T05 | H3: T06 | I3: T07 | J3: T08 | K3: T09 | L3: T10 | M3: T11 | N3: T12 | O3: T13 | P3: T14 | Q3: T15 | R3: T16 | S3: T17 | T3: T18 | U3: T19 | V3: T20 | W3: Último Proy. | X3: Pagado Actual | Y3: IBNR CL
A4: AO01 | B4: 1Q19 | C4: =IF(Triangulo1!D16=0,"-",Triangulo1!D16) -> 6418198 | D4: =IF(Triangulo1!E16=0,"-",Triangulo1!E16) -> 8351947 | E4: =IF(Triangulo1!F16=0,"-",Triangulo1!F16) -> 9393090 | F4: =IF(Triangulo1!G16=0,"-",Triangulo1!G16) -> 11183194 | G4: =IF(Triangulo1!H16=0,"-",Triangulo1!H16) -> 12100800 | H4: =IF(Triangulo1!I16=0,"-",Triangulo1!I16) -> 12721118 | I4: =IF(Triangulo1!J16=0,"-",Triangulo1!J16) -> 13073728 | J4: =IF(Triangulo1!K16=0,"-",Triangulo1!K16) -> 13548698 | ... V4: =IF(Triangulo1!W16=0,"-",Triangulo1!W16) -> 14725343 | W4: =V4 -> 14725343 | X4: =V4 -> 14725343 | Y4: =W4-X4 -> 0
A5: AO02 | B5: 2Q19 | C5: =IF(Triangulo1!D17=0,"-",Triangulo1!D17) -> 7475822 | D5: =IF(Triangulo1!E17=0,"-",Triangulo1!E17) -> 10450029 | E5: =IF(Triangulo1!F17=0,"-",Triangulo1!F17) -> 12515657 | F5: =IF(Triangulo1!G17=0,"-",Triangulo1!G17) -> 13149304 | G5: =IF(Triangulo1!H17=0,"-",Triangulo1!H17) -> 14417681 | H5: =IF(Triangulo1!I17=0,"-",Triangulo1!I17) -> 15145227 | I5: =IF(Triangulo1!J17=0,"-",Triangulo1!J17) -> 15971980 | J5: =IF(Triangulo1!K17=0,"-",Triangulo1!K17) -> 16442175 | ... U5: =IF(Triangulo1!V17=0,"-",Triangulo1!V17) -> 17734974 | V5: =U5*U$26 -> 17735127 | W5: =V5 -> 17735127 | X5: =U5 -> 17734974 | Y5: =W5-X5 -> 152.95814
A6: AO03 | B6: 3Q19 | C6: =IF(Triangulo1!D18=0,"-",Triangulo1!D18) -> 4944676 | D6: =IF(Triangulo1!E18=0,"-",Triangulo1!E18) -> 5651989 | E6: =IF(Triangulo1!F18=0,"-",Triangulo1!F18) -> 6603749 | F6: =IF(Triangulo1!G18=0,"-",Triangulo1!G18) -> 7627857 | G6: =IF(Triangulo1!H18=0,"-",Triangulo1!H18) -> 8503366 | H6: =IF(Triangulo1!I18=0,"-",Triangulo1!I18) -> 9687265 | I6: =IF(Triangulo1!J18=0,"-",Triangulo1!J18) -> 10329156 | J6: =IF(Triangulo1!K18=0,"-",Triangulo1!K18) -> 10705380 | ... T6: =IF(Triangulo1!U18=0,"-",Triangulo1!U18) -> 11880905 | U6: =T6*T$26 -> 11881263 | V6: =U6*U$26 -> 11881365 | W6: =V6 -> 11881365 | X6: =T6 -> 11880905 | Y6: =W6-X6 -> 460.07894
A7: AO04 | B7: 4Q19 | C7: =IF(Triangulo1!D19=0,"-",Triangulo1!D19) -> 5990844 | D7: =IF(Triangulo1!E19=0,"-",Triangulo1!E19) -> 12990844 | E7: =IF(Triangulo1!F19=0,"-",Triangulo1!F19) -> 14795084 | F7: =IF(Triangulo1!G19=0,"-",Triangulo1!G19) -> 15558421 | G7: =IF(Triangulo1!H19=0,"-",Triangulo1!H19) -> 16698078 | H7: =IF(Triangulo1!I19=0,"-",Triangulo1!I19) -> 17591115 | I7: =IF(Triangulo1!J19=0,"-",Triangulo1!J19) -> 17858613 | J7: =IF(Triangulo1!K19=0,"-",Triangulo1!K19) -> 18161498 | ... S7: =IF(Triangulo1!T19=0,"-",Triangulo1!T19) -> 19459976 | T7: =S7*S$26 -> 19461128 | U7: =T7*T$26 -> 19461713 | V7: =U7*U$26 -> 19461881 | W7: =V7 -> 19461881 | X7: =S7 -> 19459976 | Y7: =W7-X7 -> 1905.3056
A8: AO05 | B8: 1Q20 | C8: =IF(Triangulo1!D20=0,"-",Triangulo1!D20) -> 6106533 | D8: =IF(Triangulo1!E20=0,"-",Triangulo1!E20) -> 7227067 | E8: =IF(Triangulo1!F20=0,"-",Triangulo1!F20) -> 8316481 | F8: =IF(Triangulo1!G20=0,"-",Triangulo1!G20) -> 8778769 | G8: =IF(Triangulo1!H20=0,"-",Triangulo1!H20) -> 9616196 | H8: =IF(Triangulo1!I20=0,"-",Triangulo1!I20) -> 9944940 | I8: =IF(Triangulo1!J20=0,"-",Triangulo1!J20) -> 10596973 | J8: =IF(Triangulo1!K20=0,"-",Triangulo1!K20) -> 10938865 | ... R8: =IF(Triangulo1!S20=0,"-",Triangulo1!S20) -> 11812430 | S8: =R8*R$26 -> 11813870 | T8: =S8*S$26 -> 11814569 | U8: =T8*T$26 -> 11814924 | V8: =U8*U$26 -> 11815026 | W8: =V8 -> 11815026 | X8: =R8 -> 11812430 | Y8: =W8-X8 -> 2596.255
A9: AO06 | B9: 2Q20 | C9: =IF(Triangulo1!D21=0,"-",Triangulo1!D21) -> 3511339 | D9: =IF(Triangulo1!E21=0,"-",Triangulo1!E21) -> 5097855 | E9: =IF(Triangulo1!F21=0,"-",Triangulo1!F21) -> 6037374 | F9: =IF(Triangulo1!G21=0,"-",Triangulo1!G21) -> 6436248 | G9: =IF(Triangulo1!H21=0,"-",Triangulo1!H21) -> 7366573 | H9: =IF(Triangulo1!I21=0,"-",Triangulo1!I21) -> 8575992 | I9: =IF(Triangulo1!J21=0,"-",Triangulo1!J21) -> 9082448 | J9: =IF(Triangulo1!K21=0,"-",Triangulo1!K21) -> 12082448 | ... Q9: =IF(Triangulo1!R21=0,"-",Triangulo1!R21) -> 13041104 | R9: =Q9*Q$26 -> 13046228 | S9: =R9*R$26 -> 13047818 | T9: =S9*S$26 -> 13048590 | U9: =T9*T$26 -> 13048983 | V9: =U9*U$26 -> 13049095 | W9: =V9 -> 13049095 | X9: =Q9 -> 13041104 | Y9: =W9-X9 -> 7991.3833
A10: AO07 | B10: 3Q20 | C10: =IF(Triangulo1!D22=0,"-",Triangulo1!D22) -> 4141271 | D10: =IF(Triangulo1!E22=0,"-",Triangulo1!E22) -> 5675304 | E10: =IF(Triangulo1!F22=0,"-",Triangulo1!F22) -> 6514051 | F10: =IF(Triangulo1!G22=0,"-",Triangulo1!G22) -> 7799341 | G10: =IF(Triangulo1!H22=0,"-",Triangulo1!H22) -> 8118940 | H10: =IF(Triangulo1!I22=0,"-",Triangulo1!I22) -> 8328067 | I10: =IF(Triangulo1!J22=0,"-",Triangulo1!J22) -> 9073367 | J10: =IF(Triangulo1!K22=0,"-",Triangulo1!K22) -> 9580777 | ... P10: =IF(Triangulo1!Q22=0,"-",Triangulo1!Q22) -> 10825407 | Q10: =P10*P$26 -> 10833173 | R10: =Q10*Q$26 -> 10837430 | S10: =R10*R$26 -> 10838750 | T10: =S10*S$26 -> 10839392 | U10: =T10*T$26 -> 10839718 | V10: =U10*U$26 -> 10839812 | W10: =V10 -> 10839812 | X10: =P10 -> 10825407 | Y10: =W10-X10 -> 14404.695
A11: AO08 | B11: 4Q20 | C11: =IF(Triangulo1!D23=0,"-",Triangulo1!D23) -> 6591656 | D11: =IF(Triangulo1!E23=0,"-",Triangulo1!E23) -> 9149839 | E11: =IF(Triangulo1!F23=0,"-",Triangulo1!F23) -> 9876574 | F11: =IF(Triangulo1!G23=0,"-",Triangulo1!G23) -> 11324778 | G11: =IF(Triangulo1!H23=0,"-",Triangulo1!H23) -> 11791969 | H11: =IF(Triangulo1!I23=0,"-",Triangulo1!I23) -> 12446387 | I11: =IF(Triangulo1!J23=0,"-",Triangulo1!J23) -> 12820241 | J11: =IF(Triangulo1!K23=0,"-",Triangulo1!K23) -> 13419392 | ... O11: =IF(Triangulo1!P23=0,"-",Triangulo1!P23) -> 14079323 | P11: =O11*O$26 -> 14098787 | Q11: =P11*P$26 -> 14108901 | R11: =Q11*Q$26 -> 14114445 | S11: =R11*R$26 -> 14116165 | T11: =S11*S$26 -> 14117001 | U11: =T11*T$26 -> 14117425 | V11: =U11*U$26 -> 14117547 | W11: =V11 -> 14117547 | X11: =O11 -> 14079323 | Y11: =W11-X11 -> 38224.212
A12: AO09 | B12: 1Q21 | C12: =IF(Triangulo1!D24=0,"-",Triangulo1!D24) -> 6289704 | D12: =IF(Triangulo1!E24=0,"-",Triangulo1!E24) -> 9074583 | E12: =IF(Triangulo1!F24=0,"-",Triangulo1!F24) -> 11031640 | F12: =IF(Triangulo1!G24=0,"-",Triangulo1!G24) -> 12328713 | G12: =IF(Triangulo1!H24=0,"-",Triangulo1!H24) -> 12743016 | H12: =IF(Triangulo1!I24=0,"-",Triangulo1!I24) -> 13716063 | I12: =IF(Triangulo1!J24=0,"-",Triangulo1!J24) -> 13936735 | J12: =IF(Triangulo1!K24=0,"-",Triangulo1!K24) -> 14684360 | ... N12: =IF(Triangulo1!O24=0,"-",Triangulo1!O24) -> 15669883 | O12: =N12*N$26 -> 15718375 | P12: =O12*O$26 -> 15740105 | Q12: =P12*P$26 -> 15751397 | R12: =Q12*Q$26 -> 15757586 | S12: =R12*R$26 -> 15759506 | T12: =S12*S$26 -> 15760439 | U12: =T12*T$26 -> 15760913 | V12: =U12*U$26 -> 15761049 | W12: =V12 -> 15761049 | X12: =N12 -> 15669883 | Y12: =W12-X12 -> 91166.174
A13: AO10 | B13: 2Q21 | C13: =IF(Triangulo1!D25=0,"-",Triangulo1!D25) -> 4959185 | D13: =IF(Triangulo1!E25=0,"-",Triangulo1!E25) -> 7332815 | E13: =IF(Triangulo1!F25=0,"-",Triangulo1!F25) -> 8942057 | F13: =IF(Triangulo1!G25=0,"-",Triangulo1!G25) -> 10413724 | G13: =IF(Triangulo1!H25=0,"-",Triangulo1!H25) -> 11109326 | H13: =IF(Triangulo1!I25=0,"-",Triangulo1!I25) -> 11743877 | I13: =IF(Triangulo1!J25=0,"-",Triangulo1!J25) -> 12264947 | J13: =IF(Triangulo1!K25=0,"-",Triangulo1!K25) -> 13331758 | ... M13: =IF(Triangulo1!N25=0,"-",Triangulo1!N25) -> 14231236 | N13: =M13*M$26 -> 14349283 | O13: =N13*N$26 -> 14393688 | P13: =O13*O$26 -> 14413586 | Q13: =P13*P$26 -> 14423927 | R13: =Q13*Q$26 -> 14429594 | S13: =R13*R$26 -> 14431353 | T13: =S13*S$26 -> 14432207 | U13: =T13*T$26 -> 14432641 | V13: =U13*U$26 -> 14432766 | W13: =V13 -> 14432766 | X13: =M13 -> 14231236 | Y13: =W13-X13 -> 201529.72
A14: AO11 | B14: 3Q21 | C14: =IF(Triangulo1!D26=0,"-",Triangulo1!D26) -> 6194048 | D14: =IF(Triangulo1!E26=0,"-",Triangulo1!E26) -> 7741218 | E14: =IF(Triangulo1!F26=0,"-",Triangulo1!F26) -> 9386858 | F14: =IF(Triangulo1!G26=0,"-",Triangulo1!G26) -> 9734366 | G14: =IF(Triangulo1!H26=0,"-",Triangulo1!H26) -> 10964336 | H14: =IF(Triangulo1!I26=0,"-",Triangulo1!I26) -> 11346897 | I14: =IF(Triangulo1!J26=0,"-",Triangulo1!J26) -> 13064544 | J14: =IF(Triangulo1!K26=0,"-",Triangulo1!K26) -> 14121948 | ... L14: =IF(Triangulo1!M26=0,"-",Triangulo1!M26) -> 14862271 | M14: =L14*L$26 -> 15037771 | N14: =M14*M$26 -> 15162508 | O14: =N14*N$26 -> 15209430 | P14: =O14*O$26 -> 15230456 | Q14: =P14*P$26 -> 15241383 | R14: =Q14*Q$26 -> 15247371 | S14: =R14*R$26 -> 15249229 | T14: =S14*S$26 -> 15250132 | ... V14: =U14*U$26 -> 15250722 | W14: =V14 -> 15250722 | X14: =L14 -> 14862271 | Y14: =W14-X14 -> 388451.33
A15: AO12 | B15: 4Q21 | C15: =IF(Triangulo1!D27=0,"-",Triangulo1!D27) -> 6500694 | D15: =IF(Triangulo1!E27=0,"-",Triangulo1!E27) -> 9436157 | E15: =IF(Triangulo1!F27=0,"-",Triangulo1!F27) -> 11552953 | F15: =IF(Triangulo1!G27=0,"-",Triangulo1!G27) -> 12130358 | G15: =IF(Triangulo1!H27=0,"-",Triangulo1!H27) -> 13369514 | H15: =IF(Triangulo1!I27=0,"-",Triangulo1!I27) -> 15030308 | I15: =IF(Triangulo1!J27=0,"-",Triangulo1!J27) -> 16697100 | J15: =IF(Triangulo1!K27=0,"-",Triangulo1!K27) -> 17828453 | K15: =IF(Triangulo1!L27=0,"-",Triangulo1!L27) -> 18294564 | L15: =K15*K$26 -> 18730329 | M15: =L15*L$26 -> 18951505 | N15: =M15*M$26 -> 19108706 | O15: =N15*N$26 -> 19167840 | P15: =O15*O$26 -> 19194338 | Q15: =P15*P$26 -> 19208108 | R15: =Q15*Q$26 -> 19215655 | S15: =R15*R$26 -> 19217997 | ... V15: =U15*U$26 -> 19219879 | W15: =V15 -> 19219879 | X15: =K15 -> 18294564 | Y15: =W15-X15 -> 925314.82
A16: AO13 | B16: 1Q22 | C16: =IF(Triangulo1!D28=0,"-",Triangulo1!D28) -> 5205434 | D16: =IF(Triangulo1!E28=0,"-",Triangulo1!E28) -> 7752400 | E16: =IF(Triangulo1!F28=0,"-",Triangulo1!F28) -> 9411446 | F16: =IF(Triangulo1!G28=0,"-",Triangulo1!G28) -> 10805763 | G16: =IF(Triangulo1!H28=0,"-",Triangulo1!H28) -> 13284336 | H16: =IF(Triangulo1!I28=0,"-",Triangulo1!I28) -> 15384835 | I16: =IF(Triangulo1!J28=0,"-",Triangulo1!J28) -> 17438864 | J16: =IF(Triangulo1!K28=0,"-",Triangulo1!K28) -> 18514044 | K16: =J16*J$26 -> 19059916 | L16: =K16*K$26 -> 19513912 | M16: =L16*L$26 -> 19744341 | N16: =M16*M$26 -> 19908118 | O16: =N16*N$26 -> 19969726 | P16: =O16*O$26 -> 19997333 | Q16: =P16*P$26 -> 20011679 | R16: =Q16*Q$26 -> 20019542 | ... V16: =U16*U$26 -> 20023942 | W16: =V16 -> 20023942 | X16: =J16 -> 18514044 | Y16: =W16-X16 -> 1509897.8
A17: AO14 | B17: 2Q22 | C17: =IF(Triangulo1!D29=0,"-",Triangulo1!D29) -> 5184519 | D17: =IF(Triangulo1!E29=0,"-",Triangulo1!E29) -> 7275135 | E17: =IF(Triangulo1!F29=0,"-",Triangulo1!F29) -> 7974797 | F17: =IF(Triangulo1!G29=0,"-",Triangulo1!G29) -> 11597296 | G17: =IF(Triangulo1!H29=0,"-",Triangulo1!H29) -> 14585912 | H17: =IF(Triangulo1!I29=0,"-",Triangulo1!I29) -> 16285147 | I17: =IF(Triangulo1!J29=0,"-",Triangulo1!J29) -> 18338971 | J17: =I17*I$26 -> 19526482 | K17: =J17*J$26 -> 20102205 | L17: =K17*K$26 -> 20581027 | M17: =L17*L$26 -> 20824057 | N17: =M17*M$26 -> 20996790 | O17: =N17*N$26 -> 21061767 | P17: =O17*O$26 -> 21090884 | Q17: =P17*P$26 -> 21106015 | ... V17: =U17*U$26 -> 21118948 | W17: =V17 -> 21118948 | X17: =I17 -> 18338971 | Y17: =W17-X17 -> 2779977.2
A18: AO15 | B18: 3Q22 | C18: =IF(Triangulo1!D30=0,"-",Triangulo1!D30) -> 3419011 | D18: =IF(Triangulo1!E30=0,"-",Triangulo1!E30) -> 4773306 | E18: =IF(Triangulo1!F30=0,"-",Triangulo1!F30) -> 8697825 | F18: =IF(Triangulo1!G30=0,"-",Triangulo1!G30) -> 12220494 | G18: =IF(Triangulo1!H30=0,"-",Triangulo1!H30) -> 14462971 | H18: =IF(Triangulo1!I30=0,"-",Triangulo1!I30) -> 16656668 | I18: =H18*H$26 -> 17836125 | J18: =I18*I$26 -> 18991075 | K18: =J18*J$26 -> 19551013 | L18: =K18*K$26 -> 20016705 | M18: =L18*L$26 -> 20253071 | N18: =M18*M$26 -> 20421069 | O18: =N18*N$26 -> 20484264 | P18: =O18*O$26 -> 20512582 | ... V18: =U18*U$26 -> 20539877 | W18: =V18 -> 20539877 | X18: =H18 -> 16656668 | Y18: =W18-X18 -> 3883208.8
A19: AO16 | B19: 4Q22 | C19: =IF(Triangulo1!D31=0,"-",Triangulo1!D31) -> 5498188 | D19: =IF(Triangulo1!E31=0,"-",Triangulo1!E31) -> 10669557 | E19: =IF(Triangulo1!F31=0,"-",Triangulo1!F31) -> 14420577 | F19: =IF(Triangulo1!G31=0,"-",Triangulo1!G31) -> 17838126 | G19: =IF(Triangulo1!H31=0,"-",Triangulo1!H31) -> 20243242 | H19: =G19*G$26 -> 21991557 | I19: =H19*H$26 -> 23548778 | J19: =I19*I$26 -> 25073641 | K19: =J19*J$26 -> 25812919 | L19: =K19*K$26 -> 26427766 | M19: =L19*L$26 -> 26739837 | N19: =M19*M$26 -> 26961641 | O19: =N19*N$26 -> 27045077 | ... V19: =U19*U$26 -> 27118502 | W19: =V19 -> 27118502 | X19: =G19 -> 20243242 | Y19: =W19-X19 -> 6875259.8
A20: AO17 | B20: 1Q23 | C20: =IF(Triangulo1!D32=0,"-",Triangulo1!D32) -> 6382667 | D20: =IF(Triangulo1!E32=0,"-",Triangulo1!E32) -> 10460689 | E20: =IF(Triangulo1!F32=0,"-",Triangulo1!F32) -> 15242265 | F20: =IF(Triangulo1!G32=0,"-",Triangulo1!G32) -> 19075882 | G20: =F20*F$26 -> 21256061 | H20: =G20*G$26 -> 23091849 | I20: =H20*H$26 -> 24726981 | J20: =I20*I$26 -> 26328137 | K20: =J20*J$26 -> 27104402 | L20: =K20*K$26 -> 27750012 | M20: =L20*L$26 -> 28077696 | N20: =M20*M$26 -> 28310598 | ... V20: =U20*U$26 -> 28475307 | W20: =V20 -> 28475307 | X20: =F20 -> 19075882 | Y20: =W20-X20 -> 9399424.7
A21: AO18 | B21: 2Q23 | C21: =IF(Triangulo1!D33=0,"-",Triangulo1!D33) -> 3022770 | D21: =IF(Triangulo1!E33=0,"-",Triangulo1!E33) -> 7899209 | E21: =IF(Triangulo1!F33=0,"-",Triangulo1!F33) -> 11259161 | F21: =E21*E$26 -> 13059054 | G21: =F21*F$26 -> 14551571 | H21: =G21*G$26 -> 15808323 | I21: =H21*H$26 -> 16927709 | J21: =I21*I$26 -> 18023836 | K21: =J21*J$26 -> 18555255 | L21: =K21*K$26 -> 18997230 | M21: =L21*L$26 -> 19221557 | ... V21: =U21*U$26 -> 19493755 | W21: =V21 -> 19493755 | X21: =E21 -> 11259161 | Y21: =W21-X21 -> 8234594.5
A22: AO19 | B22: 3Q23 | C22: =IF(Triangulo1!D34=0,"-",Triangulo1!D34) -> 6936281 | D22: =IF(Triangulo1!E34=0,"-",Triangulo1!E34) -> 21936281 | E22: =D22*D$26 -> 27153136 | F22: =E22*E$26 -> 31493846 | G22: =F22*F$26 -> 35093272 | H22: =G22*G$26 -> 38124116 | I22: =H22*H$26 -> 40823681 | J22: =I22*I$26 -> 43467153 | K22: =J22*J$26 -> 44748749 | L22: =K22*K$26 -> 45814636 | ... V22: =U22*U$26 -> 47012082 | W22: =V22 -> 47012082 | X22: =D22 -> 21936281 | Y22: =W22-X22 -> 25075801
A23: AO20 | B23: 4Q23 | C23: =IF(Triangulo1!D35=0,"-",Triangulo1!D35) -> 6691248 | D23: =C23*C$26 -> 10789639 | E23: =D23*D$26 -> 13355615 | F23: =E23*E$26 -> 15490648 | G23: =F23*F$26 -> 17261072 | H23: =G23*G$26 -> 18751831 | I23: =H23*H$26 -> 20079646 | J23: =I23*I$26 -> 21379872 | K23: =J23*J$26 -> 22010241 | ... V23: =U23*U$26 -> 23123490 | W23: =V23 -> 23123490 | X23: =C23 -> 6691248 | Y23: =W23-X23 -> 16432242
A24: Numerado | C24: =SUM(D4:D22) -> 168946224 | D24: =SUM(E4:E21) -> 181971639 | E24: =SUM(F4:F20) -> 198002634 | F24: =SUM(G4:G19) -> 199376256 | G24: =SUM(H4:H18) -> 194603906 | H24: =SUM(I4:I17) -> 190547667 | I24: =SUM(J4:J16) -> 183359796 | J24: =SUM(K4:K15) -> 169706103 | K24: =SUM(L4:L14) -> 155018067 | L24: =SUM(M4:M13) -> 141810817 | M24: =SUM(N4:N12) -> 128637841 | N24: =SUM(O4:O11) -> 113317549 | O24: =SUM(P4:P10) -> 99375417 | P24: =SUM(Q4:Q9) -> 88613537 | Q24: =SUM(R4:R8) -> 75602126 | R24: =SUM(S4:S7) -> 63797470 | S24: =SUM(T4:T6) -> 44340118 | T24: =SUM(U4:U5) -> 32460190 | U24: =SUM(V4) -> 14725343 | V24: =V4 -> 14725343
A25: Denominador | C25: =SUM(C4:C22) -> 104772840 | D25: =SUM(D4:D21) -> 147009943 | E25: =SUM(E4:E20) -> 170712478 | F25: =SUM(F4:F19) -> 178926752 | G25: =SUM(G4:G18) -> 179133014 | H25: =SUM(H4:H17) -> 177947238 | I25: =SUM(I4:I16) -> 172208696 | J25: =SUM(J4:J15) -> 164845752 | K25: =SUM(K4:K14) -> 151411539 | L25: =SUM(L4:L13) -> 140155796 | M25: =SUM(M4:M12) -> 127579581 | N25: =SUM(N4:N11) -> 112967958 | O25: =SUM(O4:O10) -> 99238226 | P25: =SUM(P4:P9) -> 88550010 | Q25: =SUM(Q4:Q8) -> 75572433 | R25: =SUM(R4:R7) -> 63789696 | S25: =SUM(S4:S6) -> 44337494 | T25: =SUM(T4:T5) -> 32459213 | U25: =SUM(U4) -> 14725216 | V25: =SUM(V4) -> 14725343
A26: Factores | C26: =C24/C25 -> 1.6125002 | D26: =D24/D25 -> 1.2378186 | E26: =E24/E25 -> 1.1598603 | F26: =F24/F25 -> 1.1142898 | G26: =G24/G25 -> 1.0863654 | H26: =H24/H25 -> 1.0708099 | I26: =I24/I25 -> 1.0647534 | J26: =J24/J25 -> 1.0294842 | ... V26: =V24/V25 -> 1
A27: Total | W27: =+SUM(W4:W23) -> 3.8519552e+08 | X27: =+SUM(X4:X23) -> 309332913 | Y27: =SUM(Y4:Y24) -> 75862602

Sheet todo_corte2024_promedio_simple
A1: CHAIN-LADDER — Triángulo Proyectado e IBNR | Vinculado a hojas 1_Triangulo y 2_Factores
A2: AZUL=observado (hoja 1) · AMARILLO=proyección CL = C_{i,j-1} × f̂_{j-1} (hoja 2) · VERDE=IBNR
A3: AO | B3: Trim. | C3: T01 | D3: T02 | E3: T03 | F3: T04 | G3: T05 | H3: T06 | I3: T07 | J3: T08 | K3: T09 | L3: T10 | M3: T11 | N3: T12 | O3: T13 | P3: T14 | Q3: T15 | R3: T16 | S3: T17 | T3: T18 | U3: T19 | V3: T20 | W3: T21 | X3: T22 | Y3: T23 | Z3: T24 | AA3: Último Proy. | AB3: Pagado Actual | AC3: IBNR CL
A4: AO01 | B4: 1Q19 | C4: =IF(Triangulo1!D16=0,"-",Triangulo1!D16) -> 6418198 | D4: =IF(Triangulo1!E16=0,"-",Triangulo1!E16) -> 8351947 | E4: =IF(Triangulo1!F16=0,"-",Triangulo1!F16) -> 9393090 | F4: =IF(Triangulo1!G16=0,"-",Triangulo1!G16) -> 11183194 | G4: =IF(Triangulo1!H16=0,"-",Triangulo1!H16) -> 12100800 | H4: =IF(Triangulo1!I16=0,"-",Triangulo1!I16) -> 12721118 | I4: =IF(Triangulo1!J16=0,"-",Triangulo1!J16) -> 13073728 | J4: =IF(Triangulo1!K16=0,"-",Triangulo1!K16) -> 13548698 | ... Z4: =IF(Triangulo1!AA16=0,"-",Triangulo1!AA16) -> 14725385 | AA4: =+Z4 -> 14725385 | AB4: =+Z4 -> 14725385 | AC4: =AA4-AB4 -> 0
A5: AO02 | B5: 2Q19 | C5: =IF(Triangulo1!D17=0,"-",Triangulo1!D17) -> 7475822 | D5: =IF(Triangulo1!E17=0,"-",Triangulo1!E17) -> 10450029 | E5: =IF(Triangulo1!F17=0,"-",Triangulo1!F17) -> 12515657 | F5: =IF(Triangulo1!G17=0,"-",Triangulo1!G17) -> 13149304 | G5: =IF(Triangulo1!H17=0,"-",Triangulo1!H17) -> 14417681 | H5: =IF(Triangulo1!I17=0,"-",Triangulo1!I17) -> 15145227 | I5: =IF(Triangulo1!J17=0,"-",Triangulo1!J17) -> 15971980 | J5: =IF(Triangulo1!K17=0,"-",Triangulo1!K17) -> 16442175 | ... Y5: =IF(Triangulo1!Z17=0,"-",Triangulo1!Z17) -> 17735279 | Z5: =+Y5*Y$30 -> 17735298 | AA5: =+Z5 -> 17735298 | AB5: =+Y5 -> 17735279 | AC5: =AA5-AB5 -> 19.270448
A6: AO03 | B6: 3Q19 | C6: =IF(Triangulo1!D18=0,"-",Triangulo1!D18) -> 4944676 | D6: =IF(Triangulo1!E18=0,"-",Triangulo1!E18) -> 5651989 | E6: =IF(Triangulo1!F18=0,"-",Triangulo1!F18) -> 6603749 | F6: =IF(Triangulo1!G18=0,"-",Triangulo1!G18) -> 7627857 | G6: =IF(Triangulo1!H18=0,"-",Triangulo1!H18) -> 8503366 | H6: =IF(Triangulo1!I18=0,"-",Triangulo1!I18) -> 9687265 | I6: =IF(Triangulo1!J18=0,"-",Triangulo1!J18) -> 10329156 | J6: =IF(Triangulo1!K18=0,"-",Triangulo1!K18) -> 10705380 | ... X6: =IF(Triangulo1!Y18=0,"-",Triangulo1!Y18) -> 11881761 | Y6: =+X6*X$30 -> 11881768 | Z6: =+Y6*Y$30 -> 11881781 | AA6: =+Z6 -> 11881781 | AB6: =+X6 -> 11881761 | AC6: =AA6-AB6 -> 19.822551
A7: AO04 | B7: 4Q19 | C7: =IF(Triangulo1!D19=0,"-",Triangulo1!D19) -> 5990844 | D7: =IF(Triangulo1!E19=0,"-",Triangulo1!E19) -> 12990844 | E7: =IF(Triangulo1!F19=0,"-",Triangulo1!F19) -> 14795084 | F7: =IF(Triangulo1!G19=0,"-",Triangulo1!G19) -> 15558421 | G7: =IF(Triangulo1!H19=0,"-",Triangulo1!H19) -> 16698078 | H7: =IF(Triangulo1!I19=0,"-",Triangulo1!I19) -> 17591115 | I7: =IF(Triangulo1!J19=0,"-",Triangulo1!J19) -> 17858613 | J7: =IF(Triangulo1!K19=0,"-",Triangulo1!K19) -> 18161498 | ... W7: =IF(Triangulo1!X19=0,"-",Triangulo1!X19) -> 19461650 | X7: =+W7*W$30 -> 19461676 | Y7: =+X7*X$30 -> 19461687 | Z7: =+Y7*Y$30 -> 19461708 | AA7: =+Z7 -> 19461708 | AB7: =+W7 -> 19461650 | AC7: =AA7-AB7 -> 57.984178
A8: AO05 | B8: 1Q20 | C8: =IF(Triangulo1!D20=0,"-",Triangulo1!D20) -> 6106533 | D8: =IF(Triangulo1!E20=0,"-",Triangulo1!E20) -> 7227067 | E8: =IF(Triangulo1!F20=0,"-",Triangulo1!F20) -> 8316481 | F8: =IF(Triangulo1!G20=0,"-",Triangulo1!G20) -> 8778769 | G8: =IF(Triangulo1!H20=0,"-",Triangulo1!H20) -> 9616196 | H8: =IF(Triangulo1!I20=0,"-",Triangulo1!I20) -> 9944940 | I8: =IF(Triangulo1!J20=0,"-",Triangulo1!J20) -> 10596973 | J8: =IF(Triangulo1!K20=0,"-",Triangulo1!K20) -> 10938865 | ... V8: =IF(Triangulo1!W20=0,"-",Triangulo1!W20) -> 11816173 | W8: =+V8*V$30 -> 11816215 | X8: =+W8*W$30 -> 11816231 | Y8: =+X8*X$30 -> 11816238 | Z8: =+Y8*Y$30 -> 11816250 | AA8: =+Z8 -> 11816250 | AB8: =+V8 -> 11816173 | AC8: =AA8-AB8 -> 77.462962
A9: AO06 | B9: 2Q20 | C9: =IF(Triangulo1!D21=0,"-",Triangulo1!D21) -> 3511339 | D9: =IF(Triangulo1!E21=0,"-",Triangulo1!E21) -> 5097855 | E9: =IF(Triangulo1!F21=0,"-",Triangulo1!F21) -> 6037374 | F9: =IF(Triangulo1!G21=0,"-",Triangulo1!G21) -> 6436248 | G9: =IF(Triangulo1!H21=0,"-",Triangulo1!H21) -> 7366573 | H9: =IF(Triangulo1!I21=0,"-",Triangulo1!I21) -> 8575992 | I9: =IF(Triangulo1!J21=0,"-",Triangulo1!J21) -> 9082448 | J9: =IF(Triangulo1!K21=0,"-",Triangulo1!K21) -> 12082448 | ... U9: =IF(Triangulo1!V21=0,"-",Triangulo1!V21) -> 13048471 | V9: =+U9*U$30 -> 13048603 | W9: =+V9*V$30 -> 13048650 | X9: =+W9*W$30 -> 13048667 | Y9: =+X9*X$30 -> 13048675 | Z9: =+Y9*Y$30 -> 13048689 | AA9: =+Z9 -> 13048689 | AB9: =+U9 -> 13048471 | AC9: =AA9-AB9 -> 217.72616
A10: AO07 | B10: 3Q20 | C10: =IF(Triangulo1!D22=0,"-",Triangulo1!D22) -> 4141271 | D10: =IF(Triangulo1!E22=0,"-",Triangulo1!E22) -> 5675304 | E10: =IF(Triangulo1!F22=0,"-",Triangulo1!F22) -> 6514051 | F10: =IF(Triangulo1!G22=0,"-",Triangulo1!G22) -> 7799341 | G10: =IF(Triangulo1!H22=0,"-",Triangulo1!H22) -> 8118940 | H10: =IF(Triangulo1!I22=0,"-",Triangulo1!I22) -> 8328067 | I10: =IF(Triangulo1!J22=0,"-",Triangulo1!J22) -> 9073367 | J10: =IF(Triangulo1!K22=0,"-",Triangulo1!K22) -> 9580777 | ... T10: =IF(Triangulo1!U22=0,"-",Triangulo1!U22) -> 10840140 | U10: =+T10*T$30 -> 10840509 | V10: =+U10*U$30 -> 10840619 | W10: =+V10*V$30 -> 10840658 | X10: =+W10*W$30 -> 10840672 | Y10: =+X10*X$30 -> 10840678 | Z10: =+Y10*Y$30 -> 10840690 | AA10: =+Z10 -> 10840690 | AB10: =+T10 -> 10840140 | AC10: =AA10-AB10 -> 550.2051
A11: AO08 | B11: 4Q20 | C11: =IF(Triangulo1!D23=0,"-",Triangulo1!D23) -> 6591656 | D11: =IF(Triangulo1!E23=0,"-",Triangulo1!E23) -> 9149839 | E11: =IF(Triangulo1!F23=0,"-",Triangulo1!F23) -> 9876574 | F11: =IF(Triangulo1!G23=0,"-",Triangulo1!G23) -> 11324778 | G11: =IF(Triangulo1!H23=0,"-",Triangulo1!H23) -> 11791969 | H11: =IF(Triangulo1!I23=0,"-",Triangulo1!I23) -> 12446387 | I11: =IF(Triangulo1!J23=0,"-",Triangulo1!J23) -> 12820241 | J11: =IF(Triangulo1!K23=0,"-",Triangulo1!K23) -> 13419392 | ... S11: =IF(Triangulo1!T23=0,"-",Triangulo1!T23) -> 14111136 | T11: =+S11*S$30 -> 14112143 | U11: =+T11*T$30 -> 14112624 | V11: =+U11*U$30 -> 14112767 | W11: =+V11*V$30 -> 14112817 | X11: =+W11*W$30 -> 14112836 | Y11: =+X11*X$30 -> 14112844 | Z11: =+Y11*Y$30 -> 14112860 | AA11: =+Z11 -> 14112860 | AB11: =+S11 -> 14111136 | AC11: =AA11-AB11 -> 1723.5343
A12: AO09 | B12: 1Q21 | C12: =IF(Triangulo1!D24=0,"-",Triangulo1!D24) -> 6289704 | D12: =IF(Triangulo1!E24=0,"-",Triangulo1!E24) -> 9074583 | E12: =IF(Triangulo1!F24=0,"-",Triangulo1!F24) -> 11031640 | F12: =IF(Triangulo1!G24=0,"-",Triangulo1!G24) -> 12328713 | G12: =IF(Triangulo1!H24=0,"-",Triangulo1!H24) -> 12743016 | H12: =IF(Triangulo1!I24=0,"-",Triangulo1!I24) -> 13716063 | I12: =IF(Triangulo1!J24=0,"-",Triangulo1!J24) -> 13936735 | J12: =IF(Triangulo1!K24=0,"-",Triangulo1!K24) -> 14684360 | ... R12: =IF(Triangulo1!S24=0,"-",Triangulo1!S24) -> 15729334 | S12: =+R12*R30 -> 15731638 | T12: =+S12*S30 -> 15732761 | U12: =+T12*T30 -> 15733297 | V12: =+U12*U30 -> 15733456 | W12: =+V12*V30 -> 15733513 | X12: =+W12*W30 -> 15733533 | Y12: =+X12*X30 -> 15733542 | Z12: =+Y12*Y30 -> 15733559 | AA12: =+Z12 -> 15733559 | AB12: =+R12 -> 15729334 | AC12: =AA12-AB12 -> 4225.4334
A13: AO10 | B13: 2Q21 | C13: =IF(Triangulo1!D25=0,"-",Triangulo1!D25) -> 4959185 | D13: =IF(Triangulo1!E25=0,"-",Triangulo1!E25) -> 7332815 | E13: =IF(Triangulo1!F25=0,"-",Triangulo1!F25) -> 8942057 | F13: =IF(Triangulo1!G25=0,"-",Triangulo1!G25) -> 10413724 | G13: =IF(Triangulo1!H25=0,"-",Triangulo1!H25) -> 11109326 | H13: =IF(Triangulo1!I25=0,"-",Triangulo1!I25) -> 11743877 | I13: =IF(Triangulo1!J25=0,"-",Triangulo1!J25) -> 12264947 | J13: =IF(Triangulo1!K25=0,"-",Triangulo1!K25) -> 13331758 | ... Q13: =IF(Triangulo1!R25=0,"-",Triangulo1!R25) -> 14343596 | R13: =+Q13*Q30 -> 14348967 | S13: =+R13*R30 -> 14351069 | T13: =+S13*S30 -> 14352094 | U13: =+T13*T30 -> 14352583 | V13: =+U13*U30 -> 14352728 | W13: =+V13*V30 -> 14352779 | X13: =+W13*W30 -> 14352798 | Y13: =+X13*X30 -> 14352807 | Z13: =+Y13*Y30 -> 14352822 | AA13: =+Z13 -> 14352822 | AB13: =+Q13 -> 14343596 | AC13: =AA13-AB13 -> 9226.1169
A14: AO11 | B14: 3Q21 | C14: =IF(Triangulo1!D26=0,"-",Triangulo1!D26) -> 6194048 | D14: =IF(Triangulo1!E26=0,"-",Triangulo1!E26) -> 7741218 | E14: =IF(Triangulo1!F26=0,"-",Triangulo1!F26) -> 9386858 | F14: =IF(Triangulo1!G26=0,"-",Triangulo1!G26) -> 9734366 | G14: =IF(Triangulo1!H26=0,"-",Triangulo1!H26) -> 10964336 | H14: =IF(Triangulo1!I26=0,"-",Triangulo1!I26) -> 11346897 | I14: =IF(Triangulo1!J26=0,"-",Triangulo1!J26) -> 13064544 | J14: =IF(Triangulo1!K26=0,"-",Triangulo1!K26) -> 14121948 | ... P14: =IF(Triangulo1!Q26=0,"-",Triangulo1!Q26) -> 15119935 | Q14: =+P14*P30 -> 15130000 | R14: =+Q14*Q30 -> 15135666 | S14: =+R14*R30 -> 15137883 | T14: =+S14*S30 -> 15138963 | U14: =+T14*T30 -> 15139479 | V14: =+U14*U30 -> 15139632 | W14: =+V14*V30 -> 15139687 | X14: =+W14*W30 -> 15139706 | ... Z14: =+Y14*Y30 -> 15139732 | AA14: =+Z14 -> 15139732 | AB14: =+P14 -> 15119935 | AC14: =AA14-AB14 -> 19796.711
A15: AO12 | B15: 4Q21 | C15: =IF(Triangulo1!D27=0,"-",Triangulo1!D27) -> 6500694 | D15: =IF(Triangulo1!E27=0,"-",Triangulo1!E27) -> 9436157 | E15: =IF(Triangulo1!F27=0,"-",Triangulo1!F27) -> 11552953 | F15: =IF(Triangulo1!G27=0,"-",Triangulo1!G27) -> 12130358 | G15: =IF(Triangulo1!H27=0,"-",Triangulo1!H27) -> 13369514 | H15: =IF(Triangulo1!I27=0,"-",Triangulo1!I27) -> 15030308 | I15: =IF(Triangulo1!J27=0,"-",Triangulo1!J27) -> 16697100 | J15: =IF(Triangulo1!K27=0,"-",Triangulo1!K27) -> 17828453 | ... O15: =IF(Triangulo1!P27=0,"-",Triangulo1!P27) -> 18730024 | P15: =+O15*O30 -> 18754563 | Q15: =+P15*P30 -> 18767048 | R15: =+Q15*Q30 -> 18774076 | S15: =+R15*R30 -> 18776826 | T15: =+S15*S30 -> 18778166 | U15: =+T15*T30 -> 18778806 | V15: =+U15*U30 -> 18778996 | W15: =+V15*V30 -> 18779063 | ... Z15: =+Y15*Y30 -> 18779119 | AA15: =+Z15 -> 18779119 | AB15: =+O15 -> 18730024 | AC15: =AA15-AB15 -> 49094.973
A16: AO13 | B16: 1Q22 | C16: =IF(Triangulo1!D28=0,"-",Triangulo1!D28) -> 5205434 | D16: =IF(Triangulo1!E28=0,"-",Triangulo1!E28) -> 7752400 | E16: =IF(Triangulo1!F28=0,"-",Triangulo1!F28) -> 9411446 | F16: =IF(Triangulo1!G28=0,"-",Triangulo1!G28) -> 10805763 | G16: =IF(Triangulo1!H28=0,"-",Triangulo1!H28) -> 13284336 | H16: =IF(Triangulo1!I28=0,"-",Triangulo1!I28) -> 15384835 | I16: =IF(Triangulo1!J28=0,"-",Triangulo1!J28) -> 17438864 | J16: =IF(Triangulo1!K28=0,"-",Triangulo1!K28) -> 18514044 | ... N16: =IF(Triangulo1!O28=0,"-",Triangulo1!O28) -> 19627354 | O16: =+N16*N30 -> 19680827 | P16: =+O16*O30 -> 19706612 | Q16: =+P16*P30 -> 19719730 | R16: =+Q16*Q30 -> 19727115 | S16: =+R16*R30 -> 19730005 | T16: =+S16*S30 -> 19731413 | U16: =+T16*T30 -> 19732085 | V16: =+U16*U30 -> 19732285 | ... Z16: =+Y16*Y30 -> 19732415 | AA16: =+Z16 -> 19732415 | AB16: =+N16 -> 19627354 | AC16: =AA16-AB16 -> 105060.58
A17: AO14 | B17: 2Q22 | C17: =IF(Triangulo1!D29=0,"-",Triangulo1!D29) -> 5184519 | D17: =IF(Triangulo1!E29=0,"-",Triangulo1!E29) -> 7275135 | E17: =IF(Triangulo1!F29=0,"-",Triangulo1!F29) -> 7974797 | F17: =IF(Triangulo1!G29=0,"-",Triangulo1!G29) -> 11597296 | G17: =IF(Triangulo1!H29=0,"-",Triangulo1!H29) -> 14585912 | H17: =IF(Triangulo1!I29=0,"-",Triangulo1!I29) -> 16285147 | I17: =IF(Triangulo1!J29=0,"-",Triangulo1!J29) -> 18338971 | J17: =IF(Triangulo1!K29=0,"-",Triangulo1!K29) -> 19214501 | ... M17: =IF(Triangulo1!N29=0,"-",Triangulo1!N29) -> 20049671 | N17: =+M17*M30 -> 20184696 | O17: =+N17*N30 -> 20239688 | P17: =+O17*O30 -> 20266205 | Q17: =+P17*P30 -> 20279696 | R17: =+Q17*Q30 -> 20287290 | S17: =+R17*R30 -> 20290262 | T17: =+S17*S30 -> 20291710 | U17: =+T17*T30 -> 20292401 | ... Z17: =+Y17*Y30 -> 20292740 | AA17: =+Z17 -> 20292740 | AB17: =+M17 -> 20049671 | AC17: =AA17-AB17 -> 243069.04
A18: AO15 | B18: 3Q22 | C18: =IF(Triangulo1!D30=0,"-",Triangulo1!D30) -> 3419011 | D18: =IF(Triangulo1!E30=0,"-",Triangulo1!E30) -> 4773306 | E18: =IF(Triangulo1!F30=0,"-",Triangulo1!F30) -> 8697825 | F18: =IF(Triangulo1!G30=0,"-",Triangulo1!G30) -> 12220494 | G18: =IF(Triangulo1!H30=0,"-",Triangulo1!H30) -> 14462971 | H18: =IF(Triangulo1!I30=0,"-",Triangulo1!I30) -> 16656668 | I18: =IF(Triangulo1!J30=0,"-",Triangulo1!J30) -> 19017438 | J18: =IF(Triangulo1!K30=0,"-",Triangulo1!K30) -> 19939378 | ... L18: =IF(Triangulo1!M30=0,"-",Triangulo1!M30) -> 20688336 | M18: =+L18*L30 -> 20905273 | N18: =+M18*M30 -> 21046060 | O18: =+N18*N30 -> 21103399 | P18: =+O18*O30 -> 21131048 | Q18: =+P18*P30 -> 21145114 | R18: =+Q18*Q30 -> 21153033 | S18: =+R18*R30 -> 21156131 | T18: =+S18*S30 -> 21157641 | ... Z18: =+Y18*Y30 -> 21158715 | AA18: =+Z18 -> 21158715 | AB18: =+L18 -> 20688336 | AC18: =AA18-AB18 -> 470379.05
A19: AO16 | B19: 4Q22 | C19: =IF(Triangulo1!D31=0,"-",Triangulo1!D31) -> 5498188 | D19: =IF(Triangulo1!E31=0,"-",Triangulo1!E31) -> 10669557 | E19: =IF(Triangulo1!F31=0,"-",Triangulo1!F31) -> 14420577 | F19: =IF(Triangulo1!G31=0,"-",Triangulo1!G31) -> 17838126 | G19: =IF(Triangulo1!H31=0,"-",Triangulo1!H31) -> 20243242 | H19: =IF(Triangulo1!I31=0,"-",Triangulo1!I31) -> 22179116 | I19: =IF(Triangulo1!J31=0,"-",Triangulo1!J31) -> 24155749 | J19: =IF(Triangulo1!K31=0,"-",Triangulo1!K31) -> 25145296 | K19: =IF(Triangulo1!L31=0,"-",Triangulo1!L31) -> 25647723 | L19: =+K19*K30 -> 26222361 | M19: =+L19*L30 -> 26497327 | N19: =+M19*M30 -> 26675775 | O19: =+N19*N30 -> 26748451 | P19: =+O19*O30 -> 26783496 | Q19: =+P19*P30 -> 26801324 | R19: =+Q19*Q30 -> 26811361 | S19: =+R19*R30 -> 26815288 | ... Z19: =+Y19*Y30 -> 26818564 | AA19: =+Z19 -> 26818564 | AB19: =+K19 -> 25647723 | AC19: =AA19-AB19 -> 1170840.6
A20: AO17 | B20: 1Q23 | C20: =IF(Triangulo1!D32=0,"-",Triangulo1!D32) -> 6382667 | D20: =IF(Triangulo1!E32=0,"-",Triangulo1!E32) -> 10460689 | E20: =IF(Triangulo1!F32=0,"-",Triangulo1!F32) -> 15242265 | F20: =IF(Triangulo1!G32=0,"-",Triangulo1!G32) -> 19075882 | G20: =IF(Triangulo1!H32=0,"-",Triangulo1!H32) -> 21908553 | H20: =IF(Triangulo1!I32=0,"-",Triangulo1!I32) -> 23938666 | I20: =IF(Triangulo1!J32=0,"-",Triangulo1!J32) -> 25653115 | J20: =IF(Triangulo1!K32=0,"-",Triangulo1!K32) -> 26811464 | K20: =+J20*J30 -> 27584886 | L20: =+K20*K30 -> 28202926 | M20: =+L20*L30 -> 28498661 | N20: =+M20*M30 -> 28690586 | O20: =+N20*N30 -> 28768752 | P20: =+O20*O30 -> 28806444 | Q20: =+P20*P30 -> 28825619 | R20: =+Q20*Q30 -> 28836414 | ... Z20: =+Y20*Y30 -> 28844160 | AA20: =+Z20 -> 28844160 | AB20: =+J20 -> 26811464 | AC20: =AA20-AB20 -> 2032696.2
A21: AO18 | B21: 2Q23 | C21: =IF(Triangulo1!D33=0,"-",Triangulo1!D33) -> 3022770 | D21: =IF(Triangulo1!E33=0,"-",Triangulo1!E33) -> 7899209 | E21: =IF(Triangulo1!F33=0,"-",Triangulo1!F33) -> 11259161 | F21: =IF(Triangulo1!G33=0,"-",Triangulo1!G33) -> 14497513 | G21: =IF(Triangulo1!H33=0,"-",Triangulo1!H33) -> 17221120 | H21: =IF(Triangulo1!I33=0,"-",Triangulo1!I33) -> 19234288 | I21: =IF(Triangulo1!J33=0,"-",Triangulo1!J33) -> 21399003 | J21: =+I21*I30 -> 22805917 | K21: =+J21*J30 -> 23463792 | L21: =+K21*K30 -> 23989499 | M21: =+L21*L30 -> 24241052 | N21: =+M21*M30 -> 24404304 | O21: =+N21*N30 -> 24470792 | P21: =+O21*O30 -> 24502853 | Q21: =+P21*P30 -> 24519164 | ... Z21: =+Y21*Y30 -> 24534935 | AA21: =+Z21 -> 24534935 | AB21: =+I21 -> 21399003 | AC21: =AA21-AB21 -> 3135931.8
A22: AO19 | B22: 3Q23 | C22: =IF(Triangulo1!D34=0,"-",Triangulo1!D34) -> 6936281 | D22: =IF(Triangulo1!E34=0,"-",Triangulo1!E34) -> 21936281 | E22: =IF(Triangulo1!F34=0,"-",Triangulo1!F34) -> 25150070 | F22: =IF(Triangulo1!G34=0,"-",Triangulo1!G34) -> 28898330 | G22: =IF(Triangulo1!H34=0,"-",Triangulo1!H34) -> 31903741 | H22: =IF(Triangulo1!I34=0,"-",Triangulo1!I34) -> 33589263 | I22: =H30*H22 -> 36211642 | J22: =I30*I22 -> 38592438 | K22: =J30*J22 -> 39705703 | L22: =K30*K22 -> 40595310 | M22: =L30*L22 -> 41020991 | N22: =M30*M22 -> 41297248 | O22: =N30*N22 -> 41409760 | P22: =O30*O22 -> 41464013 | ... Z22: =Y30*Y22 -> 41518302 | AA22: =+Z22 -> 41518302 | AB22: =+H22 -> 33589263 | AC22: =AA22-AB22 -> 7929039.4
A23: AO20 | B23: 4Q23 | C23: =IF(Triangulo1!D35=0,"-",Triangulo1!D35) -> 6691248 | D23: =IF(Triangulo1!E35=0,"-",Triangulo1!E35) -> 11756013 | E23: =IF(Triangulo1!F35=0,"-",Triangulo1!F35) -> 15391294 | F23: =IF(Triangulo1!G35=0,"-",Triangulo1!G35) -> 18736499 | G23: =IF(Triangulo1!H35=0,"-",Triangulo1!H35) -> 21705785 | H23: =G30*G23 -> 23591861 | I23: =H30*H23 -> 25433724 | J23: =I30*I23 -> 27105907 | K23: =J30*J23 -> 27887823 | L23: =K30*K23 -> 28512650 | M23: =L30*L23 -> 28811633 | N23: =M30*M23 -> 29005666 | O23: =N30*N23 -> 29084690 | ... Z23: =Y30*Y23 -> 29160926 | AA23: =+Z23 -> 29160926 | AB23: =+G23 -> 21705785 | AC23: =AA23-AB23 -> 7455141.3
A24: AO21 | B24: 1Q24 | C24: =IF(Triangulo1!D36=0,"-",Triangulo1!D36) -> 4191817 | D24: =IF(Triangulo1!E36=0,"-",Triangulo1!E36) -> 9775450 | E24: =IF(Triangulo1!F36=0,"-",Triangulo1!F36) -> 14374440 | F24: =IF(Triangulo1!G36=0,"-",Triangulo1!G36) -> 17306094 | G24: =F30*F24 -> 19401741 | H24: =G30*G24 -> 21087612 | I24: =H30*H24 -> 22733963 | J24: =I30*I24 -> 24228646 | K24: =J30*J24 -> 24927563 | L24: =K30*K24 -> 25486065 | M24: =L30*L24 -> 25753311 | N24: =M30*M24 -> 25926748 | ... Z24: =Y30*Y24 -> 26065527 | AA24: =+Z24 -> 26065527 | AB24: =+F24 -> 17306094 | AC24: =AA24-AB24 -> 8759433.3
A25: AO22 | B25: 2Q24 | C25: =IF(Triangulo1!D37=0,"-",Triangulo1!D37) -> 5916671 | D25: =IF(Triangulo1!E37=0,"-",Triangulo1!E37) -> 11716355 | E25: =IF(Triangulo1!F37=0,"-",Triangulo1!F37) -> 15374462 | F25: =E25*E30 -> 18036792 | G25: =F25*F30 -> 20220922 | H25: =G25*G30 -> 21977974 | I25: =H25*H30 -> 23693837 | J25: =I25*I30 -> 25251629 | K25: =J25*J30 -> 25980055 | L25: =K25*K30 -> 26562139 | M25: =L25*L30 -> 26840668 | ... Z25: =Y25*Y30 -> 27166067 | AA25: =+Z25 -> 27166067 | AB25: =+E25 -> 15374462 | AC25: =AA25-AB25 -> 11791605
A26: AO23 | B26: 3Q24 | C26: =IF(Triangulo1!D38=0,"-",Triangulo1!D38) -> 4926500 | D26: =IF(Triangulo1!E38=0,"-",Triangulo1!E38) -> 9321834 | E26: =D26*D30 -> 11723765 | F26: =E26*E30 -> 13753920 | G26: =F26*F30 -> 15419423 | H26: =G26*G30 -> 16759260 | I26: =H26*H30 -> 18067688 | J26: =I26*I30 -> 19255579 | K26: =J26*J30 -> 19811039 | L26: =K26*K30 -> 20254905 | ... Z26: =Y26*Y30 -> 20715430 | AA26: =+Z26 -> 20715430 | AB26: =+D26 -> 9321834 | AC26: =AA26-AB26 -> 11393596
A27: AO24 | B27: 4Q24 | C27: =IF(Triangulo1!D39=0,"-",Triangulo1!D39) -> 5149958 | D27: =C27*C30 -> 8650245.9 | E27: =D27*D30 -> 10879131 | F27: =E27*E30 -> 12763024 | G27: =F27*F30 -> 14308537 | H27: =G27*G30 -> 15551845 | I27: =H27*H30 -> 16766008 | J27: =I27*I30 -> 17868318 | K27: =J27*J30 -> 18383760 | ... Z27: =Y27*Y30 -> 19222994 | AA27: =+Z27 -> 19222994 | AB27: =+C27 -> 5149958 | AC27: =AA27-AB27 -> 14073036
A28: Numerado | C28: =SUM(D4:D26) -> 211515876 | D28: =SUM(E4:E25) -> 252261905 | E28: =SUM(F4:F24) -> 277441070 | F28: =SUM(G4:G23) -> 292115455 | G28: =SUM(H4:H22) -> 293545239 | H28: =SUM(I4:I21) -> 280772972 | I28: =SUM(J4:J20) -> 274470435 | J28: =SUM(K4:K19) -> 254564289 | K28: =SUM(L4:L18) -> 233587211 | L28: =SUM(M4:M17) -> 215088266 | M28: =SUM(N4:N16) -> 196318410 | N28: =SUM(O4:O15) -> 177170491 | O28: =SUM(P4:P14) -> 158643001 | P28: =SUM(Q4:Q13) -> 143619030 | Q28: =SUM(R4:R12) -> 129322660 | R28: =SUM(S4:S11) -> 113609232 | S28: =SUM(T4:T10) -> 99504954 | T28: =SUM(U4:U9) -> 88667706 | U28: =SUM(V4:V8) -> 75619969 | V28: =SUM(W4:W7) -> 63803989 | W28: =SUM(X4:X6) -> 44342390 | X28: =SUM(Y4:Y5) -> 32460648 | Y28: =SUM(Z4) -> 14725385
A29: Denominador | C29: =SUM(C4:C26) -> 126499076 | D29: =SUM(D4:D25) -> 202194042 | E29: =SUM(E4:E24) -> 236887443 | F29: =SUM(F4:F23) -> 260134976 | G29: =SUM(G4:G22) -> 270409670 | H29: =SUM(H4:H21) -> 259955976 | I29: =SUM(I4:I20) -> 259373969 | J29: =SUM(J4:J19) -> 247658971 | K29: =SUM(K4:K18) -> 228916566 | L29: =SUM(L4:L17) -> 212898875 | M29: =SUM(M4:M16) -> 195038595 | N29: =SUM(N4:N15) -> 176691056 | O29: =SUM(O4:O14) -> 158440467 | P29: =SUM(P4:P13) -> 143523066 | Q29: =SUM(Q4:Q12) -> 129275434 | R29: =SUM(R4:R11) -> 113593326 | S29: =SUM(S4:S10) -> 99498096 | T29: =SUM(T4:T9) -> 88664814 | U29: =SUM(U4:U8) -> 75619235 | V29: =SUM(V4:V7) -> 63803796 | W29: =SUM(W4:W6) -> 44342339 | X29: =SUM(X4:X5) -> 32460629 | Y29: =SUM(Y4) -> 14725369
A30: Factores | C30: =Triangulo1!D69 -> 1.6796731 | D30: =Triangulo1!E69 -> 1.2576672 | E30: =Triangulo1!F69 -> 1.1731658 | F30: =Triangulo1!G69 -> 1.121093 | G30: =Triangulo1!H69 -> 1.0868928 | H30: =Triangulo1!I69 -> 1.0780719 | I30: =Triangulo1!J69 -> 1.0657467 | J30: =Triangulo1!K69 -> 1.0288467 | ... Z30: =Triangulo1!AA69 -> 1
A31: Factor acum. F_j^{→25} | C31: =+C30*D31 -> 3.7326507 | D31: =+D30*E31 -> 2.2222483 | E31: =+E30*F31 -> 1.7669605 | F31: =+F30*G31 -> 1.5061473 | G31: =+G30*H31 -> 1.3434633 | H31: =+H30*I31 -> 1.2360587 | I31: =+I30*J31 -> 1.1465457 | J31: =+J30*K31 -> 1.0758144 | ... Y31: =+Y30*Z31 -> 1.0000011 | Z31: 1
A32: % Desarrollado = 1/F_j | C32: =1/C31 -> 0.26790613 | D32: =1/D31 -> 0.44999472 | E32: =1/E31 -> 0.56594361 | F32: =1/F31 -> 0.66394567 | G32: =1/G31 -> 0.74434484 | H32: =1/H31 -> 0.80902303 | I32: =1/I31 -> 0.87218504 | J32: =1/J31 -> 0.92952833 | ... Y32: =1/Y31 -> 0.99999891 | Z32: 1
A33: Total | AA33: =+SUM(AA4:AA27) -> 4.8285867e+08 | AB33: =+SUM(AB4:AB27) -> 414213831 | AC33: =SUM(AC4:AC28) -> 68644838

Sheet todo_corte2023_promedo_simple
A1: CHAIN-LADDER — Triángulo Proyectado e IBNR | Vinculado a hojas 1_Triangulo y 2_Factores
A2: AZUL=observado (hoja 1) · AMARILLO=proyección CL = C_{i,j-1} × f̂_{j-1} (hoja 2) · VERDE=IBNR
A3: AO | B3: Trim. | C3: T01 | D3: T02 | E3: T03 | F3: T04 | G3: T05 | H3: T06 | I3: T07 | J3: T08 | K3: T09 | L3: T10 | M3: T11 | N3: T12 | O3: T13 | P3: T14 | Q3: T15 | R3: T16 | S3: T17 | T3: T18 | U3: T19 | V3: T20 | W3: Último Proy. | X3: Pagado Actual | Y3: IBNR CL
A4: AO01 | B4: 1Q19 | C4: =IF(Triangulo1!D16=0,"-",Triangulo1!D16) -> 6418198 | D4: =IF(Triangulo1!E16=0,"-",Triangulo1!E16) -> 8351947 | E4: =IF(Triangulo1!F16=0,"-",Triangulo1!F16) -> 9393090 | F4: =IF(Triangulo1!G16=0,"-",Triangulo1!G16) -> 11183194 | G4: =IF(Triangulo1!H16=0,"-",Triangulo1!H16) -> 12100800 | H4: =IF(Triangulo1!I16=0,"-",Triangulo1!I16) -> 12721118 | I4: =IF(Triangulo1!J16=0,"-",Triangulo1!J16) -> 13073728 | J4: =IF(Triangulo1!K16=0,"-",Triangulo1!K16) -> 13548698 | ... V4: =IF(Triangulo1!W16=0,"-",Triangulo1!W16) -> 14725343 | W4: =V4 -> 14725343 | X4: =V4 -> 14725343 | Y4: =W4-X4 -> 0
A5: AO02 | B5: 2Q19 | C5: =IF(Triangulo1!D17=0,"-",Triangulo1!D17) -> 7475822 | D5: =IF(Triangulo1!E17=0,"-",Triangulo1!E17) -> 10450029 | E5: =IF(Triangulo1!F17=0,"-",Triangulo1!F17) -> 12515657 | F5: =IF(Triangulo1!G17=0,"-",Triangulo1!G17) -> 13149304 | G5: =IF(Triangulo1!H17=0,"-",Triangulo1!H17) -> 14417681 | H5: =IF(Triangulo1!I17=0,"-",Triangulo1!I17) -> 15145227 | I5: =IF(Triangulo1!J17=0,"-",Triangulo1!J17) -> 15971980 | J5: =IF(Triangulo1!K17=0,"-",Triangulo1!K17) -> 16442175 | ... U5: =IF(Triangulo1!V17=0,"-",Triangulo1!V17) -> 17734974 | V5: =U5*U$26 -> 17735154 | W5: =V5 -> 17735154 | X5: =U5 -> 17734974 | Y5: =W5-X5 -> 179.65906
A6: AO03 | B6: 3Q19 | C6: =IF(Triangulo1!D18=0,"-",Triangulo1!D18) -> 4944676 | D6: =IF(Triangulo1!E18=0,"-",Triangulo1!E18) -> 5651989 | E6: =IF(Triangulo1!F18=0,"-",Triangulo1!F18) -> 6603749 | F6: =IF(Triangulo1!G18=0,"-",Triangulo1!G18) -> 7627857 | G6: =IF(Triangulo1!H18=0,"-",Triangulo1!H18) -> 8503366 | H6: =IF(Triangulo1!I18=0,"-",Triangulo1!I18) -> 9687265 | I6: =IF(Triangulo1!J18=0,"-",Triangulo1!J18) -> 10329156 | J6: =IF(Triangulo1!K18=0,"-",Triangulo1!K18) -> 10705380 | ... T6: =IF(Triangulo1!U18=0,"-",Triangulo1!U18) -> 11880905 | U6: =T6*T$26 -> 11881310 | V6: =U6*U$26 -> 11881430 | W6: =V6 -> 11881430 | X6: =T6 -> 11880905 | Y6: =W6-X6 -> 525.13968
A7: AO04 | B7: 4Q19 | C7: =IF(Triangulo1!D19=0,"-",Triangulo1!D19) -> 5990844 | D7: =IF(Triangulo1!E19=0,"-",Triangulo1!E19) -> 12990844 | E7: =IF(Triangulo1!F19=0,"-",Triangulo1!F19) -> 14795084 | F7: =IF(Triangulo1!G19=0,"-",Triangulo1!G19) -> 15558421 | G7: =IF(Triangulo1!H19=0,"-",Triangulo1!H19) -> 16698078 | H7: =IF(Triangulo1!I19=0,"-",Triangulo1!I19) -> 17591115 | I7: =IF(Triangulo1!J19=0,"-",Triangulo1!J19) -> 17858613 | J7: =IF(Triangulo1!K19=0,"-",Triangulo1!K19) -> 18161498 | ... S7: =IF(Triangulo1!T19=0,"-",Triangulo1!T19) -> 19459976 | T7: =S7*S$26 -> 19461365 | U7: =T7*T$26 -> 19462028 | V7: =U7*U$26 -> 19462225 | W7: =V7 -> 19462225 | X7: =S7 -> 19459976 | Y7: =W7-X7 -> 2249.2536
A8: AO05 | B8: 1Q20 | C8: =IF(Triangulo1!D20=0,"-",Triangulo1!D20) -> 6106533 | D8: =IF(Triangulo1!E20=0,"-",Triangulo1!E20) -> 7227067 | E8: =IF(Triangulo1!F20=0,"-",Triangulo1!F20) -> 8316481 | F8: =IF(Triangulo1!G20=0,"-",Triangulo1!G20) -> 8778769 | G8: =IF(Triangulo1!H20=0,"-",Triangulo1!H20) -> 9616196 | H8: =IF(Triangulo1!I20=0,"-",Triangulo1!I20) -> 9944940 | I8: =IF(Triangulo1!J20=0,"-",Triangulo1!J20) -> 10596973 | J8: =IF(Triangulo1!K20=0,"-",Triangulo1!K20) -> 10938865 | ... R8: =IF(Triangulo1!S20=0,"-",Triangulo1!S20) -> 11812430 | S8: =R8*R$26 -> 11814160 | T8: =S8*S$26 -> 11815004 | U8: =T8*T$26 -> 11815406 | V8: =U8*U$26 -> 11815526 | W8: =V8 -> 11815526 | X8: =R8 -> 11812430 | Y8: =W8-X8 -> 3095.7612
A9: AO06 | B9: 2Q20 | C9: =IF(Triangulo1!D21=0,"-",Triangulo1!D21) -> 3511339 | D9: =IF(Triangulo1!E21=0,"-",Triangulo1!E21) -> 5097855 | E9: =IF(Triangulo1!F21=0,"-",Triangulo1!F21) -> 6037374 | F9: =IF(Triangulo1!G21=0,"-",Triangulo1!G21) -> 6436248 | G9: =IF(Triangulo1!H21=0,"-",Triangulo1!H21) -> 7366573 | H9: =IF(Triangulo1!I21=0,"-",Triangulo1!I21) -> 8575992 | I9: =IF(Triangulo1!J21=0,"-",Triangulo1!J21) -> 9082448 | J9: =IF(Triangulo1!K21=0,"-",Triangulo1!K21) -> 12082448 | ... Q9: =IF(Triangulo1!R21=0,"-",Triangulo1!R21) -> 13041104 | R9: =Q9*Q$26 -> 13045988 | S9: =R9*R$26 -> 13047899 | T9: =S9*S$26 -> 13048830 | U9: =T9*T$26 -> 13049275 | V9: =U9*U$26 -> 13049407 | W9: =V9 -> 13049407 | X9: =Q9 -> 13041104 | Y9: =W9-X9 -> 8302.7777
A10: AO07 | B10: 3Q20 | C10: =IF(Triangulo1!D22=0,"-",Triangulo1!D22) -> 4141271 | D10: =IF(Triangulo1!E22=0,"-",Triangulo1!E22) -> 5675304 | E10: =IF(Triangulo1!F22=0,"-",Triangulo1!F22) -> 6514051 | F10: =IF(Triangulo1!G22=0,"-",Triangulo1!G22) -> 7799341 | G10: =IF(Triangulo1!H22=0,"-",Triangulo1!H22) -> 8118940 | H10: =IF(Triangulo1!I22=0,"-",Triangulo1!I22) -> 8328067 | I10: =IF(Triangulo1!J22=0,"-",Triangulo1!J22) -> 9073367 | J10: =IF(Triangulo1!K22=0,"-",Triangulo1!K22) -> 9580777 | ... P10: =IF(Triangulo1!Q22=0,"-",Triangulo1!Q22) -> 10825407 | Q10: =P10*P$26 -> 10832613 | R10: =Q10*Q$26 -> 10836670 | S10: =R10*R$26 -> 10838257 | T10: =S10*S$26 -> 10839031 | U10: =T10*T$26 -> 10839400 | V10: =U10*U$26 -> 10839510 | W10: =V10 -> 10839510 | X10: =P10 -> 10825407 | Y10: =W10-X10 -> 14102.774
A11: AO08 | B11: 4Q20 | C11: =IF(Triangulo1!D23=0,"-",Triangulo1!D23) -> 6591656 | D11: =IF(Triangulo1!E23=0,"-",Triangulo1!E23) -> 9149839 | E11: =IF(Triangulo1!F23=0,"-",Triangulo1!F23) -> 9876574 | F11: =IF(Triangulo1!G23=0,"-",Triangulo1!G23) -> 11324778 | G11: =IF(Triangulo1!H23=0,"-",Triangulo1!H23) -> 11791969 | H11: =IF(Triangulo1!I23=0,"-",Triangulo1!I23) -> 12446387 | I11: =IF(Triangulo1!J23=0,"-",Triangulo1!J23) -> 12820241 | J11: =IF(Triangulo1!K23=0,"-",Triangulo1!K23) -> 13419392 | ... O11: =IF(Triangulo1!P23=0,"-",Triangulo1!P23) -> 14079323 | P11: =O11*O$26 -> 14097769 | Q11: =P11*P$26 -> 14107154 | R11: =Q11*Q$26 -> 14112437 | S11: =R11*R$26 -> 14114504 | T11: =S11*S$26 -> 14115511 | U11: =T11*T$26 -> 14115992 | V11: =U11*U$26 -> 14116135 | W11: =V11 -> 14116135 | X11: =O11 -> 14079323 | Y11: =W11-X11 -> 36812.056
A12: AO09 | B12: 1Q21 | C12: =IF(Triangulo1!D24=0,"-",Triangulo1!D24) -> 6289704 | D12: =IF(Triangulo1!E24=0,"-",Triangulo1!E24) -> 9074583 | E12: =IF(Triangulo1!F24=0,"-",Triangulo1!F24) -> 11031640 | F12: =IF(Triangulo1!G24=0,"-",Triangulo1!G24) -> 12328713 | G12: =IF(Triangulo1!H24=0,"-",Triangulo1!H24) -> 12743016 | H12: =IF(Triangulo1!I24=0,"-",Triangulo1!I24) -> 13716063 | I12: =IF(Triangulo1!J24=0,"-",Triangulo1!J24) -> 13936735 | J12: =IF(Triangulo1!K24=0,"-",Triangulo1!K24) -> 14684360 | ... N12: =IF(Triangulo1!O24=0,"-",Triangulo1!O24) -> 15669883 | O12: =N12*N$26 -> 15712575 | P12: =O12*O$26 -> 15733161 | Q12: =P12*P$26 -> 15743634 | R12: =Q12*Q$26 -> 15749529 | S12: =R12*R$26 -> 15751836 | T12: =S12*S$26 -> 15752961 | U12: =T12*T$26 -> 15753497 | V12: =U12*U$26 -> 15753657 | W12: =V12 -> 15753657 | X12: =N12 -> 15669883 | Y12: =W12-X12 -> 83773.899
A13: AO10 | B13: 2Q21 | C13: =IF(Triangulo1!D25=0,"-",Triangulo1!D25) -> 4959185 | D13: =IF(Triangulo1!E25=0,"-",Triangulo1!E25) -> 7332815 | E13: =IF(Triangulo1!F25=0,"-",Triangulo1!F25) -> 8942057 | F13: =IF(Triangulo1!G25=0,"-",Triangulo1!G25) -> 10413724 | G13: =IF(Triangulo1!H25=0,"-",Triangulo1!H25) -> 11109326 | H13: =IF(Triangulo1!I25=0,"-",Triangulo1!I25) -> 11743877 | I13: =IF(Triangulo1!J25=0,"-",Triangulo1!J25) -> 12264947 | J13: =IF(Triangulo1!K25=0,"-",Triangulo1!K25) -> 13331758 | ... M13: =IF(Triangulo1!N25=0,"-",Triangulo1!N25) -> 14231236 | N13: =M13*M$26 -> 14327077 | O13: =N13*N$26 -> 14366110 | P13: =O13*O$26 -> 14384932 | Q13: =P13*P$26 -> 14394507 | R13: =Q13*Q$26 -> 14399898 | S13: =R13*R$26 -> 14402007 | T13: =S13*S$26 -> 14403035 | U13: =T13*T$26 -> 14403526 | V13: =U13*U$26 -> 14403672 | W13: =V13 -> 14403672 | X13: =M13 -> 14231236 | Y13: =W13-X13 -> 172435.73
A14: AO11 | B14: 3Q21 | C14: =IF(Triangulo1!D26=0,"-",Triangulo1!D26) -> 6194048 | D14: =IF(Triangulo1!E26=0,"-",Triangulo1!E26) -> 7741218 | E14: =IF(Triangulo1!F26=0,"-",Triangulo1!F26) -> 9386858 | F14: =IF(Triangulo1!G26=0,"-",Triangulo1!G26) -> 9734366 | G14: =IF(Triangulo1!H26=0,"-",Triangulo1!H26) -> 10964336 | H14: =IF(Triangulo1!I26=0,"-",Triangulo1!I26) -> 11346897 | I14: =IF(Triangulo1!J26=0,"-",Triangulo1!J26) -> 13064544 | J14: =IF(Triangulo1!K26=0,"-",Triangulo1!K26) -> 14121948 | ... L14: =IF(Triangulo1!M26=0,"-",Triangulo1!M26) -> 14862271 | M14: =L14*L$26 -> 15018116 | N14: =M14*M$26 -> 15119256 | O14: =N14*N$26 -> 15160448 | P14: =O14*O$26 -> 15180310 | Q14: =P14*P$26 -> 15190415 | R14: =Q14*Q$26 -> 15196104 | S14: =R14*R$26 -> 15198330 | T14: =S14*S$26 -> 15199415 | ... V14: =U14*U$26 -> 15200086 | W14: =V14 -> 15200086 | X14: =L14 -> 14862271 | Y14: =W14-X14 -> 337815.44
A15: AO12 | B15: 4Q21 | C15: =IF(Triangulo1!D27=0,"-",Triangulo1!D27) -> 6500694 | D15: =IF(Triangulo1!E27=0,"-",Triangulo1!E27) -> 9436157 | E15: =IF(Triangulo1!F27=0,"-",Triangulo1!F27) -> 11552953 | F15: =IF(Triangulo1!G27=0,"-",Triangulo1!G27) -> 12130358 | G15: =IF(Triangulo1!H27=0,"-",Triangulo1!H27) -> 13369514 | H15: =IF(Triangulo1!I27=0,"-",Triangulo1!I27) -> 15030308 | I15: =IF(Triangulo1!J27=0,"-",Triangulo1!J27) -> 16697100 | J15: =IF(Triangulo1!K27=0,"-",Triangulo1!K27) -> 17828453 | K15: =IF(Triangulo1!L27=0,"-",Triangulo1!L27) -> 18294564 | L15: =K15*K$26 -> 18704454 | M15: =L15*L$26 -> 18900588 | N15: =M15*M$26 -> 19027875 | O15: =N15*N$26 -> 19079715 | P15: =O15*O$26 -> 19104713 | Q15: =P15*P$26 -> 19117430 | R15: =Q15*Q$26 -> 19124589 | S15: =R15*R$26 -> 19127390 | ... V15: =U15*U$26 -> 19129601 | W15: =V15 -> 19129601 | X15: =K15 -> 18294564 | Y15: =W15-X15 -> 835037.19
A16: AO13 | B16: 1Q22 | C16: =IF(Triangulo1!D28=0,"-",Triangulo1!D28) -> 5205434 | D16: =IF(Triangulo1!E28=0,"-",Triangulo1!E28) -> 7752400 | E16: =IF(Triangulo1!F28=0,"-",Triangulo1!F28) -> 9411446 | F16: =IF(Triangulo1!G28=0,"-",Triangulo1!G28) -> 10805763 | G16: =IF(Triangulo1!H28=0,"-",Triangulo1!H28) -> 13284336 | H16: =IF(Triangulo1!I28=0,"-",Triangulo1!I28) -> 15384835 | I16: =IF(Triangulo1!J28=0,"-",Triangulo1!J28) -> 17438864 | J16: =IF(Triangulo1!K28=0,"-",Triangulo1!K28) -> 18514044 | K16: =J16*J$26 -> 19048113 | L16: =K16*K$26 -> 19474886 | M16: =L16*L$26 -> 19679099 | N16: =M16*M$26 -> 19811629 | O16: =N16*N$26 -> 19865604 | P16: =O16*O$26 -> 19891632 | Q16: =P16*P$26 -> 19904873 | R16: =Q16*Q$26 -> 19912327 | ... V16: =U16*U$26 -> 19917545 | W16: =V16 -> 19917545 | X16: =J16 -> 18514044 | Y16: =W16-X16 -> 1403501.4
A17: AO14 | B17: 2Q22 | C17: =IF(Triangulo1!D29=0,"-",Triangulo1!D29) -> 5184519 | D17: =IF(Triangulo1!E29=0,"-",Triangulo1!E29) -> 7275135 | E17: =IF(Triangulo1!F29=0,"-",Triangulo1!F29) -> 7974797 | F17: =IF(Triangulo1!G29=0,"-",Triangulo1!G29) -> 11597296 | G17: =IF(Triangulo1!H29=0,"-",Triangulo1!H29) -> 14585912 | H17: =IF(Triangulo1!I29=0,"-",Triangulo1!I29) -> 16285147 | I17: =IF(Triangulo1!J29=0,"-",Triangulo1!J29) -> 18338971 | J17: =I17*I$26 -> 19544698 | K17: =J17*J$26 -> 20108498 | L17: =K17*K$26 -> 20559029 | M17: =L17*L$26 -> 20774611 | N17: =M17*M$26 -> 20914518 | O17: =N17*N$26 -> 20971498 | P17: =O17*O$26 -> 20998974 | Q17: =P17*P$26 -> 21012952 | ... V17: =U17*U$26 -> 21026330 | W17: =V17 -> 21026330 | X17: =I17 -> 18338971 | Y17: =W17-X17 -> 2687359.4
A18: AO15 | B18: 3Q22 | C18: =IF(Triangulo1!D30=0,"-",Triangulo1!D30) -> 3419011 | D18: =IF(Triangulo1!E30=0,"-",Triangulo1!E30) -> 4773306 | E18: =IF(Triangulo1!F30=0,"-",Triangulo1!F30) -> 8697825 | F18: =IF(Triangulo1!G30=0,"-",Triangulo1!G30) -> 12220494 | G18: =IF(Triangulo1!H30=0,"-",Triangulo1!H30) -> 14462971 | H18: =IF(Triangulo1!I30=0,"-",Triangulo1!I30) -> 16656668 | I18: =H18*H$26 -> 17957086 | J18: =I18*I$26 -> 19137706 | K18: =J18*J$26 -> 19689765 | L18: =K18*K$26 -> 20130915 | M18: =L18*L$26 -> 20342007 | N18: =M18*M$26 -> 20479001 | O18: =N18*N$26 -> 20534795 | P18: =O18*O$26 -> 20561699 | ... V18: =U18*U$26 -> 20588485 | W18: =V18 -> 20588485 | X18: =H18 -> 16656668 | Y18: =W18-X18 -> 3931817.3
A19: AO16 | B19: 4Q22 | C19: =IF(Triangulo1!D31=0,"-",Triangulo1!D31) -> 5498188 | D19: =IF(Triangulo1!E31=0,"-",Triangulo1!E31) -> 10669557 | E19: =IF(Triangulo1!F31=0,"-",Triangulo1!F31) -> 14420577 | F19: =IF(Triangulo1!G31=0,"-",Triangulo1!G31) -> 17838126 | G19: =IF(Triangulo1!H31=0,"-",Triangulo1!H31) -> 20243242 | H19: =G19*G$26 -> 22002234 | I19: =H19*H$26 -> 23719991 | J19: =I19*I$26 -> 25279502 | K19: =J19*J$26 -> 26008732 | L19: =K19*K$26 -> 26591458 | M19: =L19*L$26 -> 26870296 | N19: =M19*M$26 -> 27051254 | O19: =N19*N$26 -> 27124954 | ... V19: =U19*U$26 -> 27195875 | W19: =V19 -> 27195875 | X19: =G19 -> 20243242 | Y19: =W19-X19 -> 6952633.1
A20: AO17 | B20: 1Q23 | C20: =IF(Triangulo1!D32=0,"-",Triangulo1!D32) -> 6382667 | D20: =IF(Triangulo1!E32=0,"-",Triangulo1!E32) -> 10460689 | E20: =IF(Triangulo1!F32=0,"-",Triangulo1!F32) -> 15242265 | F20: =IF(Triangulo1!G32=0,"-",Triangulo1!G32) -> 19075882 | G20: =F20*F$26 -> 21385838 | H20: =G20*G$26 -> 23244113 | I20: =H20*H$26 -> 25058826 | J20: =I20*I$26 -> 26706361 | K20: =J20*J$26 -> 27476751 | L20: =K20*K$26 -> 28092368 | M20: =L20*L$26 -> 28386944 | N20: =M20*M$26 -> 28578117 | ... V20: =U20*U$26 -> 28730900 | W20: =V20 -> 28730900 | X20: =F20 -> 19075882 | Y20: =W20-X20 -> 9655018.5
A21: AO18 | B21: 2Q23 | C21: =IF(Triangulo1!D33=0,"-",Triangulo1!D33) -> 3022770 | D21: =IF(Triangulo1!E33=0,"-",Triangulo1!E33) -> 7899209 | E21: =IF(Triangulo1!F33=0,"-",Triangulo1!F33) -> 11259161 | F21: =E21*E$26 -> 13191533 | G21: =F21*F$26 -> 14788935 | H21: =G21*G$26 -> 16073986 | I21: =H21*H$26 -> 17328914 | J21: =I21*I$26 -> 18468233 | K21: =J21*J$26 -> 19000980 | L21: =K21*K$26 -> 19426698 | M21: =L21*L$26 -> 19630405 | ... V21: =U21*U$26 -> 19868261 | W21: =V21 -> 19868261 | X21: =E21 -> 11259161 | Y21: =W21-X21 -> 8609100.3
A22: AO19 | B22: 3Q23 | C22: =IF(Triangulo1!D34=0,"-",Triangulo1!D34) -> 6936281 | D22: =IF(Triangulo1!E34=0,"-",Triangulo1!E34) -> 21936281 | E22: =D22*D$26 -> 27295307 | F22: =E22*E$26 -> 31979908 | G22: =F22*F$26 -> 35852451 | H22: =G22*G$26 -> 38967770 | I22: =H22*H$26 -> 42010060 | J22: =I22*I$26 -> 44772083 | K22: =J22*J$26 -> 46063610 | L22: =K22*K$26 -> 47095666 | ... V22: =U22*U$26 -> 48166138 | W22: =V22 -> 48166138 | X22: =D22 -> 21936281 | Y22: =W22-X22 -> 26229857
A23: AO20 | B23: 4Q23 | C23: =IF(Triangulo1!D35=0,"-",Triangulo1!D35) -> 6691248 | D23: =C23*C$26 -> 10849203 | E23: =D23*D$26 -> 13499660 | F23: =E23*E$26 -> 15816560 | G23: =F23*F$26 -> 17731835 | H23: =G23*G$26 -> 19272604 | I23: =H23*H$26 -> 20777253 | J23: =I23*I$26 -> 22143289 | K23: =J23*J$26 -> 22782050 | ... V23: =U23*U$26 -> 23821914 | W23: =V23 -> 23821914 | X23: =C23 -> 6691248 | Y23: =W23-X23 -> 17130666
A24: Numerado | C24: =SUM(D4:D22) -> 168946224 | D24: =SUM(E4:E21) -> 181971639 | E24: =SUM(F4:F20) -> 198002634 | F24: =SUM(G4:G19) -> 199376256 | G24: =SUM(H4:H18) -> 194603906 | H24: =SUM(I4:I17) -> 190547667 | I24: =SUM(J4:J16) -> 183359796 | J24: =SUM(K4:K15) -> 169706103 | K24: =SUM(L4:L14) -> 155018067 | L24: =SUM(M4:M13) -> 141810817 | M24: =SUM(N4:N12) -> 128637841 | N24: =SUM(O4:O11) -> 113317549 | O24: =SUM(P4:P10) -> 99375417 | P24: =SUM(Q4:Q9) -> 88613537 | Q24: =SUM(R4:R8) -> 75602126 | R24: =SUM(S4:S7) -> 63797470 | S24: =SUM(T4:T6) -> 44340118 | T24: =SUM(U4:U5) -> 32460190 | U24: =SUM(V4) -> 14725343 | V24: =V4 -> 14725343
A25: Denominador | C25: =SUM(C4:C22) -> 104772840 | D25: =SUM(D4:D21) -> 147009943 | E25: =SUM(E4:E20) -> 170712478 | F25: =SUM(F4:F19) -> 178926752 | G25: =SUM(G4:G18) -> 179133014 | H25: =SUM(H4:H17) -> 177947238 | I25: =SUM(I4:I16) -> 172208696 | J25: =SUM(J4:J15) -> 164845752 | K25: =SUM(K4:K14) -> 151411539 | L25: =SUM(L4:L13) -> 140155796 | M25: =SUM(M4:M12) -> 127579581 | N25: =M25*M$26 -> 1.2843877e+08 | O25: =N25*N$26 -> 1.2878869e+08 | P25: =SUM(P4:P9) -> 88550010 | Q25: =SUM(Q4:Q8) -> 75572433 | R25: =SUM(R4:R7) -> 63789696 | S25: =SUM(S4:S6) -> 44337494 | T25: =SUM(T4:T5) -> 32459213 | U25: =SUM(U4) -> 14725216 | V25: =SUM(V4) -> 14725343
A26: Factores | C26: =Triangulo1!D70 -> 1.621402 | D26: =Triangulo1!E70 -> 1.2442997 | E26: =Triangulo1!F70 -> 1.1716266 | F26: =Triangulo1!G70 -> 1.121093 | G26: =Triangulo1!H70 -> 1.0868928 | H26: =Triangulo1!I70 -> 1.0780719 | I26: =Triangulo1!J70 -> 1.0657467 | J26: =Triangulo1!K70 -> 1.0288467 | ... V26: =Triangulo1!W70 -> 1
A27: Total | W27: =+SUM(W4:W23) -> 3.874272e+08 | X27: =+SUM(X4:X23) -> 309332913 | Y27: =SUM(Y4:Y24) -> 78094282
