Workbook

Sheet Nombre Equipo
C3: Integrantes del equipo
C4: 1
C5: =+C4+1 -> 2
C6: =+C5+1 -> 3
C7: =+C6+1 -> 4
C8: =+C7+1 -> 5
C9: =+C8+1 -> 6
C10: =+C9+1 -> 7

Sheet Triangulo1
C2: Calcula el IBNR del siguiente triangulo usando Chain Ladder, BF y Cape Cod
D3: 1. el loss ratio a priori es 55%
D4: 2. tasa de interes | E4: 0.06
C7: Contesta las sig preguntas:
D8: 1. Qué metodología escogerías para cada trimestre y por qué?
D9: 2. Excluiste algun periodo para el calculo de lo factores? Di que periodo y en que desarrollo y por qué
D10: 3. Cómo sale el bakctesting para tu selección de ultimate para los trimestres del 1Q19 al 4Q20?
D11: 4. Qué duración tiene está cartera?
C13: TRIÁNGULO-PAGADO
D15: 1 | E15: =+D15+1 -> 2 | F15: =+E15+1 -> 3 | G15: =+F15+1 -> 4 | H15: =+G15+1 -> 5 | I15: =+H15+1 -> 6 | J15: =+I15+1 -> 7 | K15: =+J15+1 -> 8 | L15: =+K15+1 -> 9 | ... AA15: =+Z15+1 -> 24
C16: 1Q19 | D16: 6418198 | E16: 8351947 | F16: 9393090 | G16: 11183194 | H16: 12100800 | I16: 12721118 | J16: 13073728 | K16: 13548698 | L16: 13729852 | M16: 14178002 | N16: 14403018 | O16: 14589694 | P16: 14666170 | Q16: 14699145 | R16: 14709918 | S16: 14721902 | T16: 14723975 | U16: 14724778 | V16: 14725216 | W16: 14725343 | X16: 14725356 | Y16: 14725361 | Z16: 14725369 | AA16: 14725385
C17: 2Q19 | D17: 7475822 | E17: 10450029 | F17: 12515657 | G17: 13149304 | H17: 14417681 | I17: 15145227 | J17: 15971980 | K17: 16442175 | L17: 16761977 | M17: 17230340 | N17: 17479823 | O17: 17658472 | P17: 17691106 | Q17: 17707511 | R17: 17727251 | S17: 17731572 | T17: 17733454 | U17: 17734435 | V17: 17734974 | W17: 17735197 | X17: 17735258 | Y17: 17735268 | Z17: 17735279
C18: 3Q19 | D18: 4944676 | E18: 5651989 | F18: 6603749 | G18: 7627857 | H18: 8503366 | I18: 9687265 | J18: 10329156 | K18: 10705380 | L18: 11007279 | M18: 11432174 | N18: 11644639 | O18: 11802250 | P18: 11840837 | Q18: 11864201 | R18: 11873586 | S18: 11878223 | T18: 11880065 | U18: 11880905 | V18: 11881492 | W18: 11881607 | X18: 11881725 | Y18: 11881761
C19: 4Q19 | D19: 5990844 | E19: 12990844 | F19: 14795084 | G19: 15558421 | H19: 16698078 | I19: 17591115 | J19: 17858613 | K19: 18161498 | L19: 18751439 | M19: 18855100 | N19: 19152179 | O19: 19349458 | P19: 19426010 | Q19: 19444545 | R19: 19453256 | S19: 19457999 | T19: 19459976 | U19: 19461146 | V19: 19461559 | W19: 19461649 | X19: 19461650
C20: 1Q20 | D20: 6106533 | E20: 7227067 | F20: 8316481 | G20: 8778769 | H20: 9616196 | I20: 9944940 | J20: 10596973 | K20: 10938865 | L20: 11091033 | M20: 11574757 | N20: 11660948 | O20: 11754449 | P20: 11785976 | Q20: 11801623 | R20: 11808422 | S20: 11812430 | T20: 11814677 | U20: 11815553 | V20: 11815994 | W20: 11816173
C21: 2Q20 | D21: 3511339 | E21: 5097855 | F21: 6037374 | G21: 6436248 | H21: 7366573 | I21: 8575992 | J21: 9082448 | K21: 12082448 | L21: 12687409 | M21: 12838372 | N21: 12930641 | O21: 12990612 | P21: 13017211 | Q21: 13032985 | R21: 13041104 | S21: 13045224 | T21: 13046906 | U21: 13047997 | V21: 13048471
C22: 3Q20 | D22: 4141271 | E22: 5675304 | F22: 6514051 | G22: 7799341 | H22: 8118940 | I22: 8328067 | J22: 9073367 | K22: 9580777 | L22: 10084545 | M22: 10574369 | N22: 10704764 | O22: 10779530 | P22: 10810916 | Q22: 10825407 | R22: 10831969 | S22: 10836654 | T22: 10839043 | U22: 10840140
C23: 4Q20 | D23: 6591656 | E23: 9149839 | F23: 9876574 | G23: 11324778 | H23: 11791969 | I23: 12446387 | J23: 12820241 | K23: 13419392 | L23: 13586619 | M23: 13861205 | N23: 13987078 | O23: 14043493 | P23: 14079323 | Q23: 14095393 | R23: 14104571 | S23: 14109322 | T23: 14111136
C24: 1Q21 | D24: 6289704 | E24: 9074583 | F24: 11031640 | G24: 12328713 | H24: 12743016 | I24: 13716063 | J24: 13936735 | K24: 14684360 | L24: 15224487 | M24: 15505624 | N24: 15616491 | O24: 15669883 | P24: 15701026 | Q24: 15717007 | R24: 15725357 | S24: 15729334
C25: 2Q21 | D25: 4959185 | E25: 7332815 | F25: 8942057 | G25: 10413724 | H25: 11109326 | I25: 11743877 | J25: 12264947 | K25: 13331758 | L25: 13881470 | M25: 14105853 | N25: 14231236 | O25: 14285043 | P25: 14317196 | Q25: 14335249 | R25: 14343596
C26: 3Q21 | D26: 6194048 | E26: 7741218 | F26: 9386858 | G26: 9734366 | H26: 10964336 | I26: 11346897 | J26: 13064544 | K26: 14121948 | L26: 14605429 | M26: 14862271 | N26: 15012968 | O26: 15074585 | P26: 15104696 | Q26: 15119935
C27: 4Q21 | D27: 6500694 | E27: 9436157 | F27: 11552953 | G27: 12130358 | H27: 13369514 | I27: 15030308 | J27: 16697100 | K27: 17828453 | L27: 18294564 | M27: 18522862 | N27: 18641988 | O27: 18693587 | P27: 18730024
C28: 1Q22 | D28: 5205434 | E28: 7752400 | F28: 9411446 | G28: 10805763 | H28: 13284336 | I28: 15384835 | J28: 17438864 | K28: 18514044 | L28: 19125680 | M28: 19431036 | N28: 19572822 | O28: 19627354
C29: 2Q22 | D29: 5184519 | E29: 7275135 | F29: 7974797 | G29: 11597296 | H29: 14585912 | I29: 16285147 | J29: 18338971 | K29: 19214501 | L29: 19700684 | M29: 19926910 | N29: 20049671
C30: 3Q22 | D30: 3419011 | E30: 4773306 | F30: 8697825 | G30: 12220494 | H30: 14462971 | I30: 16656668 | J30: 19017438 | K30: 19939378 | L30: 20384099 | M30: 20688336
C31: 4Q22 | D31: 5498188 | E31: 10669557 | F31: 14420577 | G31: 17838126 | H31: 20243242 | I31: 22179116 | J31: 24155749 | K31: 25145296 | L31: 25647723
C32: 1Q23 | D32: 6382667 | E32: 10460689 | F32: 15242265 | G32: 19075882 | H32: 21908553 | I32: 23938666 | J32: 25653115 | K32: 26811464
C33: 2Q23 | D33: 3022770 | E33: 7899209 | F33: 11259161 | G33: 14497513 | H33: 17221120 | I33: 19234288 | J33: 21399003
C34: 3Q23 | D34: 6936281 | E34: 21936281 | F34: 25150070 | G34: 28898330 | H34: 31903741 | I34: 33589263
C35: 4Q23 | D35: 6691248 | E35: 11756013 | F35: 15391294 | G35: 18736499 | H35: 21705785
C36: 1Q24 | D36: 4191817 | E36: 9775450 | F36: 14374440 | G36: 17306094
C37: 2Q24 | D37: 5916671 | E37: 11716355 | F37: 15374462
C38: 3Q24 | D38: 4926500 | E38: 9321834
C39: 4Q24 | D39: 5149958
C41: FACTORES
D43: 1 | E43: =+D43+1 -> 2 | F43: =+E43+1 -> 3 | G43: =+F43+1 -> 4 | H43: =+G43+1 -> 5 | I43: =+H43+1 -> 6 | J43: =+I43+1 -> 7 | K43: =+J43+1 -> 8 | L43: =+K43+1 -> 9 | ... AA43: =+Z43+1 -> 24
C44: 1Q19 | D44: =E16/D16 -> 1.3012916 | E44: =F16/E16 -> 1.1246587 | F44: =G16/F16 -> 1.1905767 | G44: =H16/G16 -> 1.0820522 | H44: =I16/H16 -> 1.0512626 | I44: =J16/I16 -> 1.0277185 | J44: =K16/J16 -> 1.0363301 | K44: =L16/K16 -> 1.0133706 | ... Z44: =AA16/Z16 -> 1.0000011
C45: 2Q19 | D45: =E17/D17 -> 1.3978435 | E45: =F17/E17 -> 1.1976672 | F45: =G17/F17 -> 1.0506283 | G45: =H17/G17 -> 1.0964596 | H45: =I17/H17 -> 1.0504621 | I45: =J17/I17 -> 1.0545884 | J45: =K17/J17 -> 1.0294387 | K45: =L17/K17 -> 1.0194501 | ... Y45: =Z17/Y17 -> 1.0000006
C46: 3Q19 | D46: =E18/D18 -> 1.1430454 | E46: =F18/E18 -> 1.1683938 | F46: =G18/F18 -> 1.1550798 | G46: =H18/G18 -> 1.1147778 | H46: =I18/H18 -> 1.1392271 | I46: =J18/I18 -> 1.0662613 | J46: =K18/J18 -> 1.0364235 | K46: =L18/K18 -> 1.0282007 | ... X46: =Y18/X18 -> 1.000003
C47: 4Q19 | D47: =E19/D19 -> 2.1684497 | E47: =F19/E19 -> 1.1388855 | F47: =G19/F19 -> 1.051594 | G47: =H19/G19 -> 1.0732502 | H47: =I19/H19 -> 1.0534814 | I47: =J19/I19 -> 1.0152064 | J47: =K19/J19 -> 1.0169602 | K47: =L19/K19 -> 1.0324831 | ... W47: =X19/W19 -> 1.0000001
C48: 1Q20 | D48: =E20/D20 -> 1.1834976 | E48: =F20/E20 -> 1.1507408 | F48: =G20/F20 -> 1.055587 | G48: =H20/G20 -> 1.0953923 | H48: =I20/H20 -> 1.0341865 | I48: =J20/I20 -> 1.0655643 | J48: =K20/J20 -> 1.0322632 | K48: =L20/K20 -> 1.0139108 | ... V48: =W20/V20 -> 1.0000151
C49: 2Q20 | D49: =E21/D21 -> 1.4518265 | E49: =F21/E21 -> 1.1842969 | F49: =G21/F21 -> 1.0660675 | G49: =H21/G21 -> 1.1445446 | H49: =I21/H21 -> 1.1641766 | I49: =J21/I21 -> 1.0590551 | J49: =K21/J21 -> 1.3303074 | K49: =L21/K21 -> 1.0500694 | ... U49: =V21/U21 -> 1.0000363
C50: 3Q20 | D50: =E22/D22 -> 1.3704256 | E50: =F22/E22 -> 1.1477889 | F50: =G22/F22 -> 1.1973104 | G50: =H22/G22 -> 1.0409777 | H50: =I22/H22 -> 1.0257579 | I50: =J22/I22 -> 1.0894926 | J50: =K22/J22 -> 1.055923 | K50: =L22/K22 -> 1.0525811 | ... T50: =U22/T22 -> 1.0001012
C51: 4Q20 | D51: =E23/D23 -> 1.3880941 | E51: =F23/E23 -> 1.079426 | F51: =G23/F23 -> 1.1466302 | G51: =H23/G23 -> 1.0412539 | H51: =I23/H23 -> 1.0554969 | I51: =J23/I23 -> 1.0300372 | J51: =K23/J23 -> 1.0467348 | K51: =L23/K23 -> 1.0124616 | ... S51: =T23/S23 -> 1.0001286
C52: 1Q21 | D52: =E24/D24 -> 1.4427679 | E52: =F24/E24 -> 1.2156636 | F52: =G24/F24 -> 1.1175775 | G52: =H24/G24 -> 1.0336047 | H52: =I24/H24 -> 1.0763592 | I52: =J24/I24 -> 1.0160886 | J52: =K24/J24 -> 1.0536442 | K52: =L24/K24 -> 1.0367825 | ... R52: =S24/R24 -> 1.0002529
C53: 2Q21 | D53: =E25/D25 -> 1.4786331 | E53: =F25/E25 -> 1.2194576 | F53: =G25/F25 -> 1.1645781 | G53: =H25/G25 -> 1.0667967 | H53: =I25/H25 -> 1.0571188 | I53: =J25/I25 -> 1.0443695 | J53: =K25/J25 -> 1.0869805 | K53: =L25/K25 -> 1.0412333 | ... Q53: =R25/Q25 -> 1.0005823
C54: 3Q21 | D54: =E26/D26 -> 1.2497833 | E54: =F26/E26 -> 1.2125815 | F54: =G26/F26 -> 1.0370207 | G54: =H26/G26 -> 1.1263534 | H54: =I26/H26 -> 1.0348914 | I54: =J26/I26 -> 1.1513759 | J54: =K26/J26 -> 1.0809369 | K54: =L26/K26 -> 1.0342361 | ... P54: =Q26/P26 -> 1.0010089
C55: 4Q21 | D55: =E27/D27 -> 1.4515615 | E55: =F27/E27 -> 1.2243282 | F55: =G27/F27 -> 1.049979 | G55: =H27/G27 -> 1.1021533 | H55: =I27/H27 -> 1.1242225 | I55: =J27/I27 -> 1.1108954 | J55: =K27/J27 -> 1.0677575 | K55: =L27/K27 -> 1.0261442 | ... O55: =P27/O27 -> 1.0019492
C56: 1Q22 | D56: =E28/D28 -> 1.4892898 | E56: =F28/E28 -> 1.2140042 | F56: =G28/F28 -> 1.1481512 | G56: =H28/G28 -> 1.2293751 | H56: =I28/H28 -> 1.1581185 | I56: =J28/I28 -> 1.13351 | J56: =K28/J28 -> 1.0616542 | K56: =L28/K28 -> 1.0330363 | ... N56: =O28/N28 -> 1.0027861
C57: 2Q22 | D57: =E29/D29 -> 1.403242 | E57: =F29/E29 -> 1.0961717 | F57: =G29/F29 -> 1.4542434 | G57: =H29/G29 -> 1.2576994 | H57: =I29/H29 -> 1.1164984 | I57: =J29/I29 -> 1.1261164 | J57: =K29/J29 -> 1.0477415 | K57: =L29/K29 -> 1.0253029 | ... M57: =N29/M29 -> 1.0061606
C58: 3Q22 | D58: =E30/D30 -> 1.3961072 | E58: =F30/E30 -> 1.8221805 | F58: =G30/F30 -> 1.4050057 | G58: =H30/G30 -> 1.1835013 | H58: =I30/H30 -> 1.1516768 | I58: =J30/I30 -> 1.1417312 | J58: =K30/J30 -> 1.0484787 | K58: =L30/K30 -> 1.0223037 | L58: =M30/L30 -> 1.0149252
C59: 4Q22 | D59: =E31/D31 -> 1.9405588 | E59: =F31/E31 -> 1.3515629 | F59: =G31/F31 -> 1.2369911 | G59: =H31/G31 -> 1.1348301 | H59: =I31/H31 -> 1.0956306 | I59: =J31/I31 -> 1.0891214 | J59: =K31/J31 -> 1.0409653 | K59: =L31/K31 -> 1.019981
C60: 1Q23 | D60: =E32/D32 -> 1.6389213 | E60: =F32/E32 -> 1.4570995 | F60: =G32/F32 -> 1.2515123 | G60: =H32/G32 -> 1.1484949 | H60: =I32/H32 -> 1.092663 | I60: =J32/I32 -> 1.0716184 | J60: =K32/J32 -> 1.0451543
C61: 2Q23 | D61: =E33/D33 -> 2.6132352 | E61: =F33/E33 -> 1.425353 | F61: =G33/F33 -> 1.2876193 | G61: =H33/G33 -> 1.1878672 | H61: =I33/H33 -> 1.1169011 | I61: =J33/I33 -> 1.1125446
C62: 3Q23 | D62: =E34/D34 -> 3.1625421 | E62: =F34/E34 -> 1.1465056 | F62: =G34/F34 -> 1.1490358 | G62: =H34/G34 -> 1.1039995 | H62: =I34/H34 -> 1.0528315
C63: 4Q23 | D63: =E35/D35 -> 1.7569238 | E63: =F35/E35 -> 1.3092274 | F63: =G35/F35 -> 1.217344 | G63: =H35/G35 -> 1.158476
C64: 1Q24 | D64: =E36/D36 -> 2.3320317 | E64: =F36/E36 -> 1.4704633 | F64: =G36/F36 -> 1.2039491
C65: 2Q24 | D65: =E37/D37 -> 1.9802276 | E65: =F37/E37 -> 1.3122223
C66: 3Q24 | D66: =E38/D38 -> 1.8921819
C67: 4Q24
C68: Mediana | D68: =MEDIAN(D44:D66) -> 1.4518265 | E68: =MEDIAN(E44:E66) -> 1.2132929 | F68: =MEDIAN(F44:F66) -> 1.1550798 | G68: =MEDIAN(G44:G66) -> 1.1093887 | H68: =MEDIAN(H44:H66) -> 1.0763592 | I68: =MEDIAN(I44:I66) -> 1.0689399 | J68: =MEDIAN(J44:J66) -> 1.0477415 | K68: =MEDIAN(K44:K66) -> 1.0271725 | ... Z68: =MEDIAN(Z44:Z66) -> 1.0000011
C69: Promedio | D69: =AVERAGE(D44:D66) -> 1.6796731 | E69: =AVERAGE(E44:E66) -> 1.2576672 | F69: =AVERAGE(F44:F66) -> 1.1731658 | G69: =AVERAGE(G44:G66) -> 1.121093 | H69: =AVERAGE(H44:H66) -> 1.0868928 | I69: =AVERAGE(I44:I66) -> 1.0780719 | J69: =AVERAGE(J44:J66) -> 1.0657467 | K69: =AVERAGE(K44:K66) -> 1.0288467 | ... Z69: =AVERAGE(Z44:Z66) -> 1.0000011
C70: cota_inf | D70: =D69*0.8 -> 1.3437385 | E70: =E69*0.8 -> 1.0061338 | F70: =F69*0.8 -> 0.93853261 | G70: =G69*0.8 -> 0.8968744 | H70: =H69*0.8 -> 0.86951423 | I70: =I69*0.8 -> 0.86245756 | J70: =J69*0.8 -> 0.85259736 | K70: =K69*0.8 -> 0.82307736 | ... Z70: =Z69*0.8 -> 0.80000087
C71: cota_sup | D71: =D69*1.2 -> 2.0156077 | E71: =E69*1.2 -> 1.5092007 | F71: =F69*1.2 -> 1.4077989 | G71: =G69*1.2 -> 1.3453116 | H71: =H69*1.2 -> 1.3042713 | I71: =I69*1.2 -> 1.2936863 | J71: =J69*1.2 -> 1.278896 | K71: =K69*1.2 -> 1.234616 | ... Z71: =Z69*1.2 -> 1.2000013
F77: ULTIMATE | J77: IBNR
D78: Primas | E78: REPORTADO | F78: Chain Ladder | G78: BF | H78: CC | I78: Selección | J78: Chain Ladder | K78: BF | L78: CC | M78: Selección
B79: 24 | C79: 1Q19 | D79: 30470484 | E79: {=INDEX(D16:AA16,$B79)} -> 14725385 | F79: =+'1_CL'!AA4 -> 14725385 | G79: =+'1_BF'!I8 -> 14725385 | H79: =+'1_CC'!I8 -> 14725385 | J79: =+'1_CL'!AC4 -> 0 | K79: =+'1_BF'!H8 -> 0 | L79: =+'1_CC'!H8 -> 0
B80: =+B79-1 -> 23 | C80: 2Q19 | D80: 35502400 | E80: {=INDEX(D17:AA17,$B80)} -> 17735279 | F80: =+'1_CL'!AA5 -> 17735298 | G80: =+'1_BF'!I9 -> 17735300 | H80: =+'1_CC'!I9 -> 17735300 | J80: =+'1_CL'!AC5 -> 19.270448 | K80: =+'1_BF'!H9 -> 21.216499 | L80: =+'1_CC'!H9 -> 21.38119
B81: =+B80-1 -> 22 | C81: 3Q19 | D81: 15118899 | E81: {=INDEX(D18:AA18,$B81)} -> 11881761 | F81: =+'1_CL'!AA6 -> 11881781 | G81: =+'1_BF'!I10 -> 11881775 | H81: =+'1_CC'!I10 -> 11881775 | J81: =+'1_CL'!AC6 -> 19.864942 | K81: =+'1_BF'!H10 -> 13.902362 | L81: =+'1_CC'!H10 -> 14.010278
B82: =+B81-1 -> 21 | C82: 4Q19 | D82: 47069939 | E82: {=INDEX(D19:AA19,$B82)} -> 19461650 | F82: =+'1_CL'!AA7 -> 19461705 | G82: =+'1_BF'!I11 -> 19461723 | H82: =+'1_CC'!I11 -> 19461724 | J82: =+'1_CL'!AC7 -> 54.921351 | K82: =+'1_BF'!H11 -> 73.057811 | L82: =+'1_CC'!H11 -> 73.624914
B83: =+B82-1 -> 20 | C83: 1Q20 | D83: 10724971 | E83: {=INDEX(D20:AA20,$B83)} -> 11816173 | F83: =+'1_CL'!AA8 -> 11816242 | G83: =+'1_BF'!I12 -> 11816207 | H83: =+'1_CC'!I12 -> 11816208 | J83: =+'1_CL'!AC8 -> 69.088413 | K83: =+'1_BF'!H12 -> 34.489321 | L83: =+'1_CC'!H12 -> 34.757041
B84: =+B83-1 -> 19 | C84: 2Q20 | D84: 19800249 | E84: {=INDEX(D21:AA21,$B84)} -> 13048471 | F84: =+'1_CL'!AA9 -> 13048674 | G84: =+'1_BF'!I13 -> 13048640 | H84: =+'1_CC'!I13 -> 13048642 | J84: =+'1_CL'!AC9 -> 202.94963 | K84: =+'1_BF'!H13 -> 169.37731 | L84: =+'1_CC'!H13 -> 170.69208
B85: =+B84-1 -> 18 | C85: 3Q20 | D85: 28289118 | E85: {=INDEX(D22:AA22,$B85)} -> 10840140 | F85: =+'1_CL'!AA10 -> 10840662 | G85: =+'1_BF'!I14 -> 10840889 | H85: =+'1_CC'!I14 -> 10840895 | J85: =+'1_CL'!AC10 -> 522.18308 | K85: =+'1_BF'!H14 -> 749.46108 | L85: =+'1_CC'!H14 -> 755.27869
B86: =+B85-1 -> 17 | C86: 4Q20 | D86: 30704506 | E86: {=INDEX(D23:AA23,$B86)} -> 14111136 | F86: =+'1_CL'!AA11 -> 14112788 | G86: =+'1_BF'!I15 -> 14113113 | H86: =+'1_CC'!I15 -> 14113129 | J86: =+'1_CL'!AC11 -> 1652.4212 | K86: =+'1_BF'!H15 -> 1977.3008 | L86: =+'1_CC'!H15 -> 1992.6494
B87: =+B86-1 -> 16 | C87: 1Q21 | D87: 18880428 | E87: {=INDEX(D24:AA24,$B87)} -> 15729334 | F87: =+'1_CL'!AA12 -> 15733379 | G87: =+'1_BF'!I16 -> 15732004 | H87: =+'1_CC'!I16 -> 15732024 | J87: =+'1_CL'!AC12 -> 4044.684 | K87: =+'1_BF'!H16 -> 2669.5443 | L87: =+'1_CC'!H16 -> 2690.2664
B88: =+B87-1 -> 15 | C88: 2Q21 | D88: 17119243 | E88: {=INDEX(D25:AA25,$B88)} -> 14343596 | F88: =+'1_CL'!AA13 -> 14351698 | G88: =+'1_BF'!I17 -> 14348911 | H88: =+'1_CC'!I17 -> 14348953 | J88: =+'1_CL'!AC13 -> 8101.7825 | K88: =+'1_BF'!H17 -> 5315.2605 | L88: =+'1_CC'!H17 -> 5356.5197
B89: =+B88-1 -> 14 | C89: 3Q21 | D89: 41471482 | E89: {=INDEX(D26:AA26,$B89)} -> 15119935 | F89: =+'1_CL'!AA14 -> 15137386 | G89: =+'1_BF'!I18 -> 15146231 | H89: =+'1_CC'!I18 -> 15146435 | J89: =+'1_CL'!AC14 -> 17451.426 | K89: =+'1_BF'!H18 -> 26296.157 | L89: =+'1_CC'!H18 -> 26500.278
B90: =+B89-1 -> 13 | C90: 4Q21 | D90: 35368087 | E90: {=INDEX(D27:AA27,$B90)} -> 18730024 | F90: =+'1_CL'!AA15 -> 18772946 | G90: =+'1_BF'!I19 -> 18774499 | H90: =+'1_CC'!I19 -> 18774845 | J90: =+'1_CL'!AC15 -> 42921.81 | K90: =+'1_BF'!H19 -> 44475.4 | L90: =+'1_CC'!H19 -> 44820.636
B91: =+B90-1 -> 12 | C91: 1Q22 | D91: 26145160 | E91: {=INDEX(D28:AA28,$B91)} -> 19627354 | F91: =+'1_CL'!AA16 -> 19716644 | G91: =+'1_BF'!I20 -> 19692475 | H91: =+'1_CC'!I20 -> 19692981 | J91: =+'1_CL'!AC16 -> 89289.649 | K91: =+'1_BF'!H20 -> 65121.159 | L91: =+'1_CC'!H20 -> 65626.655
... B102: =+B101-1 -> 1 | C102: 4Q24 | D102: 55736823 | E102: {=INDEX(D39:AA39,$B102)} -> 5149958 | F102: =+'1_CL'!AA27 -> 29715993 | G102: =+'1_BF'!I31 -> 30492473 | H102: =+'1_CC'!I31 -> 30689192 | J102: =+'1_CL'!AC27 -> 24566035 | K102: =+'1_BF'!H31 -> 25342515 | L102: =+'1_CC'!H31 -> 25539234
C108: TRIÁNGULO DESARROLLADO AL 31 DE SEPTIEMBRE DE 2026
D110: 1 | E110: =+D110+1 -> 2 | F110: =+E110+1 -> 3 | G110: =+F110+1 -> 4 | H110: =+G110+1 -> 5 | I110: =+H110+1 -> 6 | J110: =+I110+1 -> 7 | K110: =+J110+1 -> 8 | L110: =+K110+1 -> 9 | ... AA110: =+Z110+1 -> 24
C111: 1Q19 | D111: 6418198 | E111: 8351947 | F111: 9393090 | G111: 11183194 | H111: 12100800 | I111: 12721118 | J111: 13073728 | K111: 13548698 | L111: 13729852 | M111: 14178002 | N111: 14403018 | O111: 14589694 | P111: 14666170 | Q111: 14699145 | R111: 14709918 | S111: 14721902 | T111: 14723975 | U111: 14724778 | V111: 14725216 | W111: 14725343 | X111: 14725356 | Y111: 14725361 | Z111: 14725369 | AA111: 14725385
C112: 2Q19 | D112: 7475822 | E112: 10450029 | F112: 12515657 | G112: 13149304 | H112: 14417681 | I112: 15145227 | J112: 15971980 | K112: 16442175 | L112: 16761977 | M112: 17230340 | N112: 17479823 | O112: 17658472 | P112: 17691106 | Q112: 17707511 | R112: 17727251 | S112: 17731572 | T112: 17733454 | U112: 17734435 | V112: 17734974 | W112: 17735197 | X112: 17735258 | Y112: 17735268 | Z112: 17735279 | AA112: 17735298
C113: 3Q19 | D113: 4944676 | E113: 5651989 | F113: 6603749 | G113: 7627857 | H113: 8503366 | I113: 9687265 | J113: 10329156 | K113: 10705380 | L113: 11007279 | M113: 11432174 | N113: 11644639 | O113: 11802250 | P113: 11840837 | Q113: 11864201 | R113: 11873586 | S113: 11878223 | T113: 11880065 | U113: 11880905 | V113: 11881492 | W113: 11881607 | X113: 11881725 | Y113: 11881761 | Z113: 11881768 | AA113: 11881781
C114: 4Q19 | D114: 5990844 | E114: 12990844 | F114: 14795084 | G114: 15558421 | H114: 16698078 | I114: 17591115 | J114: 17858613 | K114: 18161498 | L114: 18751439 | M114: 18855100 | N114: 19152179 | O114: 19349458 | P114: 19426010 | Q114: 19444545 | R114: 19453256 | S114: 19457999 | T114: 19459976 | U114: 19461146 | V114: 19461559 | W114: 19461649 | X114: 19461650 | Y114: 19461709 | Z114: 19461720 | AA114: 19461741
C115: 1Q20 | D115: 6106533 | E115: 7227067 | F115: 8316481 | G115: 8778769 | H115: 9616196 | I115: 9944940 | J115: 10596973 | K115: 10938865 | L115: 11091033 | M115: 11574757 | N115: 11660948 | O115: 11754449 | P115: 11785976 | Q115: 11801623 | R115: 11808422 | S115: 11812430 | T115: 11814677 | U115: 11815553 | V115: 11815994 | W115: 11816173 | X115: 11816183 | Y115: 11816219 | Z115: 11816226 | AA115: 11816238
C116: 2Q20 | D116: 3511339 | E116: 5097855 | F116: 6037374 | G116: 6436248 | H116: 7366573 | I116: 8575992 | J116: 9082448 | K116: 12082448 | L116: 12687409 | M116: 12838372 | N116: 12930641 | O116: 12990612 | P116: 13017211 | Q116: 13032985 | R116: 13041104 | S116: 13045224 | T116: 13046906 | U116: 13047997 | V116: 13048471 | W116: 13048635 | X116: 13048765 | Y116: 13048804 | Z116: 13048812 | AA116: 13048826
C117: 3Q20 | D117: 4141271 | E117: 5675304 | F117: 6514051 | G117: 7799341 | H117: 8118940 | I117: 8328067 | J117: 9073367 | K117: 9580777 | L117: 10084545 | M117: 10574369 | N117: 10704764 | O117: 10779530 | P117: 10810916 | Q117: 10825407 | R117: 10831969 | S117: 10836654 | T117: 10839043 | U117: 10840140 | V117: 10840676 | W117: 10840840 | X117: 10840840 | Y117: 10840846 | Z117: 10840852 | AA117: 10840864
C118: 4Q20 | D118: 6591656 | E118: 9149839 | F118: 9876574 | G118: 11324778 | H118: 11791969 | I118: 12446387 | J118: 12820241 | K118: 13419392 | L118: 13586619 | M118: 13861205 | N118: 13987078 | O118: 14043493 | P118: 14079323 | Q118: 14095393 | R118: 14104571 | S118: 14109322 | T118: 14111136 | U118: 14111984 | V118: 14112284 | W118: 14112349 | X118: 14112489 | Y118: 14112494 | Z118: 14112502 | AA118: 14112517
C119: 1Q21 | D119: 6289704 | E119: 9074583 | F119: 11031640 | G119: 12328713 | H119: 12743016 | I119: 13716063 | J119: 13936735 | K119: 14684360 | L119: 15224487 | M119: 15505624 | N119: 15616491 | O119: 15669883 | P119: 15701026 | Q119: 15717007 | R119: 15725357 | S119: 15729334 | T119: 15731356 | U119: 15732523 | V119: 15732857 | W119: 15732929 | X119: 15732930 | Y119: 15732978 | Z119: 15732988
C120: 2Q21 | D120: 4959185 | E120: 7332815 | F120: 8942057 | G120: 10413724 | H120: 11109326 | I120: 11743877 | J120: 12264947 | K120: 13331758 | L120: 13881470 | M120: 14105853 | N120: 14231236 | O120: 14285043 | P120: 14317196 | Q120: 14335249 | R120: 14343596 | S120: 14348127 | T120: 14349977 | U120: 14350771 | V120: 14351198 | W120: 14351416 | X120: 14351558 | Y120: 14351563
C121: 3Q21 | D121: 6194048 | E121: 7741218 | F121: 9386858 | G121: 9734366 | H121: 10964336 | I121: 11346897 | J121: 13064544 | K121: 14121948 | L121: 14605429 | M121: 14862271 | N121: 15012968 | O121: 15074585 | P121: 15104696 | Q121: 15119935 | R121: 15129354 | S121: 15133043 | T121: 15135174 | U121: 15136439 | V121: 15136890 | W121: 15137119 | X121: 15137269
C122: 4Q21 | D122: 6500694 | E122: 9436157 | F122: 11552953 | G122: 12130358 | H122: 13369514 | I122: 15030308 | J122: 16697100 | K122: 17828453 | L122: 18294564 | M122: 18522862 | N122: 18641988 | O122: 18693587 | P122: 18730024 | Q122: 18748921 | R122: 18758881 | S122: 18766207 | T122: 18768199 | U122: 18770099 | V122: 18770657 | W122: 18770893
C123: 1Q22 | D123: 5205434 | E123: 7752400 | F123: 9411446 | G123: 10805763 | H123: 13284336 | I123: 15384835 | J123: 17438864 | K123: 18514044 | L123: 19125680 | M123: 19431036 | N123: 19572822 | O123: 19627354 | P123: 19663627 | Q123: 19683641 | R123: 19699211 | S123: 19705847 | T123: 19708903 | U123: 19710296 | V123: 19711032
C124: 2Q22 | D124: 5184519 | E124: 7275135 | F124: 7974797 | G124: 11597296 | H124: 14585912 | I124: 16285147 | J124: 18338971 | K124: 19214501 | L124: 19700684 | M124: 19926910 | N124: 20049671 | O124: 20321045 | P124: 20372891 | Q124: 20413090 | R124: 20424976 | S124: 20432953 | T124: 20435580 | U124: 20436694
C125: 3Q22 | D125: 3419011 | E125: 4773306 | F125: 8697825 | G125: 12220494 | H125: 14462971 | I125: 16656668 | J125: 19017438 | K125: 19939378 | L125: 20384099 | M125: 20688336 | N125: 20898107 | O125: 21111692 | P125: 21152842 | Q125: 21178475 | R125: 21190676 | S125: 21197868 | T125: 21200593
C126: 4Q22 | D126: 5498188 | E126: 10669557 | F126: 14420577 | G126: 17838126 | H126: 20243242 | I126: 22179116 | J126: 24155749 | K126: 25145296 | L126: 25647723 | M126: 26098748 | N126: 26335750 | O126: 26408644 | P126: 26457449 | Q126: 26487647 | R126: 26503070 | S126: 26509530
C127: 1Q23 | D127: 6382667 | E127: 10460689 | F127: 15242265 | G127: 19075882 | H127: 21908553 | I127: 23938666 | J127: 25653115 | K127: 26811464 | L127: 28221241 | M127: 29142398 | N127: 29351843 | O127: 29651828 | P127: 29731358 | Q127: 29798205 | R127: 29821777
C128: 2Q23 | D128: 3022770 | E128: 7899209 | F128: 11259161 | G128: 14497513 | H128: 17221120 | I128: 19234288 | J128: 21399003 | K128: 22420624 | L128: 23161319 | M128: 23450349 | N128: 23594816 | O128: 23660554 | P128: 23709000 | Q128: 23738896
...

Sheet 1_CL
A1: CHAIN-LADDER — Triángulo Proyectado e IBNR | Vinculado a hojas 1_Triangulo y 2_Factores
A2: AZUL=observado (hoja 1) · AMARILLO=proyección CL = C_{i,j-1} × f̂_{j-1} (hoja 2) · VERDE=IBNR
A3: AO | B3: Trim. | C3: T01 | D3: T02 | E3: T03 | F3: T04 | G3: T05 | H3: T06 | I3: T07 | J3: T08 | K3: T09 | L3: T10 | M3: T11 | N3: T12 | O3: T13 | P3: T14 | Q3: T15 | R3: T16 | S3: T17 | T3: T18 | U3: T19 | V3: T20 | W3: T21 | X3: T22 | Y3: T23 | Z3: T24 | AA3: Último Proy. | AB3: Pagado Actual | AC3: IBNR CL
A4: AO01 | B4: 1Q19 | R4: =IF(Triangulo1!S16=0,"-",Triangulo1!S16) -> 14721902 | S4: =IF(Triangulo1!T16=0,"-",Triangulo1!T16) -> 14723975 | T4: =IF(Triangulo1!U16=0,"-",Triangulo1!U16) -> 14724778 | U4: =IF(Triangulo1!V16=0,"-",Triangulo1!V16) -> 14725216 | V4: =IF(Triangulo1!W16=0,"-",Triangulo1!W16) -> 14725343 | W4: =IF(Triangulo1!X16=0,"-",Triangulo1!X16) -> 14725356 | X4: =IF(Triangulo1!Y16=0,"-",Triangulo1!Y16) -> 14725361 | Y4: =IF(Triangulo1!Z16=0,"-",Triangulo1!Z16) -> 14725369 | Z4: =IF(Triangulo1!AA16=0,"-",Triangulo1!AA16) -> 14725385 | AA4: =+Z4 -> 14725385 | AB4: =+Z4 -> 14725385 | AC4: =AA4-AB4 -> 0
A5: AO02 | B5: 2Q19 | Q5: =IF(Triangulo1!R17=0,"-",Triangulo1!R17) -> 17727251 | R5: =IF(Triangulo1!S17=0,"-",Triangulo1!S17) -> 17731572 | S5: =IF(Triangulo1!T17=0,"-",Triangulo1!T17) -> 17733454 | T5: =IF(Triangulo1!U17=0,"-",Triangulo1!U17) -> 17734435 | U5: =IF(Triangulo1!V17=0,"-",Triangulo1!V17) -> 17734974 | V5: =IF(Triangulo1!W17=0,"-",Triangulo1!W17) -> 17735197 | W5: =IF(Triangulo1!X17=0,"-",Triangulo1!X17) -> 17735258 | X5: =IF(Triangulo1!Y17=0,"-",Triangulo1!Y17) -> 17735268 | Y5: =IF(Triangulo1!Z17=0,"-",Triangulo1!Z17) -> 17735279 | Z5: =+Y5*Y$30 -> 17735298 | AA5: =+Z5 -> 17735298 | AB5: =+Y5 -> 17735279 | AC5: =AA5-AB5 -> 19.270448
A6: AO03 | B6: 3Q19 | P6: =IF(Triangulo1!Q18=0,"-",Triangulo1!Q18) -> 11864201 | Q6: =IF(Triangulo1!R18=0,"-",Triangulo1!R18) -> 11873586 | R6: =IF(Triangulo1!S18=0,"-",Triangulo1!S18) -> 11878223 | S6: =IF(Triangulo1!T18=0,"-",Triangulo1!T18) -> 11880065 | T6: =IF(Triangulo1!U18=0,"-",Triangulo1!U18) -> 11880905 | U6: =IF(Triangulo1!V18=0,"-",Triangulo1!V18) -> 11881492 | V6: =IF(Triangulo1!W18=0,"-",Triangulo1!W18) -> 11881607 | W6: =IF(Triangulo1!X18=0,"-",Triangulo1!X18) -> 11881725 | X6: =IF(Triangulo1!Y18=0,"-",Triangulo1!Y18) -> 11881761 | Y6: =+X6*X$30 -> 11881768 | Z6: =+Y6*Y$30 -> 11881781 | AA6: =+Z6 -> 11881781 | AB6: =+X6 -> 11881761 | AC6: =AA6-AB6 -> 19.864942
A7: AO04 | B7: 4Q19 | O7: =IF(Triangulo1!P19=0,"-",Triangulo1!P19) -> 19426010 | P7: =IF(Triangulo1!Q19=0,"-",Triangulo1!Q19) -> 19444545 | Q7: =IF(Triangulo1!R19=0,"-",Triangulo1!R19) -> 19453256 | R7: =IF(Triangulo1!S19=0,"-",Triangulo1!S19) -> 19457999 | S7: =IF(Triangulo1!T19=0,"-",Triangulo1!T19) -> 19459976 | T7: =IF(Triangulo1!U19=0,"-",Triangulo1!U19) -> 19461146 | U7: =IF(Triangulo1!V19=0,"-",Triangulo1!V19) -> 19461559 | V7: =IF(Triangulo1!W19=0,"-",Triangulo1!W19) -> 19461649 | W7: =IF(Triangulo1!X19=0,"-",Triangulo1!X19) -> 19461650 | X7: =+W7*W$30 -> 19461672 | Y7: =+X7*X$30 -> 19461684 | Z7: =+Y7*Y$30 -> 19461705 | AA7: =+Z7 -> 19461705 | AB7: =+W7 -> 19461650 | AC7: =AA7-AB7 -> 54.921351
A8: AO05 | B8: 1Q20 | N8: =IF(Triangulo1!O20=0,"-",Triangulo1!O20) -> 11754449 | O8: =IF(Triangulo1!P20=0,"-",Triangulo1!P20) -> 11785976 | P8: =IF(Triangulo1!Q20=0,"-",Triangulo1!Q20) -> 11801623 | Q8: =IF(Triangulo1!R20=0,"-",Triangulo1!R20) -> 11808422 | R8: =IF(Triangulo1!S20=0,"-",Triangulo1!S20) -> 11812430 | S8: =IF(Triangulo1!T20=0,"-",Triangulo1!T20) -> 11814677 | T8: =IF(Triangulo1!U20=0,"-",Triangulo1!U20) -> 11815553 | U8: =IF(Triangulo1!V20=0,"-",Triangulo1!V20) -> 11815994 | V8: =IF(Triangulo1!W20=0,"-",Triangulo1!W20) -> 11816173 | W8: =+V8*V$30 -> 11816209 | X8: =+W8*W$30 -> 11816222 | Y8: =+X8*X$30 -> 11816229 | Z8: =+Y8*Y$30 -> 11816242 | AA8: =+Z8 -> 11816242 | AB8: =+V8 -> 11816173 | AC8: =AA8-AB8 -> 69.088413
A9: AO06 | B9: 2Q20 | M9: =IF(Triangulo1!N21=0,"-",Triangulo1!N21) -> 12930641 | N9: =IF(Triangulo1!O21=0,"-",Triangulo1!O21) -> 12990612 | O9: =IF(Triangulo1!P21=0,"-",Triangulo1!P21) -> 13017211 | P9: =IF(Triangulo1!Q21=0,"-",Triangulo1!Q21) -> 13032985 | Q9: =IF(Triangulo1!R21=0,"-",Triangulo1!R21) -> 13041104 | R9: =IF(Triangulo1!S21=0,"-",Triangulo1!S21) -> 13045224 | S9: =IF(Triangulo1!T21=0,"-",Triangulo1!T21) -> 13046906 | T9: =IF(Triangulo1!U21=0,"-",Triangulo1!U21) -> 13047997 | U9: =IF(Triangulo1!V21=0,"-",Triangulo1!V21) -> 13048471 | V9: =+U9*U$30 -> 13048598 | W9: =+V9*V$30 -> 13048637 | X9: =+W9*W$30 -> 13048652 | Y9: =+X9*X$30 -> 13048660 | Z9: =+Y9*Y$30 -> 13048674 | AA9: =+Z9 -> 13048674 | AB9: =+U9 -> 13048471 | AC9: =AA9-AB9 -> 202.94963
A10: AO07 | B10: 3Q20 | L10: =IF(Triangulo1!M22=0,"-",Triangulo1!M22) -> 10574369 | M10: =IF(Triangulo1!N22=0,"-",Triangulo1!N22) -> 10704764 | N10: =IF(Triangulo1!O22=0,"-",Triangulo1!O22) -> 10779530 | O10: =IF(Triangulo1!P22=0,"-",Triangulo1!P22) -> 10810916 | P10: =IF(Triangulo1!Q22=0,"-",Triangulo1!Q22) -> 10825407 | Q10: =IF(Triangulo1!R22=0,"-",Triangulo1!R22) -> 10831969 | R10: =IF(Triangulo1!S22=0,"-",Triangulo1!S22) -> 10836654 | S10: =IF(Triangulo1!T22=0,"-",Triangulo1!T22) -> 10839043 | T10: =IF(Triangulo1!U22=0,"-",Triangulo1!U22) -> 10840140 | U10: =+T10*T$30 -> 10840494 | V10: =+U10*U$30 -> 10840599 | W10: =+V10*V$30 -> 10840632 | X10: =+W10*W$30 -> 10840644 | Y10: =+X10*X$30 -> 10840650 | Z10: =+Y10*Y$30 -> 10840662 | AA10: =+Z10 -> 10840662 | AB10: =+T10 -> 10840140 | AC10: =AA10-AB10 -> 522.18308
A11: AO08 | B11: 4Q20 | K11: =IF(Triangulo1!L23=0,"-",Triangulo1!L23) -> 13586619 | L11: =IF(Triangulo1!M23=0,"-",Triangulo1!M23) -> 13861205 | M11: =IF(Triangulo1!N23=0,"-",Triangulo1!N23) -> 13987078 | N11: =IF(Triangulo1!O23=0,"-",Triangulo1!O23) -> 14043493 | O11: =IF(Triangulo1!P23=0,"-",Triangulo1!P23) -> 14079323 | P11: =IF(Triangulo1!Q23=0,"-",Triangulo1!Q23) -> 14095393 | Q11: =IF(Triangulo1!R23=0,"-",Triangulo1!R23) -> 14104571 | R11: =IF(Triangulo1!S23=0,"-",Triangulo1!S23) -> 14109322 | S11: =IF(Triangulo1!T23=0,"-",Triangulo1!T23) -> 14111136 | T11: =+S11*S$30 -> 14112109 | U11: =+T11*T$30 -> 14112569 | V11: =+U11*U$30 -> 14112706 | W11: =+V11*V$30 -> 14112749 | X11: =+W11*W$30 -> 14112765 | Y11: =+X11*X$30 -> 14112773 | Z11: =+Y11*Y$30 -> 14112788 | AA11: =+Z11 -> 14112788 | AB11: =+S11 -> 14111136 | AC11: =AA11-AB11 -> 1652.4212
A12: AO09 | B12: 1Q21 | J12: =IF(Triangulo1!K24=0,"-",Triangulo1!K24) -> 14684360 | K12: =IF(Triangulo1!L24=0,"-",Triangulo1!L24) -> 15224487 | L12: =IF(Triangulo1!M24=0,"-",Triangulo1!M24) -> 15505624 | M12: =IF(Triangulo1!N24=0,"-",Triangulo1!N24) -> 15616491 | N12: =IF(Triangulo1!O24=0,"-",Triangulo1!O24) -> 15669883 | O12: =IF(Triangulo1!P24=0,"-",Triangulo1!P24) -> 15701026 | P12: =IF(Triangulo1!Q24=0,"-",Triangulo1!Q24) -> 15717007 | Q12: =IF(Triangulo1!R24=0,"-",Triangulo1!R24) -> 15725357 | R12: =IF(Triangulo1!S24=0,"-",Triangulo1!S24) -> 15729334 | S12: =+R12*R30 -> 15731537 | T12: =+S12*S30 -> 15732621 | U12: =+T12*T30 -> 15733134 | V12: =+U12*U30 -> 15733287 | W12: =+V12*V30 -> 15733334 | X12: =+W12*W30 -> 15733352 | Y12: =+X12*X30 -> 15733362 | Z12: =+Y12*Y30 -> 15733379 | AA12: =+Z12 -> 15733379 | AB12: =+R12 -> 15729334 | AC12: =AA12-AB12 -> 4044.684
A13: AO10 | B13: 2Q21 | I13: =IF(Triangulo1!J25=0,"-",Triangulo1!J25) -> 12264947 | J13: =IF(Triangulo1!K25=0,"-",Triangulo1!K25) -> 13331758 | K13: =IF(Triangulo1!L25=0,"-",Triangulo1!L25) -> 13881470 | L13: =IF(Triangulo1!M25=0,"-",Triangulo1!M25) -> 14105853 | M13: =IF(Triangulo1!N25=0,"-",Triangulo1!N25) -> 14231236 | N13: =IF(Triangulo1!O25=0,"-",Triangulo1!O25) -> 14285043 | O13: =IF(Triangulo1!P25=0,"-",Triangulo1!P25) -> 14317196 | P13: =IF(Triangulo1!Q25=0,"-",Triangulo1!Q25) -> 14335249 | Q13: =IF(Triangulo1!R25=0,"-",Triangulo1!R25) -> 14343596 | R13: =+Q13*Q30 -> 14348008 | S13: =+R13*R30 -> 14350017 | T13: =+S13*S30 -> 14351006 | U13: =+T13*T30 -> 14351475 | V13: =+U13*U30 -> 14351614 | W13: =+V13*V30 -> 14351657 | X13: =+W13*W30 -> 14351674 | Y13: =+X13*X30 -> 14351682 | Z13: =+Y13*Y30 -> 14351698 | AA13: =+Z13 -> 14351698 | AB13: =+Q13 -> 14343596 | AC13: =AA13-AB13 -> 8101.7825
A14: AO11 | B14: 3Q21 | H14: =IF(Triangulo1!I26=0,"-",Triangulo1!I26) -> 11346897 | I14: =IF(Triangulo1!J26=0,"-",Triangulo1!J26) -> 13064544 | J14: =IF(Triangulo1!K26=0,"-",Triangulo1!K26) -> 14121948 | K14: =IF(Triangulo1!L26=0,"-",Triangulo1!L26) -> 14605429 | L14: =IF(Triangulo1!M26=0,"-",Triangulo1!M26) -> 14862271 | M14: =IF(Triangulo1!N26=0,"-",Triangulo1!N26) -> 15012968 | N14: =IF(Triangulo1!O26=0,"-",Triangulo1!O26) -> 15074585 | O14: =IF(Triangulo1!P26=0,"-",Triangulo1!P26) -> 15104696 | P14: =IF(Triangulo1!Q26=0,"-",Triangulo1!Q26) -> 15119935 | Q14: =+P14*P30 -> 15128841 | R14: =+Q14*Q30 -> 15133495 | S14: =+R14*R30 -> 15135614 | T14: =+S14*S30 -> 15136657 | U14: =+T14*T30 -> 15137151 | V14: =+U14*U30 -> 15137298 | W14: =+V14*V30 -> 15137344 | X14: =+W14*W30 -> 15137361 | ... Z14: =+Y14*Y30 -> 15137386 | AA14: =+Z14 -> 15137386 | AB14: =+P14 -> 15119935 | AC14: =AA14-AB14 -> 17451.426
A15: AO12 | B15: 4Q21 | G15: =IF(Triangulo1!H27=0,"-",Triangulo1!H27) -> 13369514 | H15: =IF(Triangulo1!I27=0,"-",Triangulo1!I27) -> 15030308 | I15: =IF(Triangulo1!J27=0,"-",Triangulo1!J27) -> 16697100 | J15: =IF(Triangulo1!K27=0,"-",Triangulo1!K27) -> 17828453 | K15: =IF(Triangulo1!L27=0,"-",Triangulo1!L27) -> 18294564 | L15: =IF(Triangulo1!M27=0,"-",Triangulo1!M27) -> 18522862 | M15: =IF(Triangulo1!N27=0,"-",Triangulo1!N27) -> 18641988 | N15: =IF(Triangulo1!O27=0,"-",Triangulo1!O27) -> 18693587 | O15: =IF(Triangulo1!P27=0,"-",Triangulo1!P27) -> 18730024 | P15: =+O15*O30 -> 18751303 | Q15: =+P15*P30 -> 18762348 | R15: =+Q15*Q30 -> 18768120 | S15: =+R15*R30 -> 18770748 | T15: =+S15*S30 -> 18772042 | U15: =+T15*T30 -> 18772654 | V15: =+U15*U30 -> 18772836 | W15: =+V15*V30 -> 18772893 | ... Z15: =+Y15*Y30 -> 18772946 | AA15: =+Z15 -> 18772946 | AB15: =+O15 -> 18730024 | AC15: =AA15-AB15 -> 42921.81
A16: AO13 | B16: 1Q22 | F16: =IF(Triangulo1!G28=0,"-",Triangulo1!G28) -> 10805763 | G16: =IF(Triangulo1!H28=0,"-",Triangulo1!H28) -> 13284336 | H16: =IF(Triangulo1!I28=0,"-",Triangulo1!I28) -> 15384835 | I16: =IF(Triangulo1!J28=0,"-",Triangulo1!J28) -> 17438864 | J16: =IF(Triangulo1!K28=0,"-",Triangulo1!K28) -> 18514044 | K16: =IF(Triangulo1!L28=0,"-",Triangulo1!L28) -> 19125680 | L16: =IF(Triangulo1!M28=0,"-",Triangulo1!M28) -> 19431036 | M16: =IF(Triangulo1!N28=0,"-",Triangulo1!N28) -> 19572822 | N16: =IF(Triangulo1!O28=0,"-",Triangulo1!O28) -> 19627354 | O16: =+N16*N30 -> 19671564 | P16: =+O16*O30 -> 19693913 | Q16: =+P16*P30 -> 19705513 | R16: =+Q16*Q30 -> 19711575 | S16: =+R16*R30 -> 19714335 | T16: =+S16*S30 -> 19715694 | U16: =+T16*T30 -> 19716337 | V16: =+U16*U30 -> 19716528 | ... Z16: =+Y16*Y30 -> 19716644 | AA16: =+Z16 -> 19716644 | AB16: =+N16 -> 19627354 | AC16: =AA16-AB16 -> 89289.649
A17: AO14 | B17: 2Q22 | E17: =IF(Triangulo1!F29=0,"-",Triangulo1!F29) -> 7974797 | F17: =IF(Triangulo1!G29=0,"-",Triangulo1!G29) -> 11597296 | G17: =IF(Triangulo1!H29=0,"-",Triangulo1!H29) -> 14585912 | H17: =IF(Triangulo1!I29=0,"-",Triangulo1!I29) -> 16285147 | I17: =IF(Triangulo1!J29=0,"-",Triangulo1!J29) -> 18338971 | J17: =IF(Triangulo1!K29=0,"-",Triangulo1!K29) -> 19214501 | K17: =IF(Triangulo1!L29=0,"-",Triangulo1!L29) -> 19700684 | L17: =IF(Triangulo1!M29=0,"-",Triangulo1!M29) -> 19926910 | M17: =IF(Triangulo1!N29=0,"-",Triangulo1!N29) -> 20049671 | N17: =+M17*M30 -> 20127097 | O17: =+N17*N30 -> 20172433 | P17: =+O17*O30 -> 20195350 | Q17: =+P17*P30 -> 20207246 | R17: =+Q17*Q30 -> 20213462 | S17: =+R17*R30 -> 20216293 | T17: =+S17*S30 -> 20217686 | U17: =+T17*T30 -> 20218345 | ... Z17: =+Y17*Y30 -> 20218660 | AA17: =+Z17 -> 20218660 | AB17: =+M17 -> 20049671 | AC17: =AA17-AB17 -> 168988.85
A18: AO15 | B18: 3Q22 | D18: =IF(Triangulo1!E30=0,"-",Triangulo1!E30) -> 4773306 | E18: =IF(Triangulo1!F30=0,"-",Triangulo1!F30) -> 8697825 | F18: =IF(Triangulo1!G30=0,"-",Triangulo1!G30) -> 12220494 | G18: =IF(Triangulo1!H30=0,"-",Triangulo1!H30) -> 14462971 | H18: =IF(Triangulo1!I30=0,"-",Triangulo1!I30) -> 16656668 | I18: =IF(Triangulo1!J30=0,"-",Triangulo1!J30) -> 19017438 | J18: =IF(Triangulo1!K30=0,"-",Triangulo1!K30) -> 19939378 | K18: =IF(Triangulo1!L30=0,"-",Triangulo1!L30) -> 20384099 | L18: =IF(Triangulo1!M30=0,"-",Triangulo1!M30) -> 20688336 | M18: =+L18*L30 -> 20855893 | N18: =+M18*M30 -> 20936432 | O18: =+N18*N30 -> 20983591 | P18: =+O18*O30 -> 21007431 | Q18: =+P18*P30 -> 21019805 | R18: =+Q18*Q30 -> 21026271 | S18: =+R18*R30 -> 21029215 | T18: =+S18*S30 -> 21030664 | ... Z18: =+Y18*Y30 -> 21031677 | AA18: =+Z18 -> 21031677 | AB18: =+L18 -> 20688336 | AC18: =AA18-AB18 -> 343341.34
A19: AO16 | B19: 4Q22 | C19: =IF(Triangulo1!D31=0,"-",Triangulo1!D31) -> 5498188 | D19: =IF(Triangulo1!E31=0,"-",Triangulo1!E31) -> 10669557 | E19: =IF(Triangulo1!F31=0,"-",Triangulo1!F31) -> 14420577 | F19: =IF(Triangulo1!G31=0,"-",Triangulo1!G31) -> 17838126 | G19: =IF(Triangulo1!H31=0,"-",Triangulo1!H31) -> 20243242 | H19: =IF(Triangulo1!I31=0,"-",Triangulo1!I31) -> 22179116 | I19: =IF(Triangulo1!J31=0,"-",Triangulo1!J31) -> 24155749 | J19: =IF(Triangulo1!K31=0,"-",Triangulo1!K31) -> 25145296 | K19: =IF(Triangulo1!L31=0,"-",Triangulo1!L31) -> 25647723 | L19: =+K19*K30 -> 26047473 | M19: =+L19*L30 -> 26258435 | N19: =+M19*M30 -> 26359837 | O19: =+N19*N30 -> 26419212 | P19: =+O19*O30 -> 26449226 | Q19: =+P19*P30 -> 26464806 | R19: =+Q19*Q30 -> 26472947 | S19: =+R19*R30 -> 26476654 | ... Z19: =+Y19*Y30 -> 26479754 | AA19: =+Z19 -> 26479754 | AB19: =+K19 -> 25647723 | AC19: =AA19-AB19 -> 832031.14
A20: AO17 | B20: 1Q23 | C20: =IF(Triangulo1!D32=0,"-",Triangulo1!D32) -> 6382667 | D20: =IF(Triangulo1!E32=0,"-",Triangulo1!E32) -> 10460689 | E20: =IF(Triangulo1!F32=0,"-",Triangulo1!F32) -> 15242265 | F20: =IF(Triangulo1!G32=0,"-",Triangulo1!G32) -> 19075882 | G20: =IF(Triangulo1!H32=0,"-",Triangulo1!H32) -> 21908553 | H20: =IF(Triangulo1!I32=0,"-",Triangulo1!I32) -> 23938666 | I20: =IF(Triangulo1!J32=0,"-",Triangulo1!J32) -> 25653115 | J20: =IF(Triangulo1!K32=0,"-",Triangulo1!K32) -> 26811464 | K20: =+J20*J30 -> 27578440 | L20: =+K20*K30 -> 28008283 | M20: =+L20*L30 -> 28235125 | N20: =+M20*M30 -> 28344161 | O20: =+N20*N30 -> 28408006 | P20: =+O20*O30 -> 28440280 | Q20: =+P20*P30 -> 28457032 | R20: =+Q20*Q30 -> 28465786 | ... Z20: =+Y20*Y30 -> 28473105 | AA20: =+Z20 -> 28473105 | AB20: =+J20 -> 26811464 | AC20: =AA20-AB20 -> 1661641.4
A21: AO18 | B21: 2Q23 | C21: =IF(Triangulo1!D33=0,"-",Triangulo1!D33) -> 3022770 | D21: =IF(Triangulo1!E33=0,"-",Triangulo1!E33) -> 7899209 | E21: =IF(Triangulo1!F33=0,"-",Triangulo1!F33) -> 11259161 | F21: =IF(Triangulo1!G33=0,"-",Triangulo1!G33) -> 14497513 | G21: =IF(Triangulo1!H33=0,"-",Triangulo1!H33) -> 17221120 | H21: =IF(Triangulo1!I33=0,"-",Triangulo1!I33) -> 19234288 | I21: =IF(Triangulo1!J33=0,"-",Triangulo1!J33) -> 21399003 | J21: =+I21*I30 -> 22606803 | K21: =+J21*J30 -> 23253500 | L21: =+K21*K30 -> 23615933 | M21: =+L21*L30 -> 23807201 | N21: =+M21*M30 -> 23899137 | O21: =+N21*N30 -> 23952970 | P21: =+O21*O30 -> 23980182 | Q21: =+P21*P30 -> 23994308 | ... Z21: =+Y21*Y30 -> 24007860 | AA21: =+Z21 -> 24007860 | AB21: =+I21 -> 21399003 | AC21: =AA21-AB21 -> 2608857.4
A22: AO19 | B22: 3Q23 | C22: =IF(Triangulo1!D34=0,"-",Triangulo1!D34) -> 6936281 | D22: =IF(Triangulo1!E34=0,"-",Triangulo1!E34) -> 21936281 | E22: =IF(Triangulo1!F34=0,"-",Triangulo1!F34) -> 25150070 | F22: =IF(Triangulo1!G34=0,"-",Triangulo1!G34) -> 28898330 | G22: =IF(Triangulo1!H34=0,"-",Triangulo1!H34) -> 31903741 | H22: =IF(Triangulo1!I34=0,"-",Triangulo1!I34) -> 33589263 | I22: =H30*H22 -> 37356679 | J22: =I30*I22 -> 39465161 | K22: =J30*J22 -> 40594112 | L22: =K30*K22 -> 41226820 | M22: =L30*L22 -> 41560721 | N22: =M30*M22 -> 41721215 | O22: =N30*N22 -> 41815192 | P22: =O30*O22 -> 41862698 | ... Z22: =Y30*Y22 -> 41911015 | AA22: =+Z22 -> 41911015 | AB22: =+H22 -> 33589263 | AC22: =AA22-AB22 -> 8321752.4
A23: AO20 | B23: 4Q23 | C23: =IF(Triangulo1!D35=0,"-",Triangulo1!D35) -> 6691248 | D23: =IF(Triangulo1!E35=0,"-",Triangulo1!E35) -> 11756013 | E23: =IF(Triangulo1!F35=0,"-",Triangulo1!F35) -> 15391294 | F23: =IF(Triangulo1!G35=0,"-",Triangulo1!G35) -> 18736499 | G23: =IF(Triangulo1!H35=0,"-",Triangulo1!H35) -> 21705785 | H23: =G30*G23 -> 23968067 | I23: =H30*H23 -> 26656357 | J23: =I30*I23 -> 28160892 | K23: =J30*J23 -> 28966470 | L23: =K30*K23 -> 29417947 | M23: =L30*L23 -> 29656207 | N23: =M30*M23 -> 29770730 | O23: =N30*N23 -> 29837788 | ... Z23: =Y30*Y23 -> 29906164 | AA23: =+Z23 -> 29906164 | AB23: =+G23 -> 21705785 | AC23: =AA23-AB23 -> 8200379.3
A24: AO21 | B24: 1Q24 | C24: =IF(Triangulo1!D36=0,"-",Triangulo1!D36) -> 4191817 | D24: =IF(Triangulo1!E36=0,"-",Triangulo1!E36) -> 9775450 | E24: =IF(Triangulo1!F36=0,"-",Triangulo1!F36) -> 14374440 | F24: =IF(Triangulo1!G36=0,"-",Triangulo1!G36) -> 17306094 | G24: =F30*F24 -> 20108546 | H24: =G30*G24 -> 22204356 | I24: =H30*H24 -> 24694826 | J24: =I30*I24 -> 26088649 | K24: =J30*J24 -> 26834948 | L24: =K30*K24 -> 27253202 | M24: =L30*L24 -> 27473929 | N24: =M30*M24 -> 27580025 | ... Z24: =Y30*Y24 -> 27705493 | AA24: =+Z24 -> 27705493 | AB24: =+F24 -> 17306094 | AC24: =AA24-AB24 -> 10399399
A25: AO22 | B25: 2Q24 | C25: =IF(Triangulo1!D37=0,"-",Triangulo1!D37) -> 5916671 | D25: =IF(Triangulo1!E37=0,"-",Triangulo1!E37) -> 11716355 | E25: =IF(Triangulo1!F37=0,"-",Triangulo1!F37) -> 15374462 | F25: =E25*E30 -> 19154153 | G25: =F25*F30 -> 22255869 | H25: =G25*G30 -> 24575483 | I25: =H25*H30 -> 27331902 | J25: =I25*I30 -> 28874566 | K25: =J25*J30 -> 29700560 | L25: =K25*K30 -> 30163479 | M25: =L25*L30 -> 30407776 | ... Z25: =Y25*Y30 -> 30664068 | AA25: =+Z25 -> 30664068 | AB25: =+E25 -> 15374462 | AC25: =AA25-AB25 -> 15289606
A26: AO23 | B26: 3Q24 | C26: =IF(Triangulo1!D38=0,"-",Triangulo1!D38) -> 4926500 | D26: =IF(Triangulo1!E38=0,"-",Triangulo1!E38) -> 9321834 | E26: =D26*D30 -> 12561203 | F26: =E26*E30 -> 15649276 | G26: =F26*F30 -> 18183432 | H26: =G26*G30 -> 20078597 | I26: =H26*H30 -> 22330639 | J26: =I26*I30 -> 23591023 | K26: =J26*J30 -> 24265874 | L26: =K26*K30 -> 24644087 | ... Z26: =Y26*Y30 -> 25053077 | AA26: =+Z26 -> 25053077 | AB26: =+D26 -> 9321834 | AC26: =AA26-AB26 -> 15731243
A27: AO24 | B27: 4Q24 | C27: =IF(Triangulo1!D39=0,"-",Triangulo1!D39) -> 5149958 | D27: =C27*C30 -> 11056828 | E27: =D27*D30 -> 14899112 | F27: =E27*E30 -> 18561942 | G27: =F27*F30 -> 21567759 | H27: =G27*G30 -> 23815655 | I27: =H27*H30 -> 26486851 | J27: =I27*I30 -> 27981819 | K27: =J27*J30 -> 28782275 | ... Z27: =Y27*Y30 -> 29715993 | AA27: =+Z27 -> 29715993 | AB27: =+C27 -> 5149958 | AC27: =AA27-AB27 -> 24566035
A28: Numerado | C28: =SUM(D19:D26) -> 93535388 | D28: =SUM(E18:E25) -> 119910094 | E28: =SUM(F17:F24) -> 140170234 | F28: =SUM(G16:G23) -> 155315660 | G28: =SUM(H15:H22) -> 162298291 | H28: =SUM(I14:I21) -> 155764784 | I28: =SUM(J13:J20) -> 154906842 | J28: =SUM(K12:K19) -> 146864136 | K28: =SUM(L11:L18) -> 136904097 | L28: =SUM(M10:M17) -> 127817018 | M28: =SUM(N9:N16) -> 121164087 | N28: =SUM(O8:O15) -> 113546368 | O28: =SUM(P7:P14) -> 114372144 | P28: =SUM(Q6:Q13) -> 111181861 | Q28: =SUM(R5:R12) -> 114600758 | R28: =SUM(S4:S11) -> 113609232 | S28: =SUM(T4:T10) -> 99504954 | T28: =SUM(U4:U9) -> 88667706 | U28: =SUM(V4:V8) -> 75619969 | V28: =SUM(W4:W7) -> 63803989 | W28: =SUM(X4:X6) -> 44342390 | X28: =SUM(Y4:Y5) -> 32460648 | Y28: =SUM(Z4) -> 14725385
A29: Denominador | C29: =SUM(C19:C26) -> 43566142 | D29: =SUM(D18:D25) -> 88986860 | E29: =SUM(E17:E24) -> 112510429 | F29: =SUM(F16:F23) -> 133669903 | G29: =SUM(G15:G22) -> 146979389 | H29: =SUM(H14:H21) -> 140055925 | I29: =SUM(I13:I20) -> 146630728 | J29: =SUM(J12:J19) -> 142779738 | K29: =SUM(K11:K18) -> 134803032 | L29: =SUM(L10:L17) -> 126790130 | M29: =SUM(M9:M16) -> 120697988 | N29: =SUM(N8:N15) -> 113291182 | O29: =SUM(O7:O14) -> 114242354 | P29: =SUM(P6:P13) -> 111116410 | Q29: =SUM(Q5:Q12) -> 114565516 | R29: =SUM(R4:R11) -> 113593326 | S29: =SUM(S4:S10) -> 99498096 | T29: =SUM(T4:T9) -> 88664814 | U29: =SUM(U4:U8) -> 75619235 | V29: =SUM(V4:V7) -> 63803796 | W29: =SUM(W4:W6) -> 44342339 | X29: =SUM(X4:X5) -> 32460629 | Y29: =SUM(Y4) -> 14725369
A30: Factores | C30: =C28/C29 -> 2.1469743 | D30: =D28/D29 -> 1.3475034 | E30: =E28/E29 -> 1.2458421 | F30: =F28/F29 -> 1.1619344 | G30: =G28/G29 -> 1.1042248 | H30: =H28/H29 -> 1.1121613 | I30: =I28/I29 -> 1.0564419 | J30: =J28/J29 -> 1.0286063 | ... Y30: =Y28/Y29 -> 1.0000011 | Z30: 1
A31: Factor acum. F_j^{→25} | C31: =+C30*D31 -> 5.7701428 | D31: =+D30*E31 -> 2.6875695 | E31: =+E30*F31 -> 1.9944807 | F31: =+F30*G31 -> 1.6009097 | G31: =+G30*H31 -> 1.3777969 | H31: =+H30*I31 -> 1.2477504 | I31: =+I30*J31 -> 1.1219149 | J31: =+J30*K31 -> 1.061975 | ... Y31: =+Y30*Z31 -> 1.0000011 | Z31: 1
A32: % Desarrollado = 1/F_j | C32: =1/C31 -> 0.17330594 | D32: =1/D31 -> 0.3720834 | E32: =1/E31 -> 0.50138363 | F32: =1/F31 -> 0.62464486 | G32: =1/G31 -> 0.72579635 | H32: =1/H31 -> 0.80144236 | I32: =1/I31 -> 0.8913332 | J32: =1/J31 -> 0.94164172 | ... Y32: =1/Y31 -> 0.99999891 | Z32: 1
A33: Total | AA33: =+SUM(AA4:AA27) -> 5.0250146e+08 | AB33: =+SUM(AB4:AB27) -> 414213831 | AC33: =SUM(AC4:AC28) -> 88287626

Sheet 1_BF
A4: ELR a priori (BF): | B4: 0.55
A7: AO | B7: Trim. | C7: Pagado actual (diagonal) | D7: Prima Devengada | E7: % Des. (de 2_Factores) | F7: % No-Des. =1−%Des | G7: Apriori =Prima×ELR | H7: IBNR_BF =Apriori×%NoDes | I7: Último_BF =Pag+IBNR
A8: AO001 | B8: 1Q19 | C8: =+Triangulo1!E79 -> 14725385 | D8: =+Triangulo1!D79 -> 30470484 | E8: 1 | F8: =1-E8 -> 0 | G8: =+$B$4*D8 -> 16758766 | H8: =+G8*F8 -> 0 | I8: =+H8+C8 -> 14725385
A9: AO002 | B9: 2Q19 | C9: =+Triangulo1!E80 -> 17735279 | D9: =+Triangulo1!D80 -> 35502400 | E9: =+'1_CL'!Y32 -> 0.99999891 | F9: =1-E9 -> 1.086559e-06 | G9: =+$B$4*D9 -> 19526320 | H9: =+G9*F9 -> 21.216499 | I9: =+H9+C9 -> 17735300
A10: AO003 | B10: 3Q19 | C10: =+Triangulo1!E81 -> 11881761 | D10: =+Triangulo1!D81 -> 15118899 | E10: =+'1_CL'!X32 -> 0.99999833 | F10: =1-E10 -> 1.6718825e-06 | G10: =+$B$4*D10 -> 8315394.3 | H10: =+G10*F10 -> 13.902362 | I10: =+H10+C10 -> 11881775
A11: AO004 | B11: 4Q19 | C11: =+Triangulo1!E82 -> 19461650 | D11: =+Triangulo1!D82 -> 47069939 | E11: =+'1_CL'!W32 -> 0.99999718 | F11: =1-E11 -> 2.8220216e-06 | G11: =+$B$4*D11 -> 25888467 | H11: =+G11*F11 -> 73.057811 | I11: =+H11+C11 -> 19461723
A12: AO005 | B12: 1Q20 | C12: =+Triangulo1!E83 -> 11816173 | D12: =+Triangulo1!D83 -> 10724971 | E12: =+'1_CL'!V32 -> 0.99999415 | F12: =1-E12 -> 5.8469023e-06 | G12: =+$B$4*D12 -> 5898734 | H12: =+G12*F12 -> 34.489321 | I12: =+H12+C12 -> 11816207
A13: AO006 | B13: 2Q20 | C13: =+Triangulo1!E84 -> 13048471 | D13: =+Triangulo1!D84 -> 19800249 | E13: =+'1_CL'!U32 -> 0.99998445 | F13: =1-E13 -> 1.5553276e-05 | G13: =+$B$4*D13 -> 10890137 | H13: =+G13*F13 -> 169.37731 | I13: =+H13+C13 -> 13048640
A14: AO007 | B14: 3Q20 | C14: =+Triangulo1!E85 -> 10840140 | D14: =+Triangulo1!D85 -> 28289118 | E14: =+'1_CL'!T32 -> 0.99995183 | F14: =1-E14 -> 4.8168928e-05 | G14: =+$B$4*D14 -> 15559015 | H14: =+G14*F14 -> 749.46108 | I14: =+H14+C14 -> 10840889
A15: AO008 | B15: 4Q20 | C15: =+Triangulo1!E86 -> 14111136 | D15: =+Triangulo1!D86 -> 30704506 | E15: =+'1_CL'!S32 -> 0.99988291 | F15: =1-E15 -> 0.0001170868 | G15: =+$B$4*D15 -> 16887478 | H15: =+G15*F15 -> 1977.3008 | I15: =+H15+C15 -> 14113113
A16: AO009 | B16: 1Q21 | C16: =+Triangulo1!E87 -> 15729334 | D16: =+Triangulo1!D87 -> 18880428 | E16: =+'1_CL'!R32 -> 0.99974292 | F16: =1-E16 -> 0.00025707663 | G16: =+$B$4*D16 -> 10384236 | H16: =+G16*F16 -> 2669.5443 | I16: =+H16+C16 -> 15732004
A17: AO010 | B17: 2Q21 | C17: =+Triangulo1!E88 -> 14343596 | D17: =+Triangulo1!D88 -> 17119243 | E17: =+'1_CL'!Q32 -> 0.99943548 | F17: =1-E17 -> 0.00056451736 | G17: =+$B$4*D17 -> 9415583.8 | H17: =+G17*F17 -> 5315.2605 | I17: =+H17+C17 -> 14348911
A18: AO011 | B18: 3Q21 | C18: =+Triangulo1!E89 -> 15119935 | D18: =+Triangulo1!D89 -> 41471482 | E18: =+'1_CL'!P32 -> 0.99884713 | F18: =1-E18 -> 0.0011528692 | G18: =+$B$4*D18 -> 22809315 | H18: =+G18*F18 -> 26296.157 | I18: =+H18+C18 -> 15146231
A19: AO012 | B19: 4Q21 | C19: =+Triangulo1!E90 -> 18730024 | D19: =+Triangulo1!D90 -> 35368087 | E19: =+'1_CL'!O32 -> 0.99771363 | F19: =1-E19 -> 0.0022863652 | G19: =+$B$4*D19 -> 19452448 | H19: =+G19*F19 -> 44475.4 | I19: =+H19+C19 -> 18774499
A20: AO013 | B20: 1Q22 | C20: =+Triangulo1!E91 -> 19627354 | D20: =+Triangulo1!D91 -> 26145160 | E20: =+'1_CL'!N32 -> 0.99547136 | F20: =1-E20 -> 0.0045286435 | G20: =+$B$4*D20 -> 14379838 | H20: =+G20*F20 -> 65121.159 | I20: =+H20+C20 -> 19692475
A21: AO014 | B21: 2Q22 | C21: =+Triangulo1!E92 -> 20049671 | D21: =+Triangulo1!D92 -> 46483439 | E21: =+'1_CL'!M32 -> 0.99164194 | F21: =1-E21 -> 0.0083580637 | G21: =+$B$4*D21 -> 25565891 | H21: =+G21*F21 -> 213681.35 | I21: =+H21+C21 -> 20263352
A22: AO015 | B22: 3Q22 | C22: =+Triangulo1!E93 -> 20688336 | D22: =+Triangulo1!D93 -> 28927094 | E22: =+'1_CL'!L32 -> 0.98367504 | F22: =1-E22 -> 0.016324962 | G22: =+$B$4*D22 -> 15909902 | H22: =+G22*F22 -> 259728.55 | I22: =+H22+C22 -> 20948065
A23: AO016 | B23: 4Q22 | C23: =+Triangulo1!E94 -> 25647723 | D23: =+Triangulo1!D94 -> 62474507 | E23: =+'1_CL'!K32 -> 0.96857859 | F23: =1-E23 -> 0.031421407 | G23: =+$B$4*D23 -> 34360979 | H23: =+G23*F23 -> 1079670.3 | I23: =+H23+C23 -> 26727393
A24: AO017 | B24: 1Q23 | C24: =+Triangulo1!E95 -> 26811464 | D24: =+Triangulo1!D95 -> 40231087 | E24: =+'1_CL'!J32 -> 0.94164172 | F24: =1-E24 -> 0.05835828 | G24: =+$B$4*D24 -> 22127098 | H24: =+G24*F24 -> 1291299.3 | I24: =+H24+C24 -> 28102763
A25: AO018 | B25: 2Q23 | C25: =+Triangulo1!E96 -> 21399003 | D25: =+Triangulo1!D96 -> 50080346 | E25: =+'1_CL'!I32 -> 0.8913332 | F25: =1-E25 -> 0.1086668 | G25: =+$B$4*D25 -> 27544190 | H25: =+G25*F25 -> 2993139.1 | I25: =+H25+C25 -> 24392142
A26: AO019 | B26: 3Q23 | C26: =+Triangulo1!E97 -> 33589263 | D26: =+Triangulo1!D97 -> 68225324 | E26: =+'1_CL'!H32 -> 0.80144236 | F26: =1-E26 -> 0.19855764 | G26: =+$B$4*D26 -> 37523928 | H26: =+G26*F26 -> 7450662.8 | I26: =+H26+C26 -> 41039926
A27: AO020 | B27: 4Q23 | C27: =+Triangulo1!E98 -> 21705785 | D27: =+Triangulo1!D98 -> 46727120 | E27: =+'1_CL'!G32 -> 0.72579635 | F27: =1-E27 -> 0.27420365 | G27: =+$B$4*D27 -> 25699916 | H27: =+G27*F27 -> 7047010.6 | I27: =+H27+C27 -> 28752796
A28: AO021 | B28: 1Q24 | C28: =+Triangulo1!E99 -> 17306094 | D28: =+Triangulo1!D99 -> 63421725 | E28: =+'1_CL'!F32 -> 0.62464486 | F28: =1-E28 -> 0.37535514 | G28: =+$B$4*D28 -> 34881949 | H28: =+G28*F28 -> 13093119 | I28: =+H28+C28 -> 30399213
A29: AO022 | B29: 2Q24 | C29: =+Triangulo1!E100 -> 15374462 | D29: =+Triangulo1!D100 -> 44130894 | E29: =+'1_CL'!E32 -> 0.50138363 | F29: =1-E29 -> 0.49861637 | G29: =+$B$4*D29 -> 24271992 | H29: =+G29*F29 -> 12102412 | I29: =+H29+C29 -> 27476874
A30: AO023 | B30: 3Q24 | C30: =+Triangulo1!E101 -> 9321834 | D30: =+Triangulo1!D101 -> 35850381 | E30: =+'1_CL'!D32 -> 0.3720834 | F30: =1-E30 -> 0.6279166 | G30: =+$B$4*D30 -> 19717709 | H30: =+G30*F30 -> 12381077 | I30: =+H30+C30 -> 21702911
A31: AO024 | B31: 4Q24 | C31: =+Triangulo1!E102 -> 5149958 | D31: =+Triangulo1!D102 -> 55736823 | E31: =+'1_CL'!C32 -> 0.17330594 | F31: =1-E31 -> 0.82669406 | G31: =+$B$4*D31 -> 30655252 | H31: =+G31*F31 -> 25342515 | I31: =+H31+C31 -> 30492473
A32: TOTAL | H32: =SUM(H8:H31) -> 83401232 | I32: =SUM(I8:I31) -> 4.9761506e+08

Sheet 1_CC
A1: CAPE COD · ELR_CC = Σ Pagados / Σ(Prima×%Des) · ELR endógeno calculado en B4
A2: ELR_CC en B4 calculado automáticamente · % Des de 4_BF · Primas de 1_Triangulo
A4: ELR Cape Cod: | B4: =SUM(C8:C31)/SUM(G8:G31) -> 0.55426932 | C4: Σ Pagados / Σ(Prima×%Des) — se actualiza automáticamente
A7: AO | B7: Trim. | C7: Pagado actual | D7: Prima Devengada | E7: % Des. | F7: % No-Des. | G7: Prima × %Des | H7: IBNR_CC =Prima×%NoDes×ELR_CC | I7: Último_CC
A8: =+'1_BF'!A8 -> AO001 | B8: =+'1_BF'!B8 -> 1Q19 | C8: =+'1_BF'!C8 -> 14725385 | D8: =+'1_BF'!D8 -> 30470484 | E8: =+'1_BF'!E8 -> 1 | F8: =1-E8 -> 0 | G8: =D8*E8 -> 30470484 | H8: =D8*F8*$B$4 -> 0 | I8: =C8+H8 -> 14725385
A9: =+'1_BF'!A9 -> AO002 | B9: =+'1_BF'!B9 -> 2Q19 | C9: =+'1_BF'!C9 -> 17735279 | D9: =+'1_BF'!D9 -> 35502400 | E9: =+'1_BF'!E9 -> 0.99999891 | F9: =1-E9 -> 1.086559e-06 | G9: =D9*E9 -> 35502361 | H9: =D9*F9*$B$4 -> 21.38119 | I9: =C9+H9 -> 17735300
A10: =+'1_BF'!A10 -> AO003 | B10: =+'1_BF'!B10 -> 3Q19 | C10: =+'1_BF'!C10 -> 11881761 | D10: =+'1_BF'!D10 -> 15118899 | E10: =+'1_BF'!E10 -> 0.99999833 | F10: =1-E10 -> 1.6718825e-06 | G10: =D10*E10 -> 15118874 | H10: =D10*F10*$B$4 -> 14.010278 | I10: =C10+H10 -> 11881775
A11: =+'1_BF'!A11 -> AO004 | B11: =+'1_BF'!B11 -> 4Q19 | C11: =+'1_BF'!C11 -> 19461650 | D11: =+'1_BF'!D11 -> 47069939 | E11: =+'1_BF'!E11 -> 0.99999718 | F11: =1-E11 -> 2.8220216e-06 | G11: =D11*E11 -> 47069806 | H11: =D11*F11*$B$4 -> 73.624914 | I11: =C11+H11 -> 19461724
A12: =+'1_BF'!A12 -> AO005 | B12: =+'1_BF'!B12 -> 1Q20 | C12: =+'1_BF'!C12 -> 11816173 | D12: =+'1_BF'!D12 -> 10724971 | E12: =+'1_BF'!E12 -> 0.99999415 | F12: =1-E12 -> 5.8469023e-06 | G12: =D12*E12 -> 10724908 | H12: =D12*F12*$B$4 -> 34.757041 | I12: =C12+H12 -> 11816208
A13: =+'1_BF'!A13 -> AO006 | B13: =+'1_BF'!B13 -> 2Q20 | C13: =+'1_BF'!C13 -> 13048471 | D13: =+'1_BF'!D13 -> 19800249 | E13: =+'1_BF'!E13 -> 0.99998445 | F13: =1-E13 -> 1.5553276e-05 | G13: =D13*E13 -> 19799941 | H13: =D13*F13*$B$4 -> 170.69208 | I13: =C13+H13 -> 13048642
A14: =+'1_BF'!A14 -> AO007 | B14: =+'1_BF'!B14 -> 3Q20 | C14: =+'1_BF'!C14 -> 10840140 | D14: =+'1_BF'!D14 -> 28289118 | E14: =+'1_BF'!E14 -> 0.99995183 | F14: =1-E14 -> 4.8168928e-05 | G14: =D14*E14 -> 28287756 | H14: =D14*F14*$B$4 -> 755.27869 | I14: =C14+H14 -> 10840895
A15: =+'1_BF'!A15 -> AO008 | B15: =+'1_BF'!B15 -> 4Q20 | C15: =+'1_BF'!C15 -> 14111136 | D15: =+'1_BF'!D15 -> 30704506 | E15: =+'1_BF'!E15 -> 0.99988291 | F15: =1-E15 -> 0.0001170868 | G15: =D15*E15 -> 30700911 | H15: =D15*F15*$B$4 -> 1992.6494 | I15: =C15+H15 -> 14113129
A16: =+'1_BF'!A16 -> AO009 | B16: =+'1_BF'!B16 -> 1Q21 | C16: =+'1_BF'!C16 -> 15729334 | D16: =+'1_BF'!D16 -> 18880428 | E16: =+'1_BF'!E16 -> 0.99974292 | F16: =1-E16 -> 0.00025707663 | G16: =D16*E16 -> 18875575 | H16: =D16*F16*$B$4 -> 2690.2664 | I16: =C16+H16 -> 15732024
A17: =+'1_BF'!A17 -> AO010 | B17: =+'1_BF'!B17 -> 2Q21 | C17: =+'1_BF'!C17 -> 14343596 | D17: =+'1_BF'!D17 -> 17119243 | E17: =+'1_BF'!E17 -> 0.99943548 | F17: =1-E17 -> 0.00056451736 | G17: =D17*E17 -> 17109579 | H17: =D17*F17*$B$4 -> 5356.5197 | I17: =C17+H17 -> 14348953
A18: =+'1_BF'!A18 -> AO011 | B18: =+'1_BF'!B18 -> 3Q21 | C18: =+'1_BF'!C18 -> 15119935 | D18: =+'1_BF'!D18 -> 41471482 | E18: =+'1_BF'!E18 -> 0.99884713 | F18: =1-E18 -> 0.0011528692 | G18: =D18*E18 -> 41423671 | H18: =D18*F18*$B$4 -> 26500.278 | I18: =C18+H18 -> 15146435
A19: =+'1_BF'!A19 -> AO012 | B19: =+'1_BF'!B19 -> 4Q21 | C19: =+'1_BF'!C19 -> 18730024 | D19: =+'1_BF'!D19 -> 35368087 | E19: =+'1_BF'!E19 -> 0.99771363 | F19: =1-E19 -> 0.0022863652 | G19: =D19*E19 -> 35287223 | H19: =D19*F19*$B$4 -> 44820.636 | I19: =C19+H19 -> 18774845
... A31: =+'1_BF'!A31 -> AO024 | B31: =+'1_BF'!B31 -> 4Q24 | C31: =+'1_BF'!C31 -> 5149958 | D31: =+'1_BF'!D31 -> 55736823 | E31: =+'1_BF'!E31 -> 0.17330594 | F31: =1-E31 -> 0.82669406 | G31: =D31*E31 -> 9659522.3 | H31: =D31*F31*$B$4 -> 25539234 | I31: =C31+H31 -> 30689192
A32: TOTAL | G32: =SUM(G8:G31) -> 7.473151e+08 | H32: =SUM(H8:H31) -> 84048625 | I32: =SUM(I8:I31) -> 4.9826246e+08

Sheet 1_Duration
B1: DURACIÓN DE CARTERA — AUTO DAÑOS / RC PERSONAL
B2: Metodología: Macaulay · Modificada · Efectiva | Fuente: D'Arcy & Gorvett (2000), PCAS | N2: Trimestral
N3: Anual
B4: PARÁMETROS DE ENTRADA | I4: Trimestral
B5: Reserva total (MXN) | C5: ='1_CL'!AC33 -> 88287626 | D5: Monto total de la reserva IBNR a valuar
B6: Tasa de descuento (r) | C6: =IF(I4="Anual",Triangulo1!E4, POWER(1+Triangulo1!E4,0.25)-1) -> 0.014673846 | D6: Tasa libre de riesgo (CETES / curva CNSF) | J6: 0.04
B7: Shock de tasa (Δr) | C7: 0.01 | D7: Desplazamiento para calcular duración efectiva (±100 bps)
B8: Correlación tasas-inflación | C8: 0.4 | D8: ρ: usada para ajustar D_Efectiva (D'Arcy 2000, Tabla 3)
B10: A. PATRÓN DE DESARROLLO Y FLUJOS DE PAGO
B11: Trimestre (t) | C11: % Pago Acumulado | D11: % Pago Incremental | E11: Flujo Nominal (MXN) | F11: PV del Flujo (MXN) | G11: Peso = PV/PV_Total | H11: t × Peso | I11: t(t+1)×PV/(1+r)² (Convexidad)
B12: =IF(I4= "Anual",1,0.25) -> 0.25 | C12: ='1_BF'!E31 -> 0.17330594 | D12: =C12 -> 0.17330594 | E12: =D12*$C$5 -> 15300770 | F12: =IF($I$4="Anual",E12/(1+$C$6)^B12,E12/(1+$C$6)^(B12*4)) -> 15079496 | G12: =F12/$F$36 -> 0.18100643 | H12: =B12*G12 -> 0.045251607 | I12: =B12*(B12+1)*F12/((1+$C$6)^2)/$F$36 -> 0.054940308 | J12: =+B12*F12 -> 3769873.9
B13: =IF($I$4="Anual",B12+1,B12+0.25) -> 0.5 | C13: ='1_BF'!E30 -> 0.3720834 | D13: =C13-C12 -> 0.19877746 | E13: =D13*$C$5 -> 17549590 | F13: =IF($I$4="Anual",E13/(1+$C$6)^B13,E13/(1+$C$6)^(B13*4)) -> 17045669 | G13: =F13/$F$36 -> 0.20460735 | H13: =B13*G13 -> 0.10230367 | I13: =B13*(B13+1)*F13/((1+$C$6)^2)/$F$36 -> 0.14904917 | J13: =+B13*F13 -> 8522834.3
B14: =IF($I$4="Anual",B13+1,B13+0.25) -> 0.75 | C14: ='1_BF'!E29 -> 0.50138363 | D14: =C14-C13 -> 0.12930024 | E14: =D14*$C$5 -> 11415611 | F14: =IF($I$4="Anual",E14/(1+$C$6)^B14,E14/(1+$C$6)^(B14*4)) -> 10927473 | G14: =F14/$F$36 -> 0.13116771 | H14: =B14*G14 -> 0.098375783 | I14: =B14*(B14+1)*F14/((1+$C$6)^2)/$F$36 -> 0.16721426 | J14: =+B14*F14 -> 8195605
B15: =IF($I$4="Anual",B14+1,B14+0.25) -> 1 | C15: ='1_BF'!E28 -> 0.62464486 | D15: =C15-C14 -> 0.12326123 | E15: =D15*$C$5 -> 10882441 | F15: =IF($I$4="Anual",E15/(1+$C$6)^B15,E15/(1+$C$6)^(B15*4)) -> 10266454 | G15: =F15/$F$36 -> 0.12323318 | H15: =B15*G15 -> 0.12323318 | I15: =B15*(B15+1)*F15/((1+$C$6)^2)/$F$36 -> 0.23938928 | J15: =+B15*F15 -> 10266454
B16: =IF($I$4="Anual",B15+1,B15+0.25) -> 1.25 | C16: ='1_BF'!E27 -> 0.72579635 | D16: =C16-C15 -> 0.1011515 | E16: =D16*$C$5 -> 8930425.5 | F16: =IF($I$4="Anual",E16/(1+$C$6)^B16,E16/(1+$C$6)^(B16*4)) -> 8303091.5 | G16: =F16/$F$36 -> 0.099665995 | H16: =B16*G16 -> 0.12458249 | I16: =B16*(B16+1)*F16/((1+$C$6)^2)/$F$36 -> 0.27226173 | J16: =+B16*F16 -> 10378864
B17: =IF($I$4="Anual",B16+1,B16+0.25) -> 1.5 | C17: ='1_BF'!E26 -> 0.80144236 | D17: =C17-C16 -> 0.075646002 | E17: =D17*$C$5 -> 6678606 | F17: =IF($I$4="Anual",E17/(1+$C$6)^B17,E17/(1+$C$6)^(B17*4)) -> 6119656.2 | G17: =F17/$F$36 -> 0.073457172 | H17: =B17*G17 -> 0.11018576 | I17: =B17*(B17+1)*F17/((1+$C$6)^2)/$F$36 -> 0.26755467 | J17: =+B17*F17 -> 9179484.3
B18: =IF($I$4="Anual",B17+1,B17+0.25) -> 1.75 | C18: ='1_BF'!E25 -> 0.8913332 | D18: =C18-C17 -> 0.089890842 | E18: =D18*$C$5 -> 7936249 | F18: =IF($I$4="Anual",E18/(1+$C$6)^B18,E18/(1+$C$6)^(B18*4)) -> 7166878.2 | G18: =F18/$F$36 -> 0.086027481 | H18: =B18*G18 -> 0.15054809 | I18: =B18*(B18+1)*F18/((1+$C$6)^2)/$F$36 -> 0.40211939 | J18: =+B18*F18 -> 12542037
B19: =IF($I$4="Anual",B18+1,B18+0.25) -> 2 | C19: ='1_BF'!E24 -> 0.94164172 | D19: =C19-C18 -> 0.050308522 | E19: =D19*$C$5 -> 4441619.9 | F19: =IF($I$4="Anual",E19/(1+$C$6)^B19,E19/(1+$C$6)^(B19*4)) -> 3953025.9 | G19: =F19/$F$36 -> 0.047450069 | H19: =B19*G19 -> 0.094900138 | I19: =B19*(B19+1)*F19/((1+$C$6)^2)/$F$36 -> 0.27652549 | J19: =+B19*F19 -> 7906051.9
B20: =IF($I$4="Anual",B19+1,B19+0.25) -> 2.25 | C20: ='1_BF'!E23 -> 0.96857859 | D20: =C20-C19 -> 0.026936872 | E20: =D20*$C$5 -> 2378192.5 | F20: =IF($I$4="Anual",E20/(1+$C$6)^B20,E20/(1+$C$6)^(B20*4)) -> 2085973.6 | G20: =F20/$F$36 -> 0.025038943 | H20: =B20*G20 -> 0.056337622 | I20: =B20*(B20+1)*F20/((1+$C$6)^2)/$F$36 -> 0.17783979 | J20: =+B20*F20 -> 4693440.6
B21: =IF($I$4="Anual",B20+1,B20+0.25) -> 2.5 | C21: ='1_BF'!E22 -> 0.98367504 | D21: =C21-C20 -> 0.015096445 | E21: =D21*$C$5 -> 1332829.3 | F21: =IF($I$4="Anual",E21/(1+$C$6)^B21,E21/(1+$C$6)^(B21*4)) -> 1152152.2 | G21: =F21/$F$36 -> 0.013829837 | H21: =B21*G21 -> 0.034574592 | I21: =B21*(B21+1)*F21/((1+$C$6)^2)/$F$36 -> 0.11753634 | J21: =+B21*F21 -> 2880380.6
B22: =IF($I$4="Anual",B21+1,B21+0.25) -> 2.75 | C22: ='1_BF'!E21 -> 0.99164194 | D22: =C22-C21 -> 0.0079668985 | E22: =D22*$C$5 -> 703378.55 | F22: =IF($I$4="Anual",E22/(1+$C$6)^B22,E22/(1+$C$6)^(B22*4)) -> 599236.13 | G22: =F22/$F$36 -> 0.0071929191 | H22: =B22*G22 -> 0.019780528 | I22: =B22*(B22+1)*F22/((1+$C$6)^2)/$F$36 -> 0.07204705 | J22: =+B22*F22 -> 1647899.4
B23: =IF($I$4="Anual",B22+1,B22+0.25) -> 3 | C23: ='1_BF'!E20 -> 0.99547136 | D23: =C23-C22 -> 0.0038294202 | E23: =D23*$C$5 -> 338090.42 | F23: =IF($I$4="Anual",E23/(1+$C$6)^B23,E23/(1+$C$6)^(B23*4)) -> 283867.24 | G23: =F23/$F$36 -> 0.0034073948 | H23: =B23*G23 -> 0.010222184 | I23: =B23*(B23+1)*F23/((1+$C$6)^2)/$F$36 -> 0.039714652 | J23: =+B23*F23 -> 851601.71
B24: =IF($I$4="Anual",B23+1,B23+0.25) -> 3.25 | C24: ='1_BF'!E19 -> 0.99771363 | D24: =C24-C23 -> 0.0022422783 | E24: =D24*$C$5 -> 197965.42 | F24: =IF($I$4="Anual",E24/(1+$C$6)^B24,E24/(1+$C$6)^(B24*4)) -> 163811.84 | G24: =F24/$F$36 -> 0.0019663122 | H24: =B24*G24 -> 0.0063905145 | I24: =B24*(B24+1)*F24/((1+$C$6)^2)/$F$36 -> 0.02637982 | J24: =+B24*F24 -> 532388.47
B25: =IF($I$4="Anual",B24+1,B24+0.25) -> 3.5 | C25: ='1_BF'!E18 -> 0.99884713 | D25: =C25-C24 -> 0.001133496 | E25: =D25*$C$5 -> 100073.67 | F25: =IF($I$4="Anual",E25/(1+$C$6)^B25,E25/(1+$C$6)^(B25*4)) -> 81611.114 | G25: =F25/$F$36 -> 0.0009796174 | H25: =B25*G25 -> 0.0034286609 | I25: =B25*(B25+1)*F25/((1+$C$6)^2)/$F$36 -> 0.014985944 | J25: =+B25*F25 -> 285638.9
B26: =IF($I$4="Anual",B25+1,B25+0.25) -> 3.75 | C26: ='1_BF'!E17 -> 0.99943548 | D26: =C26-C25 -> 0.00058835183 | E26: =D26*$C$5 -> 51944.187 | F26: =IF($I$4="Anual",E26/(1+$C$6)^B26,E26/(1+$C$6)^(B26*4)) -> 41748.411 | G26: =F26/$F$36 -> 0.00050112623 | H26: =B26*G26 -> 0.0018792234 | I26: =B26*(B26+1)*F26/((1+$C$6)^2)/$F$36 -> 0.0086699997 | J26: =+B26*F26 -> 156556.54
B27: =IF($I$4="Anual",B26+1,B26+0.25) -> 4 | C27: ='1_BF'!E16 -> 0.99974292 | D27: =C27-C26 -> 0.00030744072 | E27: =D27*$C$5 -> 27143.212 | F27: =IF($I$4="Anual",E27/(1+$C$6)^B27,E27/(1+$C$6)^(B27*4)) -> 21499.966 | G27: =F27/$F$36 -> 0.00025807442 | H27: =B27*G27 -> 0.0010322977 | I27: =B27*(B27+1)*F27/((1+$C$6)^2)/$F$36 -> 0.0050132807 | J27: =+B27*F27 -> 85999.864
B28: =IF($I$4="Anual",B27+1,B27+0.25) -> 4.25 | C28: ='1_BF'!E15 -> 0.99988291 | D28: =C28-C27 -> 0.00013998983 | E28: =D28*$C$5 -> 12359.37 | F28: =IF($I$4="Anual",E28/(1+$C$6)^B28,E28/(1+$C$6)^(B28*4)) -> 9648.2025 | G28: =F28/$F$36 -> 0.00011581201 | H28: =B28*G28 -> 0.00049220104 | I28: =B28*(B28+1)*F28/((1+$C$6)^2)/$F$36 -> 0.0025098565 | J28: =+B28*F28 -> 41004.861
B29: =IF($I$4="Anual",B28+1,B28+0.25) -> 4.5 | C29: ='1_BF'!E14 -> 0.99995183 | D29: =C29-C28 -> 6.8917872e-05 | E29: =D29*$C$5 -> 6084.5953 | F29: =IF($I$4="Anual",E29/(1+$C$6)^B29,E29/(1+$C$6)^(B29*4)) -> 4681.1796 | G29: =F29/$F$36 -> 5.6190447e-05 | H29: =B29*G29 -> 0.00025285701 | I29: =B29*(B29+1)*F29/((1+$C$6)^2)/$F$36 -> 0.0013507804 | J29: =+B29*F29 -> 21065.308
B30: =IF($I$4="Anual",B29+1,B29+0.25) -> 4.75 | C30: ='1_BF'!E13 -> 0.99998445 | D30: =C30-C29 -> 3.2615652e-05 | E30: =D30*$C$5 -> 2879.5585 | F30: =IF($I$4="Anual",E30/(1+$C$6)^B30,E30/(1+$C$6)^(B30*4)) -> 2183.3484 | G30: =F30/$F$36 -> 2.6207779e-05 | H30: =B30*G30 -> 0.00012448695 | I30: =B30*(B30+1)*F30/((1+$C$6)^2)/$F$36 -> 0.00069524639 | J30: =+B30*F30 -> 10370.905
B31: =IF($I$4="Anual",B30+1,B30+0.25) -> 5 | C31: ='1_BF'!E12 -> 0.99999415 | D31: =C31-C30 -> 9.7063741e-06 | E31: =D31*$C$5 -> 856.95272 | F31: =IF($I$4="Anual",E31/(1+$C$6)^B31,E31/(1+$C$6)^(B31*4)) -> 640.36493 | G31: =F31/$F$36 -> 7.6866078e-06 | H31: =B31*G31 -> 3.8433039e-05 | I31: =B31*(B31+1)*F31/((1+$C$6)^2)/$F$36 -> 0.0002239768 | J31: =+B31*F31 -> 3201.8246
B32: =IF($I$4="Anual",B31+1,B31+0.25) -> 5.25 | C32: ='1_BF'!E11 -> 0.99999718 | D32: =C32-C31 -> 3.0248807e-06 | E32: =D32*$C$5 -> 267.05954 | F32: =IF($I$4="Anual",E32/(1+$C$6)^B32,E32/(1+$C$6)^(B32*4)) -> 196.67642 | G32: =F32/$F$36 -> 2.3608016e-06 | H32: =B32*G32 -> 1.2394208e-05 | I32: =B32*(B32+1)*F32/((1+$C$6)^2)/$F$36 -> 7.5239495e-05 | J32: =+B32*F32 -> 1032.5512
B33: =IF($I$4="Anual",B32+1,B32+0.25) -> 5.5 | C33: ='1_BF'!E10 -> 0.99999833 | D33: =C33-C32 -> 1.1501391e-06 | E33: =D33*$C$5 -> 101.54305 | F33: =IF($I$4="Anual",E33/(1+$C$6)^B33,E33/(1+$C$6)^(B33*4)) -> 73.700075 | G33: =F33/$F$36 -> 8.846574e-07 | H33: =B33*G33 -> 4.8656157e-06 | I33: =B33*(B33+1)*F33/((1+$C$6)^2)/$F$36 -> 3.0718374e-05 | J33: =+B33*F33 -> 405.35041
B34: =IF($I$4="Anual",B33+1,B33+0.25) -> 5.75 | C34: ='1_BF'!E9 -> 0.99999891 | D34: =C34-C33 -> 5.8532348e-07 | E34: =D34*$C$5 -> 51.67682 | F34: =IF($I$4="Anual",E34/(1+$C$6)^B34,E34/(1+$C$6)^(B34*4)) -> 36.964689 | G34: =F34/$F$36 -> 4.4370492e-07 | H34: =B34*G34 -> 2.5513033e-06 | I34: =B34*(B34+1)*F34/((1+$C$6)^2)/$F$36 -> 1.6726802e-05 | J34: =+B34*F34 -> 212.54696
B35: =IF($I$4="Anual",B34+1,B34+0.25) -> 6 | C35: ='1_BF'!E8 -> 1 | D35: =C35-C34 -> 1.086559e-06 | E35: =D35*$C$5 -> 95.929717 | F35: =IF($I$4="Anual",E35/(1+$C$6)^B35,E35/(1+$C$6)^(B35*4)) -> 67.626665 | G35: =F35/$F$36 -> 8.1175534e-07 | H35: =B35*G35 -> 4.8705321e-06 | I35: =B35*(B35+1)*F35/((1+$C$6)^2)/$F$36 -> 3.3114752e-05 | J35: =+B35*F35 -> 405.75999
B36: TOTAL | C36: 100.00% | D36: =SUM(D12:D35) -> 1 | E36: =SUM(E12:E35) -> 88287626 | F36: =SUM(F12:F35) -> 83309172 | G36: =SUM(G12:G35) -> 1 | H36: =SUM(H12:H35) -> 0.983959 | I36: =SUM(I12:I35) -> 2.2961768 | J36: =SUM(J12:J35) -> 81972809 | K36: =+J36/F36 -> 0.983959
F37: 895587.34
B38: B. CÁLCULO DE DURACIÓN
B39: Duración de Macaulay (D_Mac) | C39: =SUMPRODUCT(B12:B35,F12:F35)/F36 -> 0.983959 | D39: años | E39: D_Mac = Σ[t × PV(CF_t)] / PV_Total | H39: ~0.98 años
B41: Duración Modificada (D_Mod) | C41: =(SUMPRODUCT(B12:B35,F12:F35)/F36)/(1+Triangulo1!E4) -> 0.92826321 | D41: años | E41: D_Mod = D_Mac / (1 + r) | H41: ~0.92 años
B43: Convexidad | C43: {=SUMPRODUCT(B12:B35*(B12:B35+1),F12:F35)/((1+Triangulo1!E4)^2*F36)} -> 2.1040039 | E43: Conv = Σ[t(t+1)×PV(CF_t)/PV_Total] / (1+r)² | H43: Curvatura de la función PV vs tasa
B46: C. ANÁLISIS DE SENSIBILIDAD — Δ PV ante cambios de tasa
B47: Escenario | C47: Tasa aplicada | D47: PV de Pasivos | E47: Δ PV vs base | F47: Δ PV % | G47: D_Mod × Δr (aprox.)
B48: Tasa base (r) | C48: =C6 -> 0.014673846 | D48: {=SUMPRODUCT(D12:D35*$C$5,1/((1+C48)^(B12:B35*4)))} -> 83309172 | E48: — | F48: — | G48: —
B49: Sube 100 bps | C49: =POWER(1+Triangulo1!$E$4+'1_Duration'!C7,0.25)-1 -> 0.017058525 | D49: {=SUMPRODUCT(D12:D35*$C$5,1/((1+C49)^(B12:B35*4)))} -> 82544509 | E49: =D49-D48 -> -764662.39 | F49: =E49/D48 -> -0.0091786099 | G49: =-C41*(C49-$C$6)*D48 -> -184413.98
B50: Sube 200 bps | C50: =POWER(1+Triangulo1!$E$4+'1_Duration'!C7*2,0.25)-1 -> 0.019426547 | D50: {=SUMPRODUCT(D12:D35*$C$5,1/((1+C50)^(B12:B35*4)))} -> 81796795 | E50: =D50-D48 -> -1512376.7 | F50: =E50/D48 -> -0.018153784 | G50: =-C41*(C50-$C$6)*D48 -> -367539.84
B51: Baja 100 bps | C51: =POWER(1+Triangulo1!$E$4-'1_Duration'!C7,0.25)-1 -> 0.012272234 | D51: {=SUMPRODUCT(D12:D35*$C$5,1/((1+C51)^(B12:B35*4)))} -> 84091364 | E51: =D51-D48 -> 782192.89 | F51: =E51/D48 -> 0.0093890369 | G51: =-C41*(C51-$C$6)*D48 -> 185723.45
B52: Baja 200 bps | C52: =POWER(1+Triangulo1!$E$4-'1_Duration'!C7*2,0.25)-1 -> 0.0098534065 | D52: {=SUMPRODUCT(D12:D35*$C$5,1/((1+C52)^(B12:B35*4)))} -> 84891697 | E52: =D52-D48 -> 1582525.4 | F52: =E52/D48 -> 0.018995812 | G52: =-C41*(C52-$C$6)*D48 -> 372778.28

Sheet 1_Validacion_BT
A1: VALIDACIÓN DE TRIÁNGULOS Y BACKTESTING
A3: A — MONOTONICIDAD ratio_{i,j} = C_{i,j+1}/C_{i,j} ≥ 1.0
A4: Año | B4: D1/D0 | C4: D2/D1 | D4: D3/D2 | E4: D4/D3 | F4: D5/D4 | G4: D6/D5 | H4: D7/D6 | I4: D8/D7 | J4: D9/D8 | K4: D10/D9 | L4: D11/D10 | M4: D12/D11 | N4: D13/D12 | O4: D14/D13 | P4: D15/D14 | Q4: D16/D15 | R4: D17/D16 | S4: D18/D17 | T4: D19/D18 | U4: D20/D19 | V4: D21/D20 | W4: D22/D21 | X4: D23/D22 | Y4: ¿Monótono? (todos ≥1?) | Z4: ¿Outlier? | AC4: D1/D0 | AD4: D2/D1 | AE4: D3/D2 | AF4: D4/D3 | AG4: D5/D4 | AH4: D6/D5 | AI4: D7/D6 | AJ4: D8/D7 | AK4: D9/D8 | AL4: D10/D9 | AM4: D11/D10 | AN4: D12/D11 | AO4: D13/D12 | AP4: D14/D13 | AQ4: D15/D14 | AR4: D16/D15 | AS4: D17/D16 | AT4: D18/D17 | AU4: D19/D18 | AV4: D20/D19 | AW4: D21/D20 | AX4: D22/D21 | AY4: D23/D22
A5: 1Q19 | B5: =Triangulo1!D44 -> 1.3012916 | C5: =Triangulo1!E44 -> 1.1246587 | D5: =Triangulo1!F44 -> 1.1905767 | E5: =Triangulo1!G44 -> 1.0820522 | F5: =Triangulo1!H44 -> 1.0512626 | G5: =Triangulo1!I44 -> 1.0277185 | H5: =Triangulo1!J44 -> 1.0363301 | I5: =Triangulo1!K44 -> 1.0133706 | ... X5: =Triangulo1!Z44 -> 1.0000011 | Y5: =MIN(B5:X5)>1 -> TRUE | Z5: {=MAX(ABS(AC5:AC26))>0.1} -> TRUE | AC5: =(B5-B6)/B5 -> -0.074196974 | AD5: =(C5-C6)/C5 -> -0.064916125 | AE5: =(D5-D6)/D5 -> 0.11754669 | AF5: =(E5-E6)/E5 -> -0.013314885 | AG5: =(F5-F6)/F5 -> 0.00076145876 | AH5: =(G5-G6)/G5 -> -0.026145173 | AI5: =(H5-H6)/H5 -> 0.0066497824 | AJ5: =(I5-I6)/I5 -> -0.0059993053 | ... AX5: =(W5-W6)/W5 -> -7.6952645e-08
A6: 2Q19 | B6: =Triangulo1!D45 -> 1.3978435 | C6: =Triangulo1!E45 -> 1.1976672 | D6: =Triangulo1!F45 -> 1.0506283 | E6: =Triangulo1!G45 -> 1.0964596 | F6: =Triangulo1!H45 -> 1.0504621 | G6: =Triangulo1!I45 -> 1.0545884 | H6: =Triangulo1!J45 -> 1.0294387 | I6: =Triangulo1!K45 -> 1.0194501 | ... X6: =Triangulo1!Z45 -> 0 | Y6: =MIN(B6:W6)>1 -> TRUE | Z6: {=MAX(ABS(AD5:AD25))>0.1} -> TRUE | AC6: =(B6-B7)/B6 -> 0.18227943 | AD6: =(C6-C7)/C6 -> 0.024442003 | AE6: =(D6-D7)/D6 -> -0.099418071 | AF6: =(E6-E7)/E6 -> -0.016706695 | AG6: =(F6-F7)/F6 -> -0.084500941 | AH6: =(G6-G7)/G6 -> -0.011068746 | AI6: =(H6-H7)/H6 -> -0.0067850143 | AJ6: =(I6-I7)/I6 -> -0.0085836249 | ... AW6: =(V6-V7)/V6 -> -2.4660131e-06
A7: 3Q19 | B7: =Triangulo1!D46 -> 1.1430454 | C7: =Triangulo1!E46 -> 1.1683938 | D7: =Triangulo1!F46 -> 1.1550798 | E7: =Triangulo1!G46 -> 1.1147778 | F7: =Triangulo1!H46 -> 1.1392271 | G7: =Triangulo1!I46 -> 1.0662613 | H7: =Triangulo1!J46 -> 1.0364235 | I7: =Triangulo1!K46 -> 1.0282007 | ... X7: =Triangulo1!Z46 -> 0 | Y7: =MIN(B7:V7)>1 -> TRUE | Z7: {=MAX(ABS(AE5:AE26))>0.1} -> TRUE | AC7: =(B7-B8)/B7 -> -0.89708106 | AD7: =(C7-C8)/C7 -> 0.025255445 | AE7: =(D7-D8)/D7 -> 0.089591929 | AF7: =(E7-E8)/E7 -> 0.037251974 | AG7: =(F7-F8)/F7 -> 0.075266535 | AH7: =(G7-G8)/G7 -> 0.047882161 | AI7: =(H7-H8)/H7 -> 0.018779326 | AJ7: =(I7-I8)/I7 -> -0.0041649243 | ... AV7: =(U7-U8)/U7 -> 9.8798353e-06
A8: 4Q19 | B8: =Triangulo1!D47 -> 2.1684497 | C8: =Triangulo1!E47 -> 1.1388855 | D8: =Triangulo1!F47 -> 1.051594 | E8: =Triangulo1!G47 -> 1.0732502 | F8: =Triangulo1!H47 -> 1.0534814 | G8: =Triangulo1!I47 -> 1.0152064 | H8: =Triangulo1!J47 -> 1.0169602 | I8: =Triangulo1!K47 -> 1.0324831 | ... X8: =Triangulo1!Z47 -> 0 | Y8: =MIN(B8:U8)>1 -> TRUE | Z8: {=MAX(ABS(AF5:AF26))>0.1} -> TRUE | AC8: =(B8-B9)/B8 -> 0.4542195 | AD8: =(C8-C9)/C8 -> -0.01040957 | AE8: =(D8-D9)/D8 -> -0.003797103 | AF8: =(E8-E9)/E8 -> -0.020630915 | AG8: =(F8-F9)/F8 -> 0.0183154 | AH8: =(G8-G9)/G8 -> -0.049603577 | AI8: =(H8-H9)/H8 -> -0.015047799 | AJ8: =(I8-I9)/I8 -> 0.017987987 | ... AU8: =(T8-T9)/T8 -> -1.0524409e-05
A9: 1Q20 | B9: =Triangulo1!D48 -> 1.1834976 | C9: =Triangulo1!E48 -> 1.1507408 | D9: =Triangulo1!F48 -> 1.055587 | E9: =Triangulo1!G48 -> 1.0953923 | F9: =Triangulo1!H48 -> 1.0341865 | G9: =Triangulo1!I48 -> 1.0655643 | H9: =Triangulo1!J48 -> 1.0322632 | I9: =Triangulo1!K48 -> 1.0139108 | ... X9: =Triangulo1!Z48 -> 0 | Y9: =MIN(B9:T9)>1 -> TRUE | Z9: {=MAX(ABS(AG5:AG26))>0.1} -> TRUE | AC9: =(B9-B10)/B9 -> -0.22672537 | AD9: =(C9-C10)/C9 -> -0.029160437 | AE9: =(D9-D10)/D9 -> -0.0099285929 | AF9: =(E9-E10)/E9 -> -0.044871881 | AG9: =(F9-F10)/F9 -> -0.12569311 | AH9: =(G9-G10)/G9 -> 0.0061086925 | AI9: =(H9-H10)/H9 -> -0.28872894 | AJ9: =(I9-I10)/I9 -> -0.035662546 | ... AT9: =(S9-S10)/S9 -> 9.962348e-07
A10: 2Q20 | B10: =Triangulo1!D49 -> 1.4518265 | C10: =Triangulo1!E49 -> 1.1842969 | D10: =Triangulo1!F49 -> 1.0660675 | E10: =Triangulo1!G49 -> 1.1445446 | F10: =Triangulo1!H49 -> 1.1641766 | G10: =Triangulo1!I49 -> 1.0590551 | H10: =Triangulo1!J49 -> 1.3303074 | I10: =Triangulo1!K49 -> 1.0500694 | ... X10: =Triangulo1!Z49 -> 0 | Y10: =MIN(B10:S10)>1 -> TRUE | Z10: {=MAX(ABS(AH5:AH26))>0.1} -> TRUE | AC10: =(B10-B11)/B10 -> 0.056067889 | AD10: =(C10-C11)/C10 -> 0.03082674 | AE10: =(D10-D11)/D10 -> -0.12310941 | AF10: =(E10-E11)/E10 -> 0.09048745 | AG10: =(F10-F11)/F10 -> 0.11889836 | AH10: =(G10-G11)/G10 -> -0.028740208 | AI10: =(H10-H11)/H10 -> 0.20625639 | AJ10: =(I10-I11)/I10 -> -0.0023919515 | ... AS10: =(R10-R11)/R10 -> -1.7585368e-05
A11: 3Q20 | B11: =Triangulo1!D50 -> 1.3704256 | C11: =Triangulo1!E50 -> 1.1477889 | D11: =Triangulo1!F50 -> 1.1973104 | E11: =Triangulo1!G50 -> 1.0409777 | F11: =Triangulo1!H50 -> 1.0257579 | G11: =Triangulo1!I50 -> 1.0894926 | H11: =Triangulo1!J50 -> 1.055923 | I11: =Triangulo1!K50 -> 1.0525811 | ... X11: =Triangulo1!Z50 -> 0 | Y11: =MIN(B11:R11)>1 -> TRUE | Z11: {=MAX(ABS(AI5:AI26))>0.1} -> TRUE | AC11: =(B11-B12)/B11 -> -0.012892695 | AD11: =(C11-C12)/C11 -> 0.059560537 | AE11: =(D11-D12)/D11 -> 0.042328373 | AF11: =(E11-E12)/E11 -> -0.00026531237 | AG11: =(F11-F12)/F11 -> -0.028992225 | AH11: =(G11-G12)/G11 -> 0.054571649 | AI11: =(H11-H12)/H11 -> 0.008701621 | AJ11: =(I11-I12)/I11 -> 0.038115379 | ... AR11: =(Q11-Q12)/Q11 -> 9.1867768e-05
A12: 4Q20 | B12: =Triangulo1!D51 -> 1.3880941 | C12: =Triangulo1!E51 -> 1.079426 | D12: =Triangulo1!F51 -> 1.1466302 | E12: =Triangulo1!G51 -> 1.0412539 | F12: =Triangulo1!H51 -> 1.0554969 | G12: =Triangulo1!I51 -> 1.0300372 | H12: =Triangulo1!J51 -> 1.0467348 | I12: =Triangulo1!K51 -> 1.0124616 | ... X12: =Triangulo1!Z51 -> 0 | Y12: =MIN(B12:Q12)>1 -> TRUE | Z12: {=MAX(ABS(AJ5:AJ26))>0.1} -> FALSE | AC12: =(B12-B13)/B12 -> -0.039387649 | AD12: =(C12-C13)/C12 -> -0.12621299 | AE12: =(D12-D13)/D12 -> 0.025337433 | AF12: =(E12-E13)/E12 -> 0.0073460979 | AG12: =(F12-F13)/F12 -> -0.019765397 | AH12: =(G12-G13)/G12 -> 0.013541811 | AI12: =(H12-H13)/H12 -> -0.0066009378 | AJ12: =(I12-I13)/I12 -> -0.024021528 | ... AQ12: =(P12-P13)/P12 -> 8.3909254e-05
A13: 1Q21 | B13: =Triangulo1!D52 -> 1.4427679 | C13: =Triangulo1!E52 -> 1.2156636 | D13: =Triangulo1!F52 -> 1.1175775 | E13: =Triangulo1!G52 -> 1.0336047 | F13: =Triangulo1!H52 -> 1.0763592 | G13: =Triangulo1!I52 -> 1.0160886 | H13: =Triangulo1!J52 -> 1.0536442 | I13: =Triangulo1!K52 -> 1.0367825 | ... X13: =Triangulo1!Z52 -> 0 | Y13: =MIN(B13:P13)>1 -> TRUE | Z13: {=MAX(ABS(AK5:AK26))>0.1} -> FALSE | AC13: =(B13-B14)/B13 -> -0.024858598 | AD13: =(C13-C14)/C13 -> -0.003120953 | AE13: =(D13-D14)/D13 -> -0.042055781 | AF13: =(E13-E14)/E13 -> -0.032112796 | AG13: =(F13-F14)/F13 -> 0.017875512 | AH13: =(G13-G14)/G13 -> -0.027833127 | AI13: =(H13-H14)/H13 -> -0.031639031 | AJ13: =(I13-I14)/I13 -> -0.0042929004 | ... AP13: =(O13-O14)/O13 -> -5.0972301e-05
A14: 2Q21 | B14: =Triangulo1!D53 -> 1.4786331 | C14: =Triangulo1!E53 -> 1.2194576 | D14: =Triangulo1!F53 -> 1.1645781 | E14: =Triangulo1!G53 -> 1.0667967 | F14: =Triangulo1!H53 -> 1.0571188 | G14: =Triangulo1!I53 -> 1.0443695 | H14: =Triangulo1!J53 -> 1.0869805 | I14: =Triangulo1!K53 -> 1.0412333 | ... X14: =Triangulo1!Z53 -> 0 | Y14: =MIN(B14:O14)>1 -> TRUE | Z14: {=MAX(ABS(AL5:AL26))>0.1} -> FALSE | AC14: =(B14-B15)/B14 -> 0.15477115 | AD14: =(C14-C15)/C14 -> 0.0056386284 | AE14: =(D14-D15)/D14 -> 0.10953102 | AF14: =(E14-E15)/E14 -> -0.055827615 | AG14: =(F14-F15)/F14 -> 0.021026369 | AH14: =(G14-G15)/G14 -> -0.10246031 | AI14: =(H14-H15)/H14 -> 0.005559951 | AJ14: =(I14-I15)/I14 -> 0.0067200416 | ... AO14: =(N14-N15)/N14 -> 0.00025172232
A15: 3Q21 | B15: =Triangulo1!D54 -> 1.2497833 | C15: =Triangulo1!E54 -> 1.2125815 | D15: =Triangulo1!F54 -> 1.0370207 | E15: =Triangulo1!G54 -> 1.1263534 | F15: =Triangulo1!H54 -> 1.0348914 | G15: =Triangulo1!I54 -> 1.1513759 | H15: =Triangulo1!J54 -> 1.0809369 | I15: =Triangulo1!K54 -> 1.0342361 | ... X15: =Triangulo1!Z54 -> 0 | Y15: =MIN(B15:N15)>1 -> TRUE | Z15: {=MAX(ABS(AM5:AM26))>0.1} -> FALSE | AC15: =(B15-B16)/B15 -> -0.1614505 | AD15: =(C15-C16)/C15 -> -0.0096873102 | AE15: =(D15-D16)/D15 -> -0.012495703 | AF15: =(E15-E16)/E15 -> 0.021485338 | AG15: =(F15-F16)/F15 -> -0.086319269 | AH15: =(G15-G16)/G15 -> 0.03515839 | AI15: =(H15-H16)/H15 -> 0.012192634 | AJ15: =(I15-I16)/I15 -> 0.0078240552 | ... AN15: =(M15-M16)/M15 -> 4.820052e-05
A16: 4Q21 | B16: =Triangulo1!D55 -> 1.4515615 | C16: =Triangulo1!E55 -> 1.2243282 | D16: =Triangulo1!F55 -> 1.049979 | E16: =Triangulo1!G55 -> 1.1021533 | F16: =Triangulo1!H55 -> 1.1242225 | G16: =Triangulo1!I55 -> 1.1108954 | H16: =Triangulo1!J55 -> 1.0677575 | I16: =Triangulo1!K55 -> 1.0261442 | ... X16: =Triangulo1!Z55 -> 0 | Y16: =MIN(B16:M16)>1 -> TRUE | Z16: {=MAX(ABS(AN5:AN26))>0.1} -> FALSE | AC16: =(B16-B17)/B16 -> -0.025991573 | AD16: =(C16-C17)/C16 -> 0.0084323865 | AE16: =(D16-D17)/D16 -> -0.093499205 | AF16: =(E16-E17)/E16 -> -0.11543023 | AG16: =(F16-F17)/F16 -> -0.030150627 | AH16: =(G16-G17)/G16 -> -0.020357074 | AI16: =(H16-H17)/H16 -> 0.0057159138 | AJ16: =(I16-I17)/I16 -> -0.0067165084 | ... AM16: =(L16-L17)/L16 -> -1.8166431e-05
A17: 1Q22 | B17: =Triangulo1!D56 -> 1.4892898 | C17: =Triangulo1!E56 -> 1.2140042 | D17: =Triangulo1!F56 -> 1.1481512 | E17: =Triangulo1!G56 -> 1.2293751 | F17: =Triangulo1!H56 -> 1.1581185 | G17: =Triangulo1!I56 -> 1.13351 | H17: =Triangulo1!J56 -> 1.0616542 | I17: =Triangulo1!K56 -> 1.0330363 | ... X17: =Triangulo1!Z56 -> 0 | Y17: =MIN(B17:L17)>1 -> TRUE | Z17: {=MAX(ABS(AO5:AO26))>0.1} -> FALSE | AC17: =(B17-B18)/B17 -> 0.057777745 | AD17: =(C17-C18)/C17 -> 0.097061028 | AE17: =(D17-D18)/D17 -> -0.26659574 | AF17: =(E17-E18)/E17 -> -0.023039574 | AG17: =(F17-F18)/F17 -> 0.035937694 | AH17: =(G17-G18)/G17 -> 0.0065227358 | AI17: =(H17-H18)/H17 -> 0.013104779 | AJ17: =(I17-I18)/I17 -> 0.0074860924 | ... AL17: =(K17-K18)/K17 -> 0.0011280879
A18: 2Q22 | B18: =Triangulo1!D57 -> 1.403242 | C18: =Triangulo1!E57 -> 1.0961717 | D18: =Triangulo1!F57 -> 1.4542434 | E18: =Triangulo1!G57 -> 1.2576994 | F18: =Triangulo1!H57 -> 1.1164984 | G18: =Triangulo1!I57 -> 1.1261164 | H18: =Triangulo1!J57 -> 1.0477415 | I18: =Triangulo1!K57 -> 1.0253029 | ... X18: =Triangulo1!Z57 -> 0 | Y18: =MIN(B18:K18)>1 -> TRUE | Z18: {=MAX(ABS(AP5:AP26))>0.1} -> FALSE | AC18: =(B18-B19)/B18 -> 0.0050845111 | AD18: =(C18-C19)/C18 -> -0.66231303 | AE18: =(D18-D19)/D18 -> 0.033857934 | AF18: =(E18-E19)/E18 -> 0.058995054 | AG18: =(F18-F19)/F18 -> -0.031507809 | AH18: =(G18-G19)/G18 -> -0.013866093 | AI18: =(H18-H19)/H18 -> -0.00070357413 | AJ18: =(I18-I19)/I18 -> 0.002925249 | AK18: =(J18-J19)/J18 -> -0.0034029805
A19: 3Q22 | B19: =Triangulo1!D58 -> 1.3961072 | C19: =Triangulo1!E58 -> 1.8221805 | D19: =Triangulo1!F58 -> 1.4050057 | E19: =Triangulo1!G58 -> 1.1835013 | F19: =Triangulo1!H58 -> 1.1516768 | G19: =Triangulo1!I58 -> 1.1417312 | H19: =Triangulo1!J58 -> 1.0484787 | I19: =Triangulo1!K58 -> 1.0223037 | ... X19: =Triangulo1!Z58 -> 0 | Y19: =MIN(B19:J19)>1 -> TRUE | Z19: {=MAX(ABS(AQ5:AQ26))>0.1} -> FALSE | AC19: =(B19-B20)/B19 -> -0.38997831 | AD19: =(C19-C20)/C19 -> 0.25827168 | AE19: =(D19-D20)/D19 -> 0.11958285 | AF19: =(E19-E20)/E19 -> 0.0411248 | AG19: =(F19-F20)/F19 -> 0.048664833 | AH19: =(G19-G20)/G19 -> 0.046079029 | AI19: =(H19-H20)/H19 -> 0.007165988 | AJ19: =(I19-I20)/I19 -> 0.0022720262
A20: 4Q22 | B20: =Triangulo1!D59 -> 1.9405588 | C20: =Triangulo1!E59 -> 1.3515629 | D20: =Triangulo1!F59 -> 1.2369911 | E20: =Triangulo1!G59 -> 1.1348301 | F20: =Triangulo1!H59 -> 1.0956306 | G20: =Triangulo1!I59 -> 1.0891214 | H20: =Triangulo1!J59 -> 1.0409653 | I20: =Triangulo1!K59 -> 1.019981 | ... X20: =Triangulo1!Z59 -> 0 | Y20: =MIN(B20:I20)>1 -> TRUE | Z20: {=MAX(ABS(AR5:AR26))>0.1} -> FALSE | AC20: =(B20-B21)/B20 -> 0.15543846 | AD20: =(C20-C21)/C20 -> -0.07808491 | AE20: =(D20-D21)/D20 -> -0.01173909 | AF20: =(E20-E21)/E20 -> -0.012041281 | AG20: =(F20-F21)/F20 -> 0.0027085737 | AH20: =(G20-G21)/G20 -> 0.016070715 | AI20: =(H20-H21)/H20 -> -0.0040241902
A21: 1Q23 | B21: =Triangulo1!D60 -> 1.6389213 | C21: =Triangulo1!E60 -> 1.4570995 | D21: =Triangulo1!F60 -> 1.2515123 | E21: =Triangulo1!G60 -> 1.1484949 | F21: =Triangulo1!H60 -> 1.092663 | G21: =Triangulo1!I60 -> 1.0716184 | H21: =Triangulo1!J60 -> 1.0451543 | I21: =Triangulo1!K60 -> 0 | ... X21: =Triangulo1!Z60 -> 0 | Y21: =MIN(B21:H21)>1 -> TRUE | Z21: {=MAX(ABS(AS5:AS26))>0.1} -> FALSE | AC21: =(B21-B22)/B21 -> -0.59448485 | AD21: =(C21-C22)/C21 -> 0.021787502 | AE21: =(D21-D22)/D21 -> -0.028850702 | AF21: =(E21-E22)/E21 -> -0.034281648 | AG21: =(F21-F22)/F21 -> -0.022182569 | AH21: =(G21-G22)/G21 -> -0.038191006
A22: 2Q23 | B22: =Triangulo1!D61 -> 2.6132352 | C22: =Triangulo1!E61 -> 1.425353 | D22: =Triangulo1!F61 -> 1.2876193 | E22: =Triangulo1!G61 -> 1.1878672 | F22: =Triangulo1!H61 -> 1.1169011 | G22: =Triangulo1!I61 -> 1.1125446 | H22: =Triangulo1!J61 -> 0 | I22: =Triangulo1!K61 -> 0 | ... X22: =Triangulo1!Z61 -> 0 | Y22: =MIN(B22:G22)>1 -> TRUE | Z22: {=MAX(ABS(AT5:AT26))>0.1} -> FALSE | AC22: =(B22-B23)/B22 -> -0.21020187 | AD22: =(C22-C23)/C22 -> 0.19563387 | AE22: =(D22-D23)/D22 -> 0.10762772 | AF22: =(E22-E23)/E22 -> 0.070603615 | AG22: =(F22-F23)/F22 -> 0.057363738
A23: 3Q23 | B23: =Triangulo1!D62 -> 3.1625421 | C23: =Triangulo1!E62 -> 1.1465056 | D23: =Triangulo1!F62 -> 1.1490358 | E23: =Triangulo1!G62 -> 1.1039995 | F23: =Triangulo1!H62 -> 1.0528315 | G23: =Triangulo1!I62 -> 0 | H23: =Triangulo1!J62 -> 0 | I23: =Triangulo1!K62 -> 0 | ... X23: =Triangulo1!Z62 -> 0 | Y23: =MIN(B23:F23)>1 -> TRUE | Z23: {=MAX(ABS(AU5:AU26))>0.1} -> FALSE | AC23: =(B23-B24)/B23 -> 0.44445837 | AD23: =(C23-C24)/C23 -> -0.14192841 | AE23: =(D23-D24)/D23 -> -0.059448285 | AF23: =(E23-E24)/E23 -> -0.049344735
A24: 4Q23 | B24: =Triangulo1!D63 -> 1.7569238 | C24: =Triangulo1!E63 -> 1.3092274 | D24: =Triangulo1!F63 -> 1.217344 | E24: =Triangulo1!G63 -> 1.158476 | F24: =Triangulo1!H63 -> 0 | G24: =Triangulo1!I63 -> 0 | H24: =Triangulo1!J63 -> 0 | I24: =Triangulo1!K63 -> 0 | ... X24: =Triangulo1!Z63 -> 0 | Y24: =MIN(B24:E24)>1 -> TRUE | Z24: {=MAX(ABS(AV5:AV25))>0.1} -> FALSE | AC24: =(B24-B25)/B24 -> -0.32733795 | AD24: =(C24-C25)/C24 -> -0.12315346 | AE24: =(D24-D25)/D24 -> 0.011003366
A25: 1Q24 | B25: =Triangulo1!D64 -> 2.3320317 | C25: =Triangulo1!E64 -> 1.4704633 | D25: =Triangulo1!F64 -> 1.2039491 | E25: =Triangulo1!G64 -> 0 | F25: =Triangulo1!H64 -> 0 | G25: =Triangulo1!I64 -> 0 | H25: =Triangulo1!J64 -> 0 | I25: =Triangulo1!K64 -> 0 | ... X25: =Triangulo1!Z64 -> 0 | Y25: =MIN(B25:D25)>1 -> TRUE | Z25: {=MAX(ABS(AW5:AW24))>0.1} -> FALSE | AC25: =(B25-B26)/B25 -> 0.15085735 | AD25: =(C25-C26)/C25 -> 0.10761301
A26: 2Q24 | B26: =Triangulo1!D65 -> 1.9802276 | C26: =Triangulo1!E65 -> 1.3122223 | D26: =Triangulo1!F65 -> 0 | E26: =Triangulo1!G65 -> 0 | F26: =Triangulo1!H65 -> 0 | G26: =Triangulo1!I65 -> 0 | H26: =Triangulo1!J65 -> 0 | I26: =Triangulo1!K65 -> 0 | ... X26: =Triangulo1!Z65 -> 0 | Y26: =MIN(B26:C26)>1 -> TRUE | Z26: =MAX(ABS(AX5))>0.1 -> FALSE | AC26: =(B26-B27)/B26 -> 0.04446241
A27: 3Q24 | B27: =Triangulo1!D66 -> 1.8921819 | C27: =Triangulo1!E66 -> 0 | D27: =Triangulo1!F66 -> 0 | E27: =Triangulo1!G66 -> 0 | F27: =Triangulo1!H66 -> 0 | G27: =Triangulo1!I66 -> 0 | H27: =Triangulo1!J66 -> 0 | I27: =Triangulo1!K66 -> 0 | ... X27: =Triangulo1!Z66 -> 0 | Y27: =MIN(B27:B27)>1 -> TRUE
A28: 4Q24 | C28: =Triangulo1!E67 -> 0 | D28: =Triangulo1!F67 -> 0 | E28: =Triangulo1!G67 -> 0 | F28: =Triangulo1!H67 -> 0 | G28: =Triangulo1!I67 -> 0 | H28: =Triangulo1!J67 -> 0 | I28: =Triangulo1!K67 -> 0 | J28: =Triangulo1!L67 -> 0 | ... X28: =Triangulo1!Z67 -> 0
B29: ='1_CL'!C30 -> 2.1469743 | C29: ='1_CL'!D30 -> 1.3475034 | D29: ='1_CL'!E30 -> 1.2458421 | E29: ='1_CL'!F30 -> 1.1619344 | F29: ='1_CL'!G30 -> 1.1042248 | G29: ='1_CL'!H30 -> 1.1121613 | H29: ='1_CL'!I30 -> 1.0564419 | I29: ='1_CL'!J30 -> 1.0286063 | ... X29: ='1_CL'!Y30 -> 1.0000011
A31: B — DETECCIÓN DE OUTLIERS |ratio_{i,j} − f̂_j| / f̂_j > 20%
A32: Columna | B32: f̂_j (Ej1) | C32: Límite −20% | D32: Límite +20% | E32: ¿Outlier en Parte A?
A33: {=TRANSPOSE(B4:X4)} -> D1/D0 | B33: {=TRANSPOSE(B29:X29)} -> 2.1469743 | C33: =B33*0.8 -> 1.7175795 | D33: =B33*1.2 -> 2.5763692 | E33: =IF(F33, "No", "Sí") -> Sí | F33: =AND(MIN($B$5:$B$27)>=$C$33,MAX($B$5:$B$27)<=$D$33) -> FALSE
A34: D2/D1 | B34: 1.3475034 | C34: =B34*0.8 -> 1.0780027 | D34: =B34*1.2 -> 1.617004 | E34: =IF(F34, "No", "Sí") -> Sí | F34: =AND(MIN($C$5:$C$26)>=$C$34,MAX($C$5:$C$26)<=$D$34) -> FALSE
A35: D3/D2 | B35: 1.2458421 | C35: =B35*0.8 -> 0.99667371 | D35: =B35*1.2 -> 1.4950106 | E35: =IF(F35, "No", "Sí") -> No | F35: =AND(MIN($D$5:$D$25)>=$C$35,MAX($D$5:$D$25)<=$D$35) -> TRUE
A36: D4/D3 | B36: 1.1619344 | C36: =B36*0.8 -> 0.92954753 | D36: =B36*1.2 -> 1.3943213 | E36: =IF(F36, "No", "Sí") -> No | F36: =AND(MIN($E$5:$E$24)>=$C$36,MAX($E$5:$E$24)<=$D$36) -> TRUE
A37: D5/D4 | B37: 1.1042248 | C37: =B37*0.8 -> 0.88337986 | D37: =B37*1.2 -> 1.3250698 | E37: =IF(F37, "No", "Sí") -> No | F37: =AND(MIN($F$5:$F$23)>=C37,MAX($F$5:$F$23)<=D37) -> TRUE
A38: D6/D5 | B38: 1.1121613 | C38: =B38*0.8 -> 0.88972907 | D38: =B38*1.2 -> 1.3345936 | E38: =IF(F38, "No", "Sí") -> No | F38: =AND(MIN($G$5:$G$22)>=C38,MAX($G$5:$G$22)<=D38) -> TRUE
A39: D7/D6 | B39: 1.0564419 | C39: =B39*0.8 -> 0.8451535 | D39: =B39*1.2 -> 1.2677303 | E39: =IF(F39, "No", "Sí") -> Sí | F39: =AND(MIN($H$5:$H$21)>=C39,MAX($H$5:$H$21)<=D39) -> FALSE
A40: D8/D7 | B40: 1.0286063 | C40: =B40*0.8 -> 0.82288503 | D40: =B40*1.2 -> 1.2343275 | E40: =IF(F40, "No", "Sí") -> No | F40: =AND(MIN($I$5:$I$20)>=C40,MAX($I$5:$I$20)<=D40) -> TRUE
A41: D9/D8 | B41: 1.0155862 | C41: =B41*0.8 -> 0.81246895 | D41: =B41*1.2 -> 1.2187034 | E41: =IF(F41, "No", "Sí") -> No | F41: =AND(MIN($J$5:$J$19)>=C41,MAX($J$5:$J$19)<=D41) -> TRUE
A42: D10/D9 | B42: 1.0080991 | C42: =B42*0.8 -> 0.80647929 | D42: =B42*1.2 -> 1.2097189 | E42: =IF(F42, "No", "Sí") -> No | F42: =AND(MIN($K$5:$K$18)>=C42,MAX($K$5:$K$18)<=D42) -> TRUE
A43: D11/D10 | B43: 1.0038617 | C43: =B43*0.8 -> 0.80308936 | D43: =B43*1.2 -> 1.204634 | E43: =IF(F43, "No", "Sí") -> No | F43: =AND(MIN($L$5:$L$17)>=C43,MAX($L$5:$L$17)<=D43) -> TRUE
A44: D12/D11 | B44: 1.0022525 | C44: =B44*0.8 -> 0.80180198 | D44: =B44*1.2 -> 1.202703 | E44: =IF(F44, "No", "Sí") -> No | F44: =AND(MIN($M$5:$M$16)>=C44,MAX($M$5:$M$16)<=D44) -> TRUE
A45: D13/D12 | B45: 1.0011361 | C45: =B45*0.8 -> 0.80090887 | D45: =B45*1.2 -> 1.2013633 | E45: =IF(F45, "No", "Sí") -> No | F45: =AND(MIN($N$5:$N$15)>=C45,MAX($N$5:$N$15)<=D45) -> TRUE
A46: D14/D13 | B46: 1.000589 | C46: =B46*0.8 -> 0.80047122 | D46: =B46*1.2 -> 1.2007068 | E46: =IF(F46, "No", "Sí") -> No | F46: =AND(MIN($O$5:$O$14)>=C46,MAX($O$5:$O$14)<=D46) -> TRUE
A47: D15/D14 | B47: 1.0003076 | C47: =B47*0.8 -> 0.80024609 | D47: =B47*1.2 -> 1.2003691 | E47: =IF(F47, "No", "Sí") -> No | F47: =AND(MIN($P$5:$P$13)>=C47,MAX($P$5:$P$13)<=D47) -> TRUE
A48: D16/D15 | B48: 1.00014 | C48: =B48*0.8 -> 0.80011202 | D48: =B48*1.2 -> 1.200168 | E48: =IF(F48, "No", "Sí") -> No | F48: =AND(MIN($Q$5:$Q$12)>=C48,MAX($Q$5:$Q$12)<=D48) -> TRUE
A49: D17/D16 | B49: 1.0000689 | C49: =B49*0.8 -> 0.80005514 | D49: =B49*1.2 -> 1.2000827 | E49: =IF(F49, "No", "Sí") -> No | F49: =AND(MIN($R$5:$R$11)>=C49,MAX($R$5:$R$11)<=D49) -> TRUE
A50: D18/D17 | B50: 1.0000326 | C50: =B50*0.8 -> 0.80002609 | D50: =B50*1.2 -> 1.2000391 | E50: =IF(F50, "No", "Sí") -> No | F50: =AND(MIN($S$5:$S$10)>=C50,MAX($S$5:$S$10)<=D50) -> TRUE
A51: D19/D18 | B51: 1.0000097 | C51: =B51*0.8 -> 0.80000777 | D51: =B51*1.2 -> 1.2000116 | E51: =IF(F51, "No", "Sí") -> No | F51: =AND(MIN($T$5:$T$9)>=C51,MAX($T$5:$T$9)<=D51) -> TRUE
A52: D20/D19 | B52: 1.000003 | C52: =B52*0.8 -> 0.80000242 | D52: =B52*1.2 -> 1.2000036 | E52: =IF(F52, "No", "Sí") -> No | F52: =AND(MIN($U$5:$U$8)>=C52,MAX($U$5:$U$8)<=D52) -> TRUE
A53: D21/D20 | B53: 1.0000012 | C53: =B53*0.8 -> 0.80000092 | D53: =B53*1.2 -> 1.2000014 | E53: =IF(F53, "No", "Sí") -> No | F53: =AND(MIN($V$5:$V$7)>=C53,MAX($V$5:$V$7)<=D53) -> TRUE
A54: D22/D21 | B54: 1.0000006 | C54: =B54*0.8 -> 0.80000047 | D54: =B54*1.2 -> 1.2000007 | E54: =IF(F54, "No", "Sí") -> No | F54: =AND(MIN($W$5:$W$6)>=C54,MAX($W$5:$W$6)<=D54) -> TRUE
A55: D23/D22 | B55: 1.0000011 | C55: =B55*0.8 -> 0.80000087 | D55: =B55*1.2 -> 1.2000013 | E55: =IF(F55, "No", "Sí") -> No | F55: =AND(MIN($X$5:$X$5)>=C55,MAX($X$5:$X$5)<=D55) -> TRUE
A58: C — BACKTESTING con triángulo a sep-2026 | Z58: Backtesting proyectando al final del triangulo | AF58: Backtesting a septiembre de 2026
A60: Año \ Dev. | B60: T01 | C60: T02 | D60: T03 | E60: T04 | F60: T05 | G60: T06 | H60: T07 | I60: T08 | J60: T09 | K60: T10 | L60: T11 | M60: T12 | N60: T13 | O60: T14 | P60: T15 | Q60: T16 | R60: T17 | S60: T18 | T60: T19 | U60: T20 | V60: T21 | W60: T22 | X60: T23 | Y60: T24 | Z60: Último Proy. | AA60: Pagado Actual | AB60: IBNR CL_nuv | AC60: IBNR CL | AD60: Diferencia | AE60: Conclusión | AF60: Último Proy. | AG60: Pagado Actual | AH60: IBNR CL_nuv | AI60: IBNR CL | AJ60: Diferencia | AK60: Conclusión
A61: 1Q19 | B61: ='1_CL'!C4 -> 0 | C61: ='1_CL'!D4 -> 0 | D61: ='1_CL'!E4 -> 0 | E61: ='1_CL'!F4 -> 0 | F61: ='1_CL'!G4 -> 0 | G61: ='1_CL'!H4 -> 0 | H61: ='1_CL'!I4 -> 0 | I61: ='1_CL'!J4 -> 0 | ... Y61: ='1_CL'!Z4 -> 14725385 | Z61: =+Y61 -> 14725385 | AA61: =+Y61 -> 14725385 | AB61: =Z61-AA61 -> 0 | AC61: ='1_CL'!AC4 -> 0 | AD61: =AC61-AB61 -> 0 | AE61: =IF(AD61=0,"No hay cambio",IF(AD61>0,"Sobreestimando la reserva","Subestimando la reserva")) -> No hay cambio | AF61: =Y61 -> 14725385 | AG61: =Y61 -> 14725385 | AH61: =AF61-AG61 -> 0 | AI61: ='1_CL'!Z4-AG61 -> 0
A62: 2Q19 | B62: ='1_CL'!C5 -> 0 | C62: ='1_CL'!D5 -> 0 | D62: ='1_CL'!E5 -> 0 | E62: ='1_CL'!F5 -> 0 | F62: ='1_CL'!G5 -> 0 | G62: ='1_CL'!H5 -> 0 | H62: ='1_CL'!I5 -> 0 | I62: ='1_CL'!J5 -> 0 | ... X62: ='1_CL'!Y5 -> 17735279 | Y62: =Triangulo1!AA112 -> 17735298 | Z62: =+Y62 -> 17735298 | AA62: =+X62 -> 17735279 | AB62: =Z62-AA62 -> 19.270448 | AC62: ='1_CL'!AC5 -> 19.270448 | AD62: =AC62-AB62 -> 0 | AE62: =IF(AD62=0,"No hay cambio",IF(AD62>0,"Sobreestimando la reserva","Subestimando la reserva")) -> No hay cambio | AF62: =Y62 -> 17735298 | AG62: =X62 -> 17735279 | AH62: =AF62-AG62 -> 19.270448 | AI62: ='1_CL'!Z5-AG62 -> 19.270448 | AJ62: =AI62-AH62 -> 0 | AK62: =IF(AJ62=0,"No hay cambio",IF(AJ62>0,"Sobreestimando la reserva","Subestimando la reserva")) -> No hay cambio
A63: 3Q19 | B63: ='1_CL'!C6 -> 0 | C63: ='1_CL'!D6 -> 0 | D63: ='1_CL'!E6 -> 0 | E63: ='1_CL'!F6 -> 0 | F63: ='1_CL'!G6 -> 0 | G63: ='1_CL'!H6 -> 0 | H63: ='1_CL'!I6 -> 0 | I63: ='1_CL'!J6 -> 0 | ... W63: ='1_CL'!X6 -> 11881761 | X63: =Triangulo1!Z113 -> 11881768 | Y63: =Triangulo1!AA113 -> 11881781 | Z63: =+Y63 -> 11881781 | AA63: =+W63 -> 11881761 | AB63: =Z63-AA63 -> 20.279718 | AC63: ='1_CL'!AC6 -> 19.864942 | AD63: =AC63-AB63 -> -0.41477645 | AE63: =IF(AD63=0,"No hay cambio",IF(AD63>0,"Sobreestimando la reserva","Subestimando la reserva")) -> Subestimando la reserva | AF63: =Y63 -> 11881781 | AG63: =W63 -> 11881761 | AH63: =AF63-AG63 -> 20.279718 | AI63: ='1_CL'!Z6-'1_Validacion_BT'!AG63 -> 19.864942 | AJ63: =AI63-AH63 -> -0.41477645 | AK63: =IF(AJ63=0,"No hay cambio",IF(AJ63>0,"Sobreestimando la reserva","Subestimando la reserva")) -> Subestimando la reserva
A64: 4Q19 | B64: ='1_CL'!C7 -> 0 | C64: ='1_CL'!D7 -> 0 | D64: ='1_CL'!E7 -> 0 | E64: ='1_CL'!F7 -> 0 | F64: ='1_CL'!G7 -> 0 | G64: ='1_CL'!H7 -> 0 | H64: ='1_CL'!I7 -> 0 | I64: ='1_CL'!J7 -> 0 | ... V64: ='1_CL'!W7 -> 19461650 | W64: =Triangulo1!Y114 -> 19461709 | X64: =Triangulo1!Z114 -> 19461720 | Y64: =Triangulo1!AA114 -> 19461741 | Z64: =+Y64 -> 19461741 | AA64: =+V64 -> 19461650 | AB64: =Z64-AA64 -> 90.68563 | AC64: ='1_CL'!AC7 -> 54.921351 | AD64: =AC64-AB64 -> -35.764279 | AE64: =IF(AD64=0,"No hay cambio",IF(AD64>0,"Sobreestimando la reserva","Subestimando la reserva")) -> Subestimando la reserva | AF64: =Y64 -> 19461741 | AG64: =V64 -> 19461650 | AH64: =AF64-AG64 -> 90.68563 | AI64: ='1_CL'!Z7-'1_Validacion_BT'!AG64 -> 54.921351 | AJ64: =AI64-AH64 -> -35.764279 | AK64: =IF(AJ64=0,"No hay cambio",IF(AJ64>0,"Sobreestimando la reserva","Subestimando la reserva")) -> Subestimando la reserva
A65: 1Q20 | B65: ='1_CL'!C8 -> 0 | C65: ='1_CL'!D8 -> 0 | D65: ='1_CL'!E8 -> 0 | E65: ='1_CL'!F8 -> 0 | F65: ='1_CL'!G8 -> 0 | G65: ='1_CL'!H8 -> 0 | H65: ='1_CL'!I8 -> 0 | I65: ='1_CL'!J8 -> 0 | ... U65: ='1_CL'!V8 -> 11816173 | V65: =Triangulo1!X115 -> 11816183 | W65: =Triangulo1!Y115 -> 11816219 | X65: =Triangulo1!Z115 -> 11816226 | Y65: =Triangulo1!AA115 -> 11816238 | Z65: =+Y65 -> 11816238 | AA65: =+U65 -> 11816173 | AB65: =Z65-AA65 -> 65.491671 | AC65: ='1_CL'!AC8 -> 69.088413 | AD65: =AC65-AB65 -> 3.5967414 | AE65: =IF(AD65=0,"No hay cambio",IF(AD65>0,"Sobreestimando la reserva","Subestimando la reserva")) -> Sobreestimando la reserva | AF65: =Y65 -> 11816238 | AG65: =U65 -> 11816173 | AH65: =AF65-AG65 -> 65.491671 | AI65: ='1_CL'!Y8-'1_Validacion_BT'!AG65 -> 56.249368 | AJ65: =AI65-AH65 -> -9.2423032 | AK65: =IF(AJ65=0,"No hay cambio",IF(AJ65>0,"Sobreestimando la reserva","Subestimando la reserva")) -> Subestimando la reserva
A66: 2Q20 | B66: ='1_CL'!C9 -> 0 | C66: ='1_CL'!D9 -> 0 | D66: ='1_CL'!E9 -> 0 | E66: ='1_CL'!F9 -> 0 | F66: ='1_CL'!G9 -> 0 | G66: ='1_CL'!H9 -> 0 | H66: ='1_CL'!I9 -> 0 | I66: ='1_CL'!J9 -> 0 | ... T66: ='1_CL'!U9 -> 13048471 | U66: =Triangulo1!W116 -> 13048635 | V66: =Triangulo1!X116 -> 13048765 | W66: =Triangulo1!Y116 -> 13048804 | X66: =Triangulo1!Z116 -> 13048812 | Y66: =Triangulo1!AA116 -> 13048826 | Z66: =+Y66 -> 13048826 | AA66: =+T66 -> 13048471 | AB66: =Z66-AA66 -> 355.46951 | AC66: ='1_CL'!AC9 -> 202.94963 | AD66: =AC66-AB66 -> -152.51988 | AE66: =IF(AD66=0,"No hay cambio",IF(AD66>0,"Sobreestimando la reserva","Subestimando la reserva")) -> Subestimando la reserva | AF66: =Y66 -> 13048826 | AG66: =T66 -> 13048471 | AH66: =AF66-AG66 -> 355.46951 | AI66: ='1_CL'!Z9-'1_Validacion_BT'!AG66 -> 202.94963 | AJ66: =AI66-AH66 -> -152.51988 | AK66: =IF(AJ66=0,"No hay cambio",IF(AJ66>0,"Sobreestimando la reserva","Subestimando la reserva")) -> Subestimando la reserva
A67: 3Q20 | B67: ='1_CL'!C10 -> 0 | C67: ='1_CL'!D10 -> 0 | D67: ='1_CL'!E10 -> 0 | E67: ='1_CL'!F10 -> 0 | F67: ='1_CL'!G10 -> 0 | G67: ='1_CL'!H10 -> 0 | H67: ='1_CL'!I10 -> 0 | I67: ='1_CL'!J10 -> 0 | ... S67: ='1_CL'!T10 -> 10840140 | T67: =Triangulo1!V117 -> 10840676 | U67: =Triangulo1!W117 -> 10840840 | V67: =Triangulo1!X117 -> 10840840 | W67: =Triangulo1!Y117 -> 10840846 | X67: =Triangulo1!Z117 -> 10840852 | Y67: =Triangulo1!AA117 -> 10840864 | Z67: =+Y67 -> 10840864 | AA67: =+S67 -> 10840140 | AB67: =Z67-AA67 -> 724.14234 | AC67: ='1_CL'!AC10 -> 522.18308 | AD67: =AC67-AB67 -> -201.95926 | AE67: =IF(AD67=0,"No hay cambio",IF(AD67>0,"Sobreestimando la reserva","Subestimando la reserva")) -> Subestimando la reserva | AF67: =Y67 -> 10840864 | AG67: =S67 -> 10840140 | AH67: =AF67-AG67 -> 724.14234 | AI67: ='1_CL'!Z10-'1_Validacion_BT'!AG67 -> 522.18308 | AJ67: =AI67-AH67 -> -201.95926 | AK67: =IF(AJ67=0,"No hay cambio",IF(AJ67>0,"Sobreestimando la reserva","Subestimando la reserva")) -> Subestimando la reserva
A68: 4Q20 | B68: ='1_CL'!C11 -> 0 | C68: ='1_CL'!D11 -> 0 | D68: ='1_CL'!E11 -> 0 | E68: ='1_CL'!F11 -> 0 | F68: ='1_CL'!G11 -> 0 | G68: ='1_CL'!H11 -> 0 | H68: ='1_CL'!I11 -> 0 | I68: ='1_CL'!J11 -> 0 | ... R68: ='1_CL'!S11 -> 14111136 | S68: =Triangulo1!U118 -> 14111984 | T68: =Triangulo1!V118 -> 14112284 | U68: =Triangulo1!W118 -> 14112349 | V68: =Triangulo1!X118 -> 14112489 | W68: =Triangulo1!Y118 -> 14112494 | X68: =Triangulo1!Z118 -> 14112502 | Y68: =Triangulo1!AA118 -> 14112517 | Z68: =+Y68 -> 14112517 | AA68: =+R68 -> 14111136 | AB68: =Z68-AA68 -> 1381.1003 | AC68: ='1_CL'!AC11 -> 1652.4212 | AD68: =AC68-AB68 -> 271.32089 | AE68: =IF(AD68=0,"No hay cambio",IF(AD68>0,"Sobreestimando la reserva","Subestimando la reserva")) -> Sobreestimando la reserva | AF68: =Y68 -> 14112517 | AG68: =R68 -> 14111136 | AH68: =AF68-AG68 -> 1381.1003 | AI68: ='1_CL'!Z11-'1_Validacion_BT'!AG68 -> 1652.4212 | AJ68: =AI68-AH68 -> 271.32089 | AK68: =IF(AJ68=0,"No hay cambio",IF(AJ68>0,"Sobreestimando la reserva","Subestimando la reserva")) -> Sobreestimando la reserva
A69: 1Q21 | B69: ='1_CL'!C12 -> 0 | C69: ='1_CL'!D12 -> 0 | D69: ='1_CL'!E12 -> 0 | E69: ='1_CL'!F12 -> 0 | F69: ='1_CL'!G12 -> 0 | G69: ='1_CL'!H12 -> 0 | H69: ='1_CL'!I12 -> 0 | I69: ='1_CL'!J12 -> 14684360 | ... Q69: ='1_CL'!R12 -> 15729334 | R69: =Triangulo1!T119 -> 15731356 | S69: =Triangulo1!U119 -> 15732523 | T69: =Triangulo1!V119 -> 15732857 | U69: =Triangulo1!W119 -> 15732929 | V69: =Triangulo1!X119 -> 15732930 | W69: =Triangulo1!Y119 -> 15732978 | X69: =Triangulo1!Z119 -> 15732988 | Y69: =X69*X87 -> 15733005 | Z69: =+Y69 -> 15733005 | AA69: =+Q69 -> 15729334 | AB69: =Z69-AA69 -> 3670.6419 | AC69: ='1_CL'!AC12 -> 4044.684 | AD69: =AC69-AB69 -> 374.04214 | AE69: =IF(AD69=0,"No hay cambio",IF(AD69>0,"Sobreestimando la reserva","Subestimando la reserva")) -> Sobreestimando la reserva | AF69: =X69 -> 15732988 | AG69: =Q69 -> 15729334 | AH69: =AF69-AG69 -> 3653.5471 | AI69: ='1_CL'!Y12-'1_Validacion_BT'!AG69 -> 4027.5888 | AJ69: =AI69-AH69 -> 374.04173 | AK69: =IF(AJ69=0,"No hay cambio",IF(AJ69>0,"Sobreestimando la reserva","Subestimando la reserva")) -> Sobreestimando la reserva
A70: 2Q21 | B70: ='1_CL'!C13 -> 0 | C70: ='1_CL'!D13 -> 0 | D70: ='1_CL'!E13 -> 0 | E70: ='1_CL'!F13 -> 0 | F70: ='1_CL'!G13 -> 0 | G70: ='1_CL'!H13 -> 0 | H70: ='1_CL'!I13 -> 12264947 | I70: ='1_CL'!J13 -> 13331758 | ... P70: ='1_CL'!Q13 -> 14343596 | Q70: =Triangulo1!S120 -> 14348127 | R70: =Triangulo1!T120 -> 14349977 | S70: =Triangulo1!U120 -> 14350771 | T70: =Triangulo1!V120 -> 14351198 | U70: =Triangulo1!W120 -> 14351416 | V70: =Triangulo1!X120 -> 14351558 | W70: =Triangulo1!Y120 -> 14351563 | X70: =W70*W87 -> 14351571 | Y70: =X70*X87 -> 14351587 | Z70: =+Y70 -> 14351587 | AA70: =+P70 -> 14343596 | AB70: =Z70-AA70 -> 7990.8803 | AC70: ='1_CL'!AC13 -> 8101.7825 | AD70: =AC70-AB70 -> 110.90222 | AE70: =IF(AD70=0,"No hay cambio",IF(AD70>0,"Sobreestimando la reserva","Subestimando la reserva")) -> Sobreestimando la reserva | AF70: =W70 -> 14351563 | AG70: =P70 -> 14343596 | AH70: =AF70-AG70 -> 7966.991 | AI70: ='1_CL'!X13-'1_Validacion_BT'!AG70 -> 8077.7882 | AJ70: =AI70-AH70 -> 110.79722 | AK70: =IF(AJ70=0,"No hay cambio",IF(AJ70>0,"Sobreestimando la reserva","Subestimando la reserva")) -> Sobreestimando la reserva
A71: 3Q21 | B71: ='1_CL'!C14 -> 0 | C71: ='1_CL'!D14 -> 0 | D71: ='1_CL'!E14 -> 0 | E71: ='1_CL'!F14 -> 0 | F71: ='1_CL'!G14 -> 0 | G71: ='1_CL'!H14 -> 11346897 | H71: ='1_CL'!I14 -> 13064544 | I71: ='1_CL'!J14 -> 14121948 | ... O71: ='1_CL'!P14 -> 15119935 | P71: =Triangulo1!R121 -> 15129354 | Q71: =Triangulo1!S121 -> 15133043 | R71: =Triangulo1!T121 -> 15135174 | S71: =Triangulo1!U121 -> 15136439 | T71: =Triangulo1!V121 -> 15136890 | U71: =Triangulo1!W121 -> 15137119 | V71: =Triangulo1!X121 -> 15137269 | W71: =V71*V87 -> 15137295 | X71: =W71*W87 -> 15137304 | Y71: =X71*X87 -> 15137321 | Z71: =+Y71 -> 15137321 | AA71: =+O71 -> 15119935 | AB71: =Z71-AA71 -> 17385.649 | AC71: ='1_CL'!AC14 -> 17451.426 | AD71: =AC71-AB71 -> 65.776981 | AE71: =IF(AD71=0,"No hay cambio",IF(AD71>0,"Sobreestimando la reserva","Subestimando la reserva")) -> Sobreestimando la reserva | AF71: =V71 -> 15137269 | AG71: =O71 -> 15119935 | AH71: =AF71-AG71 -> 17334.25 | AI71: ='1_CL'!W14-'1_Validacion_BT'!AG71 -> 17408.708 | AJ71: =AI71-AH71 -> 74.458134 | AK71: =IF(AJ71=0,"No hay cambio",IF(AJ71>0,"Sobreestimando la reserva","Subestimando la reserva")) -> Sobreestimando la reserva
A72: 4Q21 | B72: ='1_CL'!C15 -> 0 | C72: ='1_CL'!D15 -> 0 | D72: ='1_CL'!E15 -> 0 | E72: ='1_CL'!F15 -> 0 | F72: ='1_CL'!G15 -> 13369514 | G72: ='1_CL'!H15 -> 15030308 | H72: ='1_CL'!I15 -> 16697100 | I72: ='1_CL'!J15 -> 17828453 | ... N72: ='1_CL'!O15 -> 18730024 | O72: =Triangulo1!Q122 -> 18748921 | P72: =Triangulo1!R122 -> 18758881 | Q72: =Triangulo1!S122 -> 18766207 | R72: =Triangulo1!T122 -> 18768199 | S72: =Triangulo1!U122 -> 18770099 | T72: =Triangulo1!V122 -> 18770657 | U72: =Triangulo1!W122 -> 18770893 | V72: =U72*U87 -> 18770984 | W72: =V72*V87 -> 18771016 | X72: =W72*W87 -> 18771027 | Y72: =X72*X87 -> 18771047 | Z72: =+Y72 -> 18771047 | AA72: =+N72 -> 18730024 | AB72: =Z72-AA72 -> 41023.339 | AC72: ='1_CL'!AC15 -> 42921.81 | AD72: =AC72-AB72 -> 1898.4711 | AE72: =IF(AD72=0,"No hay cambio",IF(AD72>0,"Sobreestimando la reserva","Subestimando la reserva")) -> Sobreestimando la reserva | AF72: =U72 -> 18770893 | AG72: =N72 -> 18730024 | AH72: =AF72-AG72 -> 40868.916 | AI72: ='1_CL'!V15-'1_Validacion_BT'!AG72 -> 42812.047 | AJ72: =AI72-AH72 -> 1943.1308 | AK72: =IF(AJ72=0,"No hay cambio",IF(AJ72>0,"Sobreestimando la reserva","Subestimando la reserva")) -> Sobreestimando la reserva
A73: 1Q22 | B73: ='1_CL'!C16 -> 0 | C73: ='1_CL'!D16 -> 0 | D73: ='1_CL'!E16 -> 0 | E73: ='1_CL'!F16 -> 10805763 | F73: ='1_CL'!G16 -> 13284336 | G73: ='1_CL'!H16 -> 15384835 | H73: ='1_CL'!I16 -> 17438864 | I73: ='1_CL'!J16 -> 18514044 | ... M73: ='1_CL'!N16 -> 19627354 | N73: =Triangulo1!P123 -> 19663627 | O73: =Triangulo1!Q123 -> 19683641 | P73: =Triangulo1!R123 -> 19699211 | Q73: =Triangulo1!S123 -> 19705847 | R73: =Triangulo1!T123 -> 19708903 | S73: =Triangulo1!U123 -> 19710296 | T73: =Triangulo1!V123 -> 19711032 | U73: =T73*T87 -> 19711241 | V73: =U73*U87 -> 19711336 | W73: =V73*V87 -> 19711370 | X73: =W73*W87 -> 19711382 | Y73: =X73*X87 -> 19711403 | Z73: =+Y73 -> 19711403 | AA73: =+M73 -> 19627354 | AB73: =Z73-AA73 -> 84049.045 | AC73: ='1_CL'!AC16 -> 89289.649 | AD73: =AC73-AB73 -> 5240.6038 | AE73: =IF(AD73=0,"No hay cambio",IF(AD73>0,"Sobreestimando la reserva","Subestimando la reserva")) -> Sobreestimando la reserva | AF73: =T73 -> 19711032 | AG73: =M73 -> 19627354 | AH73: =AF73-AG73 -> 83677.909 | AI73: ='1_CL'!U16-'1_Validacion_BT'!AG73 -> 88982.991 | AJ73: =AI73-AH73 -> 5305.0818 | AK73: =IF(AJ73=0,"No hay cambio",IF(AJ73>0,"Sobreestimando la reserva","Subestimando la reserva")) -> Sobreestimando la reserva
A74: 2Q22 | B74: ='1_CL'!C17 -> 0 | C74: ='1_CL'!D17 -> 0 | D74: ='1_CL'!E17 -> 7974797 | E74: ='1_CL'!F17 -> 11597296 | F74: ='1_CL'!G17 -> 14585912 | G74: ='1_CL'!H17 -> 16285147 | H74: ='1_CL'!I17 -> 18338971 | I74: ='1_CL'!J17 -> 19214501 | ... L74: ='1_CL'!M17 -> 20049671 | M74: =Triangulo1!O124 -> 20321045 | N74: =Triangulo1!P124 -> 20372891 | O74: =Triangulo1!Q124 -> 20413090 | P74: =Triangulo1!R124 -> 20424976 | Q74: =Triangulo1!S124 -> 20432953 | R74: =Triangulo1!T124 -> 20435580 | S74: =Triangulo1!U124 -> 20436694 | T74: =S74*S87 -> 20437340 | U74: =T74*T87 -> 20437556 | V74: =U74*U87 -> 20437655 | W74: =V74*V87 -> 20437690 | X74: =W74*W87 -> 20437702 | Y74: =X74*X87 -> 20437725 | Z74: =+Y74 -> 20437725 | AA74: =+L74 -> 20049671 | AB74: =Z74-AA74 -> 388053.51 | AC74: ='1_CL'!AC17 -> 168988.85 | AD74: =AC74-AB74 -> -219064.66 | AE74: =IF(AD74=0,"No hay cambio",IF(AD74>0,"Sobreestimando la reserva","Subestimando la reserva")) -> Subestimando la reserva | AF74: =S74 -> 20436694 | AG74: =L74 -> 20049671 | AH74: =AF74-AG74 -> 387023.23 | AI74: ='1_CL'!T17-AG74 -> 168014.94 | AJ74: =AI74-AH74 -> -219008.29 | AK74: =IF(AJ74=0,"No hay cambio",IF(AJ74>0,"Sobreestimando la reserva","Subestimando la reserva")) -> Subestimando la reserva
A75: 3Q22 | B75: ='1_CL'!C18 -> 0 | C75: ='1_CL'!D18 -> 4773306 | D75: ='1_CL'!E18 -> 8697825 | E75: ='1_CL'!F18 -> 12220494 | F75: ='1_CL'!G18 -> 14462971 | G75: ='1_CL'!H18 -> 16656668 | H75: ='1_CL'!I18 -> 19017438 | I75: ='1_CL'!J18 -> 19939378 | ... K75: ='1_CL'!L18 -> 20688336 | L75: =Triangulo1!N125 -> 20898107 | M75: =Triangulo1!O125 -> 21111692 | N75: =Triangulo1!P125 -> 21152842 | O75: =Triangulo1!Q125 -> 21178475 | P75: =Triangulo1!R125 -> 21190676 | Q75: =Triangulo1!S125 -> 21197868 | R75: =Triangulo1!T125 -> 21200593 | S75: =R75*R87 -> 21202087 | T75: =S75*S87 -> 21202757 | U75: =T75*T87 -> 21202982 | V75: =U75*U87 -> 21203084 | W75: =V75*V87 -> 21203121 | X75: =W75*W87 -> 21203133 | Y75: =X75*X87 -> 21203156 | Z75: =+Y75 -> 21203156 | AA75: =+K75 -> 20688336 | AB75: =Z75-AA75 -> 514819.96 | AC75: ='1_CL'!AC18 -> 343341.34 | AD75: =AC75-AB75 -> -171478.62 | AE75: =IF(AD75=0,"No hay cambio",IF(AD75>0,"Sobreestimando la reserva","Subestimando la reserva")) -> Subestimando la reserva | AF75: =R75 -> 21200593 | AG75: =K75 -> 20688336 | AH75: =AF75-AG75 -> 512257.5 | AI75: ='1_CL'!S18-'1_Validacion_BT'!AG75 -> 340878.8 | AJ75: =AI75-AH75 -> -171378.69 | AK75: =IF(AJ75=0,"No hay cambio",IF(AJ75>0,"Sobreestimando la reserva","Subestimando la reserva")) -> Subestimando la reserva
A76: 4Q22 | B76: ='1_CL'!C19 -> 5498188 | C76: ='1_CL'!D19 -> 10669557 | D76: ='1_CL'!E19 -> 14420577 | E76: ='1_CL'!F19 -> 17838126 | F76: ='1_CL'!G19 -> 20243242 | G76: ='1_CL'!H19 -> 22179116 | H76: ='1_CL'!I19 -> 24155749 | I76: ='1_CL'!J19 -> 25145296 | J76: ='1_CL'!K19 -> 25647723 | K76: =Triangulo1!M126 -> 26098748 | L76: =Triangulo1!N126 -> 26335750 | M76: =Triangulo1!O126 -> 26408644 | N76: =Triangulo1!P126 -> 26457449 | O76: =Triangulo1!Q126 -> 26487647 | P76: =Triangulo1!R126 -> 26503070 | Q76: =Triangulo1!S126 -> 26509530 | R76: =Q76*Q87 -> 26513115 | S76: =R76*R87 -> 26514983 | T76: =S76*S87 -> 26515821 | U76: =T76*T87 -> 26516102 | V76: =U76*U87 -> 26516230 | W76: =V76*V87 -> 26516276 | X76: =W76*W87 -> 26516291 | Y76: =X76*X87 -> 26516320 | Z76: =+Y76 -> 26516320 | AA76: =+J76 -> 25647723 | AB76: =Z76-AA76 -> 868596.92 | AC76: ='1_CL'!AC19 -> 832031.14 | AD76: =AC76-AB76 -> -36565.78 | AE76: =IF(AD76=0,"No hay cambio",IF(AD76>0,"Sobreestimando la reserva","Subestimando la reserva")) -> Subestimando la reserva | AF76: =Q76 -> 26509530 | AG76: =+J76 -> 25647723 | AH76: =AF76-AG76 -> 861807.26 | AI76: ='1_CL'!R19-'1_Validacion_BT'!AG76 -> 825223.81 | AJ76: =AI76-AH76 -> -36583.442 | AK76: =IF(AJ76=0,"No hay cambio",IF(AJ76>0,"Sobreestimando la reserva","Subestimando la reserva")) -> Subestimando la reserva
A77: 1Q23 | B77: ='1_CL'!C20 -> 6382667 | C77: ='1_CL'!D20 -> 10460689 | D77: ='1_CL'!E20 -> 15242265 | E77: ='1_CL'!F20 -> 19075882 | F77: ='1_CL'!G20 -> 21908553 | G77: ='1_CL'!H20 -> 23938666 | H77: ='1_CL'!I20 -> 25653115 | I77: ='1_CL'!J20 -> 26811464 | J77: =Triangulo1!L127 -> 28221241 | K77: =Triangulo1!M127 -> 29142398 | L77: =Triangulo1!N127 -> 29351843 | M77: =Triangulo1!O127 -> 29651828 | N77: =Triangulo1!P127 -> 29731358 | O77: =Triangulo1!Q127 -> 29798205 | P77: =Triangulo1!R127 -> 29821777 | Q77: =P77*P87 -> 29831184 | R77: =Q77*Q87 -> 29835218 | S77: =R77*R87 -> 29837320 | T77: =S77*S87 -> 29838262 | U77: =T77*T87 -> 29838578 | V77: =U77*U87 -> 29838723 | W77: =V77*V87 -> 29838774 | X77: =W77*W87 -> 29838792 | Y77: =X77*X87 -> 29838824 | Z77: =+Y77 -> 29838824 | AA77: =+I77 -> 26811464 | AB77: =Z77-AA77 -> 3027359.9 | AC77: ='1_CL'!AC20 -> 1661641.4 | AD77: =AC77-AB77 -> -1365718.5 | AE77: =IF(AD77=0,"No hay cambio",IF(AD77>0,"Sobreestimando la reserva","Subestimando la reserva")) -> Subestimando la reserva | AF77: =P77 -> 29821777 | AG77: =+I77 -> 26811464 | AH77: =AF77-AG77 -> 3010312.7 | AI77: ='1_CL'!Q20-'1_Validacion_BT'!AG77 -> 1645567.9 | AJ77: =AI77-AH77 -> -1364744.8 | AK77: =IF(AJ77=0,"No hay cambio",IF(AJ77>0,"Sobreestimando la reserva","Subestimando la reserva")) -> Subestimando la reserva
A78: 2Q23 | B78: ='1_CL'!C21 -> 3022770 | C78: ='1_CL'!D21 -> 7899209 | D78: ='1_CL'!E21 -> 11259161 | E78: ='1_CL'!F21 -> 14497513 | F78: ='1_CL'!G21 -> 17221120 | G78: ='1_CL'!H21 -> 19234288 | H78: ='1_CL'!I21 -> 21399003 | I78: =Triangulo1!K128 -> 22420624 | J78: =Triangulo1!L128 -> 23161319 | K78: =Triangulo1!M128 -> 23450349 | L78: =Triangulo1!N128 -> 23594816 | M78: =Triangulo1!O128 -> 23660554 | N78: =Triangulo1!P128 -> 23709000 | O78: =Triangulo1!Q128 -> 23738896 | P78: =O78*O87 -> 23753677 | Q78: =P78*P87 -> 23761170 | R78: =Q78*Q87 -> 23764384 | S78: =R78*R87 -> 23766058 | T78: =S78*S87 -> 23766808 | U78: =T78*T87 -> 23767060 | V78: =U78*U87 -> 23767175 | W78: =V78*V87 -> 23767216 | ... Y78: =X78*X87 -> 23767256 | Z78: =+Y78 -> 23767256 | AA78: =+H78 -> 21399003 | AB78: =Z78-AA78 -> 2368252.9 | AC78: ='1_CL'!AC21 -> 2608857.4 | AD78: =AC78-AB78 -> 240604.51 | AE78: =IF(AD78=0,"No hay cambio",IF(AD78>0,"Sobreestimando la reserva","Subestimando la reserva")) -> Sobreestimando la reserva | AF78: =O78 -> 23738896 | AG78: =+H78 -> 21399003 | AH78: =AF78-AG78 -> 2339892.6 | AI78: ='1_CL'!P21-'1_Validacion_BT'!AG78 -> 2581179.5 | AJ78: =AI78-AH78 -> 241286.85 | AK78: =IF(AJ78=0,"No hay cambio",IF(AJ78>0,"Sobreestimando la reserva","Subestimando la reserva")) -> Sobreestimando la reserva
A79: 3Q23 | B79: ='1_CL'!C22 -> 6936281 | C79: ='1_CL'!D22 -> 21936281 | D79: ='1_CL'!E22 -> 25150070 | E79: ='1_CL'!F22 -> 28898330 | F79: ='1_CL'!G22 -> 31903741 | G79: ='1_CL'!H22 -> 33589263 | H79: =Triangulo1!J129 -> 35791519 | I79: =Triangulo1!K129 -> 37793089 | J79: =Triangulo1!L129 -> 39020724 | K79: =Triangulo1!M129 -> 39236437 | L79: =Triangulo1!N129 -> 39592741 | M79: =Triangulo1!O129 -> 40000570 | N79: =Triangulo1!P129 -> 40080069 | O79: =N79*N87 -> 40132933 | P79: =O79*O87 -> 40157923 | Q79: =P79*P87 -> 40170591 | R79: =Q79*Q87 -> 40176023 | S79: =R79*R87 -> 40178854 | T79: =S79*S87 -> 40180123 | U79: =T79*T87 -> 40180549 | V79: =U79*U87 -> 40180743 | ... Y79: =X79*X87 -> 40180879 | Z79: =+Y79 -> 40180879 | AA79: =+G79 -> 33589263 | AB79: =Z79-AA79 -> 6591616.1 | AC79: ='1_CL'!AC22 -> 8321752.4 | AD79: =AC79-AB79 -> 1730136.3 | AE79: =IF(AD79=0,"No hay cambio",IF(AD79>0,"Sobreestimando la reserva","Subestimando la reserva")) -> Sobreestimando la reserva | AF79: =N79 -> 40080069 | AG79: =+G79 -> 33589263 | AH79: =AF79-AG79 -> 6490806.3 | AI79: ='1_CL'!O22-'1_Validacion_BT'!AG79 -> 8225928.6 | AJ79: =AI79-AH79 -> 1735122.2 | AK79: =IF(AJ79=0,"No hay cambio",IF(AJ79>0,"Sobreestimando la reserva","Subestimando la reserva")) -> Sobreestimando la reserva
A80: 4Q23 | B80: ='1_CL'!C23 -> 6691248 | C80: ='1_CL'!D23 -> 11756013 | D80: ='1_CL'!E23 -> 15391294 | E80: ='1_CL'!F23 -> 18736499 | F80: ='1_CL'!G23 -> 21705785 | G80: =Triangulo1!I130 -> 25137871 | H80: =Triangulo1!J130 -> 26253226 | I80: =Triangulo1!K130 -> 34924861 | J80: =Triangulo1!L130 -> 36209483 | K80: =Triangulo1!M130 -> 36787595 | L80: =Triangulo1!N130 -> 37320253 | M80: =Triangulo1!O130 -> 37580912 | N80: =M80*M87 -> 37662794 | O80: =N80*N87 -> 37712470 | P80: =O80*O87 -> 37735953 | Q80: =P80*P87 -> 37747856 | R80: =Q80*Q87 -> 37752961 | S80: =R80*R87 -> 37755621 | T80: =S80*S87 -> 37756813 | U80: =T80*T87 -> 37757213 | ... Y80: =X80*X87 -> 37757524 | Z80: =+Y80 -> 37757524 | AA80: =+F80 -> 21705785 | AB80: =Z80-AA80 -> 16051739 | AC80: ='1_CL'!AC23 -> 8200379.3 | AD80: =AC80-AB80 -> -7851359.8 | AE80: =IF(AD80=0,"No hay cambio",IF(AD80>0,"Sobreestimando la reserva","Subestimando la reserva")) -> Subestimando la reserva | AF80: =M80 -> 37580912 | AG80: =+F80 -> 21705785 | AH80: =AF80-AG80 -> 15875127 | AI80: ='1_CL'!N23-'1_Validacion_BT'!AG80 -> 8064944.9 | AJ80: =AI80-AH80 -> -7810181.8 | AK80: =IF(AJ80=0,"No hay cambio",IF(AJ80>0,"Sobreestimando la reserva","Subestimando la reserva")) -> Subestimando la reserva
A81: 1Q24 | B81: ='1_CL'!C24 -> 4191817 | C81: ='1_CL'!D24 -> 9775450 | D81: ='1_CL'!E24 -> 14374440 | E81: ='1_CL'!F24 -> 17306094 | F81: =Triangulo1!H131 -> 21275681 | G81: =Triangulo1!I131 -> 24237832 | H81: =Triangulo1!J131 -> 25973707 | I81: =Triangulo1!K131 -> 26811702 | J81: =Triangulo1!L131 -> 27490116 | K81: =Triangulo1!M131 -> 27642086 | L81: =Triangulo1!N131 -> 27982947 | M81: =L81*L87 -> 28164149 | N81: =M81*M87 -> 28225514 | O81: =N81*N87 -> 28262742 | P81: =O81*O87 -> 28280341 | Q81: =P81*P87 -> 28289261 | R81: =Q81*Q87 -> 28293087 | S81: =R81*R87 -> 28295080 | T81: =S81*S87 -> 28295974 | ... Y81: =X81*X87 -> 28296507 | Z81: =+Y81 -> 28296507 | AA81: =+E81 -> 17306094 | AB81: =Z81-AA81 -> 10990413 | AC81: ='1_CL'!AC24 -> 10399399 | AD81: =AC81-AB81 -> -591013.32 | AE81: =IF(AD81=0,"No hay cambio",IF(AD81>0,"Sobreestimando la reserva","Subestimando la reserva")) -> Subestimando la reserva | AF81: =L81 -> 27982947 | AG81: =+E81 -> 17306094 | AH81: =AF81-AG81 -> 10676853 | AI81: ='1_CL'!M24-'1_Validacion_BT'!AG81 -> 10167835 | AJ81: =AI81-AH81 -> -509017.62 | AK81: =IF(AJ81=0,"No hay cambio",IF(AJ81>0,"Sobreestimando la reserva","Subestimando la reserva")) -> Subestimando la reserva
A82: 2Q24 | B82: ='1_CL'!C25 -> 5916671 | C82: ='1_CL'!D25 -> 11716355 | D82: ='1_CL'!E25 -> 15374462 | E82: =Triangulo1!G132 -> 16390214 | F82: =Triangulo1!H132 -> 17971208 | G82: =Triangulo1!I132 -> 19689806 | H82: =Triangulo1!J132 -> 22173013 | I82: =Triangulo1!K132 -> 22978561 | J82: =Triangulo1!L132 -> 23724975 | K82: =Triangulo1!M132 -> 24640789 | L82: =K82*K87 -> 24869196 | M82: =L82*L87 -> 25030235 | N82: =M82*M87 -> 25084771 | O82: =N82*N87 -> 25117857 | P82: =O82*O87 -> 25133497 | Q82: =P82*P87 -> 25141425 | R82: =Q82*Q87 -> 25144826 | S82: =R82*R87 -> 25146597 | ... Y82: =X82*X87 -> 25147865 | Z82: =+Y82 -> 25147865 | AA82: =+D82 -> 15374462 | AB82: =Z82-AA82 -> 9773402.7 | AC82: ='1_CL'!AC25 -> 15289606 | AD82: =AC82-AB82 -> 5516203.8 | AE82: =IF(AD82=0,"No hay cambio",IF(AD82>0,"Sobreestimando la reserva","Subestimando la reserva")) -> Sobreestimando la reserva | AF82: =K82 -> 24640789 | AG82: =+D82 -> 15374462 | AH82: =AF82-AG82 -> 9266327.1 | AI82: ='1_CL'!L25-'1_Validacion_BT'!AG82 -> 14789017 | AJ82: =AI82-AH82 -> 5522689.6 | AK82: =IF(AJ82=0,"No hay cambio",IF(AJ82>0,"Sobreestimando la reserva","Subestimando la reserva")) -> Sobreestimando la reserva
A83: 3Q24 | B83: ='1_CL'!C26 -> 4926500 | C83: ='1_CL'!D26 -> 9321834 | D83: =Triangulo1!F133 -> 10218330 | E83: =Triangulo1!G133 -> 12788366 | F83: =Triangulo1!H133 -> 13312404 | G83: =Triangulo1!I133 -> 14024370 | H83: =Triangulo1!J133 -> 14646625 | I83: =Triangulo1!K133 -> 15356673 | J83: =Triangulo1!L133 -> 16164145 | K83: =J83*J87 -> 16432874 | L83: =K83*K87 -> 16585197 | M83: =L83*L87 -> 16692594 | N83: =M83*M87 -> 16728964 | O83: =N83*N87 -> 16751029 | P83: =O83*O87 -> 16761459 | Q83: =P83*P87 -> 16766747 | R83: =Q83*Q87 -> 16769014 | ... Y83: =X83*X87 -> 16771041 | Z83: =+Y83 -> 16771041 | AA83: =+C83 -> 9321834 | AB83: =Z83-AA83 -> 7449206.9 | AC83: ='1_CL'!AC26 -> 15731243 | AD83: =AC83-AB83 -> 8282036.1 | AE83: =IF(AD83=0,"No hay cambio",IF(AD83>0,"Sobreestimando la reserva","Subestimando la reserva")) -> Sobreestimando la reserva | AF83: =J83 -> 16164145 | AG83: =+C83 -> 9321834 | AH83: =AF83-AG83 -> 6842310.6 | AI83: ='1_CL'!K26-'1_Validacion_BT'!AG83 -> 14944040 | AJ83: =AI83-AH83 -> 8101729.6 | AK83: =IF(AJ83=0,"No hay cambio",IF(AJ83>0,"Sobreestimando la reserva","Subestimando la reserva")) -> Sobreestimando la reserva
A84: 4Q24 | B84: ='1_CL'!C27 -> 5149958 | C84: =Triangulo1!E134 -> 9993796.2 | D84: =Triangulo1!F134 -> 12235686 | E84: =Triangulo1!G134 -> 13674328 | F84: =Triangulo1!H134 -> 15841381 | G84: =Triangulo1!I134 -> 16394109 | H84: =Triangulo1!J134 -> 16848529 | I84: =Triangulo1!K134 -> 17392116 | J84: =I84*I87 -> 17970985 | K84: =J84*J87 -> 18269753 | L84: =K84*K87 -> 18439104 | M84: =L84*L87 -> 18558505 | N84: =M84*M87 -> 18598941 | O84: =N84*N87 -> 18623472 | P84: =O84*O87 -> 18635069 | Q84: =P84*P87 -> 18640947 | ... Y84: =X84*X87 -> 18645721 | Z84: =+Y84 -> 18645721 | AA84: =+B84 -> 5149958 | AB84: =Z84-AA84 -> 13495763 | AC84: ='1_CL'!AC27 -> 24566035 | AD84: =AC84-AB84 -> 11070272 | AE84: =IF(AD84=0,"No hay cambio",IF(AD84>0,"Sobreestimando la reserva","Subestimando la reserva")) -> Sobreestimando la reserva | AF84: =I84 -> 17392116 | AG84: =+B84 -> 5149958 | AH84: =AF84-AG84 -> 12242158 | AI84: ='1_CL'!J27-'1_Validacion_BT'!AG84 -> 22831861 | AJ84: =AI84-AH84 -> 10589703 | AK84: =IF(AJ84=0,"No hay cambio",IF(AJ84>0,"Sobreestimando la reserva","Subestimando la reserva")) -> Sobreestimando la reserva
A85: Numerado_nuv | I85: =SUM(J69:J83) -> 3.4085614e+08 | J85: =SUM(K68:K82) -> 3.439025e+08 | K85: =SUM(L67:L81) -> 3.3289348e+08 | L85: =SUM(M66:M80) -> 3.1989933e+08 | M85: =SUM(N65:N79) -> 2.947136e+08 | N85: =SUM(O64:O78) -> 2.7442102e+08 | O85: =SUM(P63:P77) -> 2.6270981e+08 | P85: =SUM(Q62:Q76) -> 2.5069433e+08 | Q85: =SUM(R61:R75) -> 2.3893901e+08 | R85: =SUM(S61:S74) -> 2.1775376e+08 | S85: =SUM(T61:T73) -> 1.973233e+08 | T85: =SUM(U61:U72) -> 1.7761415e+08 | U85: =SUM(V61:V71) -> 1.5884402e+08 | V85: =SUM(W61:W70) -> 1.43707e+08 | W85: =SUM(X61:X69) -> 1.2935552e+08 | X85: =SUM(Y61:Y68) -> 1.1362265e+08
A86: Denominador_nuv | I86: =SUM(I69:I83) -> 3.2987671e+08 | J86: =SUM(J68:J82) -> 3.3827861e+08 | K86: =SUM(K67:K81) -> 3.2983608e+08 | L86: =SUM(L66:L80) -> 3.1784117e+08 | M86: =SUM(M65:M79) -> 2.9407287e+08 | N86: =SUM(N64:N78) -> 2.7405954e+08 | O86: =SUM(O63:O77) -> 2.6254632e+08 | P86: =SUM(P62:P76) -> 2.5061528e+08 | Q86: =SUM(Q61:Q75) -> 2.3890671e+08 | R86: =SUM(R61:R74) -> 2.1773842e+08 | S86: =SUM(S61:S73) -> 1.9731707e+08 | T86: =SUM(T61:T72) -> 1.7761227e+08 | U86: =SUM(U61:U71) -> 1.5884326e+08 | V86: =SUM(V61:V70) -> 1.4370676e+08 | W86: =SUM(W61:W69) -> 1.2935544e+08 | X86: =SUM(X61:X68) -> 1.1362253e+08
A87: Factores_nuv | I87: =I85/I86 -> 1.0332834 | J87: =J85/J86 -> 1.016625 | K87: =K85/K86 -> 1.0092694 | L87: =L85/L86 -> 1.0064754 | M87: =M85/M86 -> 1.0021788 | N87: =N85/N86 -> 1.001319 | O87: =O85/O86 -> 1.0006227 | P87: =P85/P86 -> 1.0003154 | ... X87: =X85/X86 -> 1.0000011 | Y87: 1
A88: Factores_CL | B88: ='1_CL'!C30 -> 2.1469743 | C88: ='1_CL'!D30 -> 1.3475034 | D88: ='1_CL'!E30 -> 1.2458421 | E88: ='1_CL'!F30 -> 1.1619344 | F88: ='1_CL'!G30 -> 1.1042248 | G88: ='1_CL'!H30 -> 1.1121613 | H88: ='1_CL'!I30 -> 1.0564419 | I88: ='1_CL'!J30 -> 1.0286063 | ... Y88: ='1_CL'!Z30 -> 1
A89: ¿Cambia? | I89: =IF(ABS(I87-I88)<0.001,"NO","SÍ") -> SÍ | J89: =IF(ABS(J87-J88)<0.001,"NO","SÍ") -> SÍ | K89: =IF(ABS(K87-K88)<0.001,"NO","SÍ") -> SÍ | L89: =IF(ABS(L87-L88)<0.001,"NO","SÍ") -> SÍ | M89: =IF(ABS(M87-M88)<0.001,"NO","SÍ") -> NO | N89: =IF(ABS(N87-N88)<0.001,"NO","SÍ") -> NO | O89: =IF(ABS(O87-O88)<0.001,"NO","SÍ") -> NO | P89: =IF(ABS(P87-P88)<0.001,"NO","SÍ") -> NO | ... Y89: =IF(ABS(Y87-Y88)<0.001,"NO","SÍ") -> NO

Sheet Triangulo2
C2: Calcula el IBNR del siguiente triangulo usando Chain Ladder, BF y Cape Cod
D3: 1. el loss ratio a priori es 55%
D4: 2. tasas
D5: 3. tasa de interes | E5: 0.06
C7: Contesta las sig preguntas:
D8: 1. Qué metodología escogerías para cada trimestre y por qué?
D9: 2. Excluiste algun periodo para el calculo de lo factores? Di que periodo y en que desarrollo y por qué
D10: 3. Cómo sale el bakctesting para tu selección de ultimate para los trimestres del 1Q19 al 4Q20?
D11: 4. Qué duración tiene está cartera?
C13: TRIÁNGULO-OCURRIDO
D15: 1 | E15: =+D15+1 -> 2 | F15: =+E15+1 -> 3 | G15: =+F15+1 -> 4 | H15: =+G15+1 -> 5 | I15: =+H15+1 -> 6 | J15: =+I15+1 -> 7 | K15: =+J15+1 -> 8 | L15: =+K15+1 -> 9 | ... AA15: =+Z15+1 -> 24
C16: 1Q19 | D16: 6418198 | E16: 8351947 | F16: 7241932 | G16: 6612057 | H16: 6678429 | I16: 6520501 | J16: 6390444 | K16: 6157365 | L16: 5998497 | M16: 5960040 | N16: 5927219 | O16: 5845151 | P16: 5844679 | Q16: 5823554 | R16: 5819414 | S16: 5817651 | T16: 5816446 | U16: 5815298 | V16: 5814997 | W16: 5814607 | X16: 5814513 | Y16: 5814520 | Z16: 5814527 | AA16: 5814528
C17: 2Q19 | D17: 7475822 | E17: 10450029 | F17: 10185917 | G17: 9722137 | H17: 9434292 | I17: 9020873 | J17: 8704176 | K17: 8469008 | L17: 8349635 | M17: 8209160 | N17: 8096242 | O17: 8041381 | P17: 8008712 | Q17: 8003007 | R17: 8002023 | S17: 7997629 | T17: 7997019 | U17: 7996437 | V17: 7996215 | W17: 7995857 | X17: 7995850 | Y17: 7995866 | Z17: 7995874
C18: 3Q19 | D18: 4944676 | E18: 5651989 | F18: 5515292 | G18: 5713405 | H18: 5462475 | I18: 5370959 | J18: 5305411 | K18: 5148861 | L18: 4913135 | M18: 4939885 | N18: 4852857 | O18: 4772843 | P18: 4722978 | Q18: 4724493 | R18: 4714404 | S18: 4711994 | T18: 4711744 | U18: 4711585 | V18: 4710817 | W18: 4710876 | X18: 4710870 | Y18: 4710870
C19: 4Q19 | D19: 5990844 | E19: 8317434 | F19: 7538034 | G19: 7146705 | H19: 6480112 | I19: 5918174 | J19: 5524711 | K19: 5379113 | L19: 5282322 | M19: 5218946 | N19: 5148288 | O19: 5055569 | P19: 5052150 | Q19: 5048881 | R19: 5049883 | S19: 5047150 | T19: 5047033 | U19: 5046810 | V19: 5046112 | W19: 5046155 | X19: 5046123
C20: 1Q20 | D20: 6106533 | E20: 7227067 | F20: 6609141 | G20: 6587986 | H20: 5966963 | I20: 5553219 | J20: 5440658 | K20: 5247292 | L20: 4989511 | M20: 4739938 | N20: 4632683 | O20: 4647858 | P20: 4648748 | Q20: 4631093 | R20: 4618736 | S20: 4614941 | T20: 4614019 | U20: 4612810 | V20: 4612218 | W20: 4612035
C21: 2Q20 | D21: 3511339 | E21: 5097855 | F21: 4392249 | G21: 4331724 | H21: 3638678 | I21: 3261200 | J21: 2912378 | K21: 2561746 | L21: 2608839 | M21: 2512337 | N21: 2525572 | O21: 2539117 | P21: 2502024 | Q21: 2495301 | R21: 2491023 | S21: 2490185 | T21: 2490716 | U21: 2490652 | V21: 2490228
C22: 3Q20 | D22: 4141271 | E22: 5675304 | F22: 5003527 | G22: 4490079 | H22: 3864708 | I22: 3317046 | J22: 3043775 | K22: 2982731 | L22: 2853880 | M22: 2708486 | N22: 2687185 | O22: 2706223 | P22: 2663612 | Q22: 2649484 | R22: 2644988 | S22: 2644539 | T22: 2642763 | U22: 2642281
C23: 4Q20 | D23: 6591656 | E23: 9149839 | F23: 9246786 | G23: 8427024 | H23: 7881930 | I23: 7889306 | J23: 7459046 | K23: 7134362 | L23: 7020325 | M23: 6829753 | N23: 6654101 | O23: 6564713 | P23: 6557312 | Q23: 6540955 | R23: 6539478 | S23: 6538852 | T23: 6538885
C24: 1Q21 | D24: 6289704 | E24: 9074583 | F24: 7921104 | G24: 7241833 | H24: 6605506 | I24: 6368774 | J24: 5993512 | K24: 6063255 | L24: 6123811 | M24: 6142139 | N24: 6109898 | O24: 6094584 | P24: 6054429 | Q24: 6045198 | R24: 6039123 | S24: 6037298
C25: 2Q21 | D25: 4959185 | E25: 7332815 | F25: 6338245 | G25: 6335214 | H25: 5820802 | I25: 5372283 | J25: 5126418 | K25: 4909923 | L25: 4699737 | M25: 4565993 | N25: 4388069 | O25: 4350454 | P25: 4349470 | Q25: 4354085 | R25: 4354413
C26: 3Q21 | D26: 6194048 | E26: 7741218 | F26: 6754577 | G26: 6157468 | H26: 5562103 | I26: 5078341 | J26: 5094245 | K26: 4970573 | L26: 4756133 | M26: 4568920 | N26: 4414181 | O26: 4318353 | P26: 4308927 | Q26: 4284653
C27: 4Q21 | D27: 6500694 | E27: 9436157 | F27: 8641541 | G27: 8462835 | H27: 8478196 | I27: 8406511 | J27: 7938776 | K27: 7694015 | L27: 7414340 | M27: 7365359 | N27: 7323515 | O27: 7284864 | P27: 7266841
C28: 1Q22 | D28: 5205434 | E28: 7752400 | F28: 7497356 | G28: 7293599 | H28: 6566528 | I28: 6681703 | J28: 6326840 | K28: 6334277 | L28: 6175261 | M28: 6025240 | N28: 5846424 | O28: 5844768
C29: 2Q22 | D29: 5184519 | E29: 7275135 | F29: 7269751 | G29: 6967745 | H29: 6399402 | I29: 5827678 | J29: 5837462 | K29: 5752901 | L29: 5510232 | M29: 5306283 | N29: 5171805
C30: 3Q22 | D30: 3419011 | E30: 4773306 | F30: 3716822 | G30: 3313659 | H30: 3377536 | I30: 3222093 | J30: 2783981 | K30: 2603716 | L30: 2643618 | M30: 2473125
C31: 4Q22 | D31: 5498188 | E31: 10669557 | F31: 10857709 | G31: 14275258 | H31: 14084665 | I31: 14163048 | J31: 13850553 | K31: 13534768 | L31: 13371613
C32: 1Q23 | D32: 6382667 | E32: 10460689 | F32: 9727516 | G32: 13561133 | H32: 12865538 | I32: 12816850 | J32: 12593535 | K32: 12422697
C33: 2Q23 | D33: 3022770 | E33: 7899209 | F33: 7498380 | G33: 10736732 | H33: 10856995 | I33: 10834399 | J33: 10568629
C34: 3Q23 | D34: 6936281 | E34: 21936281 | F34: 21767538 | G34: 25515798 | H34: 25644750 | I34: 25593031
C35: 4Q23 | D35: 6691248 | E35: 11756013 | F35: 11113520 | G35: 14458725 | H35: 14275150
C36: 1Q24 | D36: 4191817 | E36: 9775450 | F36: 9803541 | G36: 12735195
C37: 2Q24 | D37: 5916671 | E37: 11716355 | F37: 11277873
C38: 3Q24 | D38: 4926500 | E38: 9321834
C39: 4Q24 | D39: 5149958
C42: Factores
C43: 1 | D43: =+C43+1 -> 2 | E43: =+D43+1 -> 3 | F43: =+E43+1 -> 4 | G43: =+F43+1 -> 5 | H43: =+G43+1 -> 6 | I43: =+H43+1 -> 7 | J43: =+I43+1 -> 8 | K43: =+J43+1 -> 9 | ... Z43: =+Y43+1 -> 24
C44: 1Q19 | D44: =E16/D16 -> 1.3012916 | E44: =F16/E16 -> 0.86709506 | F44: =G16/F16 -> 0.9130239 | G44: =H16/G16 -> 1.010038 | H44: =I16/H16 -> 0.97635252 | I44: =J16/I16 -> 0.98005414 | J44: =K16/J16 -> 0.96352695 | K44: =L16/K16 -> 0.9741987 | ... Z44: =AA16/Z16 -> 1.0000002
C45: 2Q19 | D45: =E17/D17 -> 1.3978435 | E45: =F17/E17 -> 0.97472619 | F45: =G17/F17 -> 0.95446851 | G45: =H17/G17 -> 0.97039283 | H45: =I17/H17 -> 0.95617912 | I45: =J17/I17 -> 0.96489287 | J45: =K17/J17 -> 0.97298216 | K45: =L17/K17 -> 0.98590472 | ... Y45: =Z17/Y17 -> 1.000001
C46: 3Q19 | D46: =E18/D18 -> 1.1430454 | E46: =F18/E18 -> 0.97581435 | F46: =G18/F18 -> 1.0359207 | G46: =H18/G18 -> 0.95608048 | H46: =I18/H18 -> 0.98324642 | I46: =J18/I18 -> 0.98779585 | J46: =K18/J18 -> 0.97049239 | K46: =L18/K18 -> 0.95421784 | ... X46: =Y18/X18 -> 1
C47: 4Q19 | D47: =E19/D19 -> 1.3883576 | E47: =F19/E19 -> 0.90629321 | F47: =G19/F19 -> 0.94808607 | G47: =H19/G19 -> 0.90672723 | H47: =I19/H19 -> 0.91328267 | I47: =J19/I19 -> 0.93351615 | J47: =K19/J19 -> 0.97364604 | K47: =L19/K19 -> 0.98200614 | ... W47: =X19/W19 -> 0.99999366
C48: 1Q20 | D48: =E20/D20 -> 1.1834976 | E48: =F20/E20 -> 0.91449837 | F48: =G20/F20 -> 0.99679913 | G48: =H20/G20 -> 0.90573401 | H48: =I20/H20 -> 0.93066087 | I48: =J20/I20 -> 0.9797305 | J48: =K20/J20 -> 0.96445908 | K48: =L20/K20 -> 0.95087352 | ... V48: =W20/V20 -> 0.99996032
C49: 2Q20 | D49: =E21/D21 -> 1.4518265 | E49: =F21/E21 -> 0.86158767 | F49: =G21/F21 -> 0.98622004 | G49: =H21/G21 -> 0.84000689 | H49: =I21/H21 -> 0.89625958 | I49: =J21/I21 -> 0.89303876 | J49: =K21/J21 -> 0.87960629 | K49: =L21/K21 -> 1.0183832 | ... U49: =V21/U21 -> 0.99982976
C50: 3Q20 | D50: =E22/D22 -> 1.3704256 | E50: =F22/E22 -> 0.88163154 | F50: =G22/F22 -> 0.89738279 | G50: =H22/G22 -> 0.8607216 | H50: =I22/H22 -> 0.85829149 | I50: =J22/I22 -> 0.91761616 | J50: =K22/J22 -> 0.97994464 | K50: =L22/K22 -> 0.956801 | ... T50: =U22/T22 -> 0.99981762
C51: 4Q20 | D51: =E23/D23 -> 1.3880941 | E51: =F23/E23 -> 1.0105955 | F51: =G23/F23 -> 0.91134628 | G51: =H23/G23 -> 0.93531595 | H51: =I23/H23 -> 1.0009358 | I51: =J23/I23 -> 0.94546288 | J51: =K23/J23 -> 0.95647111 | K51: =L23/K23 -> 0.98401581 | ... S51: =T23/S23 -> 1.000005
C52: 1Q21 | D52: =E24/D24 -> 1.4427679 | E52: =F24/E24 -> 0.87288904 | F52: =G24/F24 -> 0.91424541 | G52: =H24/G24 -> 0.91213178 | H52: =I24/H24 -> 0.96416141 | I52: =J24/I24 -> 0.94107783 | J52: =K24/J24 -> 1.0116364 | K52: =L24/K24 -> 1.0099874 | ... R52: =S24/R24 -> 0.9996978
C53: 2Q21 | D53: =E25/D25 -> 1.4786331 | E53: =F25/E25 -> 0.86436723 | F53: =G25/F25 -> 0.99952179 | G53: =H25/G25 -> 0.91880116 | H53: =I25/H25 -> 0.9229455 | I53: =J25/I25 -> 0.95423454 | J53: =K25/J25 -> 0.95776876 | K53: =L25/K25 -> 0.95719159 | ... Q53: =R25/Q25 -> 1.0000753
C54: 3Q21 | D54: =E26/D26 -> 1.2497833 | E54: =F26/E26 -> 0.87254706 | F54: =G26/F26 -> 0.91159935 | G54: =H26/G26 -> 0.90331009 | H54: =I26/H26 -> 0.91302534 | I54: =J26/I26 -> 1.0031317 | J54: =K26/J26 -> 0.97572319 | K54: =L26/K26 -> 0.95685809 | ... P54: =Q26/P26 -> 0.99436658
C55: 4Q21 | D55: =E27/D27 -> 1.4515615 | E55: =F27/E27 -> 0.91579029 | F55: =G27/F27 -> 0.97932012 | G55: =H27/G27 -> 1.0018151 | H55: =I27/H27 -> 0.99154478 | I55: =J27/I27 -> 0.94436039 | J55: =K27/J27 -> 0.96916892 | K55: =L27/K27 -> 0.96365032 | ... O55: =P27/O27 -> 0.99752597
C56: 1Q22 | D56: =E28/D28 -> 1.4892898 | E56: =F28/E28 -> 0.96710128 | F56: =G28/F28 -> 0.97282282 | G56: =H28/G28 -> 0.90031382 | H56: =I28/H28 -> 1.0175397 | I56: =J28/I28 -> 0.94689034 | J56: =K28/J28 -> 1.0011755 | K56: =L28/K28 -> 0.97489595 | ... N56: =O28/N28 -> 0.99971675
C57: 2Q22 | D57: =E29/D29 -> 1.403242 | E57: =F29/E29 -> 0.99925995 | F57: =G29/F29 -> 0.95845717 | G57: =H29/G29 -> 0.91843229 | H57: =I29/H29 -> 0.91065978 | I57: =J29/I29 -> 1.0016789 | J57: =K29/J29 -> 0.98551408 | K57: =L29/K29 -> 0.95781798 | ... M57: =N29/M29 -> 0.97465684
C58: 3Q22 | D58: =E30/D30 -> 1.3961072 | E58: =F30/E30 -> 0.77866829 | F58: =G30/F30 -> 0.89153018 | G58: =H30/G30 -> 1.0192769 | H58: =I30/H30 -> 0.9539774 | I58: =J30/I30 -> 0.86402875 | J58: =K30/J30 -> 0.9352492 | K58: =L30/K30 -> 1.015325 | L58: =M30/L30 -> 0.9355077
C59: 4Q22 | D59: =E31/D31 -> 1.9405588 | E59: =F31/E31 -> 1.0176345 | F59: =G31/F31 -> 1.3147578 | G59: =H31/G31 -> 0.98664872 | H59: =I31/H31 -> 1.0055651 | I59: =J31/I31 -> 0.97793589 | J59: =K31/J31 -> 0.97720055 | K59: =L31/K31 -> 0.98794549
C60: 1Q23 | D60: =E32/D32 -> 1.6389213 | E60: =F32/E32 -> 0.9299116 | F60: =G32/F32 -> 1.3941003 | G60: =H32/G32 -> 0.94870672 | H60: =I32/H32 -> 0.99621563 | I60: =J32/I32 -> 0.98257645 | J60: =K32/J32 -> 0.98643447
C61: 2Q23 | D61: =E33/D33 -> 2.6132352 | E61: =F33/E33 -> 0.94925707 | F61: =G33/F33 -> 1.4318736 | G61: =H33/G33 -> 1.0112011 | H61: =I33/H33 -> 0.99791876 | I61: =J33/I33 -> 0.9754698
C62: 3Q23 | D62: =E34/D34 -> 3.1625421 | E62: =F34/E34 -> 0.99230758 | F62: =G34/F34 -> 1.1721949 | G62: =H34/G34 -> 1.0050538 | H62: =I34/H34 -> 0.99798325
C63: 4Q23 | D63: =E35/D35 -> 1.7569238 | E63: =F35/E35 -> 0.94534771 | F63: =G35/F35 -> 1.3010032 | G63: =H35/G35 -> 0.98730351
C64: 1Q24 | D64: =E36/D36 -> 2.3320317 | E64: =F36/E36 -> 1.0028736 | F64: =G36/F36 -> 1.2990403
C65: 2Q24 | D65: =E37/D37 -> 1.9802276 | E65: =F37/E37 -> 0.96257522
C66: 3Q24 | D66: =E38/D38 -> 1.8921819
C67: 4Q24
C68: Mediana | D68: =MEDIAN(D44:D66) -> 1.4515615 | E68: =MEDIAN(E44:E66) -> 0.93762965 | F68: =MEDIAN(F44:F66) -> 0.97932012 | G68: =MEDIAN(G44:G66) -> 0.94201134 | H68: =MEDIAN(H44:H66) -> 0.96416141 | I68: =MEDIAN(I44:I66) -> 0.9595637 | J68: =MEDIAN(J44:J66) -> 0.97298216 | K68: =MEDIAN(K44:K66) -> 0.97454733 | ... Z68: =MEDIAN(Z44:Z66) -> 1.0000002
C69: Promedio | D69: =AVERAGE(D44:D66) -> 1.6457561 | E69: =AVERAGE(E44:E66) -> 0.93012601 | F69: =AVERAGE(F44:F66) -> 1.0563674 | G69: =AVERAGE(G44:G66) -> 0.9449006 | H69: =AVERAGE(H44:H66) -> 0.95719711 | I69: =AVERAGE(I44:I66) -> 0.95519399 | J69: =AVERAGE(J44:J66) -> 0.9682941 | K69: =AVERAGE(K44:K66) -> 0.97687954 | ... Z69: =AVERAGE(Z44:Z66) -> 1.0000002
C70: cota_inf | D70: =D69*0.8 -> 1.3166048 | E70: =E69*0.8 -> 0.74410081 | F70: =F69*0.8 -> 0.84509388 | G70: =G69*0.8 -> 0.75592048 | H70: =H69*0.8 -> 0.76575769 | I70: =I69*0.8 -> 0.7641552 | J70: =J69*0.8 -> 0.77463528 | K70: =K69*0.8 -> 0.78150364 | ... Z70: =Z69*0.8 -> 0.80000014
C71: cota_sup | D71: =D69*1.2 -> 1.9749073 | E71: =E69*1.2 -> 1.1161512 | F71: =F69*1.2 -> 1.2676408 | G71: =G69*1.2 -> 1.1338807 | H71: =H69*1.2 -> 1.1486365 | I71: =I69*1.2 -> 1.1462328 | J71: =J69*1.2 -> 1.1619529 | K71: =K69*1.2 -> 1.1722555 | ... Z71: =Z69*1.2 -> 1.2000002
F76: ULTIMATE | J76: IBNR
D77: Primas | E77: REPORTADO | F77: Chain Ladder | G77: BF | H77: CC | I77: Selección | J77: Chain Ladder | K77: BF | L77: CC | M77: Selección
B78: 24 | C78: 1Q19 | D78: 20213006 | E78: {=INDEX(D16:AA16,$B78)} -> 5814528 | F78: ='2_CL'!AA4 -> 5814528 | G78: ='2_BF'!I8 -> 5814528 | H78: ='2_CC'!I8 -> 5814528 | J78: ='2_CL'!AC4 -> 0 | K78: ='2_BF'!H8 -> 0 | L78: ='2_CC'!H8 -> 0
B79: =+B78-1 -> 23 | C79: 2Q19 | D79: 22641632 | E79: {=INDEX(D17:AA17,$B79)} -> 7995874 | F79: ='2_CL'!AA5 -> 7995875.4 | G79: ='2_BF'!I9 -> 7995876.1 | H79: ='2_CC'!I9 -> 7995875.7 | J79: ='2_CL'!AC5 -> 1.3751547 | K79: ='2_BF'!H9 -> 2.1416867 | L79: ='2_CC'!H9 -> 1.6912903
B80: =+B79-1 -> 22 | C80: 3Q19 | D80: 19561331 | E80: {=INDEX(D18:AA18,$B80)} -> 4710870 | F80: ='2_CL'!AA6 -> 4710875.9 | G80: ='2_BF'!I10 -> 4710883.5 | H80: ='2_CC'!I10 -> 4710880.7 | J80: ='2_CL'!AC6 -> 5.9268506 | K80: ='2_BF'!H10 -> 13.535784 | L80: ='2_CC'!H10 -> 10.68921
B81: =+B80-1 -> 21 | C81: 4Q19 | D81: 9083808.1 | E81: {=INDEX(D19:AA19,$B81)} -> 5046123 | F81: ='2_CL'!AA7 -> 5046135.6 | G81: ='2_BF'!I11 -> 5046135.5 | H81: ='2_CC'!I11 -> 5046132.9 | J81: ='2_CL'!AC7 -> 12.615014 | K81: ='2_BF'!H11 -> 12.489914 | L81: ='2_CC'!H11 -> 9.8632868
B82: =+B81-1 -> 20 | C82: 1Q20 | D82: 18994503 | E82: {=INDEX(D20:AA20,$B82)} -> 4612035 | F82: ='2_CL'!AA8 -> 4612019.3 | G82: ='2_BF'!I12 -> 4611999.5 | H82: ='2_CC'!I12 -> 4612007 | J82: ='2_CL'!AC8 -> -15.671819 | K82: ='2_BF'!H12 -> -35.499227 | L82: ='2_CC'!H12 -> -28.033744
B83: =+B82-1 -> 19 | C83: 2Q20 | D83: -1004591.6 | E83: {=INDEX(D21:AA21,$B83)} -> 2490228 | F83: ='2_CL'!AA9 -> 2490146.3 | G83: ='2_BF'!I13 -> 2490246.1 | H83: ='2_CC'!I13 -> 2490242.3 | J83: ='2_CL'!AC9 -> -81.718274 | K83: ='2_BF'!H13 -> 18.132036 | L83: ='2_CC'!H13 -> 14.318871
B84: =+B83-1 -> 18 | C84: 3Q20 | D84: -5936695 | E84: {=INDEX(D22:AA22,$B84)} -> 2642281 | F84: ='2_CL'!AA10 -> 2641935.4 | G84: ='2_BF'!I14 -> 2642708.1 | H84: ='2_CC'!I14 -> 2642618.3 | J84: ='2_CL'!AC10 -> -345.55585 | K84: ='2_BF'!H14 -> 427.07434 | L84: ='2_CC'!H14 -> 337.26065
B85: =+B84-1 -> 17 | C85: 4Q20 | D85: 4268257.7 | E85: {=INDEX(D23:AA23,$B85)} -> 6538885 | F85: ='2_CL'!AA11 -> 6537271.1 | G85: ='2_BF'!I15 -> 6538305.4 | H85: ='2_CC'!I15 -> 6538427.3 | J85: ='2_CL'!AC11 -> -1613.9375 | K85: ='2_BF'!H15 -> -579.56687 | L85: ='2_CC'!H15 -> -457.68402
B86: =+B85-1 -> 16 | C86: 1Q21 | D86: 16145782 | E86: {=INDEX(D24:AA24,$B86)} -> 6037298 | F86: ='2_CL'!AA12 -> 6035154.4 | G86: ='2_BF'!I16 -> 6034143.8 | H86: ='2_CC'!I16 -> 6034807.2 | J86: ='2_CL'!AC12 -> -2143.638 | K86: ='2_BF'!H16 -> -3154.1682 | L86: ='2_CC'!H16 -> -2490.847
B87: =+B86-1 -> 15 | C87: 2Q21 | D87: 16851117 | E87: {=INDEX(D25:AA25,$B87)} -> 4354413 | F87: ='2_CL'!AA13 -> 4351081.6 | G87: ='2_BF'!I17 -> 4347317 | H87: ='2_CC'!I17 -> 4348809.3 | J87: ='2_CL'!AC13 -> -3331.3644 | K87: ='2_BF'!H17 -> -7096.0437 | L87: ='2_CC'!H17 -> -5603.7465
B88: =+B87-1 -> 14 | C88: 3Q21 | D88: -4179642.8 | E88: {=INDEX(D26:AA26,$B88)} -> 4284653 | F88: ='2_CL'!AA14 -> 4277753.1 | G88: ='2_BF'!I18 -> 4288360.9 | H88: ='2_CC'!I18 -> 4287581.1 | J88: ='2_CL'!AC14 -> -6899.9201 | K88: ='2_BF'!H18 -> 3707.9187 | L88: ='2_CC'!H18 -> 2928.1438
B89: =+B88-1 -> 13 | C89: 4Q21 | D89: 3503669 | E89: {=INDEX(D27:AA27,$B89)} -> 7266841 | F89: ='2_CL'!AA15 -> 7240242.3 | G89: ='2_BF'!I19 -> 7259761.7 | H89: ='2_CC'!I19 -> 7261250.5 | J89: ='2_CL'!AC15 -> -26598.651 | K89: ='2_BF'!H19 -> -7079.3319 | L89: ='2_CC'!H19 -> -5590.5492
B90: =+B89-1 -> 12 | C90: 1Q22 | D90: 17466795 | E90: {=INDEX(D28:AA28,$B90)} -> 5844768 | F90: ='2_CL'!AA16 -> 5800797.6 | G90: ='2_BF'!I20 -> 5771948.4 | H90: ='2_CC'!I20 -> 5787262.3 | J90: ='2_CL'!AC16 -> -43970.39 | K90: ='2_BF'!H20 -> -72819.64 | L90: ='2_CC'!H20 -> -57505.678
... B101: =+B100-1 -> 1 | C101: 4Q24 | D101: 32995208 | E101: {=INDEX(D39:AA39,$B101)} -> 5149958 | F101: ='2_CL'!AA27 -> 6945930.3 | G101: ='2_BF'!I31 -> 9842225.6 | H101: ='2_CC'!I31 -> 8855442.3 | J101: ='2_CL'!AC27 -> 1795972.3 | K101: ='2_BF'!H31 -> 4692267.6 | L101: ='2_CC'!H31 -> 3705484.3
C107: TRIÁNGULO DESARROLLADO AL 31 DE SEPTIEMBRE DE 2026
D109: 1 | E109: =+D109+1 -> 2 | F109: =+E109+1 -> 3 | G109: =+F109+1 -> 4 | H109: =+G109+1 -> 5 | I109: =+H109+1 -> 6 | J109: =+I109+1 -> 7 | K109: =+J109+1 -> 8 | L109: =+K109+1 -> 9 | ... AA109: =+Z109+1 -> 24
C110: 1Q19 | D110: 6418198 | E110: 8351947 | F110: 7241932 | G110: 6612057 | H110: 6678429 | I110: 6520501 | J110: 6390444 | K110: 6157365 | L110: 5998497 | M110: 5960040 | N110: 5927219 | O110: 5845151 | P110: 5844679 | Q110: 5823554 | R110: 5819414 | S110: 5817651 | T110: 5816446 | U110: 5815298 | V110: 5814997 | W110: 5814607 | X110: 5814513 | Y110: 5814520 | Z110: 5814527 | AA110: 5814528
C111: 2Q19 | D111: 7475822 | E111: 10450029 | F111: 10185917 | G111: 9722137 | H111: 9434292 | I111: 9020873 | J111: 8704176 | K111: 8469008 | L111: 8349635 | M111: 8209160 | N111: 8096242 | O111: 8041381 | P111: 8008712 | Q111: 8003007 | R111: 8002023 | S111: 7997629 | T111: 7997019 | U111: 7996437 | V111: 7996215 | W111: 7995857 | X111: 7995850 | Y111: 7995866 | Z111: 7995874 | AA111: 7995875.4
C112: 3Q19 | D112: 4944676 | E112: 5651989 | F112: 5515292 | G112: 5713405 | H112: 5462475 | I112: 5370959 | J112: 5305411 | K112: 5148861 | L112: 4913135 | M112: 4939885 | N112: 4852857 | O112: 4772843 | P112: 4722978 | Q112: 4724493 | R112: 4714404 | S112: 4711994 | T112: 4711744 | U112: 4711585 | V112: 4710817 | W112: 4710876 | X112: 4710870 | Y112: 4710870 | Z112: 4710874.7 | AA112: 4710875.5
C113: 4Q19 | D113: 5990844 | E113: 8317434 | F113: 7538034 | G113: 7146705 | H113: 6480112 | I113: 5918174 | J113: 5524711 | K113: 5379113 | L113: 5282322 | M113: 5218946 | N113: 5148288 | O113: 5055569 | P113: 5052150 | Q113: 5048881 | R113: 5049883 | S113: 5047150 | T113: 5047033 | U113: 5046810 | V113: 5046112 | W113: 5046155 | X113: 5046123 | Y113: 5046129.1 | Z113: 5046134.1 | AA113: 5046135
C114: 1Q20 | D114: 6106533 | E114: 7227067 | F114: 6609141 | G114: 6587986 | H114: 5966963 | I114: 5553219 | J114: 5440658 | K114: 5247292 | L114: 4989511 | M114: 4739938 | N114: 4632683 | O114: 4647858 | P114: 4648748 | Q114: 4631093 | R114: 4618736 | S114: 4614941 | T114: 4614019 | U114: 4612810 | V114: 4612218 | W114: 4612035 | X114: 4611960.4 | Y114: 4611969.7 | Z114: 4611975.2 | AA114: 4611976
C115: 2Q20 | D115: 3511339 | E115: 5097855 | F115: 4392249 | G115: 4331724 | H115: 3638678 | I115: 3261200 | J115: 2912378 | K115: 2561746 | L115: 2608839 | M115: 2512337 | N115: 2525572 | O115: 2539117 | P115: 2502024 | Q115: 2495301 | R115: 2491023 | S115: 2490185 | T115: 2490716 | U115: 2490652 | V115: 2490228 | W115: 2490129.2 | X115: 2490126 | Y115: 2490129 | Z115: 2490132 | AA115: 2490132.4
C116: 3Q20 | D116: 4141271 | E116: 5675304 | F116: 5003527 | G116: 4490079 | H116: 3864708 | I116: 3317046 | J116: 3043775 | K116: 2982731 | L116: 2853880 | M116: 2708486 | N116: 2687185 | O116: 2706223 | P116: 2663612 | Q116: 2649484 | R116: 2644988 | S116: 2644539 | T116: 2642763 | U116: 2642281 | V116: 2642144.2 | W116: 2642025.9 | X116: 2642009.2 | Y116: 2642009.2 | Z116: 2642012.4 | AA116: 2642012.8
C117: 4Q20 | D117: 6591656 | E117: 9149839 | F117: 9246786 | G117: 8427024 | H117: 7881930 | I117: 7889306 | J117: 7459046 | K117: 7134362 | L117: 7020325 | M117: 6829753 | N117: 6654101 | O117: 6564713 | P117: 6557312 | Q117: 6540955 | R117: 6539478 | S117: 6538852 | T117: 6538885 | U117: 6538596.1 | V117: 6537756.9 | W117: 6537497.5 | X117: 6537391.8 | Y117: 6537399.7 | Z117: 6537406.3 | AA117: 6537407.4
C118: 1Q21 | D118: 6289704 | E118: 9074583 | F118: 7921104 | G118: 7241833 | H118: 6605506 | I118: 6368774 | J118: 5993512 | K118: 6063255 | L118: 6123811 | M118: 6142139 | N118: 6109898 | O118: 6094584 | P118: 6054429 | Q118: 6045198 | R118: 6039123 | S118: 6037298 | T118: 6038585.4 | U118: 6038381.6 | V118: 6038069.1 | W118: 6037664.1 | X118: 6037566.5 | Y118: 6037566.5 | Z118: 6037573.8
C119: 2Q21 | D119: 4959185 | E119: 7332815 | F119: 6338245 | G119: 6335214 | H119: 5820802 | I119: 5372283 | J119: 5126418 | K119: 4909923 | L119: 4699737 | M119: 4565993 | N119: 4388069 | O119: 4350454 | P119: 4349470 | Q119: 4354085 | R119: 4354413 | S119: 4352948.1 | T119: 4352078.5 | U119: 4351886.2 | V119: 4351284.3 | W119: 4351338.8 | X119: 4351311.2 | Y119: 4351311.2
C120: 3Q21 | D120: 6194048 | E120: 7741218 | F120: 6754577 | G120: 6157468 | H120: 5562103 | I120: 5078341 | J120: 5094245 | K120: 4970573 | L120: 4756133 | M120: 4568920 | N120: 4414181 | O120: 4318353 | P120: 4308927 | Q120: 4284653 | R120: 4284126.2 | S120: 4283398.9 | T120: 4282543.2 | U120: 4282398.7 | V120: 4281806.4 | W120: 4281860 | X120: 4281832.9
C121: 4Q21 | D121: 6500694 | E121: 9436157 | F121: 8641541 | G121: 8462835 | H121: 8478196 | I121: 8406511 | J121: 7938776 | K121: 7694015 | L121: 7414340 | M121: 7365359 | N121: 7323515 | O121: 7284864 | P121: 7266841 | Q121: 7262139 | R121: 7246630.9 | S121: 7244435.5 | T121: 7242935 | U121: 7241505.5 | V121: 7240272.7 | W121: 7239985.4
C122: 1Q22 | D122: 5205434 | E122: 7752400 | F122: 7497356 | G122: 7293599 | H122: 6566528 | I122: 6681703 | J122: 6326840 | K122: 6334277 | L122: 6175261 | M122: 6025240 | N122: 5846424 | O122: 5844768 | P122: 5844296 | Q122: 5828592.3 | R122: 5822734.9 | S122: 5820776.1 | T122: 5822017.3 | U122: 5820868.2 | V122: 5820063.2
C123: 2Q22 | D123: 5184519 | E123: 7275135 | F123: 7269751 | G123: 6967745 | H123: 6399402 | I123: 5827678 | J123: 5837462 | K123: 5752901 | L123: 5510232 | M123: 5306283 | N123: 5171805 | O123: 5144510 | P123: 5090761.9 | Q123: 5092394.9 | R123: 5083664.4 | S123: 5082128.1 | T123: 5082010.3 | U123: 5081785.8
C124: 3Q22 | D124: 3419011 | E124: 4773306 | F124: 3716822 | G124: 3313659 | H124: 3377536 | I124: 3222093 | J124: 2783981 | K124: 2603716 | L124: 2643618 | M124: 2473125 | N124: 2486153.4 | O124: 2479922.1 | P124: 2440874.3 | Q124: 2434785.6 | R124: 2432338.8 | S124: 2431602 | T124: 2432120.5
C125: 4Q22 | D125: 5498188 | E125: 10669557 | F125: 10857709 | G125: 14275258 | H125: 14084665 | I125: 14163048 | J125: 13850553 | K125: 13534768 | L125: 13371613 | M125: 12509247 | N125: 12021797 | O125: 11940336 | P125: 11752328 | Q125: 11723012 | R125: 11702914 | S125: 11698977
C126: 1Q23 | D126: 6382667 | E126: 10460689 | F126: 9727516 | G126: 13561133 | H126: 12865538 | I126: 12816850 | J126: 12593535 | K126: 12422697 | L126: 12224130 | M126: 11742959 | N126: 11581433 | O126: 11619369 | P126: 11542814 | Q126: 11501093 | R126: 11503376
...

Sheet 2_CL
A1: CHAIN-LADDER — Triángulo Proyectado e IBNR | Vinculado a hojas 1_Triangulo y 2_Factores
A2: AZUL=observado (hoja 1) · AMARILLO=proyección CL = C_{i,j-1} × f̂_{j-1} (hoja 2) · VERDE=IBNR
A3: AO | B3: Trim. | C3: T01 | D3: T02 | E3: T03 | F3: T04 | G3: T05 | H3: T06 | I3: T07 | J3: T08 | K3: T09 | L3: T10 | M3: T11 | N3: T12 | O3: T13 | P3: T14 | Q3: T15 | R3: T16 | S3: T17 | T3: T18 | U3: T19 | V3: T20 | W3: T21 | X3: T22 | Y3: T23 | Z3: T24 | AA3: Último Proy. | AB3: Pagado Actual | AC3: IBNR CL
A4: AO01 | B4: 1Q19 | C4: =IF(Triangulo2!D16=0,"-",Triangulo2!D16) -> 6418198 | D4: =IF(Triangulo2!E16=0,"-",Triangulo2!E16) -> 8351947 | E4: =IF(Triangulo2!F16=0,"-",Triangulo2!F16) -> 7241932 | F4: =IF(Triangulo2!G16=0,"-",Triangulo2!G16) -> 6612057 | G4: =IF(Triangulo2!H16=0,"-",Triangulo2!H16) -> 6678429 | H4: =IF(Triangulo2!I16=0,"-",Triangulo2!I16) -> 6520501 | I4: =IF(Triangulo2!J16=0,"-",Triangulo2!J16) -> 6390444 | J4: =IF(Triangulo2!K16=0,"-",Triangulo2!K16) -> 6157365 | ... Z4: =IF(Triangulo2!AA16=0,"-",Triangulo2!AA16) -> 5814528 | AA4: =+Z4 -> 5814528 | AB4: =+Z4 -> 5814528 | AC4: =AA4-AB4 -> 0
A5: AO02 | B5: 2Q19 | C5: =IF(Triangulo2!D17=0,"-",Triangulo2!D17) -> 7475822 | D5: =IF(Triangulo2!E17=0,"-",Triangulo2!E17) -> 10450029 | E5: =IF(Triangulo2!F17=0,"-",Triangulo2!F17) -> 10185917 | F5: =IF(Triangulo2!G17=0,"-",Triangulo2!G17) -> 9722137 | G5: =IF(Triangulo2!H17=0,"-",Triangulo2!H17) -> 9434292 | H5: =IF(Triangulo2!I17=0,"-",Triangulo2!I17) -> 9020873 | I5: =IF(Triangulo2!J17=0,"-",Triangulo2!J17) -> 8704176 | J5: =IF(Triangulo2!K17=0,"-",Triangulo2!K17) -> 8469008 | ... Y5: =IF(Triangulo2!Z17=0,"-",Triangulo2!Z17) -> 7995874 | Z5: =+Y5*Y$30 -> 7995875.4 | AA5: =+Z5 -> 7995875.4 | AB5: =+Y5 -> 7995874 | AC5: =AA5-AB5 -> 1.3751547
A6: AO03 | B6: 3Q19 | C6: =IF(Triangulo2!D18=0,"-",Triangulo2!D18) -> 4944676 | D6: =IF(Triangulo2!E18=0,"-",Triangulo2!E18) -> 5651989 | E6: =IF(Triangulo2!F18=0,"-",Triangulo2!F18) -> 5515292 | F6: =IF(Triangulo2!G18=0,"-",Triangulo2!G18) -> 5713405 | G6: =IF(Triangulo2!H18=0,"-",Triangulo2!H18) -> 5462475 | H6: =IF(Triangulo2!I18=0,"-",Triangulo2!I18) -> 5370959 | I6: =IF(Triangulo2!J18=0,"-",Triangulo2!J18) -> 5305411 | J6: =IF(Triangulo2!K18=0,"-",Triangulo2!K18) -> 5148861 | ... X6: =IF(Triangulo2!Y18=0,"-",Triangulo2!Y18) -> 4710870 | Y6: =+X6*X$30 -> 4710875.1 | Z6: =+Y6*Y$30 -> 4710875.9 | AA6: =+Z6 -> 4710875.9 | AB6: =+X6 -> 4710870 | AC6: =AA6-AB6 -> 5.9268506
A7: AO04 | B7: 4Q19 | C7: =IF(Triangulo2!D19=0,"-",Triangulo2!D19) -> 5990844 | D7: =IF(Triangulo2!E19=0,"-",Triangulo2!E19) -> 8317434 | E7: =IF(Triangulo2!F19=0,"-",Triangulo2!F19) -> 7538034 | F7: =IF(Triangulo2!G19=0,"-",Triangulo2!G19) -> 7146705 | G7: =IF(Triangulo2!H19=0,"-",Triangulo2!H19) -> 6480112 | H7: =IF(Triangulo2!I19=0,"-",Triangulo2!I19) -> 5918174 | I7: =IF(Triangulo2!J19=0,"-",Triangulo2!J19) -> 5524711 | J7: =IF(Triangulo2!K19=0,"-",Triangulo2!K19) -> 5379113 | ... W7: =IF(Triangulo2!X19=0,"-",Triangulo2!X19) -> 5046123 | X7: =+W7*W$30 -> 5046129.3 | Y7: =+X7*X$30 -> 5046134.7 | Z7: =+Y7*Y$30 -> 5046135.6 | AA7: =+Z7 -> 5046135.6 | AB7: =+W7 -> 5046123 | AC7: =AA7-AB7 -> 12.615014
A8: AO05 | B8: 1Q20 | C8: =IF(Triangulo2!D20=0,"-",Triangulo2!D20) -> 6106533 | D8: =IF(Triangulo2!E20=0,"-",Triangulo2!E20) -> 7227067 | E8: =IF(Triangulo2!F20=0,"-",Triangulo2!F20) -> 6609141 | F8: =IF(Triangulo2!G20=0,"-",Triangulo2!G20) -> 6587986 | G8: =IF(Triangulo2!H20=0,"-",Triangulo2!H20) -> 5966963 | H8: =IF(Triangulo2!I20=0,"-",Triangulo2!I20) -> 5553219 | I8: =IF(Triangulo2!J20=0,"-",Triangulo2!J20) -> 5440658 | J8: =IF(Triangulo2!K20=0,"-",Triangulo2!K20) -> 5247292 | ... V8: =IF(Triangulo2!W20=0,"-",Triangulo2!W20) -> 4612035 | W8: =+V8*V$30 -> 4612007.8 | X8: =+W8*W$30 -> 4612013.5 | Y8: =+X8*X$30 -> 4612018.5 | Z8: =+Y8*Y$30 -> 4612019.3 | AA8: =+Z8 -> 4612019.3 | AB8: =+V8 -> 4612035 | AC8: =AA8-AB8 -> -15.671819
A9: AO06 | B9: 2Q20 | C9: =IF(Triangulo2!D21=0,"-",Triangulo2!D21) -> 3511339 | D9: =IF(Triangulo2!E21=0,"-",Triangulo2!E21) -> 5097855 | E9: =IF(Triangulo2!F21=0,"-",Triangulo2!F21) -> 4392249 | F9: =IF(Triangulo2!G21=0,"-",Triangulo2!G21) -> 4331724 | G9: =IF(Triangulo2!H21=0,"-",Triangulo2!H21) -> 3638678 | H9: =IF(Triangulo2!I21=0,"-",Triangulo2!I21) -> 3261200 | I9: =IF(Triangulo2!J21=0,"-",Triangulo2!J21) -> 2912378 | J9: =IF(Triangulo2!K21=0,"-",Triangulo2!K21) -> 2561746 | ... U9: =IF(Triangulo2!V21=0,"-",Triangulo2!V21) -> 2490228 | V9: =+U9*U$30 -> 2490154.7 | W9: =+V9*V$30 -> 2490140.1 | X9: =+W9*W$30 -> 2490143.1 | Y9: =+X9*X$30 -> 2490145.9 | Z9: =+Y9*Y$30 -> 2490146.3 | AA9: =+Z9 -> 2490146.3 | AB9: =+U9 -> 2490228 | AC9: =AA9-AB9 -> -81.718274
A10: AO07 | B10: 3Q20 | C10: =IF(Triangulo2!D22=0,"-",Triangulo2!D22) -> 4141271 | D10: =IF(Triangulo2!E22=0,"-",Triangulo2!E22) -> 5675304 | E10: =IF(Triangulo2!F22=0,"-",Triangulo2!F22) -> 5003527 | F10: =IF(Triangulo2!G22=0,"-",Triangulo2!G22) -> 4490079 | G10: =IF(Triangulo2!H22=0,"-",Triangulo2!H22) -> 3864708 | H10: =IF(Triangulo2!I22=0,"-",Triangulo2!I22) -> 3317046 | I10: =IF(Triangulo2!J22=0,"-",Triangulo2!J22) -> 3043775 | J10: =IF(Triangulo2!K22=0,"-",Triangulo2!K22) -> 2982731 | ... T10: =IF(Triangulo2!U22=0,"-",Triangulo2!U22) -> 2642281 | U10: =+T10*T$30 -> 2642022.1 | V10: =+U10*U$30 -> 2641944.4 | W10: =+V10*V$30 -> 2641928.8 | X10: =+W10*W$30 -> 2641932.1 | Y10: =+X10*X$30 -> 2641935 | Z10: =+Y10*Y$30 -> 2641935.4 | AA10: =+Z10 -> 2641935.4 | AB10: =+T10 -> 2642281 | AC10: =AA10-AB10 -> -345.55585
A11: AO08 | B11: 4Q20 | C11: =IF(Triangulo2!D23=0,"-",Triangulo2!D23) -> 6591656 | D11: =IF(Triangulo2!E23=0,"-",Triangulo2!E23) -> 9149839 | E11: =IF(Triangulo2!F23=0,"-",Triangulo2!F23) -> 9246786 | F11: =IF(Triangulo2!G23=0,"-",Triangulo2!G23) -> 8427024 | G11: =IF(Triangulo2!H23=0,"-",Triangulo2!H23) -> 7881930 | H11: =IF(Triangulo2!I23=0,"-",Triangulo2!I23) -> 7889306 | I11: =IF(Triangulo2!J23=0,"-",Triangulo2!J23) -> 7459046 | J11: =IF(Triangulo2!K23=0,"-",Triangulo2!K23) -> 7134362 | ... S11: =IF(Triangulo2!T23=0,"-",Triangulo2!T23) -> 6538885 | T11: =+S11*S$30 -> 6538126.1 | U11: =+T11*T$30 -> 6537485.6 | V11: =+U11*U$30 -> 6537293.3 | W11: =+V11*V$30 -> 6537254.7 | X11: =+W11*W$30 -> 6537262.8 | Y11: =+X11*X$30 -> 6537269.9 | Z11: =+Y11*Y$30 -> 6537271.1 | AA11: =+Z11 -> 6537271.1 | AB11: =+S11 -> 6538885 | AC11: =AA11-AB11 -> -1613.9375
A12: AO09 | B12: 1Q21 | C12: =IF(Triangulo2!D24=0,"-",Triangulo2!D24) -> 6289704 | D12: =IF(Triangulo2!E24=0,"-",Triangulo2!E24) -> 9074583 | E12: =IF(Triangulo2!F24=0,"-",Triangulo2!F24) -> 7921104 | F12: =IF(Triangulo2!G24=0,"-",Triangulo2!G24) -> 7241833 | G12: =IF(Triangulo2!H24=0,"-",Triangulo2!H24) -> 6605506 | H12: =IF(Triangulo2!I24=0,"-",Triangulo2!I24) -> 6368774 | I12: =IF(Triangulo2!J24=0,"-",Triangulo2!J24) -> 5993512 | J12: =IF(Triangulo2!K24=0,"-",Triangulo2!K24) -> 6063255 | ... R12: =IF(Triangulo2!S24=0,"-",Triangulo2!S24) -> 6037298 | S12: =+R12*R30 -> 6036644.3 | T12: =+S12*S30 -> 6035943.7 | U12: =+T12*T30 -> 6035352.4 | V12: =+U12*U30 -> 6035174.9 | W12: =+V12*V30 -> 6035139.3 | X12: =+W12*W30 -> 6035146.8 | Y12: =+X12*X30 -> 6035153.3 | Z12: =+Y12*Y30 -> 6035154.4 | AA12: =+Z12 -> 6035154.4 | AB12: =+R12 -> 6037298 | AC12: =AA12-AB12 -> -2143.638
A13: AO10 | B13: 2Q21 | C13: =IF(Triangulo2!D25=0,"-",Triangulo2!D25) -> 4959185 | D13: =IF(Triangulo2!E25=0,"-",Triangulo2!E25) -> 7332815 | E13: =IF(Triangulo2!F25=0,"-",Triangulo2!F25) -> 6338245 | F13: =IF(Triangulo2!G25=0,"-",Triangulo2!G25) -> 6335214 | G13: =IF(Triangulo2!H25=0,"-",Triangulo2!H25) -> 5820802 | H13: =IF(Triangulo2!I25=0,"-",Triangulo2!I25) -> 5372283 | I13: =IF(Triangulo2!J25=0,"-",Triangulo2!J25) -> 5126418 | J13: =IF(Triangulo2!K25=0,"-",Triangulo2!K25) -> 4909923 | ... Q13: =IF(Triangulo2!R25=0,"-",Triangulo2!R25) -> 4354413 | R13: =+Q13*Q30 -> 4352627.1 | S13: =+R13*R30 -> 4352155.8 | T13: =+S13*S30 -> 4351650.7 | U13: =+T13*T30 -> 4351224.4 | V13: =+U13*U30 -> 4351096.4 | W13: =+V13*V30 -> 4351070.8 | X13: =+W13*W30 -> 4351076.2 | Y13: =+X13*X30 -> 4351080.9 | Z13: =+Y13*Y30 -> 4351081.6 | AA13: =+Z13 -> 4351081.6 | AB13: =+Q13 -> 4354413 | AC13: =AA13-AB13 -> -3331.3644
A14: AO11 | B14: 3Q21 | C14: =IF(Triangulo2!D26=0,"-",Triangulo2!D26) -> 6194048 | D14: =IF(Triangulo2!E26=0,"-",Triangulo2!E26) -> 7741218 | E14: =IF(Triangulo2!F26=0,"-",Triangulo2!F26) -> 6754577 | F14: =IF(Triangulo2!G26=0,"-",Triangulo2!G26) -> 6157468 | G14: =IF(Triangulo2!H26=0,"-",Triangulo2!H26) -> 5562103 | H14: =IF(Triangulo2!I26=0,"-",Triangulo2!I26) -> 5078341 | I14: =IF(Triangulo2!J26=0,"-",Triangulo2!J26) -> 5094245 | J14: =IF(Triangulo2!K26=0,"-",Triangulo2!K26) -> 4970573 | ... P14: =IF(Triangulo2!Q26=0,"-",Triangulo2!Q26) -> 4284653 | Q14: =+P14*P30 -> 4281028.3 | R14: =+Q14*Q30 -> 4279272.5 | S14: =+R14*R30 -> 4278809.2 | T14: =+S14*S30 -> 4278312.6 | U14: =+T14*T30 -> 4277893.5 | V14: =+U14*U30 -> 4277767.6 | W14: =+V14*V30 -> 4277742.4 | X14: =+W14*W30 -> 4277747.7 | ... Z14: =+Y14*Y30 -> 4277753.1 | AA14: =+Z14 -> 4277753.1 | AB14: =+P14 -> 4284653 | AC14: =AA14-AB14 -> -6899.9201
A15: AO12 | B15: 4Q21 | C15: =IF(Triangulo2!D27=0,"-",Triangulo2!D27) -> 6500694 | D15: =IF(Triangulo2!E27=0,"-",Triangulo2!E27) -> 9436157 | E15: =IF(Triangulo2!F27=0,"-",Triangulo2!F27) -> 8641541 | F15: =IF(Triangulo2!G27=0,"-",Triangulo2!G27) -> 8462835 | G15: =IF(Triangulo2!H27=0,"-",Triangulo2!H27) -> 8478196 | H15: =IF(Triangulo2!I27=0,"-",Triangulo2!I27) -> 8406511 | I15: =IF(Triangulo2!J27=0,"-",Triangulo2!J27) -> 7938776 | J15: =IF(Triangulo2!K27=0,"-",Triangulo2!K27) -> 7694015 | ... O15: =IF(Triangulo2!P27=0,"-",Triangulo2!P27) -> 7266841 | P15: =+O15*O30 -> 7251920.7 | Q15: =+P15*P30 -> 7245785.8 | R15: =+Q15*Q30 -> 7242814 | S15: =+R15*R30 -> 7242029.8 | T15: =+S15*S30 -> 7241189.3 | U15: =+T15*T30 -> 7240479.9 | V15: =+U15*U30 -> 7240267 | W15: =+V15*V30 -> 7240224.2 | ... Z15: =+Y15*Y30 -> 7240242.3 | AA15: =+Z15 -> 7240242.3 | AB15: =+O15 -> 7266841 | AC15: =AA15-AB15 -> -26598.651
A16: AO13 | B16: 1Q22 | C16: =IF(Triangulo2!D28=0,"-",Triangulo2!D28) -> 5205434 | D16: =IF(Triangulo2!E28=0,"-",Triangulo2!E28) -> 7752400 | E16: =IF(Triangulo2!F28=0,"-",Triangulo2!F28) -> 7497356 | F16: =IF(Triangulo2!G28=0,"-",Triangulo2!G28) -> 7293599 | G16: =IF(Triangulo2!H28=0,"-",Triangulo2!H28) -> 6566528 | H16: =IF(Triangulo2!I28=0,"-",Triangulo2!I28) -> 6681703 | I16: =IF(Triangulo2!J28=0,"-",Triangulo2!J28) -> 6326840 | J16: =IF(Triangulo2!K28=0,"-",Triangulo2!K28) -> 6334277 | ... N16: =IF(Triangulo2!O28=0,"-",Triangulo2!O28) -> 5844768 | O16: =+N16*N30 -> 5822108.1 | P16: =+O16*O30 -> 5810154.2 | Q16: =+P16*P30 -> 5805238.9 | R16: =+Q16*Q30 -> 5802858 | S16: =+R16*R30 -> 5802229.7 | T16: =+S16*S30 -> 5801556.3 | U16: =+T16*T30 -> 5800988 | V16: =+U16*U30 -> 5800817.3 | ... Z16: =+Y16*Y30 -> 5800797.6 | AA16: =+Z16 -> 5800797.6 | AB16: =+N16 -> 5844768 | AC16: =AA16-AB16 -> -43970.39
A17: AO14 | B17: 2Q22 | C17: =IF(Triangulo2!D29=0,"-",Triangulo2!D29) -> 5184519 | D17: =IF(Triangulo2!E29=0,"-",Triangulo2!E29) -> 7275135 | E17: =IF(Triangulo2!F29=0,"-",Triangulo2!F29) -> 7269751 | F17: =IF(Triangulo2!G29=0,"-",Triangulo2!G29) -> 6967745 | G17: =IF(Triangulo2!H29=0,"-",Triangulo2!H29) -> 6399402 | H17: =IF(Triangulo2!I29=0,"-",Triangulo2!I29) -> 5827678 | I17: =IF(Triangulo2!J29=0,"-",Triangulo2!J29) -> 5837462 | J17: =IF(Triangulo2!K29=0,"-",Triangulo2!K29) -> 5752901 | ... M17: =IF(Triangulo2!N29=0,"-",Triangulo2!N29) -> 5171805 | N17: =+M17*M30 -> 5131070.9 | O17: =+N17*N30 -> 5111178 | P17: =+O17*O30 -> 5100683.7 | Q17: =+P17*P30 -> 5096368.6 | R17: =+Q17*Q30 -> 5094278.4 | S17: =+R17*R30 -> 5093726.9 | T17: =+S17*S30 -> 5093135.7 | U17: =+T17*T30 -> 5092636.8 | ... Z17: =+Y17*Y30 -> 5092469.6 | AA17: =+Z17 -> 5092469.6 | AB17: =+M17 -> 5171805 | AC17: =AA17-AB17 -> -79335.361
A18: AO15 | B18: 3Q22 | C18: =IF(Triangulo2!D30=0,"-",Triangulo2!D30) -> 3419011 | D18: =IF(Triangulo2!E30=0,"-",Triangulo2!E30) -> 4773306 | E18: =IF(Triangulo2!F30=0,"-",Triangulo2!F30) -> 3716822 | F18: =IF(Triangulo2!G30=0,"-",Triangulo2!G30) -> 3313659 | G18: =IF(Triangulo2!H30=0,"-",Triangulo2!H30) -> 3377536 | H18: =IF(Triangulo2!I30=0,"-",Triangulo2!I30) -> 3222093 | I18: =IF(Triangulo2!J30=0,"-",Triangulo2!J30) -> 2783981 | J18: =IF(Triangulo2!K30=0,"-",Triangulo2!K30) -> 2603716 | ... L18: =IF(Triangulo2!M30=0,"-",Triangulo2!M30) -> 2473125 | M18: =+L18*L30 -> 2429834.7 | N18: =+M18*M30 -> 2410696.9 | O18: =+N18*N30 -> 2401350.7 | P18: =+O18*O30 -> 2396420.3 | Q18: =+P18*P30 -> 2394393 | R18: =+Q18*Q30 -> 2393410.9 | S18: =+R18*R30 -> 2393151.8 | T18: =+S18*S30 -> 2392874.1 | ... Z18: =+Y18*Y30 -> 2392561.1 | AA18: =+Z18 -> 2392561.1 | AB18: =+L18 -> 2473125 | AC18: =AA18-AB18 -> -80563.884
A19: AO16 | B19: 4Q22 | C19: =IF(Triangulo2!D31=0,"-",Triangulo2!D31) -> 5498188 | D19: =IF(Triangulo2!E31=0,"-",Triangulo2!E31) -> 10669557 | E19: =IF(Triangulo2!F31=0,"-",Triangulo2!F31) -> 10857709 | F19: =IF(Triangulo2!G31=0,"-",Triangulo2!G31) -> 14275258 | G19: =IF(Triangulo2!H31=0,"-",Triangulo2!H31) -> 14084665 | H19: =IF(Triangulo2!I31=0,"-",Triangulo2!I31) -> 14163048 | I19: =IF(Triangulo2!J31=0,"-",Triangulo2!J31) -> 13850553 | J19: =IF(Triangulo2!K31=0,"-",Triangulo2!K31) -> 13534768 | K19: =IF(Triangulo2!L31=0,"-",Triangulo2!L31) -> 13371613 | L19: =+K19*K30 -> 13072683 | M19: =+L19*L30 -> 12843855 | N19: =+M19*M30 -> 12742695 | O19: =+N19*N30 -> 12693292 | P19: =+O19*O30 -> 12667230 | Q19: =+P19*P30 -> 12656514 | R19: =+Q19*Q30 -> 12651323 | S19: =+R19*R30 -> 12649953 | ... Z19: =+Y19*Y30 -> 12646831 | AA19: =+Z19 -> 12646831 | AB19: =+K19 -> 13371613 | AC19: =AA19-AB19 -> -724781.94
A20: AO17 | B20: 1Q23 | C20: =IF(Triangulo2!D32=0,"-",Triangulo2!D32) -> 6382667 | D20: =IF(Triangulo2!E32=0,"-",Triangulo2!E32) -> 10460689 | E20: =IF(Triangulo2!F32=0,"-",Triangulo2!F32) -> 9727516 | F20: =IF(Triangulo2!G32=0,"-",Triangulo2!G32) -> 13561133 | G20: =IF(Triangulo2!H32=0,"-",Triangulo2!H32) -> 12865538 | H20: =IF(Triangulo2!I32=0,"-",Triangulo2!I32) -> 12816850 | I20: =IF(Triangulo2!J32=0,"-",Triangulo2!J32) -> 12593535 | J20: =IF(Triangulo2!K32=0,"-",Triangulo2!K32) -> 12422697 | K20: =+J20*J30 -> 12130523 | L20: =+K20*K30 -> 11859339 | M20: =+L20*L30 -> 11651750 | N20: =+M20*M30 -> 11559978 | O20: =+N20*N30 -> 11515161 | P20: =+O20*O30 -> 11491518 | Q20: =+P20*P30 -> 11481797 | R20: =+Q20*Q30 -> 11477087 | ... Z20: =+Y20*Y30 -> 11473012 | AA20: =+Z20 -> 11473012 | AB20: =+J20 -> 12422697 | AC20: =AA20-AB20 -> -949684.63
A21: AO18 | B21: 2Q23 | C21: =IF(Triangulo2!D33=0,"-",Triangulo2!D33) -> 3022770 | D21: =IF(Triangulo2!E33=0,"-",Triangulo2!E33) -> 7899209 | E21: =IF(Triangulo2!F33=0,"-",Triangulo2!F33) -> 7498380 | F21: =IF(Triangulo2!G33=0,"-",Triangulo2!G33) -> 10736732 | G21: =IF(Triangulo2!H33=0,"-",Triangulo2!H33) -> 10856995 | H21: =IF(Triangulo2!I33=0,"-",Triangulo2!I33) -> 10834399 | I21: =IF(Triangulo2!J33=0,"-",Triangulo2!J33) -> 10568629 | J21: =+I21*I30 -> 10285142 | K21: =+J21*J30 -> 10043243 | L21: =+K21*K30 -> 9818720.6 | M21: =+L21*L30 -> 9646850.9 | N21: =+M21*M30 -> 9570870.4 | O21: =+N21*N30 -> 9533764.7 | P21: =+O21*O30 -> 9514189.9 | Q21: =+P21*P30 -> 9506141.2 | ... Z21: =+Y21*Y30 -> 9498868.4 | AA21: =+Z21 -> 9498868.4 | AB21: =+I21 -> 10568629 | AC21: =AA21-AB21 -> -1069760.6
A22: AO19 | B22: 3Q23 | C22: =IF(Triangulo2!D34=0,"-",Triangulo2!D34) -> 6936281 | D22: =IF(Triangulo2!E34=0,"-",Triangulo2!E34) -> 21936281 | E22: =IF(Triangulo2!F34=0,"-",Triangulo2!F34) -> 21767538 | F22: =IF(Triangulo2!G34=0,"-",Triangulo2!G34) -> 25515798 | G22: =IF(Triangulo2!H34=0,"-",Triangulo2!H34) -> 25644750 | H22: =IF(Triangulo2!I34=0,"-",Triangulo2!I34) -> 25593031 | I22: =H30*H22 -> 24629717 | J22: =I30*I22 -> 23969064 | K22: =J30*J22 -> 23405328 | L22: =K30*K22 -> 22882089 | M22: =L30*L22 -> 22481555 | N22: =M30*M22 -> 22304486 | O22: =N30*N22 -> 22218012 | P22: =O30*O22 -> 22172394 | ... Z22: =Y30*Y22 -> 22136688 | AA22: =+Z22 -> 22136688 | AB22: =+H22 -> 25593031 | AC22: =AA22-AB22 -> -3456342.7
A23: AO20 | B23: 4Q23 | C23: =IF(Triangulo2!D35=0,"-",Triangulo2!D35) -> 6691248 | D23: =IF(Triangulo2!E35=0,"-",Triangulo2!E35) -> 11756013 | E23: =IF(Triangulo2!F35=0,"-",Triangulo2!F35) -> 11113520 | F23: =IF(Triangulo2!G35=0,"-",Triangulo2!G35) -> 14458725 | G23: =IF(Triangulo2!H35=0,"-",Triangulo2!H35) -> 14275150 | H23: =G30*G23 -> 13866746 | I23: =H30*H23 -> 13344806 | J23: =I30*I23 -> 12986853 | K23: =J30*J23 -> 12681411 | L23: =K30*K23 -> 12397911 | M23: =L30*L23 -> 12180895 | N23: =M30*M23 -> 12084955 | O23: =N30*N23 -> 12038103 | ... Z23: =Y30*Y23 -> 11994040 | AA23: =+Z23 -> 11994040 | AB23: =+G23 -> 14275150 | AC23: =AA23-AB23 -> -2281110.1
A24: AO21 | B24: 1Q24 | C24: =IF(Triangulo2!D36=0,"-",Triangulo2!D36) -> 4191817 | D24: =IF(Triangulo2!E36=0,"-",Triangulo2!E36) -> 9775450 | E24: =IF(Triangulo2!F36=0,"-",Triangulo2!F36) -> 9803541 | F24: =IF(Triangulo2!G36=0,"-",Triangulo2!G36) -> 12735195 | G24: =F30*F24 -> 12203361 | H24: =G30*G24 -> 11854229 | I24: =H30*H24 -> 11408040 | J24: =I30*I24 -> 11102037 | K24: =J30*J24 -> 10840925 | L24: =K30*K24 -> 10598570 | M24: =L30*L24 -> 10413050 | N24: =M30*M24 -> 10331035 | ... Z24: =Y30*Y24 -> 10253314 | AA24: =+Z24 -> 10253314 | AB24: =+F24 -> 12735195 | AC24: =AA24-AB24 -> -2481881
A25: AO22 | B25: 2Q24 | C25: =IF(Triangulo2!D37=0,"-",Triangulo2!D37) -> 5916671 | D25: =IF(Triangulo2!E37=0,"-",Triangulo2!E37) -> 11716355 | E25: =IF(Triangulo2!F37=0,"-",Triangulo2!F37) -> 11277873 | F25: =E25*E30 -> 12275329 | G25: =F25*F30 -> 11762699 | H25: =G25*G30 -> 11426175 | I25: =H25*H30 -> 10996097 | J25: =I25*I30 -> 10701144 | K25: =J25*J30 -> 10449461 | L25: =K25*K30 -> 10215857 | M25: =L25*L30 -> 10037036 | ... Z25: =Y25*Y30 -> 9883068.1 | AA25: =+Z25 -> 9883068.1 | AB25: =+E25 -> 11277873 | AC25: =AA25-AB25 -> -1394804.9
A26: AO23 | B26: 3Q24 | C26: =IF(Triangulo2!D38=0,"-",Triangulo2!D38) -> 4926500 | D26: =IF(Triangulo2!E38=0,"-",Triangulo2!E38) -> 9321834 | E26: =D26*D30 -> 8774273.3 | F26: =E26*E30 -> 9550301.6 | G26: =F26*F30 -> 9151471.6 | H26: =G26*G30 -> 8889653.2 | I26: =H26*H30 -> 8555049.5 | J26: =I26*I30 -> 8325573.8 | K26: =J26*J30 -> 8129761.9 | L26: =K26*K30 -> 7948016.7 | ... Z26: =Y26*Y30 -> 7689104.2 | AA26: =+Z26 -> 7689104.2 | AB26: =+D26 -> 9321834 | AC26: =AA26-AB26 -> -1632729.8
A27: AO24 | B27: 4Q24 | C27: =IF(Triangulo2!D39=0,"-",Triangulo2!D39) -> 5149958 | D27: =C27*C30 -> 8420852.1 | E27: =D27*D30 -> 7926214.7 | F27: =E27*E30 -> 8627237.7 | G27: =F27*F30 -> 8266955.7 | H27: =G27*G30 -> 8030442.8 | I27: =H27*H30 -> 7728179.5 | J27: =I27*I30 -> 7520883.3 | K27: =J27*J30 -> 7343997.2 | ... Z27: =Y27*Y30 -> 6945930.3 | AA27: =+Z27 -> 6945930.3 | AB27: =+C27 -> 5149958 | AC27: =AA27-AB27 -> 1795972.3
A28: Numerado | C28: =SUM(D4:D26) -> 206842466 | D28: =SUM(E4:E25) -> 185918351 | E28: =SUM(F4:F24) -> 190086311 | F28: =SUM(G4:G23) -> 169944758 | G28: =SUM(H4:H22) -> 151215989 | H28: =SUM(I4:I21) -> 120894550 | I28: =SUM(J4:J20) -> 107366603 | J28: =SUM(K4:K19) -> 92710889 | K28: =SUM(L4:L18) -> 77565604 | L28: =SUM(M4:M17) -> 73778039 | M28: =SUM(N4:N16) -> 68065878 | N28: =SUM(O4:O15) -> 61979882 | O28: =SUM(P4:P14) -> 54600704 | P28: =SUM(Q4:Q13) -> 50273485 | Q28: =SUM(R4:R12) -> 45900239 | R28: =SUM(S4:S11) -> 39858625 | S28: =SUM(T4:T10) -> 33315873 | T28: =SUM(U4:U9) -> 30670587 | U28: =SUM(V4:V8) -> 28179530 | V28: =SUM(W4:W7) -> 23567356 | W28: =SUM(X4:X6) -> 18521256 | X28: =SUM(Y4:Y5) -> 13810401 | Y28: =SUM(Z4) -> 5814528
A29: Denominador | C29: =SUM(C4:C26) -> 126499076 | D29: =SUM(D4:D25) -> 197520632 | E29: =SUM(E4:E24) -> 174640478 | F29: =SUM(F4:F23) -> 177351116 | G29: =SUM(G4:G22) -> 155669608 | H29: =SUM(H4:H21) -> 125622958 | I29: =SUM(I4:I20) -> 110325921 | J29: =SUM(J4:J19) -> 94943906 | K29: =SUM(K4:K18) -> 79339276 | L29: =SUM(L4:L17) -> 75092479 | M29: =SUM(M4:M16) -> 68606234 | N29: =SUM(N4:N15) -> 62221110 | O29: =SUM(O4:O14) -> 54713041 | P29: =SUM(P4:P13) -> 50316051 | Q29: =SUM(Q4:Q12) -> 45919072 | R29: =SUM(R4:R11) -> 39862941 | S29: =SUM(S4:S10) -> 33319740 | T29: =SUM(T4:T9) -> 30673592 | U29: =SUM(U4:U8) -> 28180359 | V29: =SUM(V4:V7) -> 23567495 | W29: =SUM(W4:W6) -> 18521233 | X29: =SUM(X4:X5) -> 13810386 | Y29: =SUM(Y4) -> 5814527
A30: Factores | C30: =C28/C29 -> 1.6351303 | D30: =D28/D29 -> 0.94126041 | E30: =E28/E29 -> 1.0884436 | F30: =F28/F29 -> 0.95823901 | G30: =G28/G29 -> 0.97139057 | H30: =H28/H29 -> 0.96236032 | I30: =I28/I29 -> 0.97317658 | J30: =J28/J29 -> 0.97648067 | ... Y30: =Y28/Y29 -> 1.0000002 | Z30: 1
A31: Factor acum. F_j^{→25} | C31: =+C30*D31 -> 1.3487353 | D31: =+D30*E31 -> 0.82484886 | E31: =+E30*F31 -> 0.87632376 | F31: =+F30*G31 -> 0.80511637 | G31: =+G30*H31 -> 0.84020413 | H31: =+H30*I31 -> 0.86494985 | I31: =+I30*J31 -> 0.89877963 | J31: =+J30*K31 -> 0.92355246 | ... Y31: =+Y30*Z31 -> 1.0000002 | Z31: 1
A32: % Desarrollado = 1/F_j | C32: =1/C31 -> 0.74143531 | D32: =1/D31 -> 1.2123433 | E32: =1/E31 -> 1.1411308 | F32: =1/F31 -> 1.2420565 | G32: =1/G31 -> 1.190187 | H32: =1/H31 -> 1.1561364 | I32: =1/I31 -> 1.1126198 | J32: =1/J31 -> 1.0827755 | ... Y32: =1/Y31 -> 0.99999983 | Z32: 1
A33: Total | AA33: =+SUM(AA4:AA27) -> 1.775597e+08 | AB33: =+SUM(AB4:AB27) -> 189999707 | AC33: =SUM(AC4:AC28) -> -12440003

Sheet 2_BF
A4: ELR a priori (BF): | B4: 0.55
A7: AO | B7: Trim. | C7: Pagado actual (diagonal) | D7: Prima Devengada | E7: % Des. (de 2_Factores) | F7: % No-Des. =1−%Des | G7: Apriori =Prima×ELR | H7: IBNR_BF =Apriori×%NoDes | I7: Último_BF =Pag+IBNR
A8: AO001 | B8: 1Q19 | C8: =+Triangulo2!E78 -> 5814528 | D8: =+Triangulo2!D78 -> 20213006 | E8: 1 | F8: =1-E8 -> 0 | G8: =+$B$4*D8 -> 11117153 | H8: =+G8*F8 -> 0 | I8: =+H8+C8 -> 5814528
A9: AO002 | B9: 2Q19 | C9: =+Triangulo2!E79 -> 7995874 | D9: =+Triangulo2!D79 -> 22641632 | E9: =+'2_CL'!Y32 -> 0.99999983 | F9: =1-E9 -> 1.7198301e-07 | G9: =+$B$4*D9 -> 12452897 | H9: =+G9*F9 -> 2.1416867 | I9: =+H9+C9 -> 7995876.1
A10: AO003 | B10: 3Q19 | C10: =+Triangulo2!E80 -> 4710870 | D10: =+Triangulo2!D80 -> 19561331 | E10: =+'2_CL'!X32 -> 0.99999874 | F10: =1-E10 -> 1.2581207e-06 | G10: =+$B$4*D10 -> 10758732 | H10: =+G10*F10 -> 13.535784 | I10: =+H10+C10 -> 4710883.5
A11: AO004 | B11: 4Q19 | C11: =+Triangulo2!E81 -> 5046123 | D11: =+Triangulo2!D81 -> 9083808.1 | E11: =+'2_CL'!W32 -> 0.9999975 | F11: =1-E11 -> 2.4999356e-06 | G11: =+$B$4*D11 -> 4996094.5 | H11: =+G11*F11 -> 12.489914 | I11: =+H11+C11 -> 5046135.5
A12: AO005 | B12: 1Q20 | C12: =+Triangulo2!E82 -> 4612035 | D12: =+Triangulo2!D82 -> 18994503 | E12: =+'2_CL'!V32 -> 1.0000034 | F12: =1-E12 -> -3.3980384e-06 | G12: =+$B$4*D12 -> 10446976 | H12: =+G12*F12 -> -35.499227 | I12: =+H12+C12 -> 4611999.5
A13: AO006 | B13: 2Q20 | C13: =+Triangulo2!E83 -> 2490228 | D13: =+Triangulo2!D83 -> -1004591.6 | E13: =+'2_CL'!U32 -> 1.0000328 | F13: =1-E13 -> -3.2816656e-05 | G13: =+$B$4*D13 -> -552525.39 | H13: =+G13*F13 -> 18.132036 | I13: =+H13+C13 -> 2490246.1
A14: AO007 | B14: 3Q20 | C14: =+Triangulo2!E84 -> 2642281 | D14: =+Triangulo2!D84 -> -5936695 | E14: =+'2_CL'!T32 -> 1.0001308 | F14: =1-E14 -> -0.00013079648 | G14: =+$B$4*D14 -> -3265182.3 | H14: =+G14*F14 -> 427.07434 | I14: =+H14+C14 -> 2642708.1
A15: AO008 | B15: 4Q20 | C15: =+Triangulo2!E85 -> 6538885 | D15: =+Triangulo2!D85 -> 4268257.7 | E15: =+'2_CL'!S32 -> 1.0002469 | F15: =1-E15 -> -0.00024688246 | G15: =+$B$4*D15 -> 2347541.7 | H15: =+G15*F15 -> -579.56687 | I15: =+H15+C15 -> 6538305.4
A16: AO009 | B16: 1Q21 | C16: =+Triangulo2!E86 -> 6037298 | D16: =+Triangulo2!D86 -> 16145782 | E16: =+'2_CL'!R32 -> 1.0003552 | F16: =1-E16 -> -0.0003551919 | G16: =+$B$4*D16 -> 8880180.4 | H16: =+G16*F16 -> -3154.1682 | I16: =+H16+C16 -> 6034143.8
A17: AO010 | B17: 2Q21 | C17: =+Triangulo2!E87 -> 4354413 | D17: =+Triangulo2!D87 -> 16851117 | E17: =+'2_CL'!Q32 -> 1.0007656 | F17: =1-E17 -> -0.00076564051 | G17: =+$B$4*D17 -> 9268114.2 | H17: =+G17*F17 -> -7096.0437 | I17: =+H17+C17 -> 4347317
A18: AO011 | B18: 3Q21 | C18: =+Triangulo2!E88 -> 4284653 | D18: =+Triangulo2!D88 -> -4179642.8 | E18: =+'2_CL'!P32 -> 1.001613 | F18: =1-E18 -> -0.0016129776 | G18: =+$B$4*D18 -> -2298803.5 | H18: =+G18*F18 -> 3707.9187 | I18: =+H18+C18 -> 4288360.9
A19: AO012 | B19: 4Q21 | C19: =+Triangulo2!E89 -> 7266841 | D19: =+Triangulo2!D89 -> 3503669 | E19: =+'2_CL'!O32 -> 1.0036737 | F19: =1-E19 -> -0.0036737239 | G19: =+$B$4*D19 -> 1927017.9 | H19: =+G19*F19 -> -7079.3319 | I19: =+H19+C19 -> 7259761.7
A20: AO013 | B20: 1Q22 | C20: =+Triangulo2!E90 -> 5844768 | D20: =+Triangulo2!D90 -> 17466795 | E20: =+'2_CL'!N32 -> 1.0075801 | F20: =1-E20 -> -0.0075800593 | G20: =+$B$4*D20 -> 9606737.5 | H20: =+G20*F20 -> -72819.64 | I20: =+H20+C20 -> 5771948.4
A21: AO014 | B21: 2Q22 | C21: =+Triangulo2!E91 -> 5171805 | D21: =+Triangulo2!D91 -> 15433826 | E21: =+'2_CL'!M32 -> 1.015579 | F21: =1-E21 -> -0.015578956 | G21: =+$B$4*D21 -> 8488604.1 | H21: =+G21*F21 -> -132243.59 | I21: =+H21+C21 -> 5039561.4
A22: AO015 | B22: 3Q22 | C22: =+Triangulo2!E92 -> 2473125 | D22: =+Triangulo2!D92 -> 15413448 | E22: =+'2_CL'!L32 -> 1.0336727 | F22: =1-E22 -> -0.033672655 | G22: =+$B$4*D22 -> 8477396.3 | H22: =+G22*F22 -> -285456.44 | I22: =+H22+C22 -> 2187668.6
A23: AO016 | B23: 4Q22 | C23: =+Triangulo2!E93 -> 13371613 | D23: =+Triangulo2!D93 -> 19246632 | E23: =+'2_CL'!K32 -> 1.0573094 | F23: =1-E23 -> -0.057309372 | G23: =+$B$4*D23 -> 10585648 | H23: =+G23*F23 -> -606656.81 | I23: =+H23+C23 -> 12764956
A24: AO017 | B24: 1Q23 | C24: =+Triangulo2!E94 -> 12422697 | D24: =+Triangulo2!D94 -> 32511745 | E24: =+'2_CL'!J32 -> 1.0827755 | F24: =1-E24 -> -0.082775526 | G24: =+$B$4*D24 -> 17881460 | H24: =+G24*F24 -> -1480147.2 | I24: =+H24+C24 -> 10942550
A25: AO018 | B25: 2Q23 | C25: =+Triangulo2!E95 -> 10568629 | D25: =+Triangulo2!D95 -> 24625764 | E25: =+'2_CL'!I32 -> 1.1126198 | F25: =1-E25 -> -0.11261979 | G25: =+$B$4*D25 -> 13544170 | H25: =+G25*F25 -> -1525341.6 | I25: =+H25+C25 -> 9043287.4
A26: AO019 | B26: 3Q23 | C26: =+Triangulo2!E96 -> 25593031 | D26: =+Triangulo2!D96 -> 52753854 | E26: =+'2_CL'!H32 -> 1.1561364 | F26: =1-E26 -> -0.15613639 | G26: =+$B$4*D26 -> 29014619 | H26: =+G26*F26 -> -4530238 | I26: =+H26+C26 -> 21062793
A27: AO020 | B27: 4Q23 | C27: =+Triangulo2!E97 -> 14275150 | D27: =+Triangulo2!D97 -> 31407599 | E27: =+'2_CL'!G32 -> 1.190187 | F27: =1-E27 -> -0.19018697 | G27: =+$B$4*D27 -> 17274180 | H27: =+G27*F27 -> -3285323.8 | I27: =+H27+C27 -> 10989826
A28: AO021 | B28: 1Q24 | C28: =+Triangulo2!E98 -> 12735195 | D28: =+Triangulo2!D98 -> 30304299 | E28: =+'2_CL'!F32 -> 1.2420565 | F28: =1-E28 -> -0.24205647 | G28: =+$B$4*D28 -> 16667364 | H28: =+G28*F28 -> -4034443.4 | I28: =+H28+C28 -> 8700751.6
A29: AO022 | B29: 2Q24 | C29: =+Triangulo2!E99 -> 11277873 | D29: =+Triangulo2!D99 -> 11368458 | E29: =+'2_CL'!E32 -> 1.1411308 | F29: =1-E29 -> -0.14113076 | G29: =+$B$4*D29 -> 6252651.8 | H29: =+G29*F29 -> -882441.49 | I29: =+H29+C29 -> 10395432
A30: AO023 | B30: 3Q24 | C30: =+Triangulo2!E100 -> 9321834 | D30: =+Triangulo2!D100 -> 9631669.7 | E30: =+'2_CL'!D32 -> 1.2123433 | F30: =1-E30 -> -0.21234331 | G30: =+$B$4*D30 -> 5297418.3 | H30: =+G30*F30 -> -1124871.3 | I30: =+H30+C30 -> 8196962.7
A31: AO024 | B31: 4Q24 | C31: =+Triangulo2!E101 -> 5149958 | D31: =+Triangulo2!D101 -> 32995208 | E31: =+'2_CL'!C32 -> 0.74143531 | F31: =1-E31 -> 0.25856469 | G31: =+$B$4*D31 -> 18147364 | H31: =+G31*F31 -> 4692267.6 | I31: =+H31+C31 -> 9842225.6
A32: TOTAL | H32: =SUM(H8:H31) -> -13281479 | I32: =SUM(I8:I31) -> 1.7671823e+08

Sheet 2_CC
A1: CAPE COD · ELR_CC = Σ Pagados / Σ(Prima×%Des) · ELR endógeno calculado en B4
A2: ELR_CC en B4 calculado automáticamente · % Des de 4_BF · Primas de 1_Triangulo
A4: ELR Cape Cod: | B4: =SUM(C8:C31)/SUM(G8:G31) -> 0.43433506 | C4: Σ Pagados / Σ(Prima×%Des) — se actualiza automáticamente
A7: AO | B7: Trim. | C7: Pagado actual | D7: Prima Devengada | E7: % Des. | F7: % No-Des. | G7: Prima × %Des | H7: IBNR_CC =Prima×%NoDes×ELR_CC | I7: Último_CC
A8: =+'1_BF'!A8 -> AO001 | B8: =+'1_BF'!B8 -> 1Q19 | C8: =+'2_BF'!C8 -> 5814528 | D8: =+'2_BF'!D8 -> 20213006 | E8: =+'2_BF'!E8 -> 1 | F8: =1-E8 -> 0 | G8: =D8*E8 -> 20213006 | H8: =D8*F8*$B$4 -> 0 | I8: =C8+H8 -> 5814528
A9: =+'1_BF'!A9 -> AO002 | B9: =+'1_BF'!B9 -> 2Q19 | C9: =+'2_BF'!C9 -> 7995874 | D9: =+'2_BF'!D9 -> 22641632 | E9: =+'2_BF'!E9 -> 0.99999983 | F9: =1-E9 -> 1.7198301e-07 | G9: =D9*E9 -> 22641628 | H9: =D9*F9*$B$4 -> 1.6912903 | I9: =C9+H9 -> 7995875.7
A10: =+'1_BF'!A10 -> AO003 | B10: =+'1_BF'!B10 -> 3Q19 | C10: =+'2_BF'!C10 -> 4710870 | D10: =+'2_BF'!D10 -> 19561331 | E10: =+'2_BF'!E10 -> 0.99999874 | F10: =1-E10 -> 1.2581207e-06 | G10: =D10*E10 -> 19561307 | H10: =D10*F10*$B$4 -> 10.68921 | I10: =C10+H10 -> 4710880.7
A11: =+'1_BF'!A11 -> AO004 | B11: =+'1_BF'!B11 -> 4Q19 | C11: =+'2_BF'!C11 -> 5046123 | D11: =+'2_BF'!D11 -> 9083808.1 | E11: =+'2_BF'!E11 -> 0.9999975 | F11: =1-E11 -> 2.4999356e-06 | G11: =D11*E11 -> 9083785.4 | H11: =D11*F11*$B$4 -> 9.8632868 | I11: =C11+H11 -> 5046132.9
A12: =+'1_BF'!A12 -> AO005 | B12: =+'1_BF'!B12 -> 1Q20 | C12: =+'2_BF'!C12 -> 4612035 | D12: =+'2_BF'!D12 -> 18994503 | E12: =+'2_BF'!E12 -> 1.0000034 | F12: =1-E12 -> -3.3980384e-06 | G12: =D12*E12 -> 18994567 | H12: =D12*F12*$B$4 -> -28.033744 | I12: =C12+H12 -> 4612007
A13: =+'1_BF'!A13 -> AO006 | B13: =+'1_BF'!B13 -> 2Q20 | C13: =+'2_BF'!C13 -> 2490228 | D13: =+'2_BF'!D13 -> -1004591.6 | E13: =+'2_BF'!E13 -> 1.0000328 | F13: =1-E13 -> -3.2816656e-05 | G13: =D13*E13 -> -1004624.6 | H13: =D13*F13*$B$4 -> 14.318871 | I13: =C13+H13 -> 2490242.3
A14: =+'1_BF'!A14 -> AO007 | B14: =+'1_BF'!B14 -> 3Q20 | C14: =+'2_BF'!C14 -> 2642281 | D14: =+'2_BF'!D14 -> -5936695 | E14: =+'2_BF'!E14 -> 1.0001308 | F14: =1-E14 -> -0.00013079648 | G14: =D14*E14 -> -5937471.5 | H14: =D14*F14*$B$4 -> 337.26065 | I14: =C14+H14 -> 2642618.3
A15: =+'1_BF'!A15 -> AO008 | B15: =+'1_BF'!B15 -> 4Q20 | C15: =+'2_BF'!C15 -> 6538885 | D15: =+'2_BF'!D15 -> 4268257.7 | E15: =+'2_BF'!E15 -> 1.0002469 | F15: =1-E15 -> -0.00024688246 | G15: =D15*E15 -> 4269311.4 | H15: =D15*F15*$B$4 -> -457.68402 | I15: =C15+H15 -> 6538427.3
A16: =+'1_BF'!A16 -> AO009 | B16: =+'1_BF'!B16 -> 1Q21 | C16: =+'2_BF'!C16 -> 6037298 | D16: =+'2_BF'!D16 -> 16145782 | E16: =+'2_BF'!E16 -> 1.0003552 | F16: =1-E16 -> -0.0003551919 | G16: =D16*E16 -> 16151517 | H16: =D16*F16*$B$4 -> -2490.847 | I16: =C16+H16 -> 6034807.2
A17: =+'1_BF'!A17 -> AO010 | B17: =+'1_BF'!B17 -> 2Q21 | C17: =+'2_BF'!C17 -> 4354413 | D17: =+'2_BF'!D17 -> 16851117 | E17: =+'2_BF'!E17 -> 1.0007656 | F17: =1-E17 -> -0.00076564051 | G17: =D17*E17 -> 16864019 | H17: =D17*F17*$B$4 -> -5603.7465 | I17: =C17+H17 -> 4348809.3
A18: =+'1_BF'!A18 -> AO011 | B18: =+'1_BF'!B18 -> 3Q21 | C18: =+'2_BF'!C18 -> 4284653 | D18: =+'2_BF'!D18 -> -4179642.8 | E18: =+'2_BF'!E18 -> 1.001613 | F18: =1-E18 -> -0.0016129776 | G18: =D18*E18 -> -4186384.4 | H18: =D18*F18*$B$4 -> 2928.1438 | I18: =C18+H18 -> 4287581.1
A19: =+'1_BF'!A19 -> AO012 | B19: =+'1_BF'!B19 -> 4Q21 | C19: =+'2_BF'!C19 -> 7266841 | D19: =+'2_BF'!D19 -> 3503669 | E19: =+'2_BF'!E19 -> 1.0036737 | F19: =1-E19 -> -0.0036737239 | G19: =D19*E19 -> 3516540.5 | H19: =D19*F19*$B$4 -> -5590.5492 | I19: =C19+H19 -> 7261250.5
... A31: =+'1_BF'!A31 -> AO024 | B31: =+'1_BF'!B31 -> 4Q24 | C31: =+'2_BF'!C31 -> 5149958 | D31: =+'2_BF'!D31 -> 32995208 | E31: =+'2_BF'!E31 -> 0.74143531 | F31: =1-E31 -> 0.25856469 | G31: =D31*E31 -> 24463812 | H31: =D31*F31*$B$4 -> 3705484.3 | I31: =C31+H31 -> 8855442.3
A32: TOTAL | G32: =SUM(G8:G31) -> 4.3744962e+08 | H32: =SUM(H8:H31) -> -10488386 | I32: =SUM(I8:I31) -> 1.7951132e+08

Sheet 2_Duration
B1: DURACIÓN DE CARTERA — AUTO DAÑOS / RC PERSONAL
B2: Metodología: Macaulay · Modificada · Efectiva | Fuente: D'Arcy & Gorvett (2000), PCAS | N2: Trimestral
N3: Anual
B4: PARÁMETROS DE ENTRADA | I4: Trimestral
B5: Reserva total (MXN) | C5: ='2_CL'!AC33 -> -12440003 | D5: Monto total de la reserva IBNR a valuar
B6: Tasa de descuento (r) | C6: =IF(I4="Anual",Triangulo2!E5, POWER(1+Triangulo2!E5,0.25)-1) -> 0.014673846 | D6: Tasa libre de riesgo (CETES / curva CNSF) | J6: 0.04
B7: Shock de tasa (Δr) | C7: 0.01 | D7: Desplazamiento para calcular duración efectiva (±100 bps)
B8: Correlación tasas-inflación | C8: 0.4 | D8: ρ: usada para ajustar D_Efectiva (D'Arcy 2000, Tabla 3)
B10: A. PATRÓN DE DESARROLLO Y FLUJOS DE PAGO
B11: Trimestre (t) | C11: % Pago Acumulado | D11: % Pago Incremental | E11: Flujo Nominal (MXN) | F11: PV del Flujo (MXN) | G11: Peso = PV/PV_Total | H11: t × Peso | I11: t(t+1)×PV/(1+r)² (Convexidad)
B12: =IF(I4= "Anual",1,0.25) -> 0.25 | C12: ='2_BF'!E31 -> 0.74143531 | D12: =C12 -> 0.74143531 | E12: =D12*$C$5 -> -9223457.8 | F12: =IF($I$4="Anual",E12/(1+$C$6)^B12,E12/(1+$C$6)^(B12*4)) -> -9090071.5 | G12: =F12/$F$36 -> 0.73161522 | H12: =B12*G12 -> 0.1829038 | I12: =B12*(B12+1)*F12/((1+$C$6)^2)/$F$36 -> 0.22206485 | J12: =+B12*F12 -> -2272517.9
B13: =IF($I$4="Anual",B12+1,B12+0.25) -> 0.5 | C13: ='2_BF'!E30 -> 1.2123433 | D13: =C13-C12 -> 0.470908 | E13: =D13*$C$5 -> -5858097.1 | F13: =IF($I$4="Anual",E13/(1+$C$6)^B13,E13/(1+$C$6)^(B13*4)) -> -5689886.9 | G13: =F13/$F$36 -> 0.45795105 | H13: =B13*G13 -> 0.22897553 | I13: =B13*(B13+1)*F13/((1+$C$6)^2)/$F$36 -> 0.33360104 | J13: =+B13*F13 -> -2844943.4
B14: =IF($I$4="Anual",B13+1,B13+0.25) -> 0.75 | C14: ='2_BF'!E29 -> 1.1411308 | D14: =C14-C13 -> -0.071212549 | E14: =D14*$C$5 -> 885884.36 | F14: =IF($I$4="Anual",E14/(1+$C$6)^B14,E14/(1+$C$6)^(B14*4)) -> 848003.48 | G14: =F14/$F$36 -> -0.068251636 | H14: =B14*G14 -> -0.051188727 | I14: =B14*(B14+1)*F14/((1+$C$6)^2)/$F$36 -> -0.087008052 | J14: =+B14*F14 -> 636002.61
B15: =IF($I$4="Anual",B14+1,B14+0.25) -> 1 | C15: ='2_BF'!E28 -> 1.2420565 | D15: =C15-C14 -> 0.10092572 | E15: =D15*$C$5 -> -1255516.2 | F15: =IF($I$4="Anual",E15/(1+$C$6)^B15,E15/(1+$C$6)^(B15*4)) -> -1184449.3 | G15: =F15/$F$36 -> 0.095330506 | H15: =B15*G15 -> 0.095330506 | I15: =B15*(B15+1)*F15/((1+$C$6)^2)/$F$36 -> 0.18518635 | J15: =+B15*F15 -> -1184449.3
B16: =IF($I$4="Anual",B15+1,B15+0.25) -> 1.25 | C16: ='2_BF'!E27 -> 1.190187 | D16: =C16-C15 -> -0.051869507 | E16: =D16*$C$5 -> 645256.84 | F16: =IF($I$4="Anual",E16/(1+$C$6)^B16,E16/(1+$C$6)^(B16*4)) -> 599929.59 | G16: =F16/$F$36 -> -0.048285387 | H16: =B16*G16 -> -0.060356734 | I16: =B16*(B16+1)*F16/((1+$C$6)^2)/$F$36 -> -0.13190319 | J16: =+B16*F16 -> 749911.99
B17: =IF($I$4="Anual",B16+1,B16+0.25) -> 1.5 | C17: ='2_BF'!E26 -> 1.1561364 | D17: =C17-C16 -> -0.034050573 | E17: =D17*$C$5 -> 423589.24 | F17: =IF($I$4="Anual",E17/(1+$C$6)^B17,E17/(1+$C$6)^(B17*4)) -> 388137.96 | G17: =F17/$F$36 -> -0.031239319 | H17: =B17*G17 -> -0.046858978 | I17: =B17*(B17+1)*F17/((1+$C$6)^2)/$F$36 -> -0.11378366 | J17: =+B17*F17 -> 582206.94
B18: =IF($I$4="Anual",B17+1,B17+0.25) -> 1.75 | C18: ='2_BF'!E25 -> 1.1126198 | D18: =C18-C17 -> -0.043516604 | E18: =D18*$C$5 -> 541346.71 | F18: =IF($I$4="Anual",E18/(1+$C$6)^B18,E18/(1+$C$6)^(B18*4)) -> 488866.45 | G18: =F18/$F$36 -> -0.03934646 | H18: =B18*G18 -> -0.068856305 | I18: =B18*(B18+1)*F18/((1+$C$6)^2)/$F$36 -> -0.18391768 | J18: =+B18*F18 -> 855516.29
B19: =IF($I$4="Anual",B18+1,B18+0.25) -> 2 | C19: ='2_BF'!E24 -> 1.0827755 | D19: =C19-C18 -> -0.029844263 | E19: =D19*$C$5 -> 371262.73 | F19: =IF($I$4="Anual",E19/(1+$C$6)^B19,E19/(1+$C$6)^(B19*4)) -> 330422.51 | G19: =F19/$F$36 -> -0.026594085 | H19: =B19*G19 -> -0.05318817 | I19: =B19*(B19+1)*F19/((1+$C$6)^2)/$F$36 -> -0.15498275 | J19: =+B19*F19 -> 660845.02
B20: =IF($I$4="Anual",B19+1,B19+0.25) -> 2.25 | C20: ='2_BF'!E23 -> 1.0573094 | D20: =C20-C19 -> -0.025466154 | E20: =D20*$C$5 -> 316799.05 | F20: =IF($I$4="Anual",E20/(1+$C$6)^B20,E20/(1+$C$6)^(B20*4)) -> 277872.56 | G20: =F20/$F$36 -> -0.022364598 | H20: =B20*G20 -> -0.050320346 | I20: =B20*(B20+1)*F20/((1+$C$6)^2)/$F$36 -> -0.15884518 | J20: =+B20*F20 -> 625213.27
B21: =IF($I$4="Anual",B20+1,B20+0.25) -> 2.5 | C21: ='2_BF'!E22 -> 1.0336727 | D21: =C21-C20 -> -0.023636717 | E21: =D21*$C$5 -> 294040.84 | F21: =IF($I$4="Anual",E21/(1+$C$6)^B21,E21/(1+$C$6)^(B21*4)) -> 254180.95 | G21: =F21/$F$36 -> -0.020457776 | H21: =B21*G21 -> -0.051144441 | I21: =B21*(B21+1)*F21/((1+$C$6)^2)/$F$36 -> -0.17386555 | J21: =+B21*F21 -> 635452.37
B22: =IF($I$4="Anual",B21+1,B21+0.25) -> 2.75 | C22: ='2_BF'!E21 -> 1.015579 | D22: =C22-C21 -> -0.018093699 | E22: =D22*$C$5 -> 225085.67 | F22: =IF($I$4="Anual",E22/(1+$C$6)^B22,E22/(1+$C$6)^(B22*4)) -> 191759.43 | G22: =F22/$F$36 -> -0.015433775 | H22: =B22*G22 -> -0.04244288 | I22: =B22*(B22+1)*F22/((1+$C$6)^2)/$F$36 -> -0.15459064 | J22: =+B22*F22 -> 527338.42
B23: =IF($I$4="Anual",B22+1,B22+0.25) -> 3 | C23: ='2_BF'!E20 -> 1.0075801 | D23: =C23-C22 -> -0.0079988968 | E23: =D23*$C$5 -> 99506.303 | F23: =IF($I$4="Anual",E23/(1+$C$6)^B23,E23/(1+$C$6)^(B23*4)) -> 83547.411 | G23: =F23/$F$36 -> -0.0067243208 | H23: =B23*G23 -> -0.020172962 | I23: =B23*(B23+1)*F23/((1+$C$6)^2)/$F$36 -> -0.078374853 | J23: =+B23*F23 -> 250642.23
B24: =IF($I$4="Anual",B23+1,B23+0.25) -> 3.25 | C24: ='2_BF'!E19 -> 1.0036737 | D24: =C24-C23 -> -0.0039063354 | E24: =D24*$C$5 -> 48594.825 | F24: =IF($I$4="Anual",E24/(1+$C$6)^B24,E24/(1+$C$6)^(B24*4)) -> 40211.101 | G24: =F24/$F$36 -> -0.003236394 | H24: =B24*G24 -> -0.010518281 | I24: =B24*(B24+1)*F24/((1+$C$6)^2)/$F$36 -> -0.043419094 | J24: =+B24*F24 -> 130686.08
B25: =IF($I$4="Anual",B24+1,B24+0.25) -> 3.5 | C25: ='2_BF'!E18 -> 1.001613 | D25: =C25-C24 -> -0.0020607463 | E25: =D25*$C$5 -> 25635.691 | F25: =IF($I$4="Anual",E25/(1+$C$6)^B25,E25/(1+$C$6)^(B25*4)) -> 20906.171 | G25: =F25/$F$36 -> -0.001682635 | H25: =B25*G25 -> -0.0058892226 | I25: =B25*(B25+1)*F25/((1+$C$6)^2)/$F$36 -> -0.025740534 | J25: =+B25*F25 -> 73171.598
B26: =IF($I$4="Anual",B25+1,B25+0.25) -> 3.75 | C26: ='2_BF'!E17 -> 1.0007656 | D26: =C26-C25 -> -0.00084733713 | E26: =D26*$C$5 -> 10540.877 | F26: =IF($I$4="Anual",E26/(1+$C$6)^B26,E26/(1+$C$6)^(B26*4)) -> 8471.8789 | G26: =F26/$F$36 -> -0.00068185993 | H26: =B26*G26 -> -0.0025569747 | I26: =B26*(B26+1)*F26/((1+$C$6)^2)/$F$36 -> -0.011796879 | J26: =+B26*F26 -> 31769.546
B27: =IF($I$4="Anual",B26+1,B26+0.25) -> 4 | C27: ='2_BF'!E16 -> 1.0003552 | D27: =C27-C26 -> -0.00041044861 | E27: =D27*$C$5 -> 5105.9821 | F27: =IF($I$4="Anual",E27/(1+$C$6)^B27,E27/(1+$C$6)^(B27*4)) -> 4044.4161 | G27: =F27/$F$36 -> -0.00032551519 | H27: =B27*G27 -> -0.0013020608 | I27: =B27*(B27+1)*F27/((1+$C$6)^2)/$F$36 -> -0.006323366 | J27: =+B27*F27 -> 16177.664
B28: =IF($I$4="Anual",B27+1,B27+0.25) -> 4.25 | C28: ='2_BF'!E15 -> 1.0002469 | D28: =C28-C27 -> -0.00010830944 | E28: =D28*$C$5 -> 1347.3699 | F28: =IF($I$4="Anual",E28/(1+$C$6)^B28,E28/(1+$C$6)^(B28*4)) -> 1051.809 | G28: =F28/$F$36 -> -8.4654945e-05 | H28: =B28*G28 -> -0.00035978352 | I28: =B28*(B28+1)*F28/((1+$C$6)^2)/$F$36 -> -0.0018346264 | J28: =+B28*F28 -> 4470.1885
B29: =IF($I$4="Anual",B28+1,B28+0.25) -> 4.5 | C29: ='2_BF'!E14 -> 1.0001308 | D29: =C29-C28 -> -0.00011608598 | E29: =D29*$C$5 -> 1444.11 | F29: =IF($I$4="Anual",E29/(1+$C$6)^B29,E29/(1+$C$6)^(B29*4)) -> 1111.0251 | G29: =F29/$F$36 -> -8.9420957e-05 | H29: =B29*G29 -> -0.0004023943 | I29: =B29*(B29+1)*F29/((1+$C$6)^2)/$F$36 -> -0.0021496194 | J29: =+B29*F29 -> 4999.6131
B30: =IF($I$4="Anual",B29+1,B29+0.25) -> 4.75 | C30: ='2_BF'!E13 -> 1.0000328 | D30: =C30-C29 -> -9.7979821e-05 | E30: =D30*$C$5 -> 1218.8693 | F30: =IF($I$4="Anual",E30/(1+$C$6)^B30,E30/(1+$C$6)^(B30*4)) -> 924.17514 | G30: =F30/$F$36 -> -7.4382318e-05 | H30: =B30*G30 -> -0.00035331601 | I30: =B30*(B30+1)*F30/((1+$C$6)^2)/$F$36 -> -0.0019732324 | J30: =+B30*F30 -> 4389.8319
B31: =IF($I$4="Anual",B30+1,B30+0.25) -> 5 | C31: ='2_BF'!E12 -> 1.0000034 | D31: =C31-C30 -> -2.9418618e-05 | E31: =D31*$C$5 -> 365.9677 | F31: =IF($I$4="Anual",E31/(1+$C$6)^B31,E31/(1+$C$6)^(B31*4)) -> 273.47236 | G31: =F31/$F$36 -> -2.2010447e-05 | H31: =B31*G31 -> -0.00011005224 | I31: =B31*(B31+1)*F31/((1+$C$6)^2)/$F$36 -> -0.00064135308 | J31: =+B31*F31 -> 1367.3618
B32: =IF($I$4="Anual",B31+1,B31+0.25) -> 5.25 | C32: ='2_BF'!E11 -> 0.9999975 | D32: =C32-C31 -> -5.897974e-06 | E32: =D32*$C$5 -> 73.370817 | F32: =IF($I$4="Anual",E32/(1+$C$6)^B32,E32/(1+$C$6)^(B32*4)) -> 54.034055 | G32: =F32/$F$36 -> -4.3489357e-06 | H32: =B32*G32 -> -2.2831913e-05 | I32: =B32*(B32+1)*F32/((1+$C$6)^2)/$F$36 -> -0.00013860196 | J32: =+B32*F32 -> 283.67879
B33: =IF($I$4="Anual",B32+1,B32+0.25) -> 5.5 | C33: ='2_BF'!E10 -> 0.99999874 | D33: =C33-C32 -> 1.2418149e-06 | E33: =D33*$C$5 -> -15.448181 | F33: =IF($I$4="Anual",E33/(1+$C$6)^B33,E33/(1+$C$6)^(B33*4)) -> -11.21231 | G33: =F33/$F$36 -> 9.0242377e-07 | H33: =B33*G33 -> 4.9633307e-06 | I33: =B33*(B33+1)*F33/((1+$C$6)^2)/$F$36 -> 3.1335284e-05 | J33: =+B33*F33 -> -61.667705
B34: =IF($I$4="Anual",B33+1,B33+0.25) -> 5.75 | C34: ='2_BF'!E9 -> 0.99999983 | D34: =C34-C33 -> 1.0861377e-06 | E34: =D34*$C$5 -> -13.511557 | F34: =IF($I$4="Anual",E34/(1+$C$6)^B34,E34/(1+$C$6)^(B34*4)) -> -9.6648846 | G34: =F34/$F$36 -> 7.778791e-07 | H34: =B34*G34 -> 4.4728048e-06 | I34: =B34*(B34+1)*F34/((1+$C$6)^2)/$F$36 -> 2.9324511e-05 | J34: =+B34*F34 -> -55.573086
B35: =IF($I$4="Anual",B34+1,B34+0.25) -> 6 | C35: ='2_BF'!E8 -> 1 | D35: =C35-C34 -> 1.7198301e-07 | E35: =D35*$C$5 -> -2.1394692 | F35: =IF($I$4="Anual",E35/(1+$C$6)^B35,E35/(1+$C$6)^(B35*4)) -> -1.5082413 | G35: =F35/$F$36 -> 1.2139094e-07 | H35: =B35*G35 -> 7.2834564e-07 | I35: =B35*(B35+1)*F35/((1+$C$6)^2)/$F$36 -> 4.9520227e-06 | J35: =+B35*F35 -> -9.0494481
B36: TOTAL | C36: 100.00% | D36: =SUM(D12:D35) -> 1 | E36: =SUM(E12:E35) -> -12440003 | F36: =SUM(F12:F35) -> -12424662 | G36: =SUM(G12:G35) -> 1 | H36: =SUM(H12:H35) -> 0.041175542 | I36: =SUM(I12:I35) -> -0.59037102 | J36: =SUM(J12:J35) -> -511592.18 | K36: =+J36/F36 -> 0.041175542
F37: 895587.34
B38: B. CÁLCULO DE DURACIÓN
B39: Duración de Macaulay (D_Mac) | C39: =SUMPRODUCT(B12:B35,F12:F35)/F36 -> 0.041175542 | D39: años | E39: D_Mac = Σ[t × PV(CF_t)] / PV_Total | H39: ~0.0412 años
B41: Duración Modificada (D_Mod) | C41: =(SUMPRODUCT(B12:B35,F12:F35)/F36)/(1+Triangulo2!E5) -> 0.038844851 | D41: años | E41: D_Mod = D_Mac / (1 + r) | H41: ~0.0388 | J41: =+K36/(1+C6) -> 0.040580076
B43: Convexidad | C43: {=SUMPRODUCT(B12:B35*(B12:B35+1),F12:F35)/((1+Triangulo2!E5)^2*F36)} -> -0.54096134 | E43: Conv = Σ[t(t+1)×PV(CF_t)/PV_Total] / (1+r)² | H43: Curvatura de la función PV vs tasa
B46: C. ANÁLISIS DE SENSIBILIDAD — Δ PV ante cambios de tasa
B47: Escenario | C47: Tasa aplicada | D47: PV de Pasivos | E47: Δ PV vs base | F47: Δ PV % | G47: D_Mod × Δr (aprox.)
B48: Tasa base (r) | C48: =C6 -> 0.014673846 | D48: {=SUMPRODUCT(D12:D35*$C$5,1/((1+C48)^(B12:B35*4)))} -> -12424662 | E48: — | F48: — | G48: —
B49: Sube 100 bps | C49: =POWER(1+Triangulo2!$E$5+'2_Duration'!C7,0.25)-1 -> 0.017058525 | D49: {=SUMPRODUCT(D12:D35*$C$5,1/((1+C49)^(B12:B35*4)))} -> -12419506 | E49: =D49-D48 -> 5156.0707 | F49: =E49/D48 -> -0.00041498681 | G49: =-C41*(C49-$C$6)*D48 -> 1150.9274
B50: Sube 200 bps | C50: =POWER(1+Triangulo2!$E$5+'2_Duration'!C7*2,0.25)-1 -> 0.019426547 | D50: {=SUMPRODUCT(D12:D35*$C$5,1/((1+C50)^(B12:B35*4)))} -> -12413715 | E50: =D50-D48 -> 10946.979 | F50: =E50/D48 -> -0.00088106855 | G50: =-C41*(C50-$C$6)*D48 -> 2293.8156
B51: Baja 100 bps | C51: =POWER(1+Triangulo2!$E$5-'2_Duration'!C7,0.25)-1 -> 0.012272234 | D51: {=SUMPRODUCT(D12:D35*$C$5,1/((1+C51)^(B12:B35*4)))} -> -12429145 | E51: =D51-D48 -> -4483.7592 | F51: =E51/D48 -> 0.00036087576 | G51: =-C41*(C51-$C$6)*D48 -> -1159.0998
B52: Baja 200 bps | C52: =POWER(1+Triangulo2!$E$5-'2_Duration'!C7*2,0.25)-1 -> 0.0098534065 | D52: {=SUMPRODUCT(D12:D35*$C$5,1/((1+C52)^(B12:B35*4)))} -> -12432917 | E52: =D52-D48 -> -8255.5077 | F52: =E52/D48 -> 0.00066444527 | G52: =-C41*(C52-$C$6)*D48 -> -2326.5087

Sheet 2_Validacion_BT
A1: VALIDACIÓN DE TRIÁNGULOS Y BACKTESTING
A3: A — MONOTONICIDAD ratio_{i,j} = C_{i,j+1}/C_{i,j} ≥ 1.0
A4: Año | B4: D1/D0 | C4: D2/D1 | D4: D3/D2 | E4: D4/D3 | F4: D5/D4 | G4: D6/D5 | H4: D7/D6 | I4: D8/D7 | J4: D9/D8 | K4: D10/D9 | L4: D11/D10 | M4: D12/D11 | N4: D13/D12 | O4: D14/D13 | P4: D15/D14 | Q4: D16/D15 | R4: D17/D16 | S4: D18/D17 | T4: D19/D18 | U4: D20/D19 | V4: D21/D20 | W4: D22/D21 | X4: D23/D22 | Y4: ¿Monótono? (todos ≥1?) | Z4: ¿Outlier? | AC4: D1/D0 | AD4: D2/D1 | AE4: D3/D2 | AF4: D4/D3 | AG4: D5/D4 | AH4: D6/D5 | AI4: D7/D6 | AJ4: D8/D7 | AK4: D9/D8 | AL4: D10/D9 | AM4: D11/D10 | AN4: D12/D11 | AO4: D13/D12 | AP4: D14/D13 | AQ4: D15/D14 | AR4: D16/D15 | AS4: D17/D16 | AT4: D18/D17 | AU4: D19/D18 | AV4: D20/D19 | AW4: D21/D20 | AX4: D22/D21 | AY4: D23/D22
A5: 1Q19 | B5: =Triangulo2!D44 -> 1.3012916 | C5: =Triangulo2!E44 -> 0.86709506 | D5: =Triangulo2!F44 -> 0.9130239 | E5: =Triangulo2!G44 -> 1.010038 | F5: =Triangulo2!H44 -> 0.97635252 | G5: =Triangulo2!I44 -> 0.98005414 | H5: =Triangulo2!J44 -> 0.96352695 | I5: =Triangulo2!K44 -> 0.9741987 | ... X5: =Triangulo2!Z44 -> 1.0000002 | Y5: =MIN(B5:X5)>1 -> FALSE | Z5: {=MAX(ABS(AC5:AC26))>0.1} -> TRUE | AC5: =(B5-B6)/B5 -> -0.074196974 | AD5: =(C5-C6)/C5 -> -0.12412841 | AE5: =(D5-D6)/D5 -> -0.045392686 | AF5: =(E5-E6)/E5 -> 0.039251195 | AG5: =(F5-F6)/F5 -> 0.020662009 | AH5: =(G5-G6)/G5 -> 0.015469833 | AI5: =(H5-H6)/H5 -> -0.0098131314 | AJ5: =(I5-I6)/I5 -> -0.012016051 | ... AX5: =(W5-W6)/W5 -> 2.0336543e-07
A6: 2Q19 | B6: =Triangulo2!D45 -> 1.3978435 | C6: =Triangulo2!E45 -> 0.97472619 | D6: =Triangulo2!F45 -> 0.95446851 | E6: =Triangulo2!G45 -> 0.97039283 | F6: =Triangulo2!H45 -> 0.95617912 | G6: =Triangulo2!I45 -> 0.96489287 | H6: =Triangulo2!J45 -> 0.97298216 | I6: =Triangulo2!K45 -> 0.98590472 | ... X6: =Triangulo2!Z45 -> 0 | Y6: =MIN(B6:W6)>1 -> FALSE | Z6: {=MAX(ABS(AD5:AD25))>0.1} -> TRUE | AC6: =(B6-B7)/B6 -> 0.18227943 | AD6: =(C6-C7)/C6 -> -0.0011163754 | AE6: =(D6-D7)/D6 -> -0.085337719 | AF6: =(E6-E7)/E6 -> 0.014749022 | AG6: =(F6-F7)/F6 -> -0.028307776 | AH6: =(G6-G7)/G6 -> -0.023736296 | AI6: =(H6-H7)/H6 -> 0.0025589104 | AJ6: =(I6-I7)/I6 -> 0.03213991 | ... AW6: =(V6-V7)/V6 -> 2.001034e-06
A7: 3Q19 | B7: =Triangulo2!D46 -> 1.1430454 | C7: =Triangulo2!E46 -> 0.97581435 | D7: =Triangulo2!F46 -> 1.0359207 | E7: =Triangulo2!G46 -> 0.95608048 | F7: =Triangulo2!H46 -> 0.98324642 | G7: =Triangulo2!I46 -> 0.98779585 | H7: =Triangulo2!J46 -> 0.97049239 | I7: =Triangulo2!K46 -> 0.95421784 | ... X7: =Triangulo2!Z46 -> 0 | Y7: =MIN(B7:V7)>1 -> FALSE | Z7: {=MAX(ABS(AE5:AE26))>0.1} -> TRUE | AC7: =(B7-B8)/B7 -> -0.21461289 | AD7: =(C7-C8)/C7 -> 0.071244228 | AE7: =(D7-D8)/D7 -> 0.084788932 | AF7: =(E7-E8)/E7 -> 0.051620398 | AG7: =(F7-F8)/F7 -> 0.071155866 | AH7: =(G7-G8)/G7 -> 0.054950321 | AI7: =(H7-H8)/H7 -> -0.0032495387 | AJ7: =(I7-I8)/I7 -> -0.029121553 | ... AV7: =(U7-U8)/U7 -> 5.06782e-06
A8: 4Q19 | B8: =Triangulo2!D47 -> 1.3883576 | C8: =Triangulo2!E47 -> 0.90629321 | D8: =Triangulo2!F47 -> 0.94808607 | E8: =Triangulo2!G47 -> 0.90672723 | F8: =Triangulo2!H47 -> 0.91328267 | G8: =Triangulo2!I47 -> 0.93351615 | H8: =Triangulo2!J47 -> 0.97364604 | I8: =Triangulo2!K47 -> 0.98200614 | ... X8: =Triangulo2!Z47 -> 0 | Y8: =MIN(B8:U8)>1 -> FALSE | Z8: {=MAX(ABS(AF5:AF26))>0.1} -> TRUE | AC8: =(B8-B9)/B8 -> 0.14755568 | AD8: =(C8-C9)/C8 -> -0.0090535338 | AE8: =(D8-D9)/D8 -> -0.051380424 | AF8: =(E8-E9)/E8 -> 0.001095382 | AG8: =(F8-F9)/F8 -> -0.019028284 | AH8: =(G8-G9)/G8 -> -0.049505674 | AI8: =(H8-H9)/H8 -> 0.0094356302 | AJ8: =(I8-I9)/I8 -> 0.031703085 | ... AU8: =(T8-T9)/T8 -> 4.8198224e-05
A9: 1Q20 | B9: =Triangulo2!D48 -> 1.1834976 | C9: =Triangulo2!E48 -> 0.91449837 | D9: =Triangulo2!F48 -> 0.99679913 | E9: =Triangulo2!G48 -> 0.90573401 | F9: =Triangulo2!H48 -> 0.93066087 | G9: =Triangulo2!I48 -> 0.9797305 | H9: =Triangulo2!J48 -> 0.96445908 | I9: =Triangulo2!K48 -> 0.95087352 | ... X9: =Triangulo2!Z48 -> 0 | Y9: =MIN(B9:T9)>1 -> FALSE | Z9: {=MAX(ABS(AG5:AG26))>0.1} -> TRUE | AC9: =(B9-B10)/B9 -> -0.22672537 | AD9: =(C9-C10)/C9 -> 0.057857625 | AE9: =(D9-D10)/D9 -> 0.010613058 | AF9: =(E9-E10)/E9 -> 0.0725678 | AG9: =(F9-F10)/F9 -> 0.036964376 | AH9: =(G9-G10)/G9 -> 0.088485289 | AI9: =(H9-H10)/H9 -> 0.087979669 | AJ9: =(I9-I10)/I9 -> -0.070997506 | ... AT9: =(S9-S10)/S9 -> 4.1903668e-05
A10: 2Q20 | B10: =Triangulo2!D49 -> 1.4518265 | C10: =Triangulo2!E49 -> 0.86158767 | D10: =Triangulo2!F49 -> 0.98622004 | E10: =Triangulo2!G49 -> 0.84000689 | F10: =Triangulo2!H49 -> 0.89625958 | G10: =Triangulo2!I49 -> 0.89303876 | H10: =Triangulo2!J49 -> 0.87960629 | I10: =Triangulo2!K49 -> 1.0183832 | ... X10: =Triangulo2!Z49 -> 0 | Y10: =MIN(B10:S10)>1 -> FALSE | Z10: {=MAX(ABS(AH5:AH26))>0.1} -> TRUE | AC10: =(B10-B11)/B10 -> 0.056067889 | AD10: =(C10-C11)/C10 -> -0.023263879 | AE10: =(D10-D11)/D10 -> 0.090078536 | AF10: =(E10-E11)/E10 -> -0.024660173 | AG10: =(F10-F11)/F10 -> 0.042362819 | AH10: =(G10-G11)/G10 -> -0.027521087 | AI10: =(H10-H11)/H10 -> -0.11407189 | AJ10: =(I10-I11)/I10 -> 0.060470527 | ... AS10: =(R10-R11)/R10 -> 0.00015669348
A11: 3Q20 | B11: =Triangulo2!D50 -> 1.3704256 | C11: =Triangulo2!E50 -> 0.88163154 | D11: =Triangulo2!F50 -> 0.89738279 | E11: =Triangulo2!G50 -> 0.8607216 | F11: =Triangulo2!H50 -> 0.85829149 | G11: =Triangulo2!I50 -> 0.91761616 | H11: =Triangulo2!J50 -> 0.97994464 | I11: =Triangulo2!K50 -> 0.956801 | ... X11: =Triangulo2!Z50 -> 0 | Y11: =MIN(B11:R11)>1 -> FALSE | Z11: {=MAX(ABS(AI5:AI26))>0.1} -> TRUE | AC11: =(B11-B12)/B11 -> -0.012892695 | AD11: =(C11-C12)/C11 -> -0.14627874 | AE11: =(D11-D12)/D11 -> -0.01556024 | AF11: =(E11-E12)/E11 -> -0.086664899 | AG11: =(F11-F12)/F11 -> -0.16619566 | AH11: =(G11-G12)/G11 -> -0.030346815 | AI11: =(H11-H12)/H11 -> 0.023953937 | AJ11: =(I11-I12)/I11 -> -0.028443544 | ... AR11: =(Q11-Q12)/Q11 -> -0.00067707409
A12: 4Q20 | B12: =Triangulo2!D51 -> 1.3880941 | C12: =Triangulo2!E51 -> 1.0105955 | D12: =Triangulo2!F51 -> 0.91134628 | E12: =Triangulo2!G51 -> 0.93531595 | F12: =Triangulo2!H51 -> 1.0009358 | G12: =Triangulo2!I51 -> 0.94546288 | H12: =Triangulo2!J51 -> 0.95647111 | I12: =Triangulo2!K51 -> 0.98401581 | ... X12: =Triangulo2!Z51 -> 0 | Y12: =MIN(B12:Q12)>1 -> FALSE | Z12: {=MAX(ABS(AJ5:AJ26))>0.1} -> FALSE | AC12: =(B12-B13)/B12 -> -0.039387649 | AD12: =(C12-C13)/C12 -> 0.13626268 | AE12: =(D12-D13)/D12 -> -0.0031811572 | AF12: =(E12-E13)/E12 -> 0.024787537 | AG12: =(F12-F13)/F12 -> 0.036740016 | AH12: =(G12-G13)/G12 -> 0.0046379991 | AI12: =(H12-H13)/H12 -> -0.057675874 | AJ12: =(I12-I13)/I12 -> -0.026393443 | ... AQ12: =(P12-P13)/P12 -> 0.00020648967
A13: 1Q21 | B13: =Triangulo2!D52 -> 1.4427679 | C13: =Triangulo2!E52 -> 0.87288904 | D13: =Triangulo2!F52 -> 0.91424541 | E13: =Triangulo2!G52 -> 0.91213178 | F13: =Triangulo2!H52 -> 0.96416141 | G13: =Triangulo2!I52 -> 0.94107783 | H13: =Triangulo2!J52 -> 1.0116364 | I13: =Triangulo2!K52 -> 1.0099874 | ... X13: =Triangulo2!Z52 -> 0 | Y13: =MIN(B13:P13)>1 -> FALSE | Z13: {=MAX(ABS(AK5:AK26))>0.1} -> FALSE | AC13: =(B13-B14)/B13 -> -0.024858598 | AD13: =(C13-C14)/C13 -> 0.0097627573 | AE13: =(D13-D14)/D13 -> -0.093275151 | AF13: =(E13-E14)/E13 -> -0.0073118687 | AG13: =(F13-F14)/F13 -> 0.042747941 | AH13: =(G13-G14)/G13 -> -0.013980473 | AI13: =(H13-H14)/H13 -> 0.053248042 | AJ13: =(I13-I14)/I13 -> 0.052273708 | ... AP13: =(O13-O14)/O13 -> -0.0010813481
A14: 2Q21 | B14: =Triangulo2!D53 -> 1.4786331 | C14: =Triangulo2!E53 -> 0.86436723 | D14: =Triangulo2!F53 -> 0.99952179 | E14: =Triangulo2!G53 -> 0.91880116 | F14: =Triangulo2!H53 -> 0.9229455 | G14: =Triangulo2!I53 -> 0.95423454 | H14: =Triangulo2!J53 -> 0.95776876 | I14: =Triangulo2!K53 -> 0.95719159 | ... X14: =Triangulo2!Z53 -> 0 | Y14: =MIN(B14:O14)>1 -> FALSE | Z14: {=MAX(ABS(AL5:AL26))>0.1} -> FALSE | AC14: =(B14-B15)/B14 -> 0.15477115 | AD14: =(C14-C15)/C14 -> -0.0094633709 | AE14: =(D14-D15)/D14 -> 0.087964508 | AF14: =(E14-E15)/E14 -> 0.01686009 | AG14: =(F14-F15)/F14 -> 0.010748365 | AH14: =(G14-G15)/G14 -> -0.051242319 | AI14: =(H14-H15)/H14 -> -0.018746107 | AJ14: =(I14-I15)/I14 -> 0.00034841169 | ... AO14: =(N14-N15)/N14 -> 0.0066873742
A15: 3Q21 | B15: =Triangulo2!D54 -> 1.2497833 | C15: =Triangulo2!E54 -> 0.87254706 | D15: =Triangulo2!F54 -> 0.91159935 | E15: =Triangulo2!G54 -> 0.90331009 | F15: =Triangulo2!H54 -> 0.91302534 | G15: =Triangulo2!I54 -> 1.0031317 | H15: =Triangulo2!J54 -> 0.97572319 | I15: =Triangulo2!K54 -> 0.95685809 | ... X15: =Triangulo2!Z54 -> 0 | Y15: =MIN(B15:N15)>1 -> FALSE | Z15: {=MAX(ABS(AM5:AM26))>0.1} -> FALSE | AC15: =(B15-B16)/B15 -> -0.1614505 | AD15: =(C15-C16)/C15 -> -0.049559775 | AE15: =(D15-D16)/D15 -> -0.07428787 | AF15: =(E15-E16)/E15 -> -0.10904895 | AG15: =(F15-F16)/F15 -> -0.085999188 | AH15: =(G15-G16)/G15 -> 0.058587861 | AI15: =(H15-H16)/H15 -> 0.0067173444 | AJ15: =(I15-I16)/I15 -> -0.0070984666 | ... AN15: =(M15-M16)/M15 -> 0.00029189434
A16: 4Q21 | B16: =Triangulo2!D55 -> 1.4515615 | C16: =Triangulo2!E55 -> 0.91579029 | D16: =Triangulo2!F55 -> 0.97932012 | E16: =Triangulo2!G55 -> 1.0018151 | F16: =Triangulo2!H55 -> 0.99154478 | G16: =Triangulo2!I55 -> 0.94436039 | H16: =Triangulo2!J55 -> 0.96916892 | I16: =Triangulo2!K55 -> 0.96365032 | ... X16: =Triangulo2!Z55 -> 0 | Y16: =MIN(B16:M16)>1 -> FALSE | Z16: {=MAX(ABS(AN5:AN26))>0.1} -> FALSE | AC16: =(B16-B17)/B16 -> -0.025991573 | AD16: =(C16-C17)/C16 -> -0.056029192 | AE16: =(D16-D17)/D16 -> 0.0066345052 | AF16: =(E16-E17)/E16 -> 0.10131739 | AG16: =(F16-F17)/F16 -> -0.026216596 | AH16: =(G16-G17)/G16 -> -0.0026790058 | AI16: =(H16-H17)/H16 -> -0.033024732 | AJ16: =(I16-I17)/I16 -> -0.011669828 | ... AM16: =(L16-L17)/L16 -> -0.0050209055
A17: 1Q22 | B17: =Triangulo2!D56 -> 1.4892898 | C17: =Triangulo2!E56 -> 0.96710128 | D17: =Triangulo2!F56 -> 0.97282282 | E17: =Triangulo2!G56 -> 0.90031382 | F17: =Triangulo2!H56 -> 1.0175397 | G17: =Triangulo2!I56 -> 0.94689034 | H17: =Triangulo2!J56 -> 1.0011755 | I17: =Triangulo2!K56 -> 0.97489595 | ... X17: =Triangulo2!Z56 -> 0 | Y17: =MIN(B17:L17)>1 -> FALSE | Z17: {=MAX(ABS(AO5:AO26))>0.1} -> FALSE | AC17: =(B17-B18)/B17 -> 0.057777745 | AD17: =(C17-C18)/C17 -> -0.033252629 | AE17: =(D17-D18)/D17 -> 0.01476697 | AF17: =(E17-E18)/E17 -> -0.020124613 | AG17: =(F17-F18)/F17 -> 0.1050376 | AH17: =(G17-G18)/G17 -> -0.057861556 | AI17: =(H17-H18)/H17 -> 0.015642999 | AJ17: =(I17-I18)/I17 -> 0.01751774 | ... AL17: =(K17-K18)/K17 -> -0.0044672358
A18: 2Q22 | B18: =Triangulo2!D57 -> 1.403242 | C18: =Triangulo2!E57 -> 0.99925995 | D18: =Triangulo2!F57 -> 0.95845717 | E18: =Triangulo2!G57 -> 0.91843229 | F18: =Triangulo2!H57 -> 0.91065978 | G18: =Triangulo2!I57 -> 1.0016789 | H18: =Triangulo2!J57 -> 0.98551408 | I18: =Triangulo2!K57 -> 0.95781798 | ... X18: =Triangulo2!Z57 -> 0 | Y18: =MIN(B18:K18)>1 -> FALSE | Z18: {=MAX(ABS(AP5:AP26))>0.1} -> FALSE | AC18: =(B18-B19)/B18 -> 0.0050845111 | AD18: =(C18-C19)/C18 -> 0.22075503 | AE18: =(D18-D19)/D18 -> 0.069827836 | AF18: =(E18-E19)/E18 -> -0.10980079 | AG18: =(F18-F19)/F18 -> -0.047567292 | AH18: =(G18-G19)/G18 -> 0.13741942 | AI18: =(H18-H19)/H18 -> 0.051003718 | AJ18: =(I18-I19)/I18 -> -0.060039636 | AK18: =(J18-J19)/J18 -> 0.028535705
A19: 3Q22 | B19: =Triangulo2!D58 -> 1.3961072 | C19: =Triangulo2!E58 -> 0.77866829 | D19: =Triangulo2!F58 -> 0.89153018 | E19: =Triangulo2!G58 -> 1.0192769 | F19: =Triangulo2!H58 -> 0.9539774 | G19: =Triangulo2!I58 -> 0.86402875 | H19: =Triangulo2!J58 -> 0.9352492 | I19: =Triangulo2!K58 -> 1.015325 | ... X19: =Triangulo2!Z58 -> 0 | Y19: =MIN(B19:J19)>1 -> FALSE | Z19: {=MAX(ABS(AQ5:AQ26))>0.1} -> FALSE | AC19: =(B19-B20)/B19 -> -0.38997831 | AD19: =(C19-C20)/C19 -> -0.30689087 | AE19: =(D19-D20)/D19 -> -0.4747205 | AF19: =(E19-E20)/E19 -> 0.032011086 | AG19: =(F19-F20)/F19 -> -0.054076474 | AH19: =(G19-G20)/G19 -> -0.13183258 | AI19: =(H19-H20)/H19 -> -0.044855799 | AJ19: =(I19-I20)/I19 -> 0.026966272
A20: 4Q22 | B20: =Triangulo2!D59 -> 1.9405588 | C20: =Triangulo2!E59 -> 1.0176345 | D20: =Triangulo2!F59 -> 1.3147578 | E20: =Triangulo2!G59 -> 0.98664872 | F20: =Triangulo2!H59 -> 1.0055651 | G20: =Triangulo2!I59 -> 0.97793589 | H20: =Triangulo2!J59 -> 0.97720055 | I20: =Triangulo2!K59 -> 0.98794549 | ... X20: =Triangulo2!Z59 -> 0 | Y20: =MIN(B20:I20)>1 -> FALSE | Z20: {=MAX(ABS(AR5:AR26))>0.1} -> FALSE | AC20: =(B20-B21)/B20 -> 0.15543846 | AD20: =(C20-C21)/C20 -> 0.086202736 | AE20: =(D20-D21)/D20 -> -0.060347589 | AF20: =(E20-E21)/E20 -> 0.038455428 | AG20: =(F20-F21)/F20 -> 0.0092977608 | AH20: =(G20-G21)/G20 -> -0.0047452585 | AI20: =(H20-H21)/H20 -> -0.009449359
A21: 1Q23 | B21: =Triangulo2!D60 -> 1.6389213 | C21: =Triangulo2!E60 -> 0.9299116 | D21: =Triangulo2!F60 -> 1.3941003 | E21: =Triangulo2!G60 -> 0.94870672 | F21: =Triangulo2!H60 -> 0.99621563 | G21: =Triangulo2!I60 -> 0.98257645 | H21: =Triangulo2!J60 -> 0.98643447 | I21: =Triangulo2!K60 -> 0 | ... X21: =Triangulo2!Z60 -> 0 | Y21: =MIN(B21:H21)>1 -> FALSE | Z21: {=MAX(ABS(AS5:AS26))>0.1} -> FALSE | AC21: =(B21-B22)/B21 -> -0.59448485 | AD21: =(C21-C22)/C21 -> -0.020803564 | AE21: =(D21-D22)/D21 -> -0.027095072 | AF21: =(E21-E22)/E21 -> -0.065873214 | AG21: =(F21-F22)/F21 -> -0.0017096043 | AH21: =(G21-G22)/G21 -> 0.0072326733
A22: 2Q23 | B22: =Triangulo2!D61 -> 2.6132352 | C22: =Triangulo2!E61 -> 0.94925707 | D22: =Triangulo2!F61 -> 1.4318736 | E22: =Triangulo2!G61 -> 1.0112011 | F22: =Triangulo2!H61 -> 0.99791876 | G22: =Triangulo2!I61 -> 0.9754698 | H22: =Triangulo2!J61 -> 0 | I22: =Triangulo2!K61 -> 0 | ... X22: =Triangulo2!Z61 -> 0 | Y22: =MIN(B22:G22)>1 -> FALSE | Z22: {=MAX(ABS(AT5:AT26))>0.1} -> FALSE | AC22: =(B22-B23)/B22 -> -0.21020187 | AD22: =(C22-C23)/C22 -> -0.045351796 | AE22: =(D22-D23)/D22 -> 0.18135582 | AF22: =(E22-E23)/E22 -> 0.006079177 | AG22: =(F22-F23)/F22 -> -6.4625303e-05
A23: 3Q23 | B23: =Triangulo2!D62 -> 3.1625421 | C23: =Triangulo2!E62 -> 0.99230758 | D23: =Triangulo2!F62 -> 1.1721949 | E23: =Triangulo2!G62 -> 1.0050538 | F23: =Triangulo2!H62 -> 0.99798325 | G23: =Triangulo2!I62 -> 0 | H23: =Triangulo2!J62 -> 0 | I23: =Triangulo2!K62 -> 0 | ... X23: =Triangulo2!Z62 -> 0 | Y23: =MIN(B23:F23)>1 -> FALSE | Z23: {=MAX(ABS(AU5:AU26))>0.1} -> FALSE | AC23: =(B23-B24)/B23 -> 0.44445837 | AD23: =(C23-C24)/C23 -> 0.047323906 | AE23: =(D23-D24)/D23 -> -0.10988637 | AF23: =(E23-E24)/E23 -> 0.017661041
A24: 4Q23 | B24: =Triangulo2!D63 -> 1.7569238 | C24: =Triangulo2!E63 -> 0.94534771 | D24: =Triangulo2!F63 -> 1.3010032 | E24: =Triangulo2!G63 -> 0.98730351 | F24: =Triangulo2!H63 -> 0 | G24: =Triangulo2!I63 -> 0 | H24: =Triangulo2!J63 -> 0 | I24: =Triangulo2!K63 -> 0 | ... X24: =Triangulo2!Z63 -> 0 | Y24: =MIN(B24:E24)>1 -> FALSE | Z24: {=MAX(ABS(AV5:AV25))>0.1} -> FALSE | AC24: =(B24-B25)/B24 -> -0.32733795 | AD24: =(C24-C25)/C24 -> -0.060851593 | AE24: =(D24-D25)/D24 -> 0.0015087406
A25: 1Q24 | B25: =Triangulo2!D64 -> 2.3320317 | C25: =Triangulo2!E64 -> 1.0028736 | D25: =Triangulo2!F64 -> 1.2990403 | E25: =Triangulo2!G64 -> 0 | F25: =Triangulo2!H64 -> 0 | G25: =Triangulo2!I64 -> 0 | H25: =Triangulo2!J64 -> 0 | I25: =Triangulo2!K64 -> 0 | ... X25: =Triangulo2!Z64 -> 0 | Y25: =MIN(B25:D25)>1 -> TRUE | Z25: {=MAX(ABS(AW5:AW24))>0.1} -> FALSE | AC25: =(B25-B26)/B25 -> 0.15085735 | AD25: =(C25-C26)/C25 -> 0.040182936
A26: 2Q24 | B26: =Triangulo2!D65 -> 1.9802276 | C26: =Triangulo2!E65 -> 0.96257522 | D26: =Triangulo2!F65 -> 0 | E26: =Triangulo2!G65 -> 0 | F26: =Triangulo2!H65 -> 0 | G26: =Triangulo2!I65 -> 0 | H26: =Triangulo2!J65 -> 0 | I26: =Triangulo2!K65 -> 0 | ... X26: =Triangulo2!Z65 -> 0 | Y26: =MIN(B26:C26)>1 -> FALSE | Z26: =MAX(ABS(AX5))>0.1 -> FALSE | AC26: =(B26-B27)/B26 -> 0.04446241
